Workbook

Sheet ダッシュボード
A1: OLD ORDER 原宿店 売上管理ダッシュボード 2026年4月〜2027年3月
A2: 各月シートの入力欄を埋めると、ここに自動集計されます。単位：円
A4: 年間予算 | C4: 当期実績(YTD) | E4: 年間予算進捗 | G4: 経過月 達成率 | I4: 残り必要額
A5: =IF('設定'!$B$5=0,SUM(B8:B19),'設定'!$B$5) -> 225809762 | C5: =SUM(C8:C19) -> 63872132 | E5: =IFERROR(C5/A5,0) -> 0.28285815 | G5: =IFERROR(SUMIFS($C$8:$C$19,$C$8:$C$19,">0",$B$8:$B$19,">0")/SUMIFS($B$8:$B$19,$C$8:$C$19,">0",$B$8:$B$19,">0"),0) -> 0.5076882 | I5: =A5-C5 -> 161937630
A7: 月 | B7: 月間予算 | C7: 当月実績 | D7: 達成率 | E7: 予実差 | F7: 前年実績 | G7: 前年比 | H7: 購入人数 | I7: 来客数 | J7: 決定率 | K7: 客単価 | L7: 累計予算 | M7: 累計実績 | N7: 累計達成率
A8: 2026年4月 | B8: ='2026年04月'!$A$4 -> 9820292 | C8: ='2026年04月'!$C$4 -> 9864675 | D8: =IF(C8=0,"",IFERROR(C8/B8,"")) -> 1.0045195 | E8: =C8-B8 -> 44383 | F8: =IF('設定'!C8="","",'設定'!C8) | G8: =IF(OR(F8="",C8=0),"",IFERROR(C8/F8,"")) | H8: ='2026年04月'!$M$38 -> 425 | I8: ='2026年04月'!$O$38 -> 1489 | J8: =IFERROR(H8/I8,0) -> 0.28542646 | K8: =IFERROR(C8/H8,0) -> 23211 | L8: =IF(C8=0,"",SUM($B$8:B8)) -> 9820292 | M8: =IF(C8=0,"",SUM($C$8:C8)) -> 9864675 | N8: =IF(M8="","",IFERROR(M8/L8,0)) -> 1.0045195
A9: 2026年5月 | B9: ='2026年05月'!$A$4 -> 12329470 | C9: ='2026年05月'!$C$4 -> 12381052 | D9: =IF(C9=0,"",IFERROR(C9/B9,"")) -> 1.0041836 | E9: =C9-B9 -> 51582 | F9: =IF('設定'!C9="","",'設定'!C9) | G9: =IF(OR(F9="",C9=0),"",IFERROR(C9/F9,"")) | H9: ='2026年05月'!$M$39 -> 537 | I9: ='2026年05月'!$O$39 -> 1516 | J9: =IFERROR(H9/I9,0) -> 0.35422164 | K9: =IFERROR(C9/H9,0) -> 23055.963 | L9: =IF(C9=0,"",SUM($B$8:B9)) -> 22149762 | M9: =IF(C9=0,"",SUM($C$8:C9)) -> 22245727 | N9: =IF(M9="","",IFERROR(M9/L9,0)) -> 1.0043326
A10: 2026年6月 | B10: ='2026年06月'!$A$4 -> 17000000 | C10: ='2026年06月'!$C$4 -> 10446643 | D10: =IF(C10=0,"",IFERROR(C10/B10,"")) -> 0.61450841 | E10: =C10-B10 -> -6553357 | F10: =IF('設定'!C10="","",'設定'!C10) | G10: =IF(OR(F10="",C10=0),"",IFERROR(C10/F10,"")) | H10: ='2026年06月'!$M$38 -> 450 | I10: ='2026年06月'!$O$38 -> 1283 | J10: =IFERROR(H10/I10,0) -> 0.35074045 | K10: =IFERROR(C10/H10,0) -> 23214.762 | L10: =IF(C10=0,"",SUM($B$8:B10)) -> 39149762 | M10: =IF(C10=0,"",SUM($C$8:C10)) -> 32692370 | N10: =IF(M10="","",IFERROR(M10/L10,0)) -> 0.83505923
A11: 2026年7月 | B11: ='2026年07月'!$A$4 -> 20000000 | C11: ='2026年07月'!$C$4 -> 9690000 | D11: =IF(C11=0,"",IFERROR(C11/B11,"")) -> 0.4845 | E11: =C11-B11 -> -10310000 | F11: =IF('設定'!C11="","",'設定'!C11) | G11: =IF(OR(F11="",C11=0),"",IFERROR(C11/F11,"")) | H11: ='2026年07月'!$M$39 -> 426 | I11: ='2026年07月'!$O$39 -> 1165 | J11: =IFERROR(H11/I11,0) -> 0.36566524 | K11: =IFERROR(C11/H11,0) -> 22746.479 | L11: =IF(C11=0,"",SUM($B$8:B11)) -> 59149762 | M11: =IF(C11=0,"",SUM($C$8:C11)) -> 42382370 | N11: =IF(M11="","",IFERROR(M11/L11,0)) -> 0.71652647
A12: 2026年8月 | B12: ='2026年08月'!$A$4 -> 24660000 | C12: ='2026年08月'!$C$4 -> 8510877 | D12: =IF(C12=0,"",IFERROR(C12/B12,"")) -> 0.34512883 | E12: =C12-B12 -> -16149123 | F12: =IF('設定'!C12="","",'設定'!C12) | G12: =IF(OR(F12="",C12=0),"",IFERROR(C12/F12,"")) | H12: ='2026年08月'!$M$39 -> 386 | I12: ='2026年08月'!$O$39 -> 971 | J12: =IFERROR(H12/I12,0) -> 0.39752832 | K12: =IFERROR(C12/H12,0) -> 22048.904 | L12: =IF(C12=0,"",SUM($B$8:B12)) -> 83809762 | M12: =IF(C12=0,"",SUM($C$8:C12)) -> 50893247 | N12: =IF(M12="","",IFERROR(M12/L12,0)) -> 0.60724724
A13: 2026年9月 | B13: ='2026年09月'!$A$4 -> 23000000 | C13: ='2026年09月'!$C$4 -> 7801176 | D13: =IF(C13=0,"",IFERROR(C13/B13,"")) -> 0.33918157 | E13: =C13-B13 -> -15198824 | F13: =IF('設定'!C13="","",'設定'!C13) | G13: =IF(OR(F13="",C13=0),"",IFERROR(C13/F13,"")) | H13: ='2026年09月'!$M$38 -> 333 | I13: ='2026年09月'!$O$38 -> 851 | J13: =IFERROR(H13/I13,0) -> 0.39130435 | K13: =IFERROR(C13/H13,0) -> 23426.955 | L13: =IF(C13=0,"",SUM($B$8:B13)) -> 106809762 | M13: =IF(C13=0,"",SUM($C$8:C13)) -> 58694423 | N13: =IF(M13="","",IFERROR(M13/L13,0)) -> 0.54952302
A14: 2026年10月 | B14: ='2026年10月'!$A$4 -> 19000000 | C14: ='2026年10月'!$C$4 -> 5177709 | D14: =IF(C14=0,"",IFERROR(C14/B14,"")) -> 0.272511 | E14: =C14-B14 -> -13822291 | F14: =IF('設定'!C14="","",'設定'!C14) | G14: =IF(OR(F14="",C14=0),"",IFERROR(C14/F14,"")) | H14: ='2026年10月'!$M$39 -> 222 | I14: ='2026年10月'!$O$39 -> 600 | J14: =IFERROR(H14/I14,0) -> 0.37 | K14: =IFERROR(C14/H14,0) -> 23323.014 | L14: =IF(C14=0,"",SUM($B$8:B14)) -> 125809762 | M14: =IF(C14=0,"",SUM($C$8:C14)) -> 63872132 | N14: =IF(M14="","",IFERROR(M14/L14,0)) -> 0.5076882
A15: 2026年11月 | B15: ='2026年11月'!$A$4 -> 19000000 | C15: ='2026年11月'!$C$4 -> 0 | D15: =IF(C15=0,"",IFERROR(C15/B15,"")) | E15: =C15-B15 -> -19000000 | F15: =IF('設定'!C15="","",'設定'!C15) | G15: =IF(OR(F15="",C15=0),"",IFERROR(C15/F15,"")) | H15: ='2026年11月'!$M$38 -> 0 | I15: ='2026年11月'!$O$38 -> 0 | J15: =IFERROR(H15/I15,0) -> 0 | K15: =IFERROR(C15/H15,0) -> 0 | L15: =IF(C15=0,"",SUM($B$8:B15)) | M15: =IF(C15=0,"",SUM($C$8:C15)) | N15: =IF(M15="","",IFERROR(M15/L15,0))
A16: 2026年12月 | B16: ='2026年12月'!$A$4 -> 21000000 | C16: ='2026年12月'!$C$4 -> 0 | D16: =IF(C16=0,"",IFERROR(C16/B16,"")) | E16: =C16-B16 -> -21000000 | F16: =IF('設定'!C16="","",'設定'!C16) -> 4139160 | G16: =IF(OR(F16="",C16=0),"",IFERROR(C16/F16,"")) | H16: ='2026年12月'!$M$39 -> 0 | I16: ='2026年12月'!$O$39 -> 0 | J16: =IFERROR(H16/I16,0) -> 0 | K16: =IFERROR(C16/H16,0) -> 0 | L16: =IF(C16=0,"",SUM($B$8:B16)) | M16: =IF(C16=0,"",SUM($C$8:C16)) | N16: =IF(M16="","",IFERROR(M16/L16,0))
A17: 2027年1月 | B17: ='2027年01月'!$A$4 -> 25000000 | C17: ='2027年01月'!$C$4 -> 0 | D17: =IF(C17=0,"",IFERROR(C17/B17,"")) | E17: =C17-B17 -> -25000000 | F17: =IF('設定'!C17="","",'設定'!C17) -> 9650171 | G17: =IF(OR(F17="",C17=0),"",IFERROR(C17/F17,"")) | H17: ='2027年01月'!$M$39 -> 0 | I17: ='2027年01月'!$O$39 -> 0 | J17: =IFERROR(H17/I17,0) -> 0 | K17: =IFERROR(C17/H17,0) -> 0 | L17: =IF(C17=0,"",SUM($B$8:B17)) | M17: =IF(C17=0,"",SUM($C$8:C17)) | N17: =IF(M17="","",IFERROR(M17/L17,0))
A18: 2027年2月 | B18: ='2027年02月'!$A$4 -> 19000000 | C18: ='2027年02月'!$C$4 -> 0 | D18: =IF(C18=0,"",IFERROR(C18/B18,"")) | E18: =C18-B18 -> -19000000 | F18: =IF('設定'!C18="","",'設定'!C18) -> 7476182 | G18: =IF(OR(F18="",C18=0),"",IFERROR(C18/F18,"")) | H18: ='2027年02月'!$M$36 -> 0 | I18: ='2027年02月'!$O$36 -> 0 | J18: =IFERROR(H18/I18,0) -> 0 | K18: =IFERROR(C18/H18,0) -> 0 | L18: =IF(C18=0,"",SUM($B$8:B18)) | M18: =IF(C18=0,"",SUM($C$8:C18)) | N18: =IF(M18="","",IFERROR(M18/L18,0))
A19: 2027年3月 | B19: ='2027年03月'!$A$4 -> 16000000 | C19: ='2027年03月'!$C$4 -> 0 | D19: =IF(C19=0,"",IFERROR(C19/B19,"")) | E19: =C19-B19 -> -16000000 | F19: =IF('設定'!C19="","",'設定'!C19) -> 10101265 | G19: =IF(OR(F19="",C19=0),"",IFERROR(C19/F19,"")) | H19: ='2027年03月'!$M$39 -> 0 | I19: ='2027年03月'!$O$39 -> 0 | J19: =IFERROR(H19/I19,0) -> 0 | K19: =IFERROR(C19/H19,0) -> 0 | L19: =IF(C19=0,"",SUM($B$8:B19)) | M19: =IF(C19=0,"",SUM($C$8:C19)) | N19: =IF(M19="","",IFERROR(M19/L19,0))
A20: 合計 | B20: =SUM(B8:B19) -> 225809762 | C20: =SUM(C8:C19) -> 63872132 | D20: =IFERROR(C20/B20,0) -> 0.28285815 | E20: =SUM(E8:E19) -> -161937630 | F20: =SUM(F8:F19) -> 31366778 | G20: =IFERROR(C20/F20,0) -> 2.0362988 | H20: =SUM(H8:H19) -> 2779 | I20: =SUM(I8:I19) -> 7875 | J20: =IFERROR(H20/I20,0) -> 0.35288889 | K20: =IFERROR(C20/H20,0) -> 22983.855
A22: ※前年実績は「設定」シートの青字セルに入力。元データが無い月は空欄です。
A23: ※「経過月 達成率」は予算と実績の両方が入っている月だけで計算します。
A24: 【グラフ】

Sheet 2026年04月
A1: 2026年4月 原宿店 日別売上管理
A2: 青字＋薄黄色のセルが入力欄。白セルは数式なので触らないでください。単位：円
A3: 月間予算 | C3: 当月実績 | E3: 達成率 | G3: 営業日数(/30日) | I3: 残り必要額 | K3: 残り必要日商
A4: =IF('設定'!$B$8="",SUM(C8:C37),'設定'!$B$8) -> 9820292 | C4: =SUM(G8:G37) -> 9864675 | E4: =IFERROR(C4/A4,0) -> 1.0045195 | G4: =COUNTIF(G8:G37,">0") -> 30 | I4: =A4-C4 -> -44383 | K4: =IF((30-G4)>0,(A4-C4)/(30-G4),0) -> 0
A5: 日次予算合計 | C5: 着地見込 | E5: 決定率 | G5: 客単価 | I5: セット率 | K5: 試着率
A6: =SUM(C8:C37) -> 18500000 | C6: =IFERROR(C4/G4*30,0) -> 9864675 | E6: =IFERROR(M38/O38,0) -> 0.28542646 | G6: =IFERROR(G38/M38,0) -> 23211 | I6: =IFERROR(N38/M38,0) -> 1.0988235 | K6: =IFERROR(P38/O38,0) -> 0.48153123
A7: 日付 | B7: 曜 | C7: 日次予算 | D7: 累計予算 | E7: 現金 | F7: クレジット | G7: 実績合計 | H7: 累計実績 | I7: 日次達成 | J7: 累計達成 | K7: 累計予実差 | L7: ペース | M7: 購入人数 | N7: 販売点数 | O7: 来客数 | P7: 試着組数 | Q7: 試着個数 | R7: 決定率 | S7: 客単価 | T7: セット率 | U7: 試着率 | V7: クロス クーポン | W7: インスタ フォロワー | X7: 経費 | Y7: メモ | AA7: 曜日 | AB7: 平均日商 | AC7: 日数 | AD7: 決定率 | AE7: 客単価
A8: 46113 | B8: =MID("日月火水木金土",WEEKDAY(A8),1) -> 水 | C8: 500000 | D8: =SUM($C$8:C8) -> 500000 | E8: 63338 | F8: 43500 | G8: =IF(COUNT(E8:F8)=0,"",SUM(E8:F8)) -> 106838 | H8: =IF(G8="","",SUM($G$8:G8)) -> 106838 | I8: =IF(G8="","",IFERROR(G8/C8,"")) -> 0.213676 | J8: =IF(H8="","",IFERROR(H8/D8,"")) -> 0.213676 | K8: =IF(H8="","",IF(D8=0,"",H8-D8)) -> -393162 | L8: =IF(G8="","—",IF(D8=0,"予算未入力",IF(H8>=D8,"◎ ペース内","▲ 遅れ"))) -> ▲ 遅れ | M8: 5 | N8: 6 | O8: 31 | P8: 18 | R8: =IFERROR(M8/O8,"") -> 0.16129032 | S8: =IFERROR(G8/M8,"") -> 21367.6 | T8: =IFERROR(N8/M8,"") -> 1.2 | U8: =IFERROR(P8/O8,"") -> 0.58064516 | W8: 42670 | X8: 0 | AA8: 月 | AB8: =IFERROR(AVERAGEIFS($G$8:$G$37,$B$8:$B$37,AA8,$G$8:$G$37,">0"),0) -> 225772.5 | AC8: =COUNTIFS($B$8:$B$37,AA8,$G$8:$G$37,">0") -> 4 | AD8: =IFERROR(SUMIF($B$8:$B$37,AA8,$M$8:$M$37)/SUMIF($B$8:$B$37,AA8,$O$8:$O$37),0) -> 0.24074074 | AE8: =IFERROR(SUMIF($B$8:$B$37,AA8,$G$8:$G$37)/SUMIF($B$8:$B$37,AA8,$M$8:$M$37),0) -> 23156.154
A9: 46114 | B9: =MID("日月火水木金土",WEEKDAY(A9),1) -> 木 | C9: 500000 | D9: =SUM($C$8:C9) -> 1000000 | E9: 45700 | F9: 187810 | G9: =IF(COUNT(E9:F9)=0,"",SUM(E9:F9)) -> 233510 | H9: =IF(G9="","",SUM($G$8:G9)) -> 340348 | I9: =IF(G9="","",IFERROR(G9/C9,"")) -> 0.46702 | J9: =IF(H9="","",IFERROR(H9/D9,"")) -> 0.340348 | K9: =IF(H9="","",IF(D9=0,"",H9-D9)) -> -659652 | L9: =IF(G9="","—",IF(D9=0,"予算未入力",IF(H9>=D9,"◎ ペース内","▲ 遅れ"))) -> ▲ 遅れ | M9: 11 | N9: 13 | O9: 45 | P9: 18 | R9: =IFERROR(M9/O9,"") -> 0.24444444 | S9: =IFERROR(G9/M9,"") -> 21228.182 | T9: =IFERROR(N9/M9,"") -> 1.1818182 | U9: =IFERROR(P9/O9,"") -> 0.4 | W9: 42700 | X9: 0 | AA9: 火 | AB9: =IFERROR(AVERAGEIFS($G$8:$G$37,$B$8:$B$37,AA9,$G$8:$G$37,">0"),0) -> 284647.5 | AC9: =COUNTIFS($B$8:$B$37,AA9,$G$8:$G$37,">0") -> 4 | AD9: =IFERROR(SUMIF($B$8:$B$37,AA9,$M$8:$M$37)/SUMIF($B$8:$B$37,AA9,$O$8:$O$37),0) -> 0.26136364 | AE9: =IFERROR(SUMIF($B$8:$B$37,AA9,$G$8:$G$37)/SUMIF($B$8:$B$37,AA9,$M$8:$M$37),0) -> 24751.957
A10: 46115 | B10: =MID("日月火水木金土",WEEKDAY(A10),1) -> 金 | C10: 500000 | D10: =SUM($C$8:C10) -> 1500000 | E10: 115210 | F10: 385848 | G10: =IF(COUNT(E10:F10)=0,"",SUM(E10:F10)) -> 501058 | H10: =IF(G10="","",SUM($G$8:G10)) -> 841406 | I10: =IF(G10="","",IFERROR(G10/C10,"")) -> 1.002116 | J10: =IF(H10="","",IFERROR(H10/D10,"")) -> 0.56093733 | K10: =IF(H10="","",IF(D10=0,"",H10-D10)) -> -658594 | L10: =IF(G10="","—",IF(D10=0,"予算未入力",IF(H10>=D10,"◎ ペース内","▲ 遅れ"))) -> ▲ 遅れ | M10: 25 | N10: 25 | O10: 49 | P10: 25 | R10: =IFERROR(M10/O10,"") -> 0.51020408 | S10: =IFERROR(G10/M10,"") -> 20042.32 | T10: =IFERROR(N10/M10,"") -> 1 | U10: =IFERROR(P10/O10,"") -> 0.51020408 | W10: 42726 | X10: 0 | AA10: 水 | AB10: =IFERROR(AVERAGEIFS($G$8:$G$37,$B$8:$B$37,AA10,$G$8:$G$37,">0"),0) -> 352604.6 | AC10: =COUNTIFS($B$8:$B$37,AA10,$G$8:$G$37,">0") -> 5 | AD10: =IFERROR(SUMIF($B$8:$B$37,AA10,$M$8:$M$37)/SUMIF($B$8:$B$37,AA10,$O$8:$O$37),0) -> 0.30864198 | AE10: =IFERROR(SUMIF($B$8:$B$37,AA10,$G$8:$G$37)/SUMIF($B$8:$B$37,AA10,$M$8:$M$37),0) -> 23506.973
A11: 46116 | B11: =MID("日月火水木金土",WEEKDAY(A11),1) -> 土 | C11: 800000 | D11: =SUM($C$8:C11) -> 2300000 | E11: 143589 | F11: 252249 | G11: =IF(COUNT(E11:F11)=0,"",SUM(E11:F11)) -> 395838 | H11: =IF(G11="","",SUM($G$8:G11)) -> 1237244 | I11: =IF(G11="","",IFERROR(G11/C11,"")) -> 0.4947975 | J11: =IF(H11="","",IFERROR(H11/D11,"")) -> 0.53793217 | K11: =IF(H11="","",IF(D11=0,"",H11-D11)) -> -1062756 | L11: =IF(G11="","—",IF(D11=0,"予算未入力",IF(H11>=D11,"◎ ペース内","▲ 遅れ"))) -> ▲ 遅れ | M11: 18 | N11: 18 | O11: 65 | P11: 25 | R11: =IFERROR(M11/O11,"") -> 0.27692308 | S11: =IFERROR(G11/M11,"") -> 21991 | T11: =IFERROR(N11/M11,"") -> 1 | U11: =IFERROR(P11/O11,"") -> 0.38461538 | X11: 0 | AA11: 木 | AB11: =IFERROR(AVERAGEIFS($G$8:$G$37,$B$8:$B$37,AA11,$G$8:$G$37,">0"),0) -> 218086 | AC11: =COUNTIFS($B$8:$B$37,AA11,$G$8:$G$37,">0") -> 5 | AD11: =IFERROR(SUMIF($B$8:$B$37,AA11,$M$8:$M$37)/SUMIF($B$8:$B$37,AA11,$O$8:$O$37),0) -> 0.24242424 | AE11: =IFERROR(SUMIF($B$8:$B$37,AA11,$G$8:$G$37)/SUMIF($B$8:$B$37,AA11,$M$8:$M$37),0) -> 22717.292
A12: 46117 | B12: =MID("日月火水木金土",WEEKDAY(A12),1) -> 日 | C12: 800000 | D12: =SUM($C$8:C12) -> 3100000 | E12: 29970 | F12: 389469 | G12: =IF(COUNT(E12:F12)=0,"",SUM(E12:F12)) -> 419439 | H12: =IF(G12="","",SUM($G$8:G12)) -> 1656683 | I12: =IF(G12="","",IFERROR(G12/C12,"")) -> 0.52429875 | J12: =IF(H12="","",IFERROR(H12/D12,"")) -> 0.53441387 | K12: =IF(H12="","",IF(D12=0,"",H12-D12)) -> -1443317 | L12: =IF(G12="","—",IF(D12=0,"予算未入力",IF(H12>=D12,"◎ ペース内","▲ 遅れ"))) -> ▲ 遅れ | M12: 20 | N12: 21 | O12: 67 | P12: 37 | R12: =IFERROR(M12/O12,"") -> 0.29850746 | S12: =IFERROR(G12/M12,"") -> 20971.95 | T12: =IFERROR(N12/M12,"") -> 1.05 | U12: =IFERROR(P12/O12,"") -> 0.55223881 | X12: 0 | AA12: 金 | AB12: =IFERROR(AVERAGEIFS($G$8:$G$37,$B$8:$B$37,AA12,$G$8:$G$37,">0"),0) -> 376413.75 | AC12: =COUNTIFS($B$8:$B$37,AA12,$G$8:$G$37,">0") -> 4 | AD12: =IFERROR(SUMIF($B$8:$B$37,AA12,$M$8:$M$37)/SUMIF($B$8:$B$37,AA12,$O$8:$O$37),0) -> 0.32323232 | AE12: =IFERROR(SUMIF($B$8:$B$37,AA12,$G$8:$G$37)/SUMIF($B$8:$B$37,AA12,$M$8:$M$37),0) -> 23525.859
A13: 46118 | B13: =MID("日月火水木金土",WEEKDAY(A13),1) -> 月 | C13: 500000 | D13: =SUM($C$8:C13) -> 3600000 | E13: 72430 | F13: 154830 | G13: =IF(COUNT(E13:F13)=0,"",SUM(E13:F13)) -> 227260 | H13: =IF(G13="","",SUM($G$8:G13)) -> 1883943 | I13: =IF(G13="","",IFERROR(G13/C13,"")) -> 0.45452 | J13: =IF(H13="","",IFERROR(H13/D13,"")) -> 0.5233175 | K13: =IF(H13="","",IF(D13=0,"",H13-D13)) -> -1716057 | L13: =IF(G13="","—",IF(D13=0,"予算未入力",IF(H13>=D13,"◎ ペース内","▲ 遅れ"))) -> ▲ 遅れ | M13: 10 | N13: 10 | O13: 42 | P13: 13 | R13: =IFERROR(M13/O13,"") -> 0.23809524 | S13: =IFERROR(G13/M13,"") -> 22726 | T13: =IFERROR(N13/M13,"") -> 1 | U13: =IFERROR(P13/O13,"") -> 0.30952381 | X13: 0 | AA13: 土 | AB13: =IFERROR(AVERAGEIFS($G$8:$G$37,$B$8:$B$37,AA13,$G$8:$G$37,">0"),0) -> 387582 | AC13: =COUNTIFS($B$8:$B$37,AA13,$G$8:$G$37,">0") -> 4 | AD13: =IFERROR(SUMIF($B$8:$B$37,AA13,$M$8:$M$37)/SUMIF($B$8:$B$37,AA13,$O$8:$O$37),0) -> 0.2605364 | AE13: =IFERROR(SUMIF($B$8:$B$37,AA13,$G$8:$G$37)/SUMIF($B$8:$B$37,AA13,$M$8:$M$37),0) -> 22798.941
A14: 46119 | B14: =MID("日月火水木金土",WEEKDAY(A14),1) -> 火 | C14: 500000 | D14: =SUM($C$8:C14) -> 4100000 | E14: 63410 | F14: 241630 | G14: =IF(COUNT(E14:F14)=0,"",SUM(E14:F14)) -> 305040 | H14: =IF(G14="","",SUM($G$8:G14)) -> 2188983 | I14: =IF(G14="","",IFERROR(G14/C14,"")) -> 0.61008 | J14: =IF(H14="","",IFERROR(H14/D14,"")) -> 0.53389829 | K14: =IF(H14="","",IF(D14=0,"",H14-D14)) -> -1911017 | L14: =IF(G14="","—",IF(D14=0,"予算未入力",IF(H14>=D14,"◎ ペース内","▲ 遅れ"))) -> ▲ 遅れ | M14: 14 | N14: 14 | O14: 63 | P14: 33 | R14: =IFERROR(M14/O14,"") -> 0.22222222 | S14: =IFERROR(G14/M14,"") -> 21788.571 | T14: =IFERROR(N14/M14,"") -> 1 | U14: =IFERROR(P14/O14,"") -> 0.52380952 | W14: 42790 | X14: 0 | AA14: 日 | AB14: =IFERROR(AVERAGEIFS($G$8:$G$37,$B$8:$B$37,AA14,$G$8:$G$37,">0"),0) -> 478389.75 | AC14: =COUNTIFS($B$8:$B$37,AA14,$G$8:$G$37,">0") -> 4 | AD14: =IFERROR(SUMIF($B$8:$B$37,AA14,$M$8:$M$37)/SUMIF($B$8:$B$37,AA14,$O$8:$O$37),0) -> 0.33864542 | AE14: =IFERROR(SUMIF($B$8:$B$37,AA14,$G$8:$G$37)/SUMIF($B$8:$B$37,AA14,$M$8:$M$37),0) -> 22512.459
A15: 46120 | B15: =MID("日月火水木金土",WEEKDAY(A15),1) -> 水 | C15: 500000 | D15: =SUM($C$8:C15) -> 4600000 | E15: 110150 | F15: 194900 | G15: =IF(COUNT(E15:F15)=0,"",SUM(E15:F15)) -> 305050 | H15: =IF(G15="","",SUM($G$8:G15)) -> 2494033 | I15: =IF(G15="","",IFERROR(G15/C15,"")) -> 0.6101 | J15: =IF(H15="","",IFERROR(H15/D15,"")) -> 0.54218109 | K15: =IF(H15="","",IF(D15=0,"",H15-D15)) -> -2105967 | L15: =IF(G15="","—",IF(D15=0,"予算未入力",IF(H15>=D15,"◎ ペース内","▲ 遅れ"))) -> ▲ 遅れ | M15: 14 | N15: 16 | O15: 40 | P15: 24 | R15: =IFERROR(M15/O15,"") -> 0.35 | S15: =IFERROR(G15/M15,"") -> 21789.286 | T15: =IFERROR(N15/M15,"") -> 1.1428571 | U15: =IFERROR(P15/O15,"") -> 0.6 | X15: 0
A16: 46121 | B16: =MID("日月火水木金土",WEEKDAY(A16),1) -> 木 | C16: 500000 | D16: =SUM($C$8:C16) -> 5100000 | E16: 43220 | F16: 122250 | G16: =IF(COUNT(E16:F16)=0,"",SUM(E16:F16)) -> 165470 | H16: =IF(G16="","",SUM($G$8:G16)) -> 2659503 | I16: =IF(G16="","",IFERROR(G16/C16,"")) -> 0.33094 | J16: =IF(H16="","",IFERROR(H16/D16,"")) -> 0.52147118 | K16: =IF(H16="","",IF(D16=0,"",H16-D16)) -> -2440497 | L16: =IF(G16="","—",IF(D16=0,"予算未入力",IF(H16>=D16,"◎ ペース内","▲ 遅れ"))) -> ▲ 遅れ | M16: 7 | N16: 7 | O16: 33 | P16: 16 | R16: =IFERROR(M16/O16,"") -> 0.21212121 | S16: =IFERROR(G16/M16,"") -> 23638.571 | T16: =IFERROR(N16/M16,"") -> 1 | U16: =IFERROR(P16/O16,"") -> 0.48484848 | W16: 42835 | X16: 0 | AA16: ※実績入力後に曜日別の傾向が出ます
A17: 46122 | B17: =MID("日月火水木金土",WEEKDAY(A17),1) -> 金 | C17: 500000 | D17: =SUM($C$8:C17) -> 5600000 | E17: 48620 | F17: 220380 | G17: =IF(COUNT(E17:F17)=0,"",SUM(E17:F17)) -> 269000 | H17: =IF(G17="","",SUM($G$8:G17)) -> 2928503 | I17: =IF(G17="","",IFERROR(G17/C17,"")) -> 0.538 | J17: =IF(H17="","",IFERROR(H17/D17,"")) -> 0.52294696 | K17: =IF(H17="","",IF(D17=0,"",H17-D17)) -> -2671497 | L17: =IF(G17="","—",IF(D17=0,"予算未入力",IF(H17>=D17,"◎ ペース内","▲ 遅れ"))) -> ▲ 遅れ | M17: 10 | N17: 10 | O17: 48 | P17: 19 | R17: =IFERROR(M17/O17,"") -> 0.20833333 | S17: =IFERROR(G17/M17,"") -> 26900 | T17: =IFERROR(N17/M17,"") -> 1 | U17: =IFERROR(P17/O17,"") -> 0.39583333 | W17: 42878 | X17: 0
A18: 46123 | B18: =MID("日月火水木金土",WEEKDAY(A18),1) -> 土 | C18: 800000 | D18: =SUM($C$8:C18) -> 6400000 | E18: 93430 | F18: 160680 | G18: =IF(COUNT(E18:F18)=0,"",SUM(E18:F18)) -> 254110 | H18: =IF(G18="","",SUM($G$8:G18)) -> 3182613 | I18: =IF(G18="","",IFERROR(G18/C18,"")) -> 0.3176375 | J18: =IF(H18="","",IFERROR(H18/D18,"")) -> 0.49728328 | K18: =IF(H18="","",IF(D18=0,"",H18-D18)) -> -3217387 | L18: =IF(G18="","—",IF(D18=0,"予算未入力",IF(H18>=D18,"◎ ペース内","▲ 遅れ"))) -> ▲ 遅れ | M18: 11 | N18: 12 | O18: 60 | P18: 25 | R18: =IFERROR(M18/O18,"") -> 0.18333333 | S18: =IFERROR(G18/M18,"") -> 23100.909 | T18: =IFERROR(N18/M18,"") -> 1.0909091 | U18: =IFERROR(P18/O18,"") -> 0.41666667 | X18: 0 | AA18: ■ 週次サマリー（火曜〜翌月曜） | AH18: 第1火曜 | AI18: =$A$8+MOD(2-WEEKDAY($A$8,2)+7,7) -> 46119
A19: 46124 | B19: =MID("日月火水木金土",WEEKDAY(A19),1) -> 日 | C19: 800000 | D19: =SUM($C$8:C19) -> 7200000 | E19: 44043 | F19: 337467 | G19: =IF(COUNT(E19:F19)=0,"",SUM(E19:F19)) -> 381510 | H19: =IF(G19="","",SUM($G$8:G19)) -> 3564123 | I19: =IF(G19="","",IFERROR(G19/C19,"")) -> 0.4768875 | J19: =IF(H19="","",IFERROR(H19/D19,"")) -> 0.49501708 | K19: =IF(H19="","",IF(D19=0,"",H19-D19)) -> -3635877 | L19: =IF(G19="","—",IF(D19=0,"予算未入力",IF(H19>=D19,"◎ ペース内","▲ 遅れ"))) -> ▲ 遅れ | M19: 17 | N19: 17 | O19: 56 | P19: 34 | R19: =IFERROR(M19/O19,"") -> 0.30357143 | S19: =IFERROR(G19/M19,"") -> 22441.765 | T19: =IFERROR(N19/M19,"") -> 1 | U19: =IFERROR(P19/O19,"") -> 0.60714286 | W19: 42923 | X19: 0 | AA19: 週 | AB19: 期間 | AC19: 売上 | AD19: 決定率 | AE19: 客単価 | AF19: セット率 | AG19: 試着率
A20: 46125 | B20: =MID("日月火水木金土",WEEKDAY(A20),1) -> 月 | C20: 500000 | D20: =SUM($C$8:C20) -> 7700000 | E20: 43720 | F20: 138960 | G20: =IF(COUNT(E20:F20)=0,"",SUM(E20:F20)) -> 182680 | H20: =IF(G20="","",SUM($G$8:G20)) -> 3746803 | I20: =IF(G20="","",IFERROR(G20/C20,"")) -> 0.36536 | J20: =IF(H20="","",IFERROR(H20/D20,"")) -> 0.48659779 | K20: =IF(H20="","",IF(D20=0,"",H20-D20)) -> -3953197 | L20: =IF(G20="","—",IF(D20=0,"予算未入力",IF(H20>=D20,"◎ ペース内","▲ 遅れ"))) -> ▲ 遅れ | M20: 8 | N20: 8 | O20: 44 | P20: 15 | R20: =IFERROR(M20/O20,"") -> 0.18181818 | S20: =IFERROR(G20/M20,"") -> 22835 | T20: =IFERROR(N20/M20,"") -> 1 | U20: =IFERROR(P20/O20,"") -> 0.34090909 | X20: 0 | Y20: ※要確認：旧シートの売上合計と内訳が+4,900円ズレ。合計182,680円に合わせクレジットを134,060→138,960に調整 | AA20: 1 | AB20: =IF($AI$18+7*(1-1)>$A$37,"",TEXT($AI$18+7*(1-1),"m/d")&"-"&TEXT($AI$18+7*(1-1)+6,"m/d")) -> 4/7-4/13 | AC20: =IF($AB20="","",(SUMIFS($G$8:$G$37,$A$8:$A$37,">="&$AI$18+7*(1-1),$A$8:$A$37,"<="&$AI$18+7*(1-1)+6)+SUMIFS('2026年05月'!$G$8:$G$38,'2026年05月'!$A$8:$A$38,">="&$AI$18+7*(1-1),'2026年05月'!$A$8:$A$38,"<="&$AI$18+7*(1-1)+6))) -> 1862860 | AD20: =IF($AB20="","",IFERROR((SUMIFS($M$8:$M$37,$A$8:$A$37,">="&$AI$18+7*(1-1),$A$8:$A$37,"<="&$AI$18+7*(1-1)+6)+SUMIFS('2026年05月'!$M$8:$M$38,'2026年05月'!$A$8:$A$38,">="&$AI$18+7*(1-1),'2026年05月'!$A$8:$A$38,"<="&$AI$18+7*(1-1)+6))/(SUMIFS($O$8:$O$37,$A$8:$A$37,">="&$AI$18+7*(1-1),$A$8:$A$37,"<="&$AI$18+7*(1-1)+6)+SUMIFS('2026年05月'!$O$8:$O$38,'2026年05月'!$A$8:$A$38,">="&$AI$18+7*(1-1),'2026年05月'!$A$8:$A$38,"<="&$AI$18+7*(1-1)+6)),"")) -> 0.23546512 | AE20: =IF($AB20="","",IFERROR((SUMIFS($G$8:$G$37,$A$8:$A$37,">="&$AI$18+7*(1-1),$A$8:$A$37,"<="&$AI$18+7*(1-1)+6)+SUMIFS('2026年05月'!$G$8:$G$38,'2026年05月'!$A$8:$A$38,">="&$AI$18+7*(1-1),'2026年05月'!$A$8:$A$38,"<="&$AI$18+7*(1-1)+6))/(SUMIFS($M$8:$M$37,$A$8:$A$37,">="&$AI$18+7*(1-1),$A$8:$A$37,"<="&$AI$18+7*(1-1)+6)+SUMIFS('2026年05月'!$M$8:$M$38,'2026年05月'!$A$8:$A$38,">="&$AI$18+7*(1-1),'2026年05月'!$A$8:$A$38,"<="&$AI$18+7*(1-1)+6)),"")) -> 22998.272 | AF20: =IF($AB20="","",IFERROR((SUMIFS($N$8:$N$37,$A$8:$A$37,">="&$AI$18+7*(1-1),$A$8:$A$37,"<="&$AI$18+7*(1-1)+6)+SUMIFS('2026年05月'!$N$8:$N$38,'2026年05月'!$A$8:$A$38,">="&$AI$18+7*(1-1),'2026年05月'!$A$8:$A$38,"<="&$AI$18+7*(1-1)+6))/(SUMIFS($M$8:$M$37,$A$8:$A$37,">="&$AI$18+7*(1-1),$A$8:$A$37,"<="&$AI$18+7*(1-1)+6)+SUMIFS('2026年05月'!$M$8:$M$38,'2026年05月'!$A$8:$A$38,">="&$AI$18+7*(1-1),'2026年05月'!$A$8:$A$38,"<="&$AI$18+7*(1-1)+6)),"")) -> 1.037037 | AG20: =IF($AB20="","",IFERROR((SUMIFS($P$8:$P$37,$A$8:$A$37,">="&$AI$18+7*(1-1),$A$8:$A$37,"<="&$AI$18+7*(1-1)+6)+SUMIFS('2026年05月'!$P$8:$P$38,'2026年05月'!$A$8:$A$38,">="&$AI$18+7*(1-1),'2026年05月'!$A$8:$A$38,"<="&$AI$18+7*(1-1)+6))/(SUMIFS($O$8:$O$37,$A$8:$A$37,">="&$AI$18+7*(1-1),$A$8:$A$37,"<="&$AI$18+7*(1-1)+6)+SUMIFS('2026年05月'!$O$8:$O$38,'2026年05月'!$A$8:$A$38,">="&$AI$18+7*(1-1),'2026年05月'!$A$8:$A$38,"<="&$AI$18+7*(1-1)+6)),"")) -> 0.48255814
A21: 46126 | B21: =MID("日月火水木金土",WEEKDAY(A21),1) -> 火 | C21: 500000 | D21: =SUM($C$8:C21) -> 8200000 | E21: 43720 | F21: 350990 | G21: =IF(COUNT(E21:F21)=0,"",SUM(E21:F21)) -> 394710 | H21: =IF(G21="","",SUM($G$8:G21)) -> 4141513 | I21: =IF(G21="","",IFERROR(G21/C21,"")) -> 0.78942 | J21: =IF(H21="","",IFERROR(H21/D21,"")) -> 0.50506256 | K21: =IF(H21="","",IF(D21=0,"",H21-D21)) -> -4058487 | L21: =IF(G21="","—",IF(D21=0,"予算未入力",IF(H21>=D21,"◎ ペース内","▲ 遅れ"))) -> ▲ 遅れ | M21: 13 | N21: 18 | O21: 36 | P21: 12 | R21: =IFERROR(M21/O21,"") -> 0.36111111 | S21: =IFERROR(G21/M21,"") -> 30362.308 | T21: =IFERROR(N21/M21,"") -> 1.3846154 | U21: =IFERROR(P21/O21,"") -> 0.33333333 | W21: 43062 | X21: 0 | Y21: ※要確認：旧シートの売上合計と内訳が+44,110円ズレ。合計394,710円に合わせクレジットを306,880→350,990に調整 | AA21: 2 | AB21: =IF($AI$18+7*(2-1)>$A$37,"",TEXT($AI$18+7*(2-1),"m/d")&"-"&TEXT($AI$18+7*(2-1)+6,"m/d")) -> 4/14-4/20 | AC21: =IF($AB21="","",(SUMIFS($G$8:$G$37,$A$8:$A$37,">="&$AI$18+7*(2-1),$A$8:$A$37,"<="&$AI$18+7*(2-1)+6)+SUMIFS('2026年05月'!$G$8:$G$38,'2026年05月'!$A$8:$A$38,">="&$AI$18+7*(2-1),'2026年05月'!$A$8:$A$38,"<="&$AI$18+7*(2-1)+6))) -> 2595495 | AD21: =IF($AB21="","",IFERROR((SUMIFS($M$8:$M$37,$A$8:$A$37,">="&$AI$18+7*(2-1),$A$8:$A$37,"<="&$AI$18+7*(2-1)+6)+SUMIFS('2026年05月'!$M$8:$M$38,'2026年05月'!$A$8:$A$38,">="&$AI$18+7*(2-1),'2026年05月'!$A$8:$A$38,"<="&$AI$18+7*(2-1)+6))/(SUMIFS($O$8:$O$37,$A$8:$A$37,">="&$AI$18+7*(2-1),$A$8:$A$37,"<="&$AI$18+7*(2-1)+6)+SUMIFS('2026年05月'!$O$8:$O$38,'2026年05月'!$A$8:$A$38,">="&$AI$18+7*(2-1),'2026年05月'!$A$8:$A$38,"<="&$AI$18+7*(2-1)+6)),"")) -> 0.31656805 | AE21: =IF($AB21="","",IFERROR((SUMIFS($G$8:$G$37,$A$8:$A$37,">="&$AI$18+7*(2-1),$A$8:$A$37,"<="&$AI$18+7*(2-1)+6)+SUMIFS('2026年05月'!$G$8:$G$38,'2026年05月'!$A$8:$A$38,">="&$AI$18+7*(2-1),'2026年05月'!$A$8:$A$38,"<="&$AI$18+7*(2-1)+6))/(SUMIFS($M$8:$M$37,$A$8:$A$37,">="&$AI$18+7*(2-1),$A$8:$A$37,"<="&$AI$18+7*(2-1)+6)+SUMIFS('2026年05月'!$M$8:$M$38,'2026年05月'!$A$8:$A$38,">="&$AI$18+7*(2-1),'2026年05月'!$A$8:$A$38,"<="&$AI$18+7*(2-1)+6)),"")) -> 24256.963 | AF21: =IF($AB21="","",IFERROR((SUMIFS($N$8:$N$37,$A$8:$A$37,">="&$AI$18+7*(2-1),$A$8:$A$37,"<="&$AI$18+7*(2-1)+6)+SUMIFS('2026年05月'!$N$8:$N$38,'2026年05月'!$A$8:$A$38,">="&$AI$18+7*(2-1),'2026年05月'!$A$8:$A$38,"<="&$AI$18+7*(2-1)+6))/(SUMIFS($M$8:$M$37,$A$8:$A$37,">="&$AI$18+7*(2-1),$A$8:$A$37,"<="&$AI$18+7*(2-1)+6)+SUMIFS('2026年05月'!$M$8:$M$38,'2026年05月'!$A$8:$A$38,">="&$AI$18+7*(2-1),'2026年05月'!$A$8:$A$38,"<="&$AI$18+7*(2-1)+6)),"")) -> 1.1214953 | AG21: =IF($AB21="","",IFERROR((SUMIFS($P$8:$P$37,$A$8:$A$37,">="&$AI$18+7*(2-1),$A$8:$A$37,"<="&$AI$18+7*(2-1)+6)+SUMIFS('2026年05月'!$P$8:$P$38,'2026年05月'!$A$8:$A$38,">="&$AI$18+7*(2-1),'2026年05月'!$A$8:$A$38,"<="&$AI$18+7*(2-1)+6))/(SUMIFS($O$8:$O$37,$A$8:$A$37,">="&$AI$18+7*(2-1),$A$8:$A$37,"<="&$AI$18+7*(2-1)+6)+SUMIFS('2026年05月'!$O$8:$O$38,'2026年05月'!$A$8:$A$38,">="&$AI$18+7*(2-1),'2026年05月'!$A$8:$A$38,"<="&$AI$18+7*(2-1)+6)),"")) -> 0.48816568
A22: 46127 | B22: =MID("日月火水木金土",WEEKDAY(A22),1) -> 水 | C22: 500000 | D22: =SUM($C$8:C22) -> 8700000 | E22: 141345 | F22: 219930 | G22: =IF(COUNT(E22:F22)=0,"",SUM(E22:F22)) -> 361275 | H22: =IF(G22="","",SUM($G$8:G22)) -> 4502788 | I22: =IF(G22="","",IFERROR(G22/C22,"")) -> 0.72255 | J22: =IF(H22="","",IFERROR(H22/D22,"")) -> 0.51756184 | K22: =IF(H22="","",IF(D22=0,"",H22-D22)) -> -4197212 | L22: =IF(G22="","—",IF(D22=0,"予算未入力",IF(H22>=D22,"◎ ペース内","▲ 遅れ"))) -> ▲ 遅れ | M22: 15 | N22: 17 | O22: 27 | P22: 19 | R22: =IFERROR(M22/O22,"") -> 0.55555556 | S22: =IFERROR(G22/M22,"") -> 24085 | T22: =IFERROR(N22/M22,"") -> 1.1333333 | U22: =IFERROR(P22/O22,"") -> 0.7037037 | W22: 43078 | X22: 0 | AA22: 3 | AB22: =IF($AI$18+7*(3-1)>$A$37,"",TEXT($AI$18+7*(3-1),"m/d")&"-"&TEXT($AI$18+7*(3-1)+6,"m/d")) -> 4/21-4/27 | AC22: =IF($AB22="","",(SUMIFS($G$8:$G$37,$A$8:$A$37,">="&$AI$18+7*(3-1),$A$8:$A$37,"<="&$AI$18+7*(3-1)+6)+SUMIFS('2026年05月'!$G$8:$G$38,'2026年05月'!$A$8:$A$38,">="&$AI$18+7*(3-1),'2026年05月'!$A$8:$A$38,"<="&$AI$18+7*(3-1)+6))) -> 2390767 | AD22: =IF($AB22="","",IFERROR((SUMIFS($M$8:$M$37,$A$8:$A$37,">="&$AI$18+7*(3-1),$A$8:$A$37,"<="&$AI$18+7*(3-1)+6)+SUMIFS('2026年05月'!$M$8:$M$38,'2026年05月'!$A$8:$A$38,">="&$AI$18+7*(3-1),'2026年05月'!$A$8:$A$38,"<="&$AI$18+7*(3-1)+6))/(SUMIFS($O$8:$O$37,$A$8:$A$37,">="&$AI$18+7*(3-1),$A$8:$A$37,"<="&$AI$18+7*(3-1)+6)+SUMIFS('2026年05月'!$O$8:$O$38,'2026年05月'!$A$8:$A$38,">="&$AI$18+7*(3-1),'2026年05月'!$A$8:$A$38,"<="&$AI$18+7*(3-1)+6)),"")) -> 0.28448276 | AE22: =IF($AB22="","",IFERROR((SUMIFS($G$8:$G$37,$A$8:$A$37,">="&$AI$18+7*(3-1),$A$8:$A$37,"<="&$AI$18+7*(3-1)+6)+SUMIFS('2026年05月'!$G$8:$G$38,'2026年05月'!$A$8:$A$38,">="&$AI$18+7*(3-1),'2026年05月'!$A$8:$A$38,"<="&$AI$18+7*(3-1)+6))/(SUMIFS($M$8:$M$37,$A$8:$A$37,">="&$AI$18+7*(3-1),$A$8:$A$37,"<="&$AI$18+7*(3-1)+6)+SUMIFS('2026年05月'!$M$8:$M$38,'2026年05月'!$A$8:$A$38,">="&$AI$18+7*(3-1),'2026年05月'!$A$8:$A$38,"<="&$AI$18+7*(3-1)+6)),"")) -> 24149.162 | AF22: =IF($AB22="","",IFERROR((SUMIFS($N$8:$N$37,$A$8:$A$37,">="&$AI$18+7*(3-1),$A$8:$A$37,"<="&$AI$18+7*(3-1)+6)+SUMIFS('2026年05月'!$N$8:$N$38,'2026年05月'!$A$8:$A$38,">="&$AI$18+7*(3-1),'2026年05月'!$A$8:$A$38,"<="&$AI$18+7*(3-1)+6))/(SUMIFS($M$8:$M$37,$A$8:$A$37,">="&$AI$18+7*(3-1),$A$8:$A$37,"<="&$AI$18+7*(3-1)+6)+SUMIFS('2026年05月'!$M$8:$M$38,'2026年05月'!$A$8:$A$38,">="&$AI$18+7*(3-1),'2026年05月'!$A$8:$A$38,"<="&$AI$18+7*(3-1)+6)),"")) -> 1.1515152 | AG22: =IF($AB22="","",IFERROR((SUMIFS($P$8:$P$37,$A$8:$A$37,">="&$AI$18+7*(3-1),$A$8:$A$37,"<="&$AI$18+7*(3-1)+6)+SUMIFS('2026年05月'!$P$8:$P$38,'2026年05月'!$A$8:$A$38,">="&$AI$18+7*(3-1),'2026年05月'!$A$8:$A$38,"<="&$AI$18+7*(3-1)+6))/(SUMIFS($O$8:$O$37,$A$8:$A$37,">="&$AI$18+7*(3-1),$A$8:$A$37,"<="&$AI$18+7*(3-1)+6)+SUMIFS('2026年05月'!$O$8:$O$38,'2026年05月'!$A$8:$A$38,">="&$AI$18+7*(3-1),'2026年05月'!$A$8:$A$38,"<="&$AI$18+7*(3-1)+6)),"")) -> 0.46551724
A23: 46128 | B23: =MID("日月火水木金土",WEEKDAY(A23),1) -> 木 | C23: 500000 | D23: =SUM($C$8:C23) -> 9200000 | E23: 49710 | F23: 232000 | G23: =IF(COUNT(E23:F23)=0,"",SUM(E23:F23)) -> 281710 | H23: =IF(G23="","",SUM($G$8:G23)) -> 4784498 | I23: =IF(G23="","",IFERROR(G23/C23,"")) -> 0.56342 | J23: =IF(H23="","",IFERROR(H23/D23,"")) -> 0.52005413 | K23: =IF(H23="","",IF(D23=0,"",H23-D23)) -> -4415502 | L23: =IF(G23="","—",IF(D23=0,"予算未入力",IF(H23>=D23,"◎ ペース内","▲ 遅れ"))) -> ▲ 遅れ | M23: 12 | N23: 12 | O23: 52 | P23: 38 | R23: =IFERROR(M23/O23,"") -> 0.23076923 | S23: =IFERROR(G23/M23,"") -> 23475.833 | T23: =IFERROR(N23/M23,"") -> 1 | U23: =IFERROR(P23/O23,"") -> 0.73076923 | W23: 43159 | X23: 0 | AA23: 4 | AB23: =IF($AI$18+7*(4-1)>$A$37,"",TEXT($AI$18+7*(4-1),"m/d")&"-"&TEXT($AI$18+7*(4-1)+6,"m/d")) -> 4/28-5/4 | AC23: =IF($AB23="","",(SUMIFS($G$8:$G$37,$A$8:$A$37,">="&$AI$18+7*(4-1),$A$8:$A$37,"<="&$AI$18+7*(4-1)+6)+SUMIFS('2026年05月'!$G$8:$G$38,'2026年05月'!$A$8:$A$38,">="&$AI$18+7*(4-1),'2026年05月'!$A$8:$A$38,"<="&$AI$18+7*(4-1)+6))) -> 3137766 | AD23: =IF($AB23="","",IFERROR((SUMIFS($M$8:$M$37,$A$8:$A$37,">="&$AI$18+7*(4-1),$A$8:$A$37,"<="&$AI$18+7*(4-1)+6)+SUMIFS('2026年05月'!$M$8:$M$38,'2026年05月'!$A$8:$A$38,">="&$AI$18+7*(4-1),'2026年05月'!$A$8:$A$38,"<="&$AI$18+7*(4-1)+6))/(SUMIFS($O$8:$O$37,$A$8:$A$37,">="&$AI$18+7*(4-1),$A$8:$A$37,"<="&$AI$18+7*(4-1)+6)+SUMIFS('2026年05月'!$O$8:$O$38,'2026年05月'!$A$8:$A$38,">="&$AI$18+7*(4-1),'2026年05月'!$A$8:$A$38,"<="&$AI$18+7*(4-1)+6)),"")) -> 0.33253589 | AE23: =IF($AB23="","",IFERROR((SUMIFS($G$8:$G$37,$A$8:$A$37,">="&$AI$18+7*(4-1),$A$8:$A$37,"<="&$AI$18+7*(4-1)+6)+SUMIFS('2026年05月'!$G$8:$G$38,'2026年05月'!$A$8:$A$38,">="&$AI$18+7*(4-1),'2026年05月'!$A$8:$A$38,"<="&$AI$18+7*(4-1)+6))/(SUMIFS($M$8:$M$37,$A$8:$A$37,">="&$AI$18+7*(4-1),$A$8:$A$37,"<="&$AI$18+7*(4-1)+6)+SUMIFS('2026年05月'!$M$8:$M$38,'2026年05月'!$A$8:$A$38,">="&$AI$18+7*(4-1),'2026年05月'!$A$8:$A$38,"<="&$AI$18+7*(4-1)+6)),"")) -> 22573.856 | AF23: =IF($AB23="","",IFERROR((SUMIFS($N$8:$N$37,$A$8:$A$37,">="&$AI$18+7*(4-1),$A$8:$A$37,"<="&$AI$18+7*(4-1)+6)+SUMIFS('2026年05月'!$N$8:$N$38,'2026年05月'!$A$8:$A$38,">="&$AI$18+7*(4-1),'2026年05月'!$A$8:$A$38,"<="&$AI$18+7*(4-1)+6))/(SUMIFS($M$8:$M$37,$A$8:$A$37,">="&$AI$18+7*(4-1),$A$8:$A$37,"<="&$AI$18+7*(4-1)+6)+SUMIFS('2026年05月'!$M$8:$M$38,'2026年05月'!$A$8:$A$38,">="&$AI$18+7*(4-1),'2026年05月'!$A$8:$A$38,"<="&$AI$18+7*(4-1)+6)),"")) -> 1.1007194 | AG23: =IF($AB23="","",IFERROR((SUMIFS($P$8:$P$37,$A$8:$A$37,">="&$AI$18+7*(4-1),$A$8:$A$37,"<="&$AI$18+7*(4-1)+6)+SUMIFS('2026年05月'!$P$8:$P$38,'2026年05月'!$A$8:$A$38,">="&$AI$18+7*(4-1),'2026年05月'!$A$8:$A$38,"<="&$AI$18+7*(4-1)+6))/(SUMIFS($O$8:$O$37,$A$8:$A$37,">="&$AI$18+7*(4-1),$A$8:$A$37,"<="&$AI$18+7*(4-1)+6)+SUMIFS('2026年05月'!$O$8:$O$38,'2026年05月'!$A$8:$A$38,">="&$AI$18+7*(4-1),'2026年05月'!$A$8:$A$38,"<="&$AI$18+7*(4-1)+6)),"")) -> 0.57177033
A24: 46129 | B24: =MID("日月火水木金土",WEEKDAY(A24),1) -> 金 | C24: 500000 | D24: =SUM($C$8:C24) -> 9700000 | E24: 69730 | F24: 193360 | G24: =IF(COUNT(E24:F24)=0,"",SUM(E24:F24)) -> 263090 | H24: =IF(G24="","",SUM($G$8:G24)) -> 5047588 | I24: =IF(G24="","",IFERROR(G24/C24,"")) -> 0.52618 | J24: =IF(H24="","",IFERROR(H24/D24,"")) -> 0.5203699 | K24: =IF(H24="","",IF(D24=0,"",H24-D24)) -> -4652412 | L24: =IF(G24="","—",IF(D24=0,"予算未入力",IF(H24>=D24,"◎ ペース内","▲ 遅れ"))) -> ▲ 遅れ | M24: 11 | N24: 12 | O24: 45 | P24: 17 | Q24: 36 | R24: =IFERROR(M24/O24,"") -> 0.24444444 | S24: =IFERROR(G24/M24,"") -> 23917.273 | T24: =IFERROR(N24/M24,"") -> 1.0909091 | U24: =IFERROR(P24/O24,"") -> 0.37777778 | W24: 43305 | X24: 0 | AA24: 5 | AB24: =IF($AI$18+7*(5-1)>$A$37,"",TEXT($AI$18+7*(5-1),"m/d")&"-"&TEXT($AI$18+7*(5-1)+6,"m/d")) | AC24: =IF($AB24="","",(SUMIFS($G$8:$G$37,$A$8:$A$37,">="&$AI$18+7*(5-1),$A$8:$A$37,"<="&$AI$18+7*(5-1)+6)+SUMIFS('2026年05月'!$G$8:$G$38,'2026年05月'!$A$8:$A$38,">="&$AI$18+7*(5-1),'2026年05月'!$A$8:$A$38,"<="&$AI$18+7*(5-1)+6))) | AD24: =IF($AB24="","",IFERROR((SUMIFS($M$8:$M$37,$A$8:$A$37,">="&$AI$18+7*(5-1),$A$8:$A$37,"<="&$AI$18+7*(5-1)+6)+SUMIFS('2026年05月'!$M$8:$M$38,'2026年05月'!$A$8:$A$38,">="&$AI$18+7*(5-1),'2026年05月'!$A$8:$A$38,"<="&$AI$18+7*(5-1)+6))/(SUMIFS($O$8:$O$37,$A$8:$A$37,">="&$AI$18+7*(5-1),$A$8:$A$37,"<="&$AI$18+7*(5-1)+6)+SUMIFS('2026年05月'!$O$8:$O$38,'2026年05月'!$A$8:$A$38,">="&$AI$18+7*(5-1),'2026年05月'!$A$8:$A$38,"<="&$AI$18+7*(5-1)+6)),"")) | AE24: =IF($AB24="","",IFERROR((SUMIFS($G$8:$G$37,$A$8:$A$37,">="&$AI$18+7*(5-1),$A$8:$A$37,"<="&$AI$18+7*(5-1)+6)+SUMIFS('2026年05月'!$G$8:$G$38,'2026年05月'!$A$8:$A$38,">="&$AI$18+7*(5-1),'2026年05月'!$A$8:$A$38,"<="&$AI$18+7*(5-1)+6))/(SUMIFS($M$8:$M$37,$A$8:$A$37,">="&$AI$18+7*(5-1),$A$8:$A$37,"<="&$AI$18+7*(5-1)+6)+SUMIFS('2026年05月'!$M$8:$M$38,'2026年05月'!$A$8:$A$38,">="&$AI$18+7*(5-1),'2026年05月'!$A$8:$A$38,"<="&$AI$18+7*(5-1)+6)),"")) | AF24: =IF($AB24="","",IFERROR((SUMIFS($N$8:$N$37,$A$8:$A$37,">="&$AI$18+7*(5-1),$A$8:$A$37,"<="&$AI$18+7*(5-1)+6)+SUMIFS('2026年05月'!$N$8:$N$38,'2026年05月'!$A$8:$A$38,">="&$AI$18+7*(5-1),'2026年05月'!$A$8:$A$38,"<="&$AI$18+7*(5-1)+6))/(SUMIFS($M$8:$M$37,$A$8:$A$37,">="&$AI$18+7*(5-1),$A$8:$A$37,"<="&$AI$18+7*(5-1)+6)+SUMIFS('2026年05月'!$M$8:$M$38,'2026年05月'!$A$8:$A$38,">="&$AI$18+7*(5-1),'2026年05月'!$A$8:$A$38,"<="&$AI$18+7*(5-1)+6)),"")) | AG24: =IF($AB24="","",IFERROR((SUMIFS($P$8:$P$37,$A$8:$A$37,">="&$AI$18+7*(5-1),$A$8:$A$37,"<="&$AI$18+7*(5-1)+6)+SUMIFS('2026年05月'!$P$8:$P$38,'2026年05月'!$A$8:$A$38,">="&$AI$18+7*(5-1),'2026年05月'!$A$8:$A$38,"<="&$AI$18+7*(5-1)+6))/(SUMIFS($O$8:$O$37,$A$8:$A$37,">="&$AI$18+7*(5-1),$A$8:$A$37,"<="&$AI$18+7*(5-1)+6)+SUMIFS('2026年05月'!$O$8:$O$38,'2026年05月'!$A$8:$A$38,">="&$AI$18+7*(5-1),'2026年05月'!$A$8:$A$38,"<="&$AI$18+7*(5-1)+6)),""))
A25: 46130 | B25: =MID("日月火水木金土",WEEKDAY(A25),1) -> 土 | C25: 800000 | D25: =SUM($C$8:C25) -> 10500000 | E25: 141940 | F25: 345030 | G25: =IF(COUNT(E25:F25)=0,"",SUM(E25:F25)) -> 486970 | H25: =IF(G25="","",SUM($G$8:G25)) -> 5534558 | I25: =IF(G25="","",IFERROR(G25/C25,"")) -> 0.6087125 | J25: =IF(H25="","",IFERROR(H25/D25,"")) -> 0.52710076 | K25: =IF(H25="","",IF(D25=0,"",H25-D25)) -> -4965442 | L25: =IF(G25="","—",IF(D25=0,"予算未入力",IF(H25>=D25,"◎ ペース内","▲ 遅れ"))) -> ▲ 遅れ | M25: 21 | N25: 22 | O25: 74 | P25: 35 | Q25: 55 | R25: =IFERROR(M25/O25,"") -> 0.28378378 | S25: =IFERROR(G25/M25,"") -> 23189.048 | T25: =IFERROR(N25/M25,"") -> 1.047619 | U25: =IFERROR(P25/O25,"") -> 0.47297297 | X25: 0 | AA25: 6 | AB25: =IF($AI$18+7*(6-1)>$A$37,"",TEXT($AI$18+7*(6-1),"m/d")&"-"&TEXT($AI$18+7*(6-1)+6,"m/d")) | AC25: =IF($AB25="","",(SUMIFS($G$8:$G$37,$A$8:$A$37,">="&$AI$18+7*(6-1),$A$8:$A$37,"<="&$AI$18+7*(6-1)+6)+SUMIFS('2026年05月'!$G$8:$G$38,'2026年05月'!$A$8:$A$38,">="&$AI$18+7*(6-1),'2026年05月'!$A$8:$A$38,"<="&$AI$18+7*(6-1)+6))) | AD25: =IF($AB25="","",IFERROR((SUMIFS($M$8:$M$37,$A$8:$A$37,">="&$AI$18+7*(6-1),$A$8:$A$37,"<="&$AI$18+7*(6-1)+6)+SUMIFS('2026年05月'!$M$8:$M$38,'2026年05月'!$A$8:$A$38,">="&$AI$18+7*(6-1),'2026年05月'!$A$8:$A$38,"<="&$AI$18+7*(6-1)+6))/(SUMIFS($O$8:$O$37,$A$8:$A$37,">="&$AI$18+7*(6-1),$A$8:$A$37,"<="&$AI$18+7*(6-1)+6)+SUMIFS('2026年05月'!$O$8:$O$38,'2026年05月'!$A$8:$A$38,">="&$AI$18+7*(6-1),'2026年05月'!$A$8:$A$38,"<="&$AI$18+7*(6-1)+6)),"")) | AE25: =IF($AB25="","",IFERROR((SUMIFS($G$8:$G$37,$A$8:$A$37,">="&$AI$18+7*(6-1),$A$8:$A$37,"<="&$AI$18+7*(6-1)+6)+SUMIFS('2026年05月'!$G$8:$G$38,'2026年05月'!$A$8:$A$38,">="&$AI$18+7*(6-1),'2026年05月'!$A$8:$A$38,"<="&$AI$18+7*(6-1)+6))/(SUMIFS($M$8:$M$37,$A$8:$A$37,">="&$AI$18+7*(6-1),$A$8:$A$37,"<="&$AI$18+7*(6-1)+6)+SUMIFS('2026年05月'!$M$8:$M$38,'2026年05月'!$A$8:$A$38,">="&$AI$18+7*(6-1),'2026年05月'!$A$8:$A$38,"<="&$AI$18+7*(6-1)+6)),"")) | AF25: =IF($AB25="","",IFERROR((SUMIFS($N$8:$N$37,$A$8:$A$37,">="&$AI$18+7*(6-1),$A$8:$A$37,"<="&$AI$18+7*(6-1)+6)+SUMIFS('2026年05月'!$N$8:$N$38,'2026年05月'!$A$8:$A$38,">="&$AI$18+7*(6-1),'2026年05月'!$A$8:$A$38,"<="&$AI$18+7*(6-1)+6))/(SUMIFS($M$8:$M$37,$A$8:$A$37,">="&$AI$18+7*(6-1),$A$8:$A$37,"<="&$AI$18+7*(6-1)+6)+SUMIFS('2026年05月'!$M$8:$M$38,'2026年05月'!$A$8:$A$38,">="&$AI$18+7*(6-1),'2026年05月'!$A$8:$A$38,"<="&$AI$18+7*(6-1)+6)),"")) | AG25: =IF($AB25="","",IFERROR((SUMIFS($P$8:$P$37,$A$8:$A$37,">="&$AI$18+7*(6-1),$A$8:$A$37,"<="&$AI$18+7*(6-1)+6)+SUMIFS('2026年05月'!$P$8:$P$38,'2026年05月'!$A$8:$A$38,">="&$AI$18+7*(6-1),'2026年05月'!$A$8:$A$38,"<="&$AI$18+7*(6-1)+6))/(SUMIFS($O$8:$O$37,$A$8:$A$37,">="&$AI$18+7*(6-1),$A$8:$A$37,"<="&$AI$18+7*(6-1)+6)+SUMIFS('2026年05月'!$O$8:$O$38,'2026年05月'!$A$8:$A$38,">="&$AI$18+7*(6-1),'2026年05月'!$A$8:$A$38,"<="&$AI$18+7*(6-1)+6)),""))
A26: 46131 | B26: =MID("日月火水木金土",WEEKDAY(A26),1) -> 日 | C26: 800000 | D26: =SUM($C$8:C26) -> 11300000 | E26: 88320 | F26: 459850 | G26: =IF(COUNT(E26:F26)=0,"",SUM(E26:F26)) -> 548170 | H26: =IF(G26="","",SUM($G$8:G26)) -> 6082728 | I26: =IF(G26="","",IFERROR(G26/C26,"")) -> 0.6852125 | J26: =IF(H26="","",IFERROR(H26/D26,"")) -> 0.53829451 | K26: =IF(H26="","",IF(D26=0,"",H26-D26)) -> -5217272 | L26: =IF(G26="","—",IF(D26=0,"予算未入力",IF(H26>=D26,"◎ ペース内","▲ 遅れ"))) -> ▲ 遅れ | M26: 24 | N26: 26 | O26: 62 | P26: 27 | Q26: 60 | R26: =IFERROR(M26/O26,"") -> 0.38709677 | S26: =IFERROR(G26/M26,"") -> 22840.417 | T26: =IFERROR(N26/M26,"") -> 1.0833333 | U26: =IFERROR(P26/O26,"") -> 0.43548387 | W26: 43533 | X26: 0 | Y26: ※要確認：旧シートの売上合計と内訳が+210,350円ズレ。合計548,170円に合わせクレジットを249,500→459,850に調整 | AA26: ※期間ラベルは第1火曜から自動生成。決定率・客単価・セット率・試着率は「週合計÷週合計」
A27: 46132 | B27: =MID("日月火水木金土",WEEKDAY(A27),1) -> 月 | C27: 500000 | D27: =SUM($C$8:C27) -> 11800000 | E27: 48120 | F27: 211450 | G27: =IF(COUNT(E27:F27)=0,"",SUM(E27:F27)) -> 259570 | H27: =IF(G27="","",SUM($G$8:G27)) -> 6342298 | I27: =IF(G27="","",IFERROR(G27/C27,"")) -> 0.51914 | J27: =IF(H27="","",IFERROR(H27/D27,"")) -> 0.53748288 | K27: =IF(H27="","",IF(D27=0,"",H27-D27)) -> -5457702 | L27: =IF(G27="","—",IF(D27=0,"予算未入力",IF(H27>=D27,"◎ ペース内","▲ 遅れ"))) -> ▲ 遅れ | M27: 11 | N27: 13 | O27: 42 | P27: 17 | Q27: 36 | R27: =IFERROR(M27/O27,"") -> 0.26190476 | S27: =IFERROR(G27/M27,"") -> 23597.273 | T27: =IFERROR(N27/M27,"") -> 1.1818182 | U27: =IFERROR(P27/O27,"") -> 0.4047619 | W27: 43604 | X27: 0 | AA27: ※最終週は翌月にまたぐため、2026年05月シートの実績も自動で合算します
A28: 46133 | B28: =MID("日月火水木金土",WEEKDAY(A28),1) -> 火 | C28: 500000 | D28: =SUM($C$8:C28) -> 12300000 | E28: 48120 | F28: 212270 | G28: =IF(COUNT(E28:F28)=0,"",SUM(E28:F28)) -> 260390 | H28: =IF(G28="","",SUM($G$8:G28)) -> 6602688 | I28: =IF(G28="","",IFERROR(G28/C28,"")) -> 0.52078 | J28: =IF(H28="","",IFERROR(H28/D28,"")) -> 0.5368039 | K28: =IF(H28="","",IF(D28=0,"",H28-D28)) -> -5697312 | L28: =IF(G28="","—",IF(D28=0,"予算未入力",IF(H28>=D28,"◎ ペース内","▲ 遅れ"))) -> ▲ 遅れ | M28: 11 | N28: 12 | O28: 53 | P28: 20 | Q28: 45 | R28: =IFERROR(M28/O28,"") -> 0.20754717 | S28: =IFERROR(G28/M28,"") -> 23671.818 | T28: =IFERROR(N28/M28,"") -> 1.0909091 | U28: =IFERROR(P28/O28,"") -> 0.37735849 | W28: 43732 | X28: 0 | Y28: ※要確認：旧シートの売上合計と内訳が+30円ズレ。合計260,390円に合わせクレジットを212,240→212,270に調整 | AA28: ※月初の月曜まで（例：6/1）は前月シートの最終週に含まれます
A29: 46134 | B29: =MID("日月火水木金土",WEEKDAY(A29),1) -> 水 | C29: 600000 | D29: =SUM($C$8:C29) -> 12900000 | E29: 41520 | F29: 338380 | G29: =IF(COUNT(E29:F29)=0,"",SUM(E29:F29)) -> 379900 | H29: =IF(G29="","",SUM($G$8:G29)) -> 6982588 | I29: =IF(G29="","",IFERROR(G29/C29,"")) -> 0.63316667 | J29: =IF(H29="","",IFERROR(H29/D29,"")) -> 0.54128589 | K29: =IF(H29="","",IF(D29=0,"",H29-D29)) -> -5917412 | L29: =IF(G29="","—",IF(D29=0,"予算未入力",IF(H29>=D29,"◎ ペース内","▲ 遅れ"))) -> ▲ 遅れ | M29: 15 | N29: 20 | O29: 63 | P29: 20 | Q29: 67 | R29: =IFERROR(M29/O29,"") -> 0.23809524 | S29: =IFERROR(G29/M29,"") -> 25326.667 | T29: =IFERROR(N29/M29,"") -> 1.3333333 | U29: =IFERROR(P29/O29,"") -> 0.31746032 | W29: 43777 | X29: 0
A30: 46135 | B30: =MID("日月火水木金土",WEEKDAY(A30),1) -> 木 | C30: 600000 | D30: =SUM($C$8:C30) -> 13500000 | E30: 42730 | F30: 23810 | G30: =IF(COUNT(E30:F30)=0,"",SUM(E30:F30)) -> 66540 | H30: =IF(G30="","",SUM($G$8:G30)) -> 7049128 | I30: =IF(G30="","",IFERROR(G30/C30,"")) -> 0.1109 | J30: =IF(H30="","",IFERROR(H30/D30,"")) -> 0.52215763 | K30: =IF(H30="","",IF(D30=0,"",H30-D30)) -> -6450872 | L30: =IF(G30="","—",IF(D30=0,"予算未入力",IF(H30>=D30,"◎ ペース内","▲ 遅れ"))) -> ▲ 遅れ | M30: 3 | N30: 4 | O30: 14 | P30: 9 | Q30: 15 | R30: =IFERROR(M30/O30,"") -> 0.21428571 | S30: =IFERROR(G30/M30,"") -> 22180 | T30: =IFERROR(N30/M30,"") -> 1.3333333 | U30: =IFERROR(P30/O30,"") -> 0.64285714 | W30: 43870 | X30: 0
A31: 46136 | B31: =MID("日月火水木金土",WEEKDAY(A31),1) -> 金 | C31: 600000 | D31: =SUM($C$8:C31) -> 14100000 | E31: 83640 | F31: 388867 | G31: =IF(COUNT(E31:F31)=0,"",SUM(E31:F31)) -> 472507 | H31: =IF(G31="","",SUM($G$8:G31)) -> 7521635 | I31: =IF(G31="","",IFERROR(G31/C31,"")) -> 0.78751167 | J31: =IF(H31="","",IFERROR(H31/D31,"")) -> 0.53344929 | K31: =IF(H31="","",IF(D31=0,"",H31-D31)) -> -6578365 | L31: =IF(G31="","—",IF(D31=0,"予算未入力",IF(H31>=D31,"◎ ペース内","▲ 遅れ"))) -> ▲ 遅れ | M31: 18 | N31: 22 | O31: 56 | P31: 28 | Q31: 53 | R31: =IFERROR(M31/O31,"") -> 0.32142857 | S31: =IFERROR(G31/M31,"") -> 26250.389 | T31: =IFERROR(N31/M31,"") -> 1.2222222 | U31: =IFERROR(P31/O31,"") -> 0.5 | W31: 43953 | X31: 0
A32: 46137 | B32: =MID("日月火水木金土",WEEKDAY(A32),1) -> 土 | C32: 800000 | D32: =SUM($C$8:C32) -> 14900000 | E32: 90790 | F32: 322620 | G32: =IF(COUNT(E32:F32)=0,"",SUM(E32:F32)) -> 413410 | H32: =IF(G32="","",SUM($G$8:G32)) -> 7935045 | I32: =IF(G32="","",IFERROR(G32/C32,"")) -> 0.5167625 | J32: =IF(H32="","",IFERROR(H32/D32,"")) -> 0.53255336 | K32: =IF(H32="","",IF(D32=0,"",H32-D32)) -> -6964955 | L32: =IF(G32="","—",IF(D32=0,"予算未入力",IF(H32>=D32,"◎ ペース内","▲ 遅れ"))) -> ▲ 遅れ | M32: 18 | N32: 19 | O32: 62 | P32: 27 | Q32: 53 | R32: =IFERROR(M32/O32,"") -> 0.29032258 | S32: =IFERROR(G32/M32,"") -> 22967.222 | T32: =IFERROR(N32/M32,"") -> 1.0555556 | U32: =IFERROR(P32/O32,"") -> 0.43548387 | W32: 44008 | X32: 0
A33: 46138 | B33: =MID("日月火水木金土",WEEKDAY(A33),1) -> 日 | C33: 800000 | D33: =SUM($C$8:C33) -> 15700000 | E33: 52460 | F33: 511980 | G33: =IF(COUNT(E33:F33)=0,"",SUM(E33:F33)) -> 564440 | H33: =IF(G33="","",SUM($G$8:G33)) -> 8499485 | I33: =IF(G33="","",IFERROR(G33/C33,"")) -> 0.70555 | J33: =IF(H33="","",IFERROR(H33/D33,"")) -> 0.54136847 | K33: =IF(H33="","",IF(D33=0,"",H33-D33)) -> -7200515 | L33: =IF(G33="","—",IF(D33=0,"予算未入力",IF(H33>=D33,"◎ ペース内","▲ 遅れ"))) -> ▲ 遅れ | M33: 24 | N33: 26 | O33: 66 | P33: 45 | Q33: 53 | R33: =IFERROR(M33/O33,"") -> 0.36363636 | S33: =IFERROR(G33/M33,"") -> 23518.333 | T33: =IFERROR(N33/M33,"") -> 1.0833333 | U33: =IFERROR(P33/O33,"") -> 0.68181818 | W33: 44051 | X33: 0 | Y33: ※要確認：旧シートの売上合計と内訳が-60,000円ズレ。合計564,440円に合わせクレジットを571,980→511,980に調整
A34: 46139 | B34: =MID("日月火水木金土",WEEKDAY(A34),1) -> 月 | C34: 600000 | D34: =SUM($C$8:C34) -> 16300000 | E34: 140040 | F34: 93540 | G34: =IF(COUNT(E34:F34)=0,"",SUM(E34:F34)) -> 233580 | H34: =IF(G34="","",SUM($G$8:G34)) -> 8733065 | I34: =IF(G34="","",IFERROR(G34/C34,"")) -> 0.3893 | J34: =IF(H34="","",IFERROR(H34/D34,"")) -> 0.53577086 | K34: =IF(H34="","",IF(D34=0,"",H34-D34)) -> -7566935 | L34: =IF(G34="","—",IF(D34=0,"予算未入力",IF(H34>=D34,"◎ ペース内","▲ 遅れ"))) -> ▲ 遅れ | M34: 10 | N34: 11 | O34: 34 | P34: 13 | Q34: 23 | R34: =IFERROR(M34/O34,"") -> 0.29411765 | S34: =IFERROR(G34/M34,"") -> 23358 | T34: =IFERROR(N34/M34,"") -> 1.1 | U34: =IFERROR(P34/O34,"") -> 0.38235294 | W34: 44085 | X34: 0
A35: 46140 | B35: =MID("日月火水木金土",WEEKDAY(A35),1) -> 火 | C35: 700000 | D35: =SUM($C$8:C35) -> 17000000 | E35: 45920 | F35: 132530 | G35: =IF(COUNT(E35:F35)=0,"",SUM(E35:F35)) -> 178450 | H35: =IF(G35="","",SUM($G$8:G35)) -> 8911515 | I35: =IF(G35="","",IFERROR(G35/C35,"")) -> 0.25492857 | J35: =IF(H35="","",IFERROR(H35/D35,"")) -> 0.52420676 | K35: =IF(H35="","",IF(D35=0,"",H35-D35)) -> -8088485 | L35: =IF(G35="","—",IF(D35=0,"予算未入力",IF(H35>=D35,"◎ ペース内","▲ 遅れ"))) -> ▲ 遅れ | M35: 8 | N35: 8 | O35: 24 | P35: 10 | Q35: 24 | R35: =IFERROR(M35/O35,"") -> 0.33333333 | S35: =IFERROR(G35/M35,"") -> 22306.25 | T35: =IFERROR(N35/M35,"") -> 1 | U35: =IFERROR(P35/O35,"") -> 0.41666667 | W35: 44087 | X35: 0
A36: 46141 | B36: =MID("日月火水木金土",WEEKDAY(A36),1) -> 水 | C36: 800000 | D36: =SUM($C$8:C36) -> 17800000 | E36: 155130 | F36: 454830 | G36: =IF(COUNT(E36:F36)=0,"",SUM(E36:F36)) -> 609960 | H36: =IF(G36="","",SUM($G$8:G36)) -> 9521475 | I36: =IF(G36="","",IFERROR(G36/C36,"")) -> 0.76245 | J36: =IF(H36="","",IFERROR(H36/D36,"")) -> 0.53491433 | K36: =IF(H36="","",IF(D36=0,"",H36-D36)) -> -8278525 | L36: =IF(G36="","—",IF(D36=0,"予算未入力",IF(H36>=D36,"◎ ペース内","▲ 遅れ"))) -> ▲ 遅れ | M36: 26 | N36: 30 | O36: 82 | P36: 50 | Q36: 63 | R36: =IFERROR(M36/O36,"") -> 0.31707317 | S36: =IFERROR(G36/M36,"") -> 23460 | T36: =IFERROR(N36/M36,"") -> 1.1538462 | U36: =IFERROR(P36/O36,"") -> 0.6097561 | X36: 0
A37: 46142 | B37: =MID("日月火水木金土",WEEKDAY(A37),1) -> 木 | C37: 700000 | D37: =SUM($C$8:C37) -> 18500000 | E37: 138850 | F37: 204350 | G37: =IF(COUNT(E37:F37)=0,"",SUM(E37:F37)) -> 343200 | H37: =IF(G37="","",SUM($G$8:G37)) -> 9864675 | I37: =IF(G37="","",IFERROR(G37/C37,"")) -> 0.49028571 | J37: =IF(H37="","",IFERROR(H37/D37,"")) -> 0.53322568 | K37: =IF(H37="","",IF(D37=0,"",H37-D37)) -> -8635325 | L37: =IF(G37="","—",IF(D37=0,"予算未入力",IF(H37>=D37,"◎ ペース内","▲ 遅れ"))) -> ▲ 遅れ | M37: 15 | N37: 18 | O37: 54 | P37: 28 | Q37: 51 | R37: =IFERROR(M37/O37,"") -> 0.27777778 | S37: =IFERROR(G37/M37,"") -> 22880 | T37: =IFERROR(N37/M37,"") -> 1.2 | U37: =IFERROR(P37/O37,"") -> 0.51851852 | W37: 44065 | X37: 0
A38: 月計 | C38: =SUM(C8:C37) -> 18500000 | D38: =C38 -> 18500000 | E38: =SUM(E8:E37) -> 2338915 | F38: =SUM(F8:F37) -> 7525760 | G38: =SUM(G8:G37) -> 9864675 | H38: =G38 -> 9864675 | I38: =IFERROR(G38/C38,"") -> 0.53322568 | J38: =IFERROR(G38/C38,"") -> 0.53322568 | K38: =G38-C38 -> -8635325 | M38: =SUM(M8:M37) -> 425 | N38: =SUM(N8:N37) -> 467 | O38: =SUM(O8:O37) -> 1489 | P38: =SUM(P8:P37) -> 717 | Q38: =SUM(Q8:Q37) -> 634 | R38: =IFERROR(M38/O38,"") -> 0.28542646 | S38: =IFERROR(G38/M38,"") -> 23211 | T38: =IFERROR(N38/M38,"") -> 1.0988235 | U38: =IFERROR(P38/O38,"") -> 0.48153123 | V38: =SUM(V8:V37) -> 0 | W38: =IFERROR(LOOKUP(9.99E+307,W8:W37),"") -> 44065 | X38: =SUM(X8:X37) -> 0 | Y38: フォロワーは月末値

Sheet 2026年05月
A1: 2026年5月 原宿店 日別売上管理
A2: 青字＋薄黄色のセルが入力欄。白セルは数式なので触らないでください。単位：円
A3: 月間予算 | C3: 当月実績 | E3: 達成率 | G3: 営業日数(/31日) | I3: 残り必要額 | K3: 残り必要日商
A4: =IF('設定'!$B$9="",SUM(C8:C38),'設定'!$B$9) -> 12329470 | C4: =SUM(G8:G38) -> 12381052 | E4: =IFERROR(C4/A4,0) -> 1.0041836 | G4: =COUNTIF(G8:G38,">0") -> 31 | I4: =A4-C4 -> -51582 | K4: =IF((31-G4)>0,(A4-C4)/(31-G4),0) -> 0
A5: 日次予算合計 | C5: 着地見込 | E5: 決定率 | G5: 客単価 | I5: セット率 | K5: 試着率
A6: =SUM(C8:C38) -> 20200000 | C6: =IFERROR(C4/G4*31,0) -> 12381052 | E6: =IFERROR(M39/O39,0) -> 0.35422164 | G6: =IFERROR(G39/M39,0) -> 23055.963 | I6: =IFERROR(N39/M39,0) -> 1.1061453 | K6: =IFERROR(P39/O39,0) -> 0.61081794
A7: 日付 | B7: 曜 | C7: 日次予算 | D7: 累計予算 | E7: 現金 | F7: クレジット | G7: 実績合計 | H7: 累計実績 | I7: 日次達成 | J7: 累計達成 | K7: 累計予実差 | L7: ペース | M7: 購入人数 | N7: 販売点数 | O7: 来客数 | P7: 試着組数 | Q7: 試着個数 | R7: 決定率 | S7: 客単価 | T7: セット率 | U7: 試着率 | V7: クロス クーポン | W7: インスタ フォロワー | X7: 経費 | Y7: メモ | AA7: 曜日 | AB7: 平均日商 | AC7: 日数 | AD7: 決定率 | AE7: 客単価
A8: 46143 | B8: =MID("日月火水木金土",WEEKDAY(A8),1) -> 金 | C8: 500000 | D8: =SUM($C$8:C8) -> 500000 | E8: 82330 | F8: 358729 | G8: =IF(COUNT(E8:F8)=0,"",SUM(E8:F8)) -> 441059 | H8: =IF(G8="","",SUM($G$8:G8)) -> 441059 | I8: =IF(G8="","",IFERROR(G8/C8,"")) -> 0.882118 | J8: =IF(H8="","",IFERROR(H8/D8,"")) -> 0.882118 | K8: =IF(H8="","",IF(D8=0,"",H8-D8)) -> -58941 | L8: =IF(G8="","—",IF(D8=0,"予算未入力",IF(H8>=D8,"◎ ペース内","▲ 遅れ"))) -> ▲ 遅れ | M8: 20 | N8: 21 | O8: 40 | P8: 23 | Q8: 57 | R8: =IFERROR(M8/O8,"") -> 0.5 | S8: =IFERROR(G8/M8,"") -> 22052.95 | T8: =IFERROR(N8/M8,"") -> 1.05 | U8: =IFERROR(P8/O8,"") -> 0.575 | W8: 44051 | X8: 0 | AA8: 月 | AB8: =IFERROR(AVERAGEIFS($G$8:$G$38,$B$8:$B$38,AA8,$G$8:$G$38,">0"),0) -> 445354.25 | AC8: =COUNTIFS($B$8:$B$38,AA8,$G$8:$G$38,">0") -> 4 | AD8: =IFERROR(SUMIF($B$8:$B$38,AA8,$M$8:$M$38)/SUMIF($B$8:$B$38,AA8,$O$8:$O$38),0) -> 0.34955752 | AE8: =IFERROR(SUMIF($B$8:$B$38,AA8,$G$8:$G$38)/SUMIF($B$8:$B$38,AA8,$M$8:$M$38),0) -> 22549.582
A9: 46144 | B9: =MID("日月火水木金土",WEEKDAY(A9),1) -> 土 | C9: 1000000 | D9: =SUM($C$8:C9) -> 1500000 | E9: 112090 | F9: 429750 | G9: =IF(COUNT(E9:F9)=0,"",SUM(E9:F9)) -> 541840 | H9: =IF(G9="","",SUM($G$8:G9)) -> 982899 | I9: =IF(G9="","",IFERROR(G9/C9,"")) -> 0.54184 | J9: =IF(H9="","",IFERROR(H9/D9,"")) -> 0.655266 | K9: =IF(H9="","",IF(D9=0,"",H9-D9)) -> -517101 | L9: =IF(G9="","—",IF(D9=0,"予算未入力",IF(H9>=D9,"◎ ペース内","▲ 遅れ"))) -> ▲ 遅れ | M9: 24 | N9: 26 | O9: 88 | P9: 53 | Q9: 106 | R9: =IFERROR(M9/O9,"") -> 0.27272727 | S9: =IFERROR(G9/M9,"") -> 22576.667 | T9: =IFERROR(N9/M9,"") -> 1.0833333 | U9: =IFERROR(P9/O9,"") -> 0.60227273 | W9: 44043 | X9: 0 | AA9: 火 | AB9: =IFERROR(AVERAGEIFS($G$8:$G$38,$B$8:$B$38,AA9,$G$8:$G$38,">0"),0) -> 348647.5 | AC9: =COUNTIFS($B$8:$B$38,AA9,$G$8:$G$38,">0") -> 4 | AD9: =IFERROR(SUMIF($B$8:$B$38,AA9,$M$8:$M$38)/SUMIF($B$8:$B$38,AA9,$O$8:$O$38),0) -> 0.27777778 | AE9: =IFERROR(SUMIF($B$8:$B$38,AA9,$G$8:$G$38)/SUMIF($B$8:$B$38,AA9,$M$8:$M$38),0) -> 23243.167
A10: 46145 | B10: =MID("日月火水木金土",WEEKDAY(A10),1) -> 日 | C10: 1000000 | D10: =SUM($C$8:C10) -> 2500000 | E10: 164000 | F10: 421487 | G10: =IF(COUNT(E10:F10)=0,"",SUM(E10:F10)) -> 585487 | H10: =IF(G10="","",SUM($G$8:G10)) -> 1568386 | I10: =IF(G10="","",IFERROR(G10/C10,"")) -> 0.585487 | J10: =IF(H10="","",IFERROR(H10/D10,"")) -> 0.6273544 | K10: =IF(H10="","",IF(D10=0,"",H10-D10)) -> -931614 | L10: =IF(G10="","—",IF(D10=0,"予算未入力",IF(H10>=D10,"◎ ペース内","▲ 遅れ"))) -> ▲ 遅れ | M10: 25 | N10: 28 | O10: 74 | P10: 43 | Q10: 86 | R10: =IFERROR(M10/O10,"") -> 0.33783784 | S10: =IFERROR(G10/M10,"") -> 23419.48 | T10: =IFERROR(N10/M10,"") -> 1.12 | U10: =IFERROR(P10/O10,"") -> 0.58108108 | W10: 44038 | X10: 0 | AA10: 水 | AB10: =IFERROR(AVERAGEIFS($G$8:$G$38,$B$8:$B$38,AA10,$G$8:$G$38,">0"),0) -> 388922.5 | AC10: =COUNTIFS($B$8:$B$38,AA10,$G$8:$G$38,">0") -> 4 | AD10: =IFERROR(SUMIF($B$8:$B$38,AA10,$M$8:$M$38)/SUMIF($B$8:$B$38,AA10,$O$8:$O$38),0) -> 0.35227273 | AE10: =IFERROR(SUMIF($B$8:$B$38,AA10,$G$8:$G$38)/SUMIF($B$8:$B$38,AA10,$M$8:$M$38),0) -> 25091.774
A11: 46146 | B11: =MID("日月火水木金土",WEEKDAY(A11),1) -> 月 | C11: 1000000 | D11: =SUM($C$8:C11) -> 3500000 | E11: 105540 | F11: 332230 | G11: =IF(COUNT(E11:F11)=0,"",SUM(E11:F11)) -> 437770 | H11: =IF(G11="","",SUM($G$8:G11)) -> 2006156 | I11: =IF(G11="","",IFERROR(G11/C11,"")) -> 0.43777 | J11: =IF(H11="","",IFERROR(H11/D11,"")) -> 0.57318743 | K11: =IF(H11="","",IF(D11=0,"",H11-D11)) -> -1493844 | L11: =IF(G11="","—",IF(D11=0,"予算未入力",IF(H11>=D11,"◎ ペース内","▲ 遅れ"))) -> ▲ 遅れ | M11: 21 | N11: 22 | O11: 56 | P11: 32 | Q11: 56 | R11: =IFERROR(M11/O11,"") -> 0.375 | S11: =IFERROR(G11/M11,"") -> 20846.19 | T11: =IFERROR(N11/M11,"") -> 1.047619 | U11: =IFERROR(P11/O11,"") -> 0.57142857 | W11: 44028 | X11: 0 | AA11: 木 | AB11: =IFERROR(AVERAGEIFS($G$8:$G$38,$B$8:$B$38,AA11,$G$8:$G$38,">0"),0) -> 298960.75 | AC11: =COUNTIFS($B$8:$B$38,AA11,$G$8:$G$38,">0") -> 4 | AD11: =IFERROR(SUMIF($B$8:$B$38,AA11,$M$8:$M$38)/SUMIF($B$8:$B$38,AA11,$O$8:$O$38),0) -> 0.39416058 | AE11: =IFERROR(SUMIF($B$8:$B$38,AA11,$G$8:$G$38)/SUMIF($B$8:$B$38,AA11,$M$8:$M$38),0) -> 22145.241
A12: 46147 | B12: =MID("日月火水木金土",WEEKDAY(A12),1) -> 火 | C12: 1000000 | D12: =SUM($C$8:C12) -> 4500000 | E12: 186310 | F12: 428550 | G12: =IF(COUNT(E12:F12)=0,"",SUM(E12:F12)) -> 614860 | H12: =IF(G12="","",SUM($G$8:G12)) -> 2621016 | I12: =IF(G12="","",IFERROR(G12/C12,"")) -> 0.61486 | J12: =IF(H12="","",IFERROR(H12/D12,"")) -> 0.582448 | K12: =IF(H12="","",IF(D12=0,"",H12-D12)) -> -1878984 | L12: =IF(G12="","—",IF(D12=0,"予算未入力",IF(H12>=D12,"◎ ペース内","▲ 遅れ"))) -> ▲ 遅れ | M12: 27 | N12: 30 | O12: 78 | P12: 74 | Q12: 59 | R12: =IFERROR(M12/O12,"") -> 0.34615385 | S12: =IFERROR(G12/M12,"") -> 22772.593 | T12: =IFERROR(N12/M12,"") -> 1.1111111 | U12: =IFERROR(P12/O12,"") -> 0.94871795 | W12: 44009 | X12: 0 | AA12: 金 | AB12: =IFERROR(AVERAGEIFS($G$8:$G$38,$B$8:$B$38,AA12,$G$8:$G$38,">0"),0) -> 279935.8 | AC12: =COUNTIFS($B$8:$B$38,AA12,$G$8:$G$38,">0") -> 5 | AD12: =IFERROR(SUMIF($B$8:$B$38,AA12,$M$8:$M$38)/SUMIF($B$8:$B$38,AA12,$O$8:$O$38),0) -> 0.33333333 | AE12: =IFERROR(SUMIF($B$8:$B$38,AA12,$G$8:$G$38)/SUMIF($B$8:$B$38,AA12,$M$8:$M$38),0) -> 23327.983
A13: 46148 | B13: =MID("日月火水木金土",WEEKDAY(A13),1) -> 水 | C13: 1000000 | D13: =SUM($C$8:C13) -> 5500000 | E13: 19910 | F13: 546700 | G13: =IF(COUNT(E13:F13)=0,"",SUM(E13:F13)) -> 566610 | H13: =IF(G13="","",SUM($G$8:G13)) -> 3187626 | I13: =IF(G13="","",IFERROR(G13/C13,"")) -> 0.56661 | J13: =IF(H13="","",IFERROR(H13/D13,"")) -> 0.57956836 | K13: =IF(H13="","",IF(D13=0,"",H13-D13)) -> -2312374 | L13: =IF(G13="","—",IF(D13=0,"予算未入力",IF(H13>=D13,"◎ ペース内","▲ 遅れ"))) -> ▲ 遅れ | M13: 21 | N13: 29 | O13: 73 | P13: 36 | Q13: 85 | R13: =IFERROR(M13/O13,"") -> 0.28767123 | S13: =IFERROR(G13/M13,"") -> 26981.429 | T13: =IFERROR(N13/M13,"") -> 1.3809524 | U13: =IFERROR(P13/O13,"") -> 0.49315068 | W13: 43989 | X13: 0 | AA13: 土 | AB13: =IFERROR(AVERAGEIFS($G$8:$G$38,$B$8:$B$38,AA13,$G$8:$G$38,">0"),0) -> 547375.8 | AC13: =COUNTIFS($B$8:$B$38,AA13,$G$8:$G$38,">0") -> 5 | AD13: =IFERROR(SUMIF($B$8:$B$38,AA13,$M$8:$M$38)/SUMIF($B$8:$B$38,AA13,$O$8:$O$38),0) -> 0.40802676 | AE13: =IFERROR(SUMIF($B$8:$B$38,AA13,$G$8:$G$38)/SUMIF($B$8:$B$38,AA13,$M$8:$M$38),0) -> 22433.434
A14: 46149 | B14: =MID("日月火水木金土",WEEKDAY(A14),1) -> 木 | C14: 600000 | D14: =SUM($C$8:C14) -> 6100000 | E14: 57530 | F14: 299099 | G14: =IF(COUNT(E14:F14)=0,"",SUM(E14:F14)) -> 356629 | H14: =IF(G14="","",SUM($G$8:G14)) -> 3544255 | I14: =IF(G14="","",IFERROR(G14/C14,"")) -> 0.59438167 | J14: =IF(H14="","",IFERROR(H14/D14,"")) -> 0.58102541 | K14: =IF(H14="","",IF(D14=0,"",H14-D14)) -> -2555745 | L14: =IF(G14="","—",IF(D14=0,"予算未入力",IF(H14>=D14,"◎ ペース内","▲ 遅れ"))) -> ▲ 遅れ | M14: 17 | N14: 17 | O14: 45 | P14: 32 | Q14: 56 | R14: =IFERROR(M14/O14,"") -> 0.37777778 | S14: =IFERROR(G14/M14,"") -> 20978.176 | T14: =IFERROR(N14/M14,"") -> 1 | U14: =IFERROR(P14/O14,"") -> 0.71111111 | W14: 43971 | X14: 0 | AA14: 日 | AB14: =IFERROR(AVERAGEIFS($G$8:$G$38,$B$8:$B$38,AA14,$G$8:$G$38,">0"),0) -> 463390.8 | AC14: =COUNTIFS($B$8:$B$38,AA14,$G$8:$G$38,">0") -> 5 | AD14: =IFERROR(SUMIF($B$8:$B$38,AA14,$M$8:$M$38)/SUMIF($B$8:$B$38,AA14,$O$8:$O$38),0) -> 0.35460993 | AE14: =IFERROR(SUMIF($B$8:$B$38,AA14,$G$8:$G$38)/SUMIF($B$8:$B$38,AA14,$M$8:$M$38),0) -> 23169.54
A15: 46150 | B15: =MID("日月火水木金土",WEEKDAY(A15),1) -> 金 | C15: 600000 | D15: =SUM($C$8:C15) -> 6700000 | E15: 0 | F15: 338440 | G15: =IF(COUNT(E15:F15)=0,"",SUM(E15:F15)) -> 338440 | H15: =IF(G15="","",SUM($G$8:G15)) -> 3882695 | I15: =IF(G15="","",IFERROR(G15/C15,"")) -> 0.56406667 | J15: =IF(H15="","",IFERROR(H15/D15,"")) -> 0.57950672 | K15: =IF(H15="","",IF(D15=0,"",H15-D15)) -> -2817305 | L15: =IF(G15="","—",IF(D15=0,"予算未入力",IF(H15>=D15,"◎ ペース内","▲ 遅れ"))) -> ▲ 遅れ | M15: 13 | N15: 17 | O15: 38 | P15: 29 | Q15: 39 | R15: =IFERROR(M15/O15,"") -> 0.34210526 | S15: =IFERROR(G15/M15,"") -> 26033.846 | T15: =IFERROR(N15/M15,"") -> 1.3076923 | U15: =IFERROR(P15/O15,"") -> 0.76315789 | W15: 43954 | X15: 0
A16: 46151 | B16: =MID("日月火水木金土",WEEKDAY(A16),1) -> 土 | C16: 900000 | D16: =SUM($C$8:C16) -> 7600000 | E16: 172350 | F16: 202700 | G16: =IF(COUNT(E16:F16)=0,"",SUM(E16:F16)) -> 375050 | H16: =IF(G16="","",SUM($G$8:G16)) -> 4257745 | I16: =IF(G16="","",IFERROR(G16/C16,"")) -> 0.41672222 | J16: =IF(H16="","",IFERROR(H16/D16,"")) -> 0.56022961 | K16: =IF(H16="","",IF(D16=0,"",H16-D16)) -> -3342255 | L16: =IF(G16="","—",IF(D16=0,"予算未入力",IF(H16>=D16,"◎ ペース内","▲ 遅れ"))) -> ▲ 遅れ | M16: 18 | N16: 20 | O16: 52 | P16: 29 | Q16: 58 | R16: =IFERROR(M16/O16,"") -> 0.34615385 | S16: =IFERROR(G16/M16,"") -> 20836.111 | T16: =IFERROR(N16/M16,"") -> 1.1111111 | U16: =IFERROR(P16/O16,"") -> 0.55769231 | W16: 43954 | X16: 0 | AA16: ※実績入力後に曜日別の傾向が出ます
A17: 46152 | B17: =MID("日月火水木金土",WEEKDAY(A17),1) -> 日 | C17: 900000 | D17: =SUM($C$8:C17) -> 8500000 | E17: 83970 | F17: 284370 | G17: =IF(COUNT(E17:F17)=0,"",SUM(E17:F17)) -> 368340 | H17: =IF(G17="","",SUM($G$8:G17)) -> 4626085 | I17: =IF(G17="","",IFERROR(G17/C17,"")) -> 0.40926667 | J17: =IF(H17="","",IFERROR(H17/D17,"")) -> 0.54424529 | K17: =IF(H17="","",IF(D17=0,"",H17-D17)) -> -3873915 | L17: =IF(G17="","—",IF(D17=0,"予算未入力",IF(H17>=D17,"◎ ペース内","▲ 遅れ"))) -> ▲ 遅れ | M17: 16 | N17: 18 | O17: 48 | P17: 22 | Q17: 58 | R17: =IFERROR(M17/O17,"") -> 0.33333333 | S17: =IFERROR(G17/M17,"") -> 23021.25 | T17: =IFERROR(N17/M17,"") -> 1.125 | U17: =IFERROR(P17/O17,"") -> 0.45833333 | W17: 43945 | X17: 0
A18: 46153 | B18: =MID("日月火水木金土",WEEKDAY(A18),1) -> 月 | C18: 500000 | D18: =SUM($C$8:C18) -> 9000000 | E18: 43610 | F18: 349930 | G18: =IF(COUNT(E18:F18)=0,"",SUM(E18:F18)) -> 393540 | H18: =IF(G18="","",SUM($G$8:G18)) -> 5019625 | I18: =IF(G18="","",IFERROR(G18/C18,"")) -> 0.78708 | J18: =IF(H18="","",IFERROR(H18/D18,"")) -> 0.55773611 | K18: =IF(H18="","",IF(D18=0,"",H18-D18)) -> -3980375 | L18: =IF(G18="","—",IF(D18=0,"予算未入力",IF(H18>=D18,"◎ ペース内","▲ 遅れ"))) -> ▲ 遅れ | M18: 17 | N18: 20 | O18: 52 | P18: 27 | Q18: 53 | R18: =IFERROR(M18/O18,"") -> 0.32692308 | S18: =IFERROR(G18/M18,"") -> 23149.412 | T18: =IFERROR(N18/M18,"") -> 1.1764706 | U18: =IFERROR(P18/O18,"") -> 0.51923077 | W18: 43952 | X18: 0 | AA18: ■ 週次サマリー（火曜〜翌月曜） | AH18: 第1火曜 | AI18: =$A$8+MOD(2-WEEKDAY($A$8,2)+7,7) -> 46147
A19: 46154 | B19: =MID("日月火水木金土",WEEKDAY(A19),1) -> 火 | C19: 500000 | D19: =SUM($C$8:C19) -> 9500000 | E19: 41520 | F19: 122810 | G19: =IF(COUNT(E19:F19)=0,"",SUM(E19:F19)) -> 164330 | H19: =IF(G19="","",SUM($G$8:G19)) -> 5183955 | I19: =IF(G19="","",IFERROR(G19/C19,"")) -> 0.32866 | J19: =IF(H19="","",IFERROR(H19/D19,"")) -> 0.54567947 | K19: =IF(H19="","",IF(D19=0,"",H19-D19)) -> -4316045 | L19: =IF(G19="","—",IF(D19=0,"予算未入力",IF(H19>=D19,"◎ ペース内","▲ 遅れ"))) -> ▲ 遅れ | M19: 8 | N19: 10 | O19: 38 | P19: 14 | Q19: 19 | R19: =IFERROR(M19/O19,"") -> 0.21052632 | S19: =IFERROR(G19/M19,"") -> 20541.25 | T19: =IFERROR(N19/M19,"") -> 1.25 | U19: =IFERROR(P19/O19,"") -> 0.36842105 | W19: 43940 | X19: 0 | AA19: 週 | AB19: 期間 | AC19: 売上 | AD19: 決定率 | AE19: 客単価 | AF19: セット率 | AG19: 試着率
A20: 46155 | B20: =MID("日月火水木金土",WEEKDAY(A20),1) -> 水 | C20: 500000 | D20: =SUM($C$8:C20) -> 10000000 | E20: 71930 | F20: 95300 | G20: =IF(COUNT(E20:F20)=0,"",SUM(E20:F20)) -> 167230 | H20: =IF(G20="","",SUM($G$8:G20)) -> 5351185 | I20: =IF(G20="","",IFERROR(G20/C20,"")) -> 0.33446 | J20: =IF(H20="","",IFERROR(H20/D20,"")) -> 0.5351185 | K20: =IF(H20="","",IF(D20=0,"",H20-D20)) -> -4648815 | L20: =IF(G20="","—",IF(D20=0,"予算未入力",IF(H20>=D20,"◎ ペース内","▲ 遅れ"))) -> ▲ 遅れ | M20: 8 | N20: 8 | O20: 27 | P20: 13 | Q20: 30 | R20: =IFERROR(M20/O20,"") -> 0.2962963 | S20: =IFERROR(G20/M20,"") -> 20903.75 | T20: =IFERROR(N20/M20,"") -> 1 | U20: =IFERROR(P20/O20,"") -> 0.48148148 | W20: 43930 | X20: 0 | AA20: 1 | AB20: =IF($AI$18+7*(1-1)>$A$38,"",TEXT($AI$18+7*(1-1),"m/d")&"-"&TEXT($AI$18+7*(1-1)+6,"m/d")) -> 5/5-5/11 | AC20: =IF($AB20="","",(SUMIFS($G$8:$G$38,$A$8:$A$38,">="&$AI$18+7*(1-1),$A$8:$A$38,"<="&$AI$18+7*(1-1)+6)+SUMIFS('2026年06月'!$G$8:$G$37,'2026年06月'!$A$8:$A$37,">="&$AI$18+7*(1-1),'2026年06月'!$A$8:$A$37,"<="&$AI$18+7*(1-1)+6))) -> 3013469 | AD20: =IF($AB20="","",IFERROR((SUMIFS($M$8:$M$38,$A$8:$A$38,">="&$AI$18+7*(1-1),$A$8:$A$38,"<="&$AI$18+7*(1-1)+6)+SUMIFS('2026年06月'!$M$8:$M$37,'2026年06月'!$A$8:$A$37,">="&$AI$18+7*(1-1),'2026年06月'!$A$8:$A$37,"<="&$AI$18+7*(1-1)+6))/(SUMIFS($O$8:$O$38,$A$8:$A$38,">="&$AI$18+7*(1-1),$A$8:$A$38,"<="&$AI$18+7*(1-1)+6)+SUMIFS('2026年06月'!$O$8:$O$37,'2026年06月'!$A$8:$A$37,">="&$AI$18+7*(1-1),'2026年06月'!$A$8:$A$37,"<="&$AI$18+7*(1-1)+6)),"")) -> 0.33419689 | AE20: =IF($AB20="","",IFERROR((SUMIFS($G$8:$G$38,$A$8:$A$38,">="&$AI$18+7*(1-1),$A$8:$A$38,"<="&$AI$18+7*(1-1)+6)+SUMIFS('2026年06月'!$G$8:$G$37,'2026年06月'!$A$8:$A$37,">="&$AI$18+7*(1-1),'2026年06月'!$A$8:$A$37,"<="&$AI$18+7*(1-1)+6))/(SUMIFS($M$8:$M$38,$A$8:$A$38,">="&$AI$18+7*(1-1),$A$8:$A$38,"<="&$AI$18+7*(1-1)+6)+SUMIFS('2026年06月'!$M$8:$M$37,'2026年06月'!$A$8:$A$37,">="&$AI$18+7*(1-1),'2026年06月'!$A$8:$A$37,"<="&$AI$18+7*(1-1)+6)),"")) -> 23360.225 | AF20: =IF($AB20="","",IFERROR((SUMIFS($N$8:$N$38,$A$8:$A$38,">="&$AI$18+7*(1-1),$A$8:$A$38,"<="&$AI$18+7*(1-1)+6)+SUMIFS('2026年06月'!$N$8:$N$37,'2026年06月'!$A$8:$A$37,">="&$AI$18+7*(1-1),'2026年06月'!$A$8:$A$37,"<="&$AI$18+7*(1-1)+6))/(SUMIFS($M$8:$M$38,$A$8:$A$38,">="&$AI$18+7*(1-1),$A$8:$A$38,"<="&$AI$18+7*(1-1)+6)+SUMIFS('2026年06月'!$M$8:$M$37,'2026年06月'!$A$8:$A$37,">="&$AI$18+7*(1-1),'2026年06月'!$A$8:$A$37,"<="&$AI$18+7*(1-1)+6)),"")) -> 1.1705426 | AG20: =IF($AB20="","",IFERROR((SUMIFS($P$8:$P$38,$A$8:$A$38,">="&$AI$18+7*(1-1),$A$8:$A$38,"<="&$AI$18+7*(1-1)+6)+SUMIFS('2026年06月'!$P$8:$P$37,'2026年06月'!$A$8:$A$37,">="&$AI$18+7*(1-1),'2026年06月'!$A$8:$A$37,"<="&$AI$18+7*(1-1)+6))/(SUMIFS($O$8:$O$38,$A$8:$A$38,">="&$AI$18+7*(1-1),$A$8:$A$38,"<="&$AI$18+7*(1-1)+6)+SUMIFS('2026年06月'!$O$8:$O$37,'2026年06月'!$A$8:$A$37,">="&$AI$18+7*(1-1),'2026年06月'!$A$8:$A$37,"<="&$AI$18+7*(1-1)+6)),"")) -> 0.64507772
A21: 46156 | B21: =MID("日月火水木金土",WEEKDAY(A21),1) -> 木 | C21: 500000 | D21: =SUM($C$8:C21) -> 10500000 | E21: 23810 | F21: 212930 | G21: =IF(COUNT(E21:F21)=0,"",SUM(E21:F21)) -> 236740 | H21: =IF(G21="","",SUM($G$8:G21)) -> 5587925 | I21: =IF(G21="","",IFERROR(G21/C21,"")) -> 0.47348 | J21: =IF(H21="","",IFERROR(H21/D21,"")) -> 0.53218333 | K21: =IF(H21="","",IF(D21=0,"",H21-D21)) -> -4912075 | L21: =IF(G21="","—",IF(D21=0,"予算未入力",IF(H21>=D21,"◎ ペース内","▲ 遅れ"))) -> ▲ 遅れ | M21: 11 | N21: 12 | O21: 28 | P21: 17 | Q21: 34 | R21: =IFERROR(M21/O21,"") -> 0.39285714 | S21: =IFERROR(G21/M21,"") -> 21521.818 | T21: =IFERROR(N21/M21,"") -> 1.0909091 | U21: =IFERROR(P21/O21,"") -> 0.60714286 | X21: 0 | AA21: 2 | AB21: =IF($AI$18+7*(2-1)>$A$38,"",TEXT($AI$18+7*(2-1),"m/d")&"-"&TEXT($AI$18+7*(2-1)+6,"m/d")) -> 5/12-5/18 | AC21: =IF($AB21="","",(SUMIFS($G$8:$G$38,$A$8:$A$38,">="&$AI$18+7*(2-1),$A$8:$A$38,"<="&$AI$18+7*(2-1)+6)+SUMIFS('2026年06月'!$G$8:$G$37,'2026年06月'!$A$8:$A$37,">="&$AI$18+7*(2-1),'2026年06月'!$A$8:$A$37,"<="&$AI$18+7*(2-1)+6))) -> 2242257 | AD21: =IF($AB21="","",IFERROR((SUMIFS($M$8:$M$38,$A$8:$A$38,">="&$AI$18+7*(2-1),$A$8:$A$38,"<="&$AI$18+7*(2-1)+6)+SUMIFS('2026年06月'!$M$8:$M$37,'2026年06月'!$A$8:$A$37,">="&$AI$18+7*(2-1),'2026年06月'!$A$8:$A$37,"<="&$AI$18+7*(2-1)+6))/(SUMIFS($O$8:$O$38,$A$8:$A$38,">="&$AI$18+7*(2-1),$A$8:$A$38,"<="&$AI$18+7*(2-1)+6)+SUMIFS('2026年06月'!$O$8:$O$37,'2026年06月'!$A$8:$A$37,">="&$AI$18+7*(2-1),'2026年06月'!$A$8:$A$37,"<="&$AI$18+7*(2-1)+6)),"")) -> 0.35211268 | AE21: =IF($AB21="","",IFERROR((SUMIFS($G$8:$G$38,$A$8:$A$38,">="&$AI$18+7*(2-1),$A$8:$A$38,"<="&$AI$18+7*(2-1)+6)+SUMIFS('2026年06月'!$G$8:$G$37,'2026年06月'!$A$8:$A$37,">="&$AI$18+7*(2-1),'2026年06月'!$A$8:$A$37,"<="&$AI$18+7*(2-1)+6))/(SUMIFS($M$8:$M$38,$A$8:$A$38,">="&$AI$18+7*(2-1),$A$8:$A$38,"<="&$AI$18+7*(2-1)+6)+SUMIFS('2026年06月'!$M$8:$M$37,'2026年06月'!$A$8:$A$37,">="&$AI$18+7*(2-1),'2026年06月'!$A$8:$A$37,"<="&$AI$18+7*(2-1)+6)),"")) -> 22422.57 | AF21: =IF($AB21="","",IFERROR((SUMIFS($N$8:$N$38,$A$8:$A$38,">="&$AI$18+7*(2-1),$A$8:$A$38,"<="&$AI$18+7*(2-1)+6)+SUMIFS('2026年06月'!$N$8:$N$37,'2026年06月'!$A$8:$A$37,">="&$AI$18+7*(2-1),'2026年06月'!$A$8:$A$37,"<="&$AI$18+7*(2-1)+6))/(SUMIFS($M$8:$M$38,$A$8:$A$38,">="&$AI$18+7*(2-1),$A$8:$A$38,"<="&$AI$18+7*(2-1)+6)+SUMIFS('2026年06月'!$M$8:$M$37,'2026年06月'!$A$8:$A$37,">="&$AI$18+7*(2-1),'2026年06月'!$A$8:$A$37,"<="&$AI$18+7*(2-1)+6)),"")) -> 1.08 | AG21: =IF($AB21="","",IFERROR((SUMIFS($P$8:$P$38,$A$8:$A$38,">="&$AI$18+7*(2-1),$A$8:$A$38,"<="&$AI$18+7*(2-1)+6)+SUMIFS('2026年06月'!$P$8:$P$37,'2026年06月'!$A$8:$A$37,">="&$AI$18+7*(2-1),'2026年06月'!$A$8:$A$37,"<="&$AI$18+7*(2-1)+6))/(SUMIFS($O$8:$O$38,$A$8:$A$38,">="&$AI$18+7*(2-1),$A$8:$A$38,"<="&$AI$18+7*(2-1)+6)+SUMIFS('2026年06月'!$O$8:$O$37,'2026年06月'!$A$8:$A$37,">="&$AI$18+7*(2-1),'2026年06月'!$A$8:$A$37,"<="&$AI$18+7*(2-1)+6)),"")) -> 0.58098592
A22: 46157 | B22: =MID("日月火水木金土",WEEKDAY(A22),1) -> 金 | C22: 500000 | D22: =SUM($C$8:C22) -> 11000000 | E22: 23810 | F22: 215350 | G22: =IF(COUNT(E22:F22)=0,"",SUM(E22:F22)) -> 239160 | H22: =IF(G22="","",SUM($G$8:G22)) -> 5827085 | I22: =IF(G22="","",IFERROR(G22/C22,"")) -> 0.47832 | J22: =IF(H22="","",IFERROR(H22/D22,"")) -> 0.529735 | K22: =IF(H22="","",IF(D22=0,"",H22-D22)) -> -5172915 | L22: =IF(G22="","—",IF(D22=0,"予算未入力",IF(H22>=D22,"◎ ペース内","▲ 遅れ"))) -> ▲ 遅れ | M22: 10 | N22: 10 | O22: 28 | P22: 16 | Q22: 37 | R22: =IFERROR(M22/O22,"") -> 0.35714286 | S22: =IFERROR(G22/M22,"") -> 23916 | T22: =IFERROR(N22/M22,"") -> 1 | U22: =IFERROR(P22/O22,"") -> 0.57142857 | W22: 43959 | X22: 0 | AA22: 3 | AB22: =IF($AI$18+7*(3-1)>$A$38,"",TEXT($AI$18+7*(3-1),"m/d")&"-"&TEXT($AI$18+7*(3-1)+6,"m/d")) -> 5/19-5/25 | AC22: =IF($AB22="","",(SUMIFS($G$8:$G$38,$A$8:$A$38,">="&$AI$18+7*(3-1),$A$8:$A$38,"<="&$AI$18+7*(3-1)+6)+SUMIFS('2026年06月'!$G$8:$G$37,'2026年06月'!$A$8:$A$37,">="&$AI$18+7*(3-1),'2026年06月'!$A$8:$A$37,"<="&$AI$18+7*(3-1)+6))) -> 2806389 | AD22: =IF($AB22="","",IFERROR((SUMIFS($M$8:$M$38,$A$8:$A$38,">="&$AI$18+7*(3-1),$A$8:$A$38,"<="&$AI$18+7*(3-1)+6)+SUMIFS('2026年06月'!$M$8:$M$37,'2026年06月'!$A$8:$A$37,">="&$AI$18+7*(3-1),'2026年06月'!$A$8:$A$37,"<="&$AI$18+7*(3-1)+6))/(SUMIFS($O$8:$O$38,$A$8:$A$38,">="&$AI$18+7*(3-1),$A$8:$A$38,"<="&$AI$18+7*(3-1)+6)+SUMIFS('2026年06月'!$O$8:$O$37,'2026年06月'!$A$8:$A$37,">="&$AI$18+7*(3-1),'2026年06月'!$A$8:$A$37,"<="&$AI$18+7*(3-1)+6)),"")) -> 0.34492754 | AE22: =IF($AB22="","",IFERROR((SUMIFS($G$8:$G$38,$A$8:$A$38,">="&$AI$18+7*(3-1),$A$8:$A$38,"<="&$AI$18+7*(3-1)+6)+SUMIFS('2026年06月'!$G$8:$G$37,'2026年06月'!$A$8:$A$37,">="&$AI$18+7*(3-1),'2026年06月'!$A$8:$A$37,"<="&$AI$18+7*(3-1)+6))/(SUMIFS($M$8:$M$38,$A$8:$A$38,">="&$AI$18+7*(3-1),$A$8:$A$38,"<="&$AI$18+7*(3-1)+6)+SUMIFS('2026年06月'!$M$8:$M$37,'2026年06月'!$A$8:$A$37,">="&$AI$18+7*(3-1),'2026年06月'!$A$8:$A$37,"<="&$AI$18+7*(3-1)+6)),"")) -> 23583.101 | AF22: =IF($AB22="","",IFERROR((SUMIFS($N$8:$N$38,$A$8:$A$38,">="&$AI$18+7*(3-1),$A$8:$A$38,"<="&$AI$18+7*(3-1)+6)+SUMIFS('2026年06月'!$N$8:$N$37,'2026年06月'!$A$8:$A$37,">="&$AI$18+7*(3-1),'2026年06月'!$A$8:$A$37,"<="&$AI$18+7*(3-1)+6))/(SUMIFS($M$8:$M$38,$A$8:$A$38,">="&$AI$18+7*(3-1),$A$8:$A$38,"<="&$AI$18+7*(3-1)+6)+SUMIFS('2026年06月'!$M$8:$M$37,'2026年06月'!$A$8:$A$37,">="&$AI$18+7*(3-1),'2026年06月'!$A$8:$A$37,"<="&$AI$18+7*(3-1)+6)),"")) -> 1.0840336 | AG22: =IF($AB22="","",IFERROR((SUMIFS($P$8:$P$38,$A$8:$A$38,">="&$AI$18+7*(3-1),$A$8:$A$38,"<="&$AI$18+7*(3-1)+6)+SUMIFS('2026年06月'!$P$8:$P$37,'2026年06月'!$A$8:$A$37,">="&$AI$18+7*(3-1),'2026年06月'!$A$8:$A$37,"<="&$AI$18+7*(3-1)+6))/(SUMIFS($O$8:$O$38,$A$8:$A$38,">="&$AI$18+7*(3-1),$A$8:$A$38,"<="&$AI$18+7*(3-1)+6)+SUMIFS('2026年06月'!$O$8:$O$37,'2026年06月'!$A$8:$A$37,">="&$AI$18+7*(3-1),'2026年06月'!$A$8:$A$37,"<="&$AI$18+7*(3-1)+6)),"")) -> 0.60869565
A23: 46158 | B23: =MID("日月火水木金土",WEEKDAY(A23),1) -> 土 | C23: 700000 | D23: =SUM($C$8:C23) -> 11700000 | E23: 19300 | F23: 525400 | G23: =IF(COUNT(E23:F23)=0,"",SUM(E23:F23)) -> 544700 | H23: =IF(G23="","",SUM($G$8:G23)) -> 6371785 | I23: =IF(G23="","",IFERROR(G23/C23,"")) -> 0.77814286 | J23: =IF(H23="","",IFERROR(H23/D23,"")) -> 0.54459701 | K23: =IF(H23="","",IF(D23=0,"",H23-D23)) -> -5328215 | L23: =IF(G23="","—",IF(D23=0,"予算未入力",IF(H23>=D23,"◎ ペース内","▲ 遅れ"))) -> ▲ 遅れ | M23: 25 | N23: 26 | O23: 57 | P23: 46 | Q23: 65 | R23: =IFERROR(M23/O23,"") -> 0.43859649 | S23: =IFERROR(G23/M23,"") -> 21788 | T23: =IFERROR(N23/M23,"") -> 1.04 | U23: =IFERROR(P23/O23,"") -> 0.80701754 | W23: 43976 | X23: 0 | AA23: 4 | AB23: =IF($AI$18+7*(4-1)>$A$38,"",TEXT($AI$18+7*(4-1),"m/d")&"-"&TEXT($AI$18+7*(4-1)+6,"m/d")) -> 5/26-6/1 | AC23: =IF($AB23="","",(SUMIFS($G$8:$G$38,$A$8:$A$38,">="&$AI$18+7*(4-1),$A$8:$A$38,"<="&$AI$18+7*(4-1)+6)+SUMIFS('2026年06月'!$G$8:$G$37,'2026年06月'!$A$8:$A$37,">="&$AI$18+7*(4-1),'2026年06月'!$A$8:$A$37,"<="&$AI$18+7*(4-1)+6))) -> 2628231 | AD23: =IF($AB23="","",IFERROR((SUMIFS($M$8:$M$38,$A$8:$A$38,">="&$AI$18+7*(4-1),$A$8:$A$38,"<="&$AI$18+7*(4-1)+6)+SUMIFS('2026年06月'!$M$8:$M$37,'2026年06月'!$A$8:$A$37,">="&$AI$18+7*(4-1),'2026年06月'!$A$8:$A$37,"<="&$AI$18+7*(4-1)+6))/(SUMIFS($O$8:$O$38,$A$8:$A$38,">="&$AI$18+7*(4-1),$A$8:$A$38,"<="&$AI$18+7*(4-1)+6)+SUMIFS('2026年06月'!$O$8:$O$37,'2026年06月'!$A$8:$A$37,">="&$AI$18+7*(4-1),'2026年06月'!$A$8:$A$37,"<="&$AI$18+7*(4-1)+6)),"")) -> 0.4 | AE23: =IF($AB23="","",IFERROR((SUMIFS($G$8:$G$38,$A$8:$A$38,">="&$AI$18+7*(4-1),$A$8:$A$38,"<="&$AI$18+7*(4-1)+6)+SUMIFS('2026年06月'!$G$8:$G$37,'2026年06月'!$A$8:$A$37,">="&$AI$18+7*(4-1),'2026年06月'!$A$8:$A$37,"<="&$AI$18+7*(4-1)+6))/(SUMIFS($M$8:$M$38,$A$8:$A$38,">="&$AI$18+7*(4-1),$A$8:$A$38,"<="&$AI$18+7*(4-1)+6)+SUMIFS('2026年06月'!$M$8:$M$37,'2026年06月'!$A$8:$A$37,">="&$AI$18+7*(4-1),'2026年06月'!$A$8:$A$37,"<="&$AI$18+7*(4-1)+6)),"")) -> 23893.009 | AF23: =IF($AB23="","",IFERROR((SUMIFS($N$8:$N$38,$A$8:$A$38,">="&$AI$18+7*(4-1),$A$8:$A$38,"<="&$AI$18+7*(4-1)+6)+SUMIFS('2026年06月'!$N$8:$N$37,'2026年06月'!$A$8:$A$37,">="&$AI$18+7*(4-1),'2026年06月'!$A$8:$A$37,"<="&$AI$18+7*(4-1)+6))/(SUMIFS($M$8:$M$38,$A$8:$A$38,">="&$AI$18+7*(4-1),$A$8:$A$38,"<="&$AI$18+7*(4-1)+6)+SUMIFS('2026年06月'!$M$8:$M$37,'2026年06月'!$A$8:$A$37,">="&$AI$18+7*(4-1),'2026年06月'!$A$8:$A$37,"<="&$AI$18+7*(4-1)+6)),"")) -> 1.1545455 | AG23: =IF($AB23="","",IFERROR((SUMIFS($P$8:$P$38,$A$8:$A$38,">="&$AI$18+7*(4-1),$A$8:$A$38,"<="&$AI$18+7*(4-1)+6)+SUMIFS('2026年06月'!$P$8:$P$37,'2026年06月'!$A$8:$A$37,">="&$AI$18+7*(4-1),'2026年06月'!$A$8:$A$37,"<="&$AI$18+7*(4-1)+6))/(SUMIFS($O$8:$O$38,$A$8:$A$38,">="&$AI$18+7*(4-1),$A$8:$A$38,"<="&$AI$18+7*(4-1)+6)+SUMIFS('2026年06月'!$O$8:$O$37,'2026年06月'!$A$8:$A$37,">="&$AI$18+7*(4-1),'2026年06月'!$A$8:$A$37,"<="&$AI$18+7*(4-1)+6)),"")) -> 0.63272727
A24: 46159 | B24: =MID("日月火水木金土",WEEKDAY(A24),1) -> 日 | C24: 700000 | D24: =SUM($C$8:C24) -> 12400000 | E24: 67420 | F24: 389670 | G24: =IF(COUNT(E24:F24)=0,"",SUM(E24:F24)) -> 457090 | H24: =IF(G24="","",SUM($G$8:G24)) -> 6828875 | I24: =IF(G24="","",IFERROR(G24/C24,"")) -> 0.65298571 | J24: =IF(H24="","",IFERROR(H24/D24,"")) -> 0.55071573 | K24: =IF(H24="","",IF(D24=0,"",H24-D24)) -> -5571125 | L24: =IF(G24="","—",IF(D24=0,"予算未入力",IF(H24>=D24,"◎ ペース内","▲ 遅れ"))) -> ▲ 遅れ | M24: 20 | N24: 21 | O24: 45 | P24: 38 | Q24: 86 | R24: =IFERROR(M24/O24,"") -> 0.44444444 | S24: =IFERROR(G24/M24,"") -> 22854.5 | T24: =IFERROR(N24/M24,"") -> 1.05 | U24: =IFERROR(P24/O24,"") -> 0.84444444 | W24: 43986 | X24: 0 | AA24: 5 | AB24: =IF($AI$18+7*(5-1)>$A$38,"",TEXT($AI$18+7*(5-1),"m/d")&"-"&TEXT($AI$18+7*(5-1)+6,"m/d")) | AC24: =IF($AB24="","",(SUMIFS($G$8:$G$38,$A$8:$A$38,">="&$AI$18+7*(5-1),$A$8:$A$38,"<="&$AI$18+7*(5-1)+6)+SUMIFS('2026年06月'!$G$8:$G$37,'2026年06月'!$A$8:$A$37,">="&$AI$18+7*(5-1),'2026年06月'!$A$8:$A$37,"<="&$AI$18+7*(5-1)+6))) | AD24: =IF($AB24="","",IFERROR((SUMIFS($M$8:$M$38,$A$8:$A$38,">="&$AI$18+7*(5-1),$A$8:$A$38,"<="&$AI$18+7*(5-1)+6)+SUMIFS('2026年06月'!$M$8:$M$37,'2026年06月'!$A$8:$A$37,">="&$AI$18+7*(5-1),'2026年06月'!$A$8:$A$37,"<="&$AI$18+7*(5-1)+6))/(SUMIFS($O$8:$O$38,$A$8:$A$38,">="&$AI$18+7*(5-1),$A$8:$A$38,"<="&$AI$18+7*(5-1)+6)+SUMIFS('2026年06月'!$O$8:$O$37,'2026年06月'!$A$8:$A$37,">="&$AI$18+7*(5-1),'2026年06月'!$A$8:$A$37,"<="&$AI$18+7*(5-1)+6)),"")) | AE24: =IF($AB24="","",IFERROR((SUMIFS($G$8:$G$38,$A$8:$A$38,">="&$AI$18+7*(5-1),$A$8:$A$38,"<="&$AI$18+7*(5-1)+6)+SUMIFS('2026年06月'!$G$8:$G$37,'2026年06月'!$A$8:$A$37,">="&$AI$18+7*(5-1),'2026年06月'!$A$8:$A$37,"<="&$AI$18+7*(5-1)+6))/(SUMIFS($M$8:$M$38,$A$8:$A$38,">="&$AI$18+7*(5-1),$A$8:$A$38,"<="&$AI$18+7*(5-1)+6)+SUMIFS('2026年06月'!$M$8:$M$37,'2026年06月'!$A$8:$A$37,">="&$AI$18+7*(5-1),'2026年06月'!$A$8:$A$37,"<="&$AI$18+7*(5-1)+6)),"")) | AF24: =IF($AB24="","",IFERROR((SUMIFS($N$8:$N$38,$A$8:$A$38,">="&$AI$18+7*(5-1),$A$8:$A$38,"<="&$AI$18+7*(5-1)+6)+SUMIFS('2026年06月'!$N$8:$N$37,'2026年06月'!$A$8:$A$37,">="&$AI$18+7*(5-1),'2026年06月'!$A$8:$A$37,"<="&$AI$18+7*(5-1)+6))/(SUMIFS($M$8:$M$38,$A$8:$A$38,">="&$AI$18+7*(5-1),$A$8:$A$38,"<="&$AI$18+7*(5-1)+6)+SUMIFS('2026年06月'!$M$8:$M$37,'2026年06月'!$A$8:$A$37,">="&$AI$18+7*(5-1),'2026年06月'!$A$8:$A$37,"<="&$AI$18+7*(5-1)+6)),"")) | AG24: =IF($AB24="","",IFERROR((SUMIFS($P$8:$P$38,$A$8:$A$38,">="&$AI$18+7*(5-1),$A$8:$A$38,"<="&$AI$18+7*(5-1)+6)+SUMIFS('2026年06月'!$P$8:$P$37,'2026年06月'!$A$8:$A$37,">="&$AI$18+7*(5-1),'2026年06月'!$A$8:$A$37,"<="&$AI$18+7*(5-1)+6))/(SUMIFS($O$8:$O$38,$A$8:$A$38,">="&$AI$18+7*(5-1),$A$8:$A$38,"<="&$AI$18+7*(5-1)+6)+SUMIFS('2026年06月'!$O$8:$O$37,'2026年06月'!$A$8:$A$37,">="&$AI$18+7*(5-1),'2026年06月'!$A$8:$A$37,"<="&$AI$18+7*(5-1)+6)),""))
A25: 46160 | B25: =MID("日月火水木金土",WEEKDAY(A25),1) -> 月 | C25: 500000 | D25: =SUM($C$8:C25) -> 12900000 | E25: 91877 | F25: 341130 | G25: =IF(COUNT(E25:F25)=0,"",SUM(E25:F25)) -> 433007 | H25: =IF(G25="","",SUM($G$8:G25)) -> 7261882 | I25: =IF(G25="","",IFERROR(G25/C25,"")) -> 0.866014 | J25: =IF(H25="","",IFERROR(H25/D25,"")) -> 0.56293659 | K25: =IF(H25="","",IF(D25=0,"",H25-D25)) -> -5638118 | L25: =IF(G25="","—",IF(D25=0,"予算未入力",IF(H25>=D25,"◎ ペース内","▲ 遅れ"))) -> ▲ 遅れ | M25: 18 | N25: 21 | O25: 61 | P25: 21 | Q25: 47 | R25: =IFERROR(M25/O25,"") -> 0.29508197 | S25: =IFERROR(G25/M25,"") -> 24055.944 | T25: =IFERROR(N25/M25,"") -> 1.1666667 | U25: =IFERROR(P25/O25,"") -> 0.3442623 | W25: 43999 | X25: 0 | AA25: 6 | AB25: =IF($AI$18+7*(6-1)>$A$38,"",TEXT($AI$18+7*(6-1),"m/d")&"-"&TEXT($AI$18+7*(6-1)+6,"m/d")) | AC25: =IF($AB25="","",(SUMIFS($G$8:$G$38,$A$8:$A$38,">="&$AI$18+7*(6-1),$A$8:$A$38,"<="&$AI$18+7*(6-1)+6)+SUMIFS('2026年06月'!$G$8:$G$37,'2026年06月'!$A$8:$A$37,">="&$AI$18+7*(6-1),'2026年06月'!$A$8:$A$37,"<="&$AI$18+7*(6-1)+6))) | AD25: =IF($AB25="","",IFERROR((SUMIFS($M$8:$M$38,$A$8:$A$38,">="&$AI$18+7*(6-1),$A$8:$A$38,"<="&$AI$18+7*(6-1)+6)+SUMIFS('2026年06月'!$M$8:$M$37,'2026年06月'!$A$8:$A$37,">="&$AI$18+7*(6-1),'2026年06月'!$A$8:$A$37,"<="&$AI$18+7*(6-1)+6))/(SUMIFS($O$8:$O$38,$A$8:$A$38,">="&$AI$18+7*(6-1),$A$8:$A$38,"<="&$AI$18+7*(6-1)+6)+SUMIFS('2026年06月'!$O$8:$O$37,'2026年06月'!$A$8:$A$37,">="&$AI$18+7*(6-1),'2026年06月'!$A$8:$A$37,"<="&$AI$18+7*(6-1)+6)),"")) | AE25: =IF($AB25="","",IFERROR((SUMIFS($G$8:$G$38,$A$8:$A$38,">="&$AI$18+7*(6-1),$A$8:$A$38,"<="&$AI$18+7*(6-1)+6)+SUMIFS('2026年06月'!$G$8:$G$37,'2026年06月'!$A$8:$A$37,">="&$AI$18+7*(6-1),'2026年06月'!$A$8:$A$37,"<="&$AI$18+7*(6-1)+6))/(SUMIFS($M$8:$M$38,$A$8:$A$38,">="&$AI$18+7*(6-1),$A$8:$A$38,"<="&$AI$18+7*(6-1)+6)+SUMIFS('2026年06月'!$M$8:$M$37,'2026年06月'!$A$8:$A$37,">="&$AI$18+7*(6-1),'2026年06月'!$A$8:$A$37,"<="&$AI$18+7*(6-1)+6)),"")) | AF25: =IF($AB25="","",IFERROR((SUMIFS($N$8:$N$38,$A$8:$A$38,">="&$AI$18+7*(6-1),$A$8:$A$38,"<="&$AI$18+7*(6-1)+6)+SUMIFS('2026年06月'!$N$8:$N$37,'2026年06月'!$A$8:$A$37,">="&$AI$18+7*(6-1),'2026年06月'!$A$8:$A$37,"<="&$AI$18+7*(6-1)+6))/(SUMIFS($M$8:$M$38,$A$8:$A$38,">="&$AI$18+7*(6-1),$A$8:$A$38,"<="&$AI$18+7*(6-1)+6)+SUMIFS('2026年06月'!$M$8:$M$37,'2026年06月'!$A$8:$A$37,">="&$AI$18+7*(6-1),'2026年06月'!$A$8:$A$37,"<="&$AI$18+7*(6-1)+6)),"")) | AG25: =IF($AB25="","",IFERROR((SUMIFS($P$8:$P$38,$A$8:$A$38,">="&$AI$18+7*(6-1),$A$8:$A$38,"<="&$AI$18+7*(6-1)+6)+SUMIFS('2026年06月'!$P$8:$P$37,'2026年06月'!$A$8:$A$37,">="&$AI$18+7*(6-1),'2026年06月'!$A$8:$A$37,"<="&$AI$18+7*(6-1)+6))/(SUMIFS($O$8:$O$38,$A$8:$A$38,">="&$AI$18+7*(6-1),$A$8:$A$38,"<="&$AI$18+7*(6-1)+6)+SUMIFS('2026年06月'!$O$8:$O$37,'2026年06月'!$A$8:$A$37,">="&$AI$18+7*(6-1),'2026年06月'!$A$8:$A$37,"<="&$AI$18+7*(6-1)+6)),""))
A26: 46161 | B26: =MID("日月火水木金土",WEEKDAY(A26),1) -> 火 | C26: 500000 | D26: =SUM($C$8:C26) -> 13400000 | E26: 61930 | F26: 280870 | G26: =IF(COUNT(E26:F26)=0,"",SUM(E26:F26)) -> 342800 | H26: =IF(G26="","",SUM($G$8:G26)) -> 7604682 | I26: =IF(G26="","",IFERROR(G26/C26,"")) -> 0.6856 | J26: =IF(H26="","",IFERROR(H26/D26,"")) -> 0.56751358 | K26: =IF(H26="","",IF(D26=0,"",H26-D26)) -> -5795318 | L26: =IF(G26="","—",IF(D26=0,"予算未入力",IF(H26>=D26,"◎ ペース内","▲ 遅れ"))) -> ▲ 遅れ | M26: 13 | N26: 15 | O26: 63 | P26: 34 | Q26: 51 | R26: =IFERROR(M26/O26,"") -> 0.20634921 | S26: =IFERROR(G26/M26,"") -> 26369.231 | T26: =IFERROR(N26/M26,"") -> 1.1538462 | U26: =IFERROR(P26/O26,"") -> 0.53968254 | W26: 44012 | X26: 0 | AA26: ※期間ラベルは第1火曜から自動生成。決定率・客単価・セット率・試着率は「週合計÷週合計」
A27: 46162 | B27: =MID("日月火水木金土",WEEKDAY(A27),1) -> 水 | C27: 500000 | D27: =SUM($C$8:C27) -> 13900000 | E27: 117850 | F27: 224610 | G27: =IF(COUNT(E27:F27)=0,"",SUM(E27:F27)) -> 342460 | H27: =IF(G27="","",SUM($G$8:G27)) -> 7947142 | I27: =IF(G27="","",IFERROR(G27/C27,"")) -> 0.68492 | J27: =IF(H27="","",IFERROR(H27/D27,"")) -> 0.57173683 | K27: =IF(H27="","",IF(D27=0,"",H27-D27)) -> -5952858 | L27: =IF(G27="","—",IF(D27=0,"予算未入力",IF(H27>=D27,"◎ ペース内","▲ 遅れ"))) -> ▲ 遅れ | M27: 14 | N27: 17 | O27: 39 | P27: 18 | Q27: 28 | R27: =IFERROR(M27/O27,"") -> 0.35897436 | S27: =IFERROR(G27/M27,"") -> 24461.429 | T27: =IFERROR(N27/M27,"") -> 1.2142857 | U27: =IFERROR(P27/O27,"") -> 0.46153846 | W27: 44038 | X27: 0 | AA27: ※最終週は翌月にまたぐため、2026年06月シートの実績も自動で合算します
A28: 46163 | B28: =MID("日月火水木金土",WEEKDAY(A28),1) -> 木 | C28: 500000 | D28: =SUM($C$8:C28) -> 14400000 | E28: 47510 | F28: 195570 | G28: =IF(COUNT(E28:F28)=0,"",SUM(E28:F28)) -> 243080 | H28: =IF(G28="","",SUM($G$8:G28)) -> 8190222 | I28: =IF(G28="","",IFERROR(G28/C28,"")) -> 0.48616 | J28: =IF(H28="","",IFERROR(H28/D28,"")) -> 0.56876542 | K28: =IF(H28="","",IF(D28=0,"",H28-D28)) -> -6209778 | L28: =IF(G28="","—",IF(D28=0,"予算未入力",IF(H28>=D28,"◎ ペース内","▲ 遅れ"))) -> ▲ 遅れ | M28: 9 | N28: 12 | O28: 28 | P28: 17 | Q28: 38 | R28: =IFERROR(M28/O28,"") -> 0.32142857 | S28: =IFERROR(G28/M28,"") -> 27008.889 | T28: =IFERROR(N28/M28,"") -> 1.3333333 | U28: =IFERROR(P28/O28,"") -> 0.60714286 | X28: 0 | AA28: ※月初の月曜まで（例：6/1）は前月シートの最終週に含まれます
A29: 46164 | B29: =MID("日月火水木金土",WEEKDAY(A29),1) -> 金 | C29: 500000 | D29: =SUM($C$8:C29) -> 14900000 | E29: 95240 | F29: 101530 | G29: =IF(COUNT(E29:F29)=0,"",SUM(E29:F29)) -> 196770 | H29: =IF(G29="","",SUM($G$8:G29)) -> 8386992 | I29: =IF(G29="","",IFERROR(G29/C29,"")) -> 0.39354 | J29: =IF(H29="","",IFERROR(H29/D29,"")) -> 0.56288537 | K29: =IF(H29="","",IF(D29=0,"",H29-D29)) -> -6513008 | L29: =IF(G29="","—",IF(D29=0,"予算未入力",IF(H29>=D29,"◎ ペース内","▲ 遅れ"))) -> ▲ 遅れ | M29: 9 | N29: 10 | O29: 50 | P29: 19 | Q29: 25 | R29: =IFERROR(M29/O29,"") -> 0.18 | S29: =IFERROR(G29/M29,"") -> 21863.333 | T29: =IFERROR(N29/M29,"") -> 1.1111111 | U29: =IFERROR(P29/O29,"") -> 0.38 | W29: 44064 | X29: 0
A30: 46165 | B30: =MID("日月火水木金土",WEEKDAY(A30),1) -> 土 | C30: 700000 | D30: =SUM($C$8:C30) -> 15600000 | E30: 74890 | F30: 547079 | G30: =IF(COUNT(E30:F30)=0,"",SUM(E30:F30)) -> 621969 | H30: =IF(G30="","",SUM($G$8:G30)) -> 9008961 | I30: =IF(G30="","",IFERROR(G30/C30,"")) -> 0.88852714 | J30: =IF(H30="","",IFERROR(H30/D30,"")) -> 0.5774975 | K30: =IF(H30="","",IF(D30=0,"",H30-D30)) -> -6591039 | L30: =IF(G30="","—",IF(D30=0,"予算未入力",IF(H30>=D30,"◎ ペース内","▲ 遅れ"))) -> ▲ 遅れ | M30: 27 | N30: 27 | O30: 49 | P30: 42 | Q30: 66 | R30: =IFERROR(M30/O30,"") -> 0.55102041 | S30: =IFERROR(G30/M30,"") -> 23035.889 | T30: =IFERROR(N30/M30,"") -> 1 | U30: =IFERROR(P30/O30,"") -> 0.85714286 | W30: 44088 | X30: 0
A31: 46166 | B31: =MID("日月火水木金土",WEEKDAY(A31),1) -> 日 | C31: 700000 | D31: =SUM($C$8:C31) -> 16300000 | E31: 114650 | F31: 427560 | G31: =IF(COUNT(E31:F31)=0,"",SUM(E31:F31)) -> 542210 | H31: =IF(G31="","",SUM($G$8:G31)) -> 9551171 | I31: =IF(G31="","",IFERROR(G31/C31,"")) -> 0.77458571 | J31: =IF(H31="","",IFERROR(H31/D31,"")) -> 0.58596141 | K31: =IF(H31="","",IF(D31=0,"",H31-D31)) -> -6748829 | L31: =IF(G31="","—",IF(D31=0,"予算未入力",IF(H31>=D31,"◎ ペース内","▲ 遅れ"))) -> ▲ 遅れ | M31: 24 | N31: 24 | O31: 59 | P31: 42 | Q31: 71 | R31: =IFERROR(M31/O31,"") -> 0.40677966 | S31: =IFERROR(G31/M31,"") -> 22592.083 | T31: =IFERROR(N31/M31,"") -> 1 | U31: =IFERROR(P31/O31,"") -> 0.71186441 | W31: 44130 | X31: 0
A32: 46167 | B32: =MID("日月火水木金土",WEEKDAY(A32),1) -> 月 | C32: 500000 | D32: =SUM($C$8:C32) -> 16800000 | E32: 78530 | F32: 438570 | G32: =IF(COUNT(E32:F32)=0,"",SUM(E32:F32)) -> 517100 | H32: =IF(G32="","",SUM($G$8:G32)) -> 10068271 | I32: =IF(G32="","",IFERROR(G32/C32,"")) -> 1.0342 | J32: =IF(H32="","",IFERROR(H32/D32,"")) -> 0.59930185 | K32: =IF(H32="","",IF(D32=0,"",H32-D32)) -> -6731729 | L32: =IF(G32="","—",IF(D32=0,"予算未入力",IF(H32>=D32,"◎ ペース内","▲ 遅れ"))) -> ▲ 遅れ | M32: 23 | N32: 24 | O32: 57 | P32: 38 | Q32: 65 | R32: =IFERROR(M32/O32,"") -> 0.40350877 | S32: =IFERROR(G32/M32,"") -> 22482.609 | T32: =IFERROR(N32/M32,"") -> 1.0434783 | U32: =IFERROR(P32/O32,"") -> 0.66666667 | W32: 44139 | X32: 0
A33: 46168 | B33: =MID("日月火水木金土",WEEKDAY(A33),1) -> 火 | C33: 500000 | D33: =SUM($C$8:C33) -> 17300000 | E33: 71430 | F33: 201170 | G33: =IF(COUNT(E33:F33)=0,"",SUM(E33:F33)) -> 272600 | H33: =IF(G33="","",SUM($G$8:G33)) -> 10340871 | I33: =IF(G33="","",IFERROR(G33/C33,"")) -> 0.5452 | J33: =IF(H33="","",IFERROR(H33/D33,"")) -> 0.59773821 | K33: =IF(H33="","",IF(D33=0,"",H33-D33)) -> -6959129 | L33: =IF(G33="","—",IF(D33=0,"予算未入力",IF(H33>=D33,"◎ ペース内","▲ 遅れ"))) -> ▲ 遅れ | M33: 12 | N33: 12 | O33: 37 | P33: 17 | Q33: 30 | R33: =IFERROR(M33/O33,"") -> 0.32432432 | S33: =IFERROR(G33/M33,"") -> 22716.667 | T33: =IFERROR(N33/M33,"") -> 1 | U33: =IFERROR(P33/O33,"") -> 0.45945946 | W33: 44144 | X33: 0
A34: 46169 | B34: =MID("日月火水木金土",WEEKDAY(A34),1) -> 水 | C34: 500000 | D34: =SUM($C$8:C34) -> 17800000 | E34: 45530 | F34: 433860 | G34: =IF(COUNT(E34:F34)=0,"",SUM(E34:F34)) -> 479390 | H34: =IF(G34="","",SUM($G$8:G34)) -> 10820261 | I34: =IF(G34="","",IFERROR(G34/C34,"")) -> 0.95878 | J34: =IF(H34="","",IFERROR(H34/D34,"")) -> 0.60787983 | K34: =IF(H34="","",IF(D34=0,"",H34-D34)) -> -6979739 | L34: =IF(G34="","—",IF(D34=0,"予算未入力",IF(H34>=D34,"◎ ペース内","▲ 遅れ"))) -> ▲ 遅れ | M34: 19 | N34: 25 | O34: 37 | P34: 28 | Q34: 44 | R34: =IFERROR(M34/O34,"") -> 0.51351351 | S34: =IFERROR(G34/M34,"") -> 25231.053 | T34: =IFERROR(N34/M34,"") -> 1.3157895 | U34: =IFERROR(P34/O34,"") -> 0.75675676 | W34: 44155 | X34: 0
A35: 46170 | B35: =MID("日月火水木金土",WEEKDAY(A35),1) -> 木 | C35: 500000 | D35: =SUM($C$8:C35) -> 18300000 | E35: 67920 | F35: 291474 | G35: =IF(COUNT(E35:F35)=0,"",SUM(E35:F35)) -> 359394 | H35: =IF(G35="","",SUM($G$8:G35)) -> 11179655 | I35: =IF(G35="","",IFERROR(G35/C35,"")) -> 0.718788 | J35: =IF(H35="","",IFERROR(H35/D35,"")) -> 0.61091011 | K35: =IF(H35="","",IF(D35=0,"",H35-D35)) -> -7120345 | L35: =IF(G35="","—",IF(D35=0,"予算未入力",IF(H35>=D35,"◎ ペース内","▲ 遅れ"))) -> ▲ 遅れ | M35: 17 | N35: 17 | O35: 36 | P35: 20 | Q35: 29 | R35: =IFERROR(M35/O35,"") -> 0.47222222 | S35: =IFERROR(G35/M35,"") -> 21140.824 | T35: =IFERROR(N35/M35,"") -> 1 | U35: =IFERROR(P35/O35,"") -> 0.55555556 | W35: 44172 | X35: 0
A36: 46171 | B36: =MID("日月火水木金土",WEEKDAY(A36),1) -> 金 | C36: 500000 | D36: =SUM($C$8:C36) -> 18800000 | E36: 50320 | F36: 133930 | G36: =IF(COUNT(E36:F36)=0,"",SUM(E36:F36)) -> 184250 | H36: =IF(G36="","",SUM($G$8:G36)) -> 11363905 | I36: =IF(G36="","",IFERROR(G36/C36,"")) -> 0.3685 | J36: =IF(H36="","",IFERROR(H36/D36,"")) -> 0.60446303 | K36: =IF(H36="","",IF(D36=0,"",H36-D36)) -> -7436095 | L36: =IF(G36="","—",IF(D36=0,"予算未入力",IF(H36>=D36,"◎ ペース内","▲ 遅れ"))) -> ▲ 遅れ | M36: 8 | N36: 8 | O36: 24 | P36: 18 | Q36: 40 | R36: =IFERROR(M36/O36,"") -> 0.33333333 | S36: =IFERROR(G36/M36,"") -> 23031.25 | T36: =IFERROR(N36/M36,"") -> 1 | U36: =IFERROR(P36/O36,"") -> 0.75 | W36: 44168 | X36: 0 | Y36: ※要確認：旧シートの売上合計と内訳が+1,243円ズレ。合計184,250円に合わせクレジットを132,687→133,930に調整
A37: 46172 | B37: =MID("日月火水木金土",WEEKDAY(A37),1) -> 土 | C37: 700000 | D37: =SUM($C$8:C37) -> 19500000 | E37: 133350 | F37: 519970 | G37: =IF(COUNT(E37:F37)=0,"",SUM(E37:F37)) -> 653320 | H37: =IF(G37="","",SUM($G$8:G37)) -> 12017225 | I37: =IF(G37="","",IFERROR(G37/C37,"")) -> 0.93331429 | J37: =IF(H37="","",IFERROR(H37/D37,"")) -> 0.61626795 | K37: =IF(H37="","",IF(D37=0,"",H37-D37)) -> -7482775 | L37: =IF(G37="","—",IF(D37=0,"予算未入力",IF(H37>=D37,"◎ ペース内","▲ 遅れ"))) -> ▲ 遅れ | M37: 28 | N37: 30 | O37: 53 | P37: 39 | Q37: 66 | R37: =IFERROR(M37/O37,"") -> 0.52830189 | S37: =IFERROR(G37/M37,"") -> 23332.857 | T37: =IFERROR(N37/M37,"") -> 1.0714286 | U37: =IFERROR(P37/O37,"") -> 0.73584906 | W37: 44159 | X37: 0
A38: 46173 | B38: =MID("日月火水木金土",WEEKDAY(A38),1) -> 日 | C38: 700000 | D38: =SUM($C$8:C38) -> 20200000 | E38: 19910 | F38: 343917 | G38: =IF(COUNT(E38:F38)=0,"",SUM(E38:F38)) -> 363827 | H38: =IF(G38="","",SUM($G$8:G38)) -> 12381052 | I38: =IF(G38="","",IFERROR(G38/C38,"")) -> 0.51975286 | J38: =IF(H38="","",IFERROR(H38/D38,"")) -> 0.61292337 | K38: =IF(H38="","",IF(D38=0,"",H38-D38)) -> -7818948 | L38: =IF(G38="","—",IF(D38=0,"予算未入力",IF(H38>=D38,"◎ ペース内","▲ 遅れ"))) -> ▲ 遅れ | M38: 15 | N38: 17 | O38: 56 | P38: 29 | Q38: 46 | R38: =IFERROR(M38/O38,"") -> 0.26785714 | S38: =IFERROR(G38/M38,"") -> 24255.133 | T38: =IFERROR(N38/M38,"") -> 1.1333333 | U38: =IFERROR(P38/O38,"") -> 0.51785714 | W38: 44164 | X38: 0
A39: 月計 | C39: =SUM(C8:C38) -> 20200000 | D39: =C39 -> 20200000 | E39: =SUM(E8:E38) -> 2346367 | F39: =SUM(F8:F38) -> 10034685 | G39: =SUM(G8:G38) -> 12381052 | H39: =G39 -> 12381052 | I39: =IFERROR(G39/C39,"") -> 0.61292337 | J39: =IFERROR(G39/C39,"") -> 0.61292337 | K39: =G39-C39 -> -7818948 | M39: =SUM(M8:M38) -> 537 | N39: =SUM(N8:N38) -> 594 | O39: =SUM(O8:O38) -> 1516 | P39: =SUM(P8:P38) -> 926 | Q39: =SUM(Q8:Q38) -> 1630 | R39: =IFERROR(M39/O39,"") -> 0.35422164 | S39: =IFERROR(G39/M39,"") -> 23055.963 | T39: =IFERROR(N39/M39,"") -> 1.1061453 | U39: =IFERROR(P39/O39,"") -> 0.61081794 | V39: =SUM(V8:V38) -> 0 | W39: =IFERROR(LOOKUP(9.99E+307,W8:W38),"") -> 44164 | X39: =SUM(X8:X38) -> 0 | Y39: フォロワーは月末値

Sheet 2026年06月
A1: 2026年6月 原宿店 日別売上管理
A2: 青字＋薄黄色のセルが入力欄。白セルは数式なので触らないでください。単位：円
A3: 月間予算 | C3: 当月実績 | E3: 達成率 | G3: 営業日数(/30日) | I3: 残り必要額 | K3: 残り必要日商
A4: =IF('設定'!$B$10="",SUM(C8:C37),'設定'!$B$10) -> 17000000 | C4: =SUM(G8:G37) -> 10446643 | E4: =IFERROR(C4/A4,0) -> 0.61450841 | G4: =COUNTIF(G8:G37,">0") -> 30 | I4: =A4-C4 -> 6553357 | K4: =IF((30-G4)>0,(A4-C4)/(30-G4),0) -> 0
A5: 日次予算合計 | C5: 着地見込 | E5: 決定率 | G5: 客単価 | I5: セット率 | K5: 試着率
A6: =SUM(C8:C37) -> 18500000 | C6: =IFERROR(C4/G4*30,0) -> 10446643 | E6: =IFERROR(M38/O38,0) -> 0.35074045 | G6: =IFERROR(G38/M38,0) -> 23214.762 | I6: =IFERROR(N38/M38,0) -> 1.1 | K6: =IFERROR(P38/O38,0) -> 0.60872954
A7: 日付 | B7: 曜 | C7: 日次予算 | D7: 累計予算 | E7: 現金 | F7: クレジット | G7: 実績合計 | H7: 累計実績 | I7: 日次達成 | J7: 累計達成 | K7: 累計予実差 | L7: ペース | M7: 購入人数 | N7: 販売点数 | O7: 来客数 | P7: 試着組数 | Q7: 試着個数 | R7: 決定率 | S7: 客単価 | T7: セット率 | U7: 試着率 | V7: クロス クーポン | W7: インスタ フォロワー | X7: 経費 | Y7: メモ | AA7: 曜日 | AB7: 平均日商 | AC7: 日数 | AD7: 決定率 | AE7: 客単価
A8: 46174 | B8: =MID("日月火水木金土",WEEKDAY(A8),1) -> 月 | C8: 600000 | D8: =SUM($C$8:C8) -> 600000 | E8: 2140 | F8: 313310 | G8: =IF(COUNT(E8:F8)=0,"",SUM(E8:F8)) -> 315450 | H8: =IF(G8="","",SUM($G$8:G8)) -> 315450 | I8: =IF(G8="","",IFERROR(G8/C8,"")) -> 0.52575 | J8: =IF(H8="","",IFERROR(H8/D8,"")) -> 0.52575 | K8: =IF(H8="","",IF(D8=0,"",H8-D8)) -> -284550 | L8: =IF(G8="","—",IF(D8=0,"予算未入力",IF(H8>=D8,"◎ ペース内","▲ 遅れ"))) -> ▲ 遅れ | M8: 11 | N8: 18 | O8: 32 | P8: 23 | Q8: 25 | R8: =IFERROR(M8/O8,"") -> 0.34375 | S8: =IFERROR(G8/M8,"") -> 28677.273 | T8: =IFERROR(N8/M8,"") -> 1.6363636 | U8: =IFERROR(P8/O8,"") -> 0.71875 | W8: 44180 | X8: 0 | AA8: 月 | AB8: =IFERROR(AVERAGEIFS($G$8:$G$37,$B$8:$B$37,AA8,$G$8:$G$37,">0"),0) -> 351890.4 | AC8: =COUNTIFS($B$8:$B$37,AA8,$G$8:$G$37,">0") -> 5 | AD8: =IFERROR(SUMIF($B$8:$B$37,AA8,$M$8:$M$37)/SUMIF($B$8:$B$37,AA8,$O$8:$O$37),0) -> 0.34375 | AE8: =IFERROR(SUMIF($B$8:$B$37,AA8,$G$8:$G$37)/SUMIF($B$8:$B$37,AA8,$M$8:$M$37),0) -> 22850.026
A9: 46175 | B9: =MID("日月火水木金土",WEEKDAY(A9),1) -> 火 | C9: 600000 | D9: =SUM($C$8:C9) -> 1200000 | E9: 57800 | F9: 293885 | G9: =IF(COUNT(E9:F9)=0,"",SUM(E9:F9)) -> 351685 | H9: =IF(G9="","",SUM($G$8:G9)) -> 667135 | I9: =IF(G9="","",IFERROR(G9/C9,"")) -> 0.58614167 | J9: =IF(H9="","",IFERROR(H9/D9,"")) -> 0.55594583 | K9: =IF(H9="","",IF(D9=0,"",H9-D9)) -> -532865 | L9: =IF(G9="","—",IF(D9=0,"予算未入力",IF(H9>=D9,"◎ ペース内","▲ 遅れ"))) -> ▲ 遅れ | M9: 16 | N9: 17 | O9: 32 | P9: 23 | Q9: 30 | R9: =IFERROR(M9/O9,"") -> 0.5 | S9: =IFERROR(G9/M9,"") -> 21980.312 | T9: =IFERROR(N9/M9,"") -> 1.0625 | U9: =IFERROR(P9/O9,"") -> 0.71875 | W9: 44179 | X9: 0 | AA9: 火 | AB9: =IFERROR(AVERAGEIFS($G$8:$G$37,$B$8:$B$37,AA9,$G$8:$G$37,">0"),0) -> 334181 | AC9: =COUNTIFS($B$8:$B$37,AA9,$G$8:$G$37,">0") -> 5 | AD9: =IFERROR(SUMIF($B$8:$B$37,AA9,$M$8:$M$37)/SUMIF($B$8:$B$37,AA9,$O$8:$O$37),0) -> 0.3546798 | AE9: =IFERROR(SUMIF($B$8:$B$37,AA9,$G$8:$G$37)/SUMIF($B$8:$B$37,AA9,$M$8:$M$37),0) -> 23207.014
A10: 46176 | B10: =MID("日月火水木金土",WEEKDAY(A10),1) -> 水 | C10: 600000 | D10: =SUM($C$8:C10) -> 1800000 | E10: 17710 | F10: 94430 | G10: =IF(COUNT(E10:F10)=0,"",SUM(E10:F10)) -> 112140 | H10: =IF(G10="","",SUM($G$8:G10)) -> 779275 | I10: =IF(G10="","",IFERROR(G10/C10,"")) -> 0.1869 | J10: =IF(H10="","",IFERROR(H10/D10,"")) -> 0.43293056 | K10: =IF(H10="","",IF(D10=0,"",H10-D10)) -> -1020725 | L10: =IF(G10="","—",IF(D10=0,"予算未入力",IF(H10>=D10,"◎ ペース内","▲ 遅れ"))) -> ▲ 遅れ | M10: 4 | N10: 5 | O10: 16 | P10: 8 | Q10: 14 | R10: =IFERROR(M10/O10,"") -> 0.25 | S10: =IFERROR(G10/M10,"") -> 28035 | T10: =IFERROR(N10/M10,"") -> 1.25 | U10: =IFERROR(P10/O10,"") -> 0.5 | W10: 44183 | X10: 0 | AA10: 水 | AB10: =IFERROR(AVERAGEIFS($G$8:$G$37,$B$8:$B$37,AA10,$G$8:$G$37,">0"),0) -> 243846.25 | AC10: =COUNTIFS($B$8:$B$37,AA10,$G$8:$G$37,">0") -> 4 | AD10: =IFERROR(SUMIF($B$8:$B$37,AA10,$M$8:$M$37)/SUMIF($B$8:$B$37,AA10,$O$8:$O$37),0) -> 0.3037037 | AE10: =IFERROR(SUMIF($B$8:$B$37,AA10,$G$8:$G$37)/SUMIF($B$8:$B$37,AA10,$M$8:$M$37),0) -> 23789.878
A11: 46177 | B11: =MID("日月火水木金土",WEEKDAY(A11),1) -> 木 | C11: 600000 | D11: =SUM($C$8:C11) -> 2400000 | E11: 24310 | F11: 288052 | G11: =IF(COUNT(E11:F11)=0,"",SUM(E11:F11)) -> 312362 | H11: =IF(G11="","",SUM($G$8:G11)) -> 1091637 | I11: =IF(G11="","",IFERROR(G11/C11,"")) -> 0.52060333 | J11: =IF(H11="","",IFERROR(H11/D11,"")) -> 0.45484875 | K11: =IF(H11="","",IF(D11=0,"",H11-D11)) -> -1308363 | L11: =IF(G11="","—",IF(D11=0,"予算未入力",IF(H11>=D11,"◎ ペース内","▲ 遅れ"))) -> ▲ 遅れ | M11: 16 | N11: 15 | O11: 24 | P11: 19 | Q11: 22 | R11: =IFERROR(M11/O11,"") -> 0.66666667 | S11: =IFERROR(G11/M11,"") -> 19522.625 | T11: =IFERROR(N11/M11,"") -> 0.9375 | U11: =IFERROR(P11/O11,"") -> 0.79166667 | W11: 44187 | X11: 0 | AA11: 木 | AB11: =IFERROR(AVERAGEIFS($G$8:$G$37,$B$8:$B$37,AA11,$G$8:$G$37,">0"),0) -> 301174.75 | AC11: =COUNTIFS($B$8:$B$37,AA11,$G$8:$G$37,">0") -> 4 | AD11: =IFERROR(SUMIF($B$8:$B$37,AA11,$M$8:$M$37)/SUMIF($B$8:$B$37,AA11,$O$8:$O$37),0) -> 0.29824561 | AE11: =IFERROR(SUMIF($B$8:$B$37,AA11,$G$8:$G$37)/SUMIF($B$8:$B$37,AA11,$M$8:$M$37),0) -> 23621.549
A12: 46178 | B12: =MID("日月火水木金土",WEEKDAY(A12),1) -> 金 | C12: 600000 | D12: =SUM($C$8:C12) -> 3000000 | E12: 100200 | F12: 198050 | G12: =IF(COUNT(E12:F12)=0,"",SUM(E12:F12)) -> 298250 | H12: =IF(G12="","",SUM($G$8:G12)) -> 1389887 | I12: =IF(G12="","",IFERROR(G12/C12,"")) -> 0.49708333 | J12: =IF(H12="","",IFERROR(H12/D12,"")) -> 0.46329567 | K12: =IF(H12="","",IF(D12=0,"",H12-D12)) -> -1610113 | L12: =IF(G12="","—",IF(D12=0,"予算未入力",IF(H12>=D12,"◎ ペース内","▲ 遅れ"))) -> ▲ 遅れ | M12: 13 | N12: 16 | O12: 38 | P12: 14 | Q12: 22 | R12: =IFERROR(M12/O12,"") -> 0.34210526 | S12: =IFERROR(G12/M12,"") -> 22942.308 | T12: =IFERROR(N12/M12,"") -> 1.2307692 | U12: =IFERROR(P12/O12,"") -> 0.36842105 | W12: 44186 | X12: 0 | AA12: 金 | AB12: =IFERROR(AVERAGEIFS($G$8:$G$37,$B$8:$B$37,AA12,$G$8:$G$37,">0"),0) -> 290082.5 | AC12: =COUNTIFS($B$8:$B$37,AA12,$G$8:$G$37,">0") -> 4 | AD12: =IFERROR(SUMIF($B$8:$B$37,AA12,$M$8:$M$37)/SUMIF($B$8:$B$37,AA12,$O$8:$O$37),0) -> 0.38345865 | AE12: =IFERROR(SUMIF($B$8:$B$37,AA12,$G$8:$G$37)/SUMIF($B$8:$B$37,AA12,$M$8:$M$37),0) -> 22751.569
A13: 46179 | B13: =MID("日月火水木金土",WEEKDAY(A13),1) -> 土 | C13: 900000 | D13: =SUM($C$8:C13) -> 3900000 | E13: 143050 | F13: 404400 | G13: =IF(COUNT(E13:F13)=0,"",SUM(E13:F13)) -> 547450 | H13: =IF(G13="","",SUM($G$8:G13)) -> 1937337 | I13: =IF(G13="","",IFERROR(G13/C13,"")) -> 0.60827778 | J13: =IF(H13="","",IFERROR(H13/D13,"")) -> 0.49675308 | K13: =IF(H13="","",IF(D13=0,"",H13-D13)) -> -1962663 | L13: =IF(G13="","—",IF(D13=0,"予算未入力",IF(H13>=D13,"◎ ペース内","▲ 遅れ"))) -> ▲ 遅れ | M13: 23 | N13: 24 | O13: 45 | P13: 35 | Q13: 59 | R13: =IFERROR(M13/O13,"") -> 0.51111111 | S13: =IFERROR(G13/M13,"") -> 23802.174 | T13: =IFERROR(N13/M13,"") -> 1.0434783 | U13: =IFERROR(P13/O13,"") -> 0.77777778 | W13: 44182 | X13: 0 | AA13: 土 | AB13: =IFERROR(AVERAGEIFS($G$8:$G$37,$B$8:$B$37,AA13,$G$8:$G$37,">0"),0) -> 384109.5 | AC13: =COUNTIFS($B$8:$B$37,AA13,$G$8:$G$37,">0") -> 4 | AD13: =IFERROR(SUMIF($B$8:$B$37,AA13,$M$8:$M$37)/SUMIF($B$8:$B$37,AA13,$O$8:$O$37),0) -> 0.37640449 | AE13: =IFERROR(SUMIF($B$8:$B$37,AA13,$G$8:$G$37)/SUMIF($B$8:$B$37,AA13,$M$8:$M$37),0) -> 22931.91
A14: 46180 | B14: =MID("日月火水木金土",WEEKDAY(A14),1) -> 日 | C14: 800000 | D14: =SUM($C$8:C14) -> 4700000 | E14: 113157 | F14: 253510 | G14: =IF(COUNT(E14:F14)=0,"",SUM(E14:F14)) -> 366667 | H14: =IF(G14="","",SUM($G$8:G14)) -> 2304004 | I14: =IF(G14="","",IFERROR(G14/C14,"")) -> 0.45833375 | J14: =IF(H14="","",IFERROR(H14/D14,"")) -> 0.49021362 | K14: =IF(H14="","",IF(D14=0,"",H14-D14)) -> -2395996 | L14: =IF(G14="","—",IF(D14=0,"予算未入力",IF(H14>=D14,"◎ ペース内","▲ 遅れ"))) -> ▲ 遅れ | M14: 16 | N14: 16 | O14: 57 | P14: 40 | Q14: 47 | R14: =IFERROR(M14/O14,"") -> 0.28070175 | S14: =IFERROR(G14/M14,"") -> 22916.688 | T14: =IFERROR(N14/M14,"") -> 1 | U14: =IFERROR(P14/O14,"") -> 0.70175439 | W14: 44173 | X14: 0 | AA14: 日 | AB14: =IFERROR(AVERAGEIFS($G$8:$G$37,$B$8:$B$37,AA14,$G$8:$G$37,">0"),0) -> 534858.5 | AC14: =COUNTIFS($B$8:$B$37,AA14,$G$8:$G$37,">0") -> 4 | AD14: =IFERROR(SUMIF($B$8:$B$37,AA14,$M$8:$M$37)/SUMIF($B$8:$B$37,AA14,$O$8:$O$37),0) -> 0.38075314 | AE14: =IFERROR(SUMIF($B$8:$B$37,AA14,$G$8:$G$37)/SUMIF($B$8:$B$37,AA14,$M$8:$M$37),0) -> 23510.264
A15: 46181 | B15: =MID("日月火水木金土",WEEKDAY(A15),1) -> 月 | C15: 500000 | D15: =SUM($C$8:C15) -> 5200000 | E15: 59977 | F15: 258865 | G15: =IF(COUNT(E15:F15)=0,"",SUM(E15:F15)) -> 318842 | H15: =IF(G15="","",SUM($G$8:G15)) -> 2622846 | I15: =IF(G15="","",IFERROR(G15/C15,"")) -> 0.637684 | J15: =IF(H15="","",IFERROR(H15/D15,"")) -> 0.50439346 | K15: =IF(H15="","",IF(D15=0,"",H15-D15)) -> -2577154 | L15: =IF(G15="","—",IF(D15=0,"予算未入力",IF(H15>=D15,"◎ ペース内","▲ 遅れ"))) -> ▲ 遅れ | M15: 14 | N15: 16 | O15: 54 | P15: 45 | Q15: 49 | R15: =IFERROR(M15/O15,"") -> 0.25925926 | S15: =IFERROR(G15/M15,"") -> 22774.429 | T15: =IFERROR(N15/M15,"") -> 1.1428571 | U15: =IFERROR(P15/O15,"") -> 0.83333333 | W15: 44186 | X15: 0
A16: 46182 | B16: =MID("日月火水木金土",WEEKDAY(A16),1) -> 火 | C16: 500000 | D16: =SUM($C$8:C16) -> 5700000 | E16: 87330 | F16: 209920 | G16: =IF(COUNT(E16:F16)=0,"",SUM(E16:F16)) -> 297250 | H16: =IF(G16="","",SUM($G$8:G16)) -> 2920096 | I16: =IF(G16="","",IFERROR(G16/C16,"")) -> 0.5945 | J16: =IF(H16="","",IFERROR(H16/D16,"")) -> 0.51229754 | K16: =IF(H16="","",IF(D16=0,"",H16-D16)) -> -2779904 | L16: =IF(G16="","—",IF(D16=0,"予算未入力",IF(H16>=D16,"◎ ペース内","▲ 遅れ"))) -> ▲ 遅れ | M16: 14 | N16: 15 | O16: 41 | P16: 19 | R16: =IFERROR(M16/O16,"") -> 0.34146341 | S16: =IFERROR(G16/M16,"") -> 21232.143 | T16: =IFERROR(N16/M16,"") -> 1.0714286 | U16: =IFERROR(P16/O16,"") -> 0.46341463 | W16: 44176 | X16: 0 | AA16: ※実績入力後に曜日別の傾向が出ます
A17: 46183 | B17: =MID("日月火水木金土",WEEKDAY(A17),1) -> 水 | C17: 500000 | D17: =SUM($C$8:C17) -> 6200000 | E17: 65545 | F17: 208870 | G17: =IF(COUNT(E17:F17)=0,"",SUM(E17:F17)) -> 274415 | H17: =IF(G17="","",SUM($G$8:G17)) -> 3194511 | I17: =IF(G17="","",IFERROR(G17/C17,"")) -> 0.54883 | J17: =IF(H17="","",IFERROR(H17/D17,"")) -> 0.51524371 | K17: =IF(H17="","",IF(D17=0,"",H17-D17)) -> -3005489 | L17: =IF(G17="","—",IF(D17=0,"予算未入力",IF(H17>=D17,"◎ ペース内","▲ 遅れ"))) -> ▲ 遅れ | M17: 13 | N17: 14 | O17: 54 | P17: 29 | Q17: 38 | R17: =IFERROR(M17/O17,"") -> 0.24074074 | S17: =IFERROR(G17/M17,"") -> 21108.846 | T17: =IFERROR(N17/M17,"") -> 1.0769231 | U17: =IFERROR(P17/O17,"") -> 0.53703704 | W17: 44170 | X17: 0
A18: 46184 | B18: =MID("日月火水木金土",WEEKDAY(A18),1) -> 木 | C18: 500000 | D18: =SUM($C$8:C18) -> 6700000 | E18: 50480 | F18: 219540 | G18: =IF(COUNT(E18:F18)=0,"",SUM(E18:F18)) -> 270020 | H18: =IF(G18="","",SUM($G$8:G18)) -> 3464531 | I18: =IF(G18="","",IFERROR(G18/C18,"")) -> 0.54004 | J18: =IF(H18="","",IFERROR(H18/D18,"")) -> 0.51709418 | K18: =IF(H18="","",IF(D18=0,"",H18-D18)) -> -3235469 | L18: =IF(G18="","—",IF(D18=0,"予算未入力",IF(H18>=D18,"◎ ペース内","▲ 遅れ"))) -> ▲ 遅れ | M18: 8 | N18: 17 | O18: 51 | P18: 21 | Q18: 28 | R18: =IFERROR(M18/O18,"") -> 0.15686275 | S18: =IFERROR(G18/M18,"") -> 33752.5 | T18: =IFERROR(N18/M18,"") -> 2.125 | U18: =IFERROR(P18/O18,"") -> 0.41176471 | W18: 44179 | X18: 0 | AA18: ■ 週次サマリー（火曜〜翌月曜） | AH18: 第1火曜 | AI18: =$A$8+MOD(2-WEEKDAY($A$8,2)+7,7) -> 46175
A19: 46185 | B19: =MID("日月火水木金土",WEEKDAY(A19),1) -> 金 | C19: 500000 | D19: =SUM($C$8:C19) -> 7200000 | E19: 171750 | F19: 310100 | G19: =IF(COUNT(E19:F19)=0,"",SUM(E19:F19)) -> 481850 | H19: =IF(G19="","",SUM($G$8:G19)) -> 3946381 | I19: =IF(G19="","",IFERROR(G19/C19,"")) -> 0.9637 | J19: =IF(H19="","",IFERROR(H19/D19,"")) -> 0.54810847 | K19: =IF(H19="","",IF(D19=0,"",H19-D19)) -> -3253619 | L19: =IF(G19="","—",IF(D19=0,"予算未入力",IF(H19>=D19,"◎ ペース内","▲ 遅れ"))) -> ▲ 遅れ | M19: 21 | N19: 22 | O19: 31 | P19: 29 | Q19: 54 | R19: =IFERROR(M19/O19,"") -> 0.67741935 | S19: =IFERROR(G19/M19,"") -> 22945.238 | T19: =IFERROR(N19/M19,"") -> 1.047619 | U19: =IFERROR(P19/O19,"") -> 0.93548387 | W19: 44177 | X19: 0 | AA19: 週 | AB19: 期間 | AC19: 売上 | AD19: 決定率 | AE19: 客単価 | AF19: セット率 | AG19: 試着率
A20: 46186 | B20: =MID("日月火水木金土",WEEKDAY(A20),1) -> 土 | C20: 800000 | D20: =SUM($C$8:C20) -> 8000000 | E20: 75500 | F20: 363380 | G20: =IF(COUNT(E20:F20)=0,"",SUM(E20:F20)) -> 438880 | H20: =IF(G20="","",SUM($G$8:G20)) -> 4385261 | I20: =IF(G20="","",IFERROR(G20/C20,"")) -> 0.5486 | J20: =IF(H20="","",IFERROR(H20/D20,"")) -> 0.54815762 | K20: =IF(H20="","",IF(D20=0,"",H20-D20)) -> -3614739 | L20: =IF(G20="","—",IF(D20=0,"予算未入力",IF(H20>=D20,"◎ ペース内","▲ 遅れ"))) -> ▲ 遅れ | M20: 20 | N20: 21 | O20: 70 | P20: 51 | Q20: 90 | R20: =IFERROR(M20/O20,"") -> 0.28571429 | S20: =IFERROR(G20/M20,"") -> 21944 | T20: =IFERROR(N20/M20,"") -> 1.05 | U20: =IFERROR(P20/O20,"") -> 0.72857143 | W20: 44164 | X20: 0 | AA20: 1 | AB20: =IF($AI$18+7*(1-1)>$A$37,"",TEXT($AI$18+7*(1-1),"m/d")&"-"&TEXT($AI$18+7*(1-1)+6,"m/d")) -> 6/2-6/8 | AC20: =IF($AB20="","",(SUMIFS($G$8:$G$37,$A$8:$A$37,">="&$AI$18+7*(1-1),$A$8:$A$37,"<="&$AI$18+7*(1-1)+6)+SUMIFS('2026年07月'!$G$8:$G$38,'2026年07月'!$A$8:$A$38,">="&$AI$18+7*(1-1),'2026年07月'!$A$8:$A$38,"<="&$AI$18+7*(1-1)+6))) -> 2307396 | AD20: =IF($AB20="","",IFERROR((SUMIFS($M$8:$M$37,$A$8:$A$37,">="&$AI$18+7*(1-1),$A$8:$A$37,"<="&$AI$18+7*(1-1)+6)+SUMIFS('2026年07月'!$M$8:$M$38,'2026年07月'!$A$8:$A$38,">="&$AI$18+7*(1-1),'2026年07月'!$A$8:$A$38,"<="&$AI$18+7*(1-1)+6))/(SUMIFS($O$8:$O$37,$A$8:$A$37,">="&$AI$18+7*(1-1),$A$8:$A$37,"<="&$AI$18+7*(1-1)+6)+SUMIFS('2026年07月'!$O$8:$O$38,'2026年07月'!$A$8:$A$38,">="&$AI$18+7*(1-1),'2026年07月'!$A$8:$A$38,"<="&$AI$18+7*(1-1)+6)),"")) -> 0.38345865 | AE20: =IF($AB20="","",IFERROR((SUMIFS($G$8:$G$37,$A$8:$A$37,">="&$AI$18+7*(1-1),$A$8:$A$37,"<="&$AI$18+7*(1-1)+6)+SUMIFS('2026年07月'!$G$8:$G$38,'2026年07月'!$A$8:$A$38,">="&$AI$18+7*(1-1),'2026年07月'!$A$8:$A$38,"<="&$AI$18+7*(1-1)+6))/(SUMIFS($M$8:$M$37,$A$8:$A$37,">="&$AI$18+7*(1-1),$A$8:$A$37,"<="&$AI$18+7*(1-1)+6)+SUMIFS('2026年07月'!$M$8:$M$38,'2026年07月'!$A$8:$A$38,">="&$AI$18+7*(1-1),'2026年07月'!$A$8:$A$38,"<="&$AI$18+7*(1-1)+6)),"")) -> 22621.529 | AF20: =IF($AB20="","",IFERROR((SUMIFS($N$8:$N$37,$A$8:$A$37,">="&$AI$18+7*(1-1),$A$8:$A$37,"<="&$AI$18+7*(1-1)+6)+SUMIFS('2026年07月'!$N$8:$N$38,'2026年07月'!$A$8:$A$38,">="&$AI$18+7*(1-1),'2026年07月'!$A$8:$A$38,"<="&$AI$18+7*(1-1)+6))/(SUMIFS($M$8:$M$37,$A$8:$A$37,">="&$AI$18+7*(1-1),$A$8:$A$37,"<="&$AI$18+7*(1-1)+6)+SUMIFS('2026年07月'!$M$8:$M$38,'2026年07月'!$A$8:$A$38,">="&$AI$18+7*(1-1),'2026年07月'!$A$8:$A$38,"<="&$AI$18+7*(1-1)+6)),"")) -> 1.0686275 | AG20: =IF($AB20="","",IFERROR((SUMIFS($P$8:$P$37,$A$8:$A$37,">="&$AI$18+7*(1-1),$A$8:$A$37,"<="&$AI$18+7*(1-1)+6)+SUMIFS('2026年07月'!$P$8:$P$38,'2026年07月'!$A$8:$A$38,">="&$AI$18+7*(1-1),'2026年07月'!$A$8:$A$38,"<="&$AI$18+7*(1-1)+6))/(SUMIFS($O$8:$O$37,$A$8:$A$37,">="&$AI$18+7*(1-1),$A$8:$A$37,"<="&$AI$18+7*(1-1)+6)+SUMIFS('2026年07月'!$O$8:$O$38,'2026年07月'!$A$8:$A$38,">="&$AI$18+7*(1-1),'2026年07月'!$A$8:$A$38,"<="&$AI$18+7*(1-1)+6)),"")) -> 0.69172932
A21: 46187 | B21: =MID("日月火水木金土",WEEKDAY(A21),1) -> 日 | C21: 800000 | D21: =SUM($C$8:C21) -> 8800000 | E21: 23810 | F21: 474370 | G21: =IF(COUNT(E21:F21)=0,"",SUM(E21:F21)) -> 498180 | H21: =IF(G21="","",SUM($G$8:G21)) -> 4883441 | I21: =IF(G21="","",IFERROR(G21/C21,"")) -> 0.622725 | J21: =IF(H21="","",IFERROR(H21/D21,"")) -> 0.55493648 | K21: =IF(H21="","",IF(D21=0,"",H21-D21)) -> -3916559 | L21: =IF(G21="","—",IF(D21=0,"予算未入力",IF(H21>=D21,"◎ ペース内","▲ 遅れ"))) -> ▲ 遅れ | M21: 21 | N21: 23 | O21: 70 | P21: 43 | Q21: 55 | R21: =IFERROR(M21/O21,"") -> 0.3 | S21: =IFERROR(G21/M21,"") -> 23722.857 | T21: =IFERROR(N21/M21,"") -> 1.0952381 | U21: =IFERROR(P21/O21,"") -> 0.61428571 | W21: 44144 | X21: 0 | AA21: 2 | AB21: =IF($AI$18+7*(2-1)>$A$37,"",TEXT($AI$18+7*(2-1),"m/d")&"-"&TEXT($AI$18+7*(2-1)+6,"m/d")) -> 6/9-6/15 | AC21: =IF($AB21="","",(SUMIFS($G$8:$G$37,$A$8:$A$37,">="&$AI$18+7*(2-1),$A$8:$A$37,"<="&$AI$18+7*(2-1)+6)+SUMIFS('2026年07月'!$G$8:$G$38,'2026年07月'!$A$8:$A$38,">="&$AI$18+7*(2-1),'2026年07月'!$A$8:$A$38,"<="&$AI$18+7*(2-1)+6))) -> 2687475 | AD21: =IF($AB21="","",IFERROR((SUMIFS($M$8:$M$37,$A$8:$A$37,">="&$AI$18+7*(2-1),$A$8:$A$37,"<="&$AI$18+7*(2-1)+6)+SUMIFS('2026年07月'!$M$8:$M$38,'2026年07月'!$A$8:$A$38,">="&$AI$18+7*(2-1),'2026年07月'!$A$8:$A$38,"<="&$AI$18+7*(2-1)+6))/(SUMIFS($O$8:$O$37,$A$8:$A$37,">="&$AI$18+7*(2-1),$A$8:$A$37,"<="&$AI$18+7*(2-1)+6)+SUMIFS('2026年07月'!$O$8:$O$38,'2026年07月'!$A$8:$A$38,">="&$AI$18+7*(2-1),'2026年07月'!$A$8:$A$38,"<="&$AI$18+7*(2-1)+6)),"")) -> 0.32402235 | AE21: =IF($AB21="","",IFERROR((SUMIFS($G$8:$G$37,$A$8:$A$37,">="&$AI$18+7*(2-1),$A$8:$A$37,"<="&$AI$18+7*(2-1)+6)+SUMIFS('2026年07月'!$G$8:$G$38,'2026年07月'!$A$8:$A$38,">="&$AI$18+7*(2-1),'2026年07月'!$A$8:$A$38,"<="&$AI$18+7*(2-1)+6))/(SUMIFS($M$8:$M$37,$A$8:$A$37,">="&$AI$18+7*(2-1),$A$8:$A$37,"<="&$AI$18+7*(2-1)+6)+SUMIFS('2026年07月'!$M$8:$M$38,'2026年07月'!$A$8:$A$38,">="&$AI$18+7*(2-1),'2026年07月'!$A$8:$A$38,"<="&$AI$18+7*(2-1)+6)),"")) -> 23167.888 | AF21: =IF($AB21="","",IFERROR((SUMIFS($N$8:$N$37,$A$8:$A$37,">="&$AI$18+7*(2-1),$A$8:$A$37,"<="&$AI$18+7*(2-1)+6)+SUMIFS('2026年07月'!$N$8:$N$38,'2026年07月'!$A$8:$A$38,">="&$AI$18+7*(2-1),'2026年07月'!$A$8:$A$38,"<="&$AI$18+7*(2-1)+6))/(SUMIFS($M$8:$M$37,$A$8:$A$37,">="&$AI$18+7*(2-1),$A$8:$A$37,"<="&$AI$18+7*(2-1)+6)+SUMIFS('2026年07月'!$M$8:$M$38,'2026年07月'!$A$8:$A$38,">="&$AI$18+7*(2-1),'2026年07月'!$A$8:$A$38,"<="&$AI$18+7*(2-1)+6)),"")) -> 1.1465517 | AG21: =IF($AB21="","",IFERROR((SUMIFS($P$8:$P$37,$A$8:$A$37,">="&$AI$18+7*(2-1),$A$8:$A$37,"<="&$AI$18+7*(2-1)+6)+SUMIFS('2026年07月'!$P$8:$P$38,'2026年07月'!$A$8:$A$38,">="&$AI$18+7*(2-1),'2026年07月'!$A$8:$A$38,"<="&$AI$18+7*(2-1)+6))/(SUMIFS($O$8:$O$37,$A$8:$A$37,">="&$AI$18+7*(2-1),$A$8:$A$37,"<="&$AI$18+7*(2-1)+6)+SUMIFS('2026年07月'!$O$8:$O$38,'2026年07月'!$A$8:$A$38,">="&$AI$18+7*(2-1),'2026年07月'!$A$8:$A$38,"<="&$AI$18+7*(2-1)+6)),"")) -> 0.62011173
A22: 46188 | B22: =MID("日月火水木金土",WEEKDAY(A22),1) -> 月 | C22: 500000 | D22: =SUM($C$8:C22) -> 9300000 | E22: 84530 | F22: 342350 | G22: =IF(COUNT(E22:F22)=0,"",SUM(E22:F22)) -> 426880 | H22: =IF(G22="","",SUM($G$8:G22)) -> 5310321 | I22: =IF(G22="","",IFERROR(G22/C22,"")) -> 0.85376 | J22: =IF(H22="","",IFERROR(H22/D22,"")) -> 0.57100226 | K22: =IF(H22="","",IF(D22=0,"",H22-D22)) -> -3989679 | L22: =IF(G22="","—",IF(D22=0,"予算未入力",IF(H22>=D22,"◎ ペース内","▲ 遅れ"))) -> ▲ 遅れ | M22: 19 | N22: 21 | O22: 41 | P22: 30 | Q22: 53 | R22: =IFERROR(M22/O22,"") -> 0.46341463 | S22: =IFERROR(G22/M22,"") -> 22467.368 | T22: =IFERROR(N22/M22,"") -> 1.1052632 | U22: =IFERROR(P22/O22,"") -> 0.73170732 | W22: 44142 | X22: 0 | AA22: 3 | AB22: =IF($AI$18+7*(3-1)>$A$37,"",TEXT($AI$18+7*(3-1),"m/d")&"-"&TEXT($AI$18+7*(3-1)+6,"m/d")) -> 6/16-6/22 | AC22: =IF($AB22="","",(SUMIFS($G$8:$G$37,$A$8:$A$37,">="&$AI$18+7*(3-1),$A$8:$A$37,"<="&$AI$18+7*(3-1)+6)+SUMIFS('2026年07月'!$G$8:$G$38,'2026年07月'!$A$8:$A$38,">="&$AI$18+7*(3-1),'2026年07月'!$A$8:$A$38,"<="&$AI$18+7*(3-1)+6))) -> 2275415 | AD22: =IF($AB22="","",IFERROR((SUMIFS($M$8:$M$37,$A$8:$A$37,">="&$AI$18+7*(3-1),$A$8:$A$37,"<="&$AI$18+7*(3-1)+6)+SUMIFS('2026年07月'!$M$8:$M$38,'2026年07月'!$A$8:$A$38,">="&$AI$18+7*(3-1),'2026年07月'!$A$8:$A$38,"<="&$AI$18+7*(3-1)+6))/(SUMIFS($O$8:$O$37,$A$8:$A$37,">="&$AI$18+7*(3-1),$A$8:$A$37,"<="&$AI$18+7*(3-1)+6)+SUMIFS('2026年07月'!$O$8:$O$38,'2026年07月'!$A$8:$A$38,">="&$AI$18+7*(3-1),'2026年07月'!$A$8:$A$38,"<="&$AI$18+7*(3-1)+6)),"")) -> 0.35766423 | AE22: =IF($AB22="","",IFERROR((SUMIFS($G$8:$G$37,$A$8:$A$37,">="&$AI$18+7*(3-1),$A$8:$A$37,"<="&$AI$18+7*(3-1)+6)+SUMIFS('2026年07月'!$G$8:$G$38,'2026年07月'!$A$8:$A$38,">="&$AI$18+7*(3-1),'2026年07月'!$A$8:$A$38,"<="&$AI$18+7*(3-1)+6))/(SUMIFS($M$8:$M$37,$A$8:$A$37,">="&$AI$18+7*(3-1),$A$8:$A$37,"<="&$AI$18+7*(3-1)+6)+SUMIFS('2026年07月'!$M$8:$M$38,'2026年07月'!$A$8:$A$38,">="&$AI$18+7*(3-1),'2026年07月'!$A$8:$A$38,"<="&$AI$18+7*(3-1)+6)),"")) -> 23218.52 | AF22: =IF($AB22="","",IFERROR((SUMIFS($N$8:$N$37,$A$8:$A$37,">="&$AI$18+7*(3-1),$A$8:$A$37,"<="&$AI$18+7*(3-1)+6)+SUMIFS('2026年07月'!$N$8:$N$38,'2026年07月'!$A$8:$A$38,">="&$AI$18+7*(3-1),'2026年07月'!$A$8:$A$38,"<="&$AI$18+7*(3-1)+6))/(SUMIFS($M$8:$M$37,$A$8:$A$37,">="&$AI$18+7*(3-1),$A$8:$A$37,"<="&$AI$18+7*(3-1)+6)+SUMIFS('2026年07月'!$M$8:$M$38,'2026年07月'!$A$8:$A$38,">="&$AI$18+7*(3-1),'2026年07月'!$A$8:$A$38,"<="&$AI$18+7*(3-1)+6)),"")) -> 1.0510204 | AG22: =IF($AB22="","",IFERROR((SUMIFS($P$8:$P$37,$A$8:$A$37,">="&$AI$18+7*(3-1),$A$8:$A$37,"<="&$AI$18+7*(3-1)+6)+SUMIFS('2026年07月'!$P$8:$P$38,'2026年07月'!$A$8:$A$38,">="&$AI$18+7*(3-1),'2026年07月'!$A$8:$A$38,"<="&$AI$18+7*(3-1)+6))/(SUMIFS($O$8:$O$37,$A$8:$A$37,">="&$AI$18+7*(3-1),$A$8:$A$37,"<="&$AI$18+7*(3-1)+6)+SUMIFS('2026年07月'!$O$8:$O$38,'2026年07月'!$A$8:$A$38,">="&$AI$18+7*(3-1),'2026年07月'!$A$8:$A$38,"<="&$AI$18+7*(3-1)+6)),"")) -> 0.56569343
A23: 46189 | B23: =MID("日月火水木金土",WEEKDAY(A23),1) -> 火 | C23: 500000 | D23: =SUM($C$8:C23) -> 9800000 | E23: 130550 | F23: 121640 | G23: =IF(COUNT(E23:F23)=0,"",SUM(E23:F23)) -> 252190 | H23: =IF(G23="","",SUM($G$8:G23)) -> 5562511 | I23: =IF(G23="","",IFERROR(G23/C23,"")) -> 0.50438 | J23: =IF(H23="","",IFERROR(H23/D23,"")) -> 0.56760316 | K23: =IF(H23="","",IF(D23=0,"",H23-D23)) -> -4237489 | L23: =IF(G23="","—",IF(D23=0,"予算未入力",IF(H23>=D23,"◎ ペース内","▲ 遅れ"))) -> ▲ 遅れ | M23: 11 | N23: 11 | O23: 37 | P23: 20 | Q23: 33 | R23: =IFERROR(M23/O23,"") -> 0.2972973 | S23: =IFERROR(G23/M23,"") -> 22926.364 | T23: =IFERROR(N23/M23,"") -> 1 | U23: =IFERROR(P23/O23,"") -> 0.54054054 | W23: 44113 | X23: 0 | AA23: 4 | AB23: =IF($AI$18+7*(4-1)>$A$37,"",TEXT($AI$18+7*(4-1),"m/d")&"-"&TEXT($AI$18+7*(4-1)+6,"m/d")) -> 6/23-6/29 | AC23: =IF($AB23="","",(SUMIFS($G$8:$G$37,$A$8:$A$37,">="&$AI$18+7*(4-1),$A$8:$A$37,"<="&$AI$18+7*(4-1)+6)+SUMIFS('2026年07月'!$G$8:$G$38,'2026年07月'!$A$8:$A$38,">="&$AI$18+7*(4-1),'2026年07月'!$A$8:$A$38,"<="&$AI$18+7*(4-1)+6))) -> 2380667 | AD23: =IF($AB23="","",IFERROR((SUMIFS($M$8:$M$37,$A$8:$A$37,">="&$AI$18+7*(4-1),$A$8:$A$37,"<="&$AI$18+7*(4-1)+6)+SUMIFS('2026年07月'!$M$8:$M$38,'2026年07月'!$A$8:$A$38,">="&$AI$18+7*(4-1),'2026年07月'!$A$8:$A$38,"<="&$AI$18+7*(4-1)+6))/(SUMIFS($O$8:$O$37,$A$8:$A$37,">="&$AI$18+7*(4-1),$A$8:$A$37,"<="&$AI$18+7*(4-1)+6)+SUMIFS('2026年07月'!$O$8:$O$38,'2026年07月'!$A$8:$A$38,">="&$AI$18+7*(4-1),'2026年07月'!$A$8:$A$38,"<="&$AI$18+7*(4-1)+6)),"")) -> 0.34915254 | AE23: =IF($AB23="","",IFERROR((SUMIFS($G$8:$G$37,$A$8:$A$37,">="&$AI$18+7*(4-1),$A$8:$A$37,"<="&$AI$18+7*(4-1)+6)+SUMIFS('2026年07月'!$G$8:$G$38,'2026年07月'!$A$8:$A$38,">="&$AI$18+7*(4-1),'2026年07月'!$A$8:$A$38,"<="&$AI$18+7*(4-1)+6))/(SUMIFS($M$8:$M$37,$A$8:$A$37,">="&$AI$18+7*(4-1),$A$8:$A$37,"<="&$AI$18+7*(4-1)+6)+SUMIFS('2026年07月'!$M$8:$M$38,'2026年07月'!$A$8:$A$38,">="&$AI$18+7*(4-1),'2026年07月'!$A$8:$A$38,"<="&$AI$18+7*(4-1)+6)),"")) -> 23113.272 | AF23: =IF($AB23="","",IFERROR((SUMIFS($N$8:$N$37,$A$8:$A$37,">="&$AI$18+7*(4-1),$A$8:$A$37,"<="&$AI$18+7*(4-1)+6)+SUMIFS('2026年07月'!$N$8:$N$38,'2026年07月'!$A$8:$A$38,">="&$AI$18+7*(4-1),'2026年07月'!$A$8:$A$38,"<="&$AI$18+7*(4-1)+6))/(SUMIFS($M$8:$M$37,$A$8:$A$37,">="&$AI$18+7*(4-1),$A$8:$A$37,"<="&$AI$18+7*(4-1)+6)+SUMIFS('2026年07月'!$M$8:$M$38,'2026年07月'!$A$8:$A$38,">="&$AI$18+7*(4-1),'2026年07月'!$A$8:$A$38,"<="&$AI$18+7*(4-1)+6)),"")) -> 1.0582524 | AG23: =IF($AB23="","",IFERROR((SUMIFS($P$8:$P$37,$A$8:$A$37,">="&$AI$18+7*(4-1),$A$8:$A$37,"<="&$AI$18+7*(4-1)+6)+SUMIFS('2026年07月'!$P$8:$P$38,'2026年07月'!$A$8:$A$38,">="&$AI$18+7*(4-1),'2026年07月'!$A$8:$A$38,"<="&$AI$18+7*(4-1)+6))/(SUMIFS($O$8:$O$37,$A$8:$A$37,">="&$AI$18+7*(4-1),$A$8:$A$37,"<="&$AI$18+7*(4-1)+6)+SUMIFS('2026年07月'!$O$8:$O$38,'2026年07月'!$A$8:$A$38,">="&$AI$18+7*(4-1),'2026年07月'!$A$8:$A$38,"<="&$AI$18+7*(4-1)+6)),"")) -> 0.56949153
A24: 46190 | B24: =MID("日月火水木金土",WEEKDAY(A24),1) -> 水 | C24: 500000 | D24: =SUM($C$8:C24) -> 10300000 | E24: 70230 | F24: 130560 | G24: =IF(COUNT(E24:F24)=0,"",SUM(E24:F24)) -> 200790 | H24: =IF(G24="","",SUM($G$8:G24)) -> 5763301 | I24: =IF(G24="","",IFERROR(G24/C24,"")) -> 0.40158 | J24: =IF(H24="","",IFERROR(H24/D24,"")) -> 0.55954379 | K24: =IF(H24="","",IF(D24=0,"",H24-D24)) -> -4536699 | L24: =IF(G24="","—",IF(D24=0,"予算未入力",IF(H24>=D24,"◎ ペース内","▲ 遅れ"))) -> ▲ 遅れ | M24: 9 | N24: 9 | O24: 32 | P24: 11 | Q24: 18 | R24: =IFERROR(M24/O24,"") -> 0.28125 | S24: =IFERROR(G24/M24,"") -> 22310 | T24: =IFERROR(N24/M24,"") -> 1 | U24: =IFERROR(P24/O24,"") -> 0.34375 | W24: 44115 | X24: 0 | Y24: ※要確認：旧シートの売上合計と内訳が+24,310円ズレ。合計200,790円に合わせクレジットを106,250→130,560に調整 | AA24: 5 | AB24: =IF($AI$18+7*(5-1)>$A$37,"",TEXT($AI$18+7*(5-1),"m/d")&"-"&TEXT($AI$18+7*(5-1)+6,"m/d")) -> 6/30-7/6 | AC24: =IF($AB24="","",(SUMIFS($G$8:$G$37,$A$8:$A$37,">="&$AI$18+7*(5-1),$A$8:$A$37,"<="&$AI$18+7*(5-1)+6)+SUMIFS('2026年07月'!$G$8:$G$38,'2026年07月'!$A$8:$A$38,">="&$AI$18+7*(5-1),'2026年07月'!$A$8:$A$38,"<="&$AI$18+7*(5-1)+6))) -> 3182068 | AD24: =IF($AB24="","",IFERROR((SUMIFS($M$8:$M$37,$A$8:$A$37,">="&$AI$18+7*(5-1),$A$8:$A$37,"<="&$AI$18+7*(5-1)+6)+SUMIFS('2026年07月'!$M$8:$M$38,'2026年07月'!$A$8:$A$38,">="&$AI$18+7*(5-1),'2026年07月'!$A$8:$A$38,"<="&$AI$18+7*(5-1)+6))/(SUMIFS($O$8:$O$37,$A$8:$A$37,">="&$AI$18+7*(5-1),$A$8:$A$37,"<="&$AI$18+7*(5-1)+6)+SUMIFS('2026年07月'!$O$8:$O$38,'2026年07月'!$A$8:$A$38,">="&$AI$18+7*(5-1),'2026年07月'!$A$8:$A$38,"<="&$AI$18+7*(5-1)+6)),"")) -> 0.375 | AE24: =IF($AB24="","",IFERROR((SUMIFS($G$8:$G$37,$A$8:$A$37,">="&$AI$18+7*(5-1),$A$8:$A$37,"<="&$AI$18+7*(5-1)+6)+SUMIFS('2026年07月'!$G$8:$G$38,'2026年07月'!$A$8:$A$38,">="&$AI$18+7*(5-1),'2026年07月'!$A$8:$A$38,"<="&$AI$18+7*(5-1)+6))/(SUMIFS($M$8:$M$37,$A$8:$A$37,">="&$AI$18+7*(5-1),$A$8:$A$37,"<="&$AI$18+7*(5-1)+6)+SUMIFS('2026年07月'!$M$8:$M$38,'2026年07月'!$A$8:$A$38,">="&$AI$18+7*(5-1),'2026年07月'!$A$8:$A$38,"<="&$AI$18+7*(5-1)+6)),"")) -> 23058.464 | AF24: =IF($AB24="","",IFERROR((SUMIFS($N$8:$N$37,$A$8:$A$37,">="&$AI$18+7*(5-1),$A$8:$A$37,"<="&$AI$18+7*(5-1)+6)+SUMIFS('2026年07月'!$N$8:$N$38,'2026年07月'!$A$8:$A$38,">="&$AI$18+7*(5-1),'2026年07月'!$A$8:$A$38,"<="&$AI$18+7*(5-1)+6))/(SUMIFS($M$8:$M$37,$A$8:$A$37,">="&$AI$18+7*(5-1),$A$8:$A$37,"<="&$AI$18+7*(5-1)+6)+SUMIFS('2026年07月'!$M$8:$M$38,'2026年07月'!$A$8:$A$38,">="&$AI$18+7*(5-1),'2026年07月'!$A$8:$A$38,"<="&$AI$18+7*(5-1)+6)),"")) -> 1.0942029 | AG24: =IF($AB24="","",IFERROR((SUMIFS($P$8:$P$37,$A$8:$A$37,">="&$AI$18+7*(5-1),$A$8:$A$37,"<="&$AI$18+7*(5-1)+6)+SUMIFS('2026年07月'!$P$8:$P$38,'2026年07月'!$A$8:$A$38,">="&$AI$18+7*(5-1),'2026年07月'!$A$8:$A$38,"<="&$AI$18+7*(5-1)+6))/(SUMIFS($O$8:$O$37,$A$8:$A$37,">="&$AI$18+7*(5-1),$A$8:$A$37,"<="&$AI$18+7*(5-1)+6)+SUMIFS('2026年07月'!$O$8:$O$38,'2026年07月'!$A$8:$A$38,">="&$AI$18+7*(5-1),'2026年07月'!$A$8:$A$38,"<="&$AI$18+7*(5-1)+6)),"")) -> 0.5625
A25: 46191 | B25: =MID("日月火水木金土",WEEKDAY(A25),1) -> 木 | C25: 500000 | D25: =SUM($C$8:C25) -> 10800000 | E25: 86840 | F25: 245340 | G25: =IF(COUNT(E25:F25)=0,"",SUM(E25:F25)) -> 332180 | H25: =IF(G25="","",SUM($G$8:G25)) -> 6095481 | I25: =IF(G25="","",IFERROR(G25/C25,"")) -> 0.66436 | J25: =IF(H25="","",IFERROR(H25/D25,"")) -> 0.56439639 | K25: =IF(H25="","",IF(D25=0,"",H25-D25)) -> -4704519 | L25: =IF(G25="","—",IF(D25=0,"予算未入力",IF(H25>=D25,"◎ ペース内","▲ 遅れ"))) -> ▲ 遅れ | M25: 15 | N25: 15 | O25: 51 | P25: 24 | Q25: 31 | R25: =IFERROR(M25/O25,"") -> 0.29411765 | S25: =IFERROR(G25/M25,"") -> 22145.333 | T25: =IFERROR(N25/M25,"") -> 1 | U25: =IFERROR(P25/O25,"") -> 0.47058824 | W25: 44103 | X25: 0 | AA25: 6 | AB25: =IF($AI$18+7*(6-1)>$A$37,"",TEXT($AI$18+7*(6-1),"m/d")&"-"&TEXT($AI$18+7*(6-1)+6,"m/d")) | AC25: =IF($AB25="","",(SUMIFS($G$8:$G$37,$A$8:$A$37,">="&$AI$18+7*(6-1),$A$8:$A$37,"<="&$AI$18+7*(6-1)+6)+SUMIFS('2026年07月'!$G$8:$G$38,'2026年07月'!$A$8:$A$38,">="&$AI$18+7*(6-1),'2026年07月'!$A$8:$A$38,"<="&$AI$18+7*(6-1)+6))) | AD25: =IF($AB25="","",IFERROR((SUMIFS($M$8:$M$37,$A$8:$A$37,">="&$AI$18+7*(6-1),$A$8:$A$37,"<="&$AI$18+7*(6-1)+6)+SUMIFS('2026年07月'!$M$8:$M$38,'2026年07月'!$A$8:$A$38,">="&$AI$18+7*(6-1),'2026年07月'!$A$8:$A$38,"<="&$AI$18+7*(6-1)+6))/(SUMIFS($O$8:$O$37,$A$8:$A$37,">="&$AI$18+7*(6-1),$A$8:$A$37,"<="&$AI$18+7*(6-1)+6)+SUMIFS('2026年07月'!$O$8:$O$38,'2026年07月'!$A$8:$A$38,">="&$AI$18+7*(6-1),'2026年07月'!$A$8:$A$38,"<="&$AI$18+7*(6-1)+6)),"")) | AE25: =IF($AB25="","",IFERROR((SUMIFS($G$8:$G$37,$A$8:$A$37,">="&$AI$18+7*(6-1),$A$8:$A$37,"<="&$AI$18+7*(6-1)+6)+SUMIFS('2026年07月'!$G$8:$G$38,'2026年07月'!$A$8:$A$38,">="&$AI$18+7*(6-1),'2026年07月'!$A$8:$A$38,"<="&$AI$18+7*(6-1)+6))/(SUMIFS($M$8:$M$37,$A$8:$A$37,">="&$AI$18+7*(6-1),$A$8:$A$37,"<="&$AI$18+7*(6-1)+6)+SUMIFS('2026年07月'!$M$8:$M$38,'2026年07月'!$A$8:$A$38,">="&$AI$18+7*(6-1),'2026年07月'!$A$8:$A$38,"<="&$AI$18+7*(6-1)+6)),"")) | AF25: =IF($AB25="","",IFERROR((SUMIFS($N$8:$N$37,$A$8:$A$37,">="&$AI$18+7*(6-1),$A$8:$A$37,"<="&$AI$18+7*(6-1)+6)+SUMIFS('2026年07月'!$N$8:$N$38,'2026年07月'!$A$8:$A$38,">="&$AI$18+7*(6-1),'2026年07月'!$A$8:$A$38,"<="&$AI$18+7*(6-1)+6))/(SUMIFS($M$8:$M$37,$A$8:$A$37,">="&$AI$18+7*(6-1),$A$8:$A$37,"<="&$AI$18+7*(6-1)+6)+SUMIFS('2026年07月'!$M$8:$M$38,'2026年07月'!$A$8:$A$38,">="&$AI$18+7*(6-1),'2026年07月'!$A$8:$A$38,"<="&$AI$18+7*(6-1)+6)),"")) | AG25: =IF($AB25="","",IFERROR((SUMIFS($P$8:$P$37,$A$8:$A$37,">="&$AI$18+7*(6-1),$A$8:$A$37,"<="&$AI$18+7*(6-1)+6)+SUMIFS('2026年07月'!$P$8:$P$38,'2026年07月'!$A$8:$A$38,">="&$AI$18+7*(6-1),'2026年07月'!$A$8:$A$38,"<="&$AI$18+7*(6-1)+6))/(SUMIFS($O$8:$O$37,$A$8:$A$37,">="&$AI$18+7*(6-1),$A$8:$A$37,"<="&$AI$18+7*(6-1)+6)+SUMIFS('2026年07月'!$O$8:$O$38,'2026年07月'!$A$8:$A$38,">="&$AI$18+7*(6-1),'2026年07月'!$A$8:$A$38,"<="&$AI$18+7*(6-1)+6)),""))
A26: 46192 | B26: =MID("日月火水木金土",WEEKDAY(A26),1) -> 金 | C26: 500000 | D26: =SUM($C$8:C26) -> 11300000 | E26: 96240 | F26: 126540 | G26: =IF(COUNT(E26:F26)=0,"",SUM(E26:F26)) -> 222780 | H26: =IF(G26="","",SUM($G$8:G26)) -> 6318261 | I26: =IF(G26="","",IFERROR(G26/C26,"")) -> 0.44556 | J26: =IF(H26="","",IFERROR(H26/D26,"")) -> 0.55913814 | K26: =IF(H26="","",IF(D26=0,"",H26-D26)) -> -4981739 | L26: =IF(G26="","—",IF(D26=0,"予算未入力",IF(H26>=D26,"◎ ペース内","▲ 遅れ"))) -> ▲ 遅れ | M26: 10 | N26: 10 | O26: 27 | P26: 14 | Q26: 21 | R26: =IFERROR(M26/O26,"") -> 0.37037037 | S26: =IFERROR(G26/M26,"") -> 22278 | T26: =IFERROR(N26/M26,"") -> 1 | U26: =IFERROR(P26/O26,"") -> 0.51851852 | W26: 44081 | X26: 0 | AA26: ※期間ラベルは第1火曜から自動生成。決定率・客単価・セット率・試着率は「週合計÷週合計」
A27: 46193 | B27: =MID("日月火水木金土",WEEKDAY(A27),1) -> 土 | C27: 800000 | D27: =SUM($C$8:C27) -> 12100000 | E27: 23810 | F27: 316008 | G27: =IF(COUNT(E27:F27)=0,"",SUM(E27:F27)) -> 339818 | H27: =IF(G27="","",SUM($G$8:G27)) -> 6658079 | I27: =IF(G27="","",IFERROR(G27/C27,"")) -> 0.4247725 | J27: =IF(H27="","",IFERROR(H27/D27,"")) -> 0.55025446 | K27: =IF(H27="","",IF(D27=0,"",H27-D27)) -> -5441921 | L27: =IF(G27="","—",IF(D27=0,"予算未入力",IF(H27>=D27,"◎ ペース内","▲ 遅れ"))) -> ▲ 遅れ | M27: 15 | N27: 16 | O27: 42 | P27: 29 | Q27: 34 | R27: =IFERROR(M27/O27,"") -> 0.35714286 | S27: =IFERROR(G27/M27,"") -> 22654.533 | T27: =IFERROR(N27/M27,"") -> 1.0666667 | U27: =IFERROR(P27/O27,"") -> 0.69047619 | W27: 44075 | X27: 0 | AA27: ※最終週は翌月にまたぐため、2026年07月シートの実績も自動で合算します
A28: 46194 | B28: =MID("日月火水木金土",WEEKDAY(A28),1) -> 日 | C28: 800000 | D28: =SUM($C$8:C28) -> 12900000 | E28: 119550 | F28: 619747 | G28: =IF(COUNT(E28:F28)=0,"",SUM(E28:F28)) -> 739297 | H28: =IF(G28="","",SUM($G$8:G28)) -> 7397376 | I28: =IF(G28="","",IFERROR(G28/C28,"")) -> 0.92412125 | J28: =IF(H28="","",IFERROR(H28/D28,"")) -> 0.57344 | K28: =IF(H28="","",IF(D28=0,"",H28-D28)) -> -5502624 | L28: =IF(G28="","—",IF(D28=0,"予算未入力",IF(H28>=D28,"◎ ペース内","▲ 遅れ"))) -> ▲ 遅れ | M28: 29 | N28: 33 | O28: 56 | P28: 38 | Q28: 68 | R28: =IFERROR(M28/O28,"") -> 0.51785714 | S28: =IFERROR(G28/M28,"") -> 25493 | T28: =IFERROR(N28/M28,"") -> 1.137931 | U28: =IFERROR(P28/O28,"") -> 0.67857143 | W28: 44064 | X28: 0 | AA28: ※月初の月曜まで（例：6/1）は前月シートの最終週に含まれます
A29: 46195 | B29: =MID("日月火水木金土",WEEKDAY(A29),1) -> 月 | C29: 500000 | D29: =SUM($C$8:C29) -> 13400000 | E29: 0 | F29: 188360 | G29: =IF(COUNT(E29:F29)=0,"",SUM(E29:F29)) -> 188360 | H29: =IF(G29="","",SUM($G$8:G29)) -> 7585736 | I29: =IF(G29="","",IFERROR(G29/C29,"")) -> 0.37672 | J29: =IF(H29="","",IFERROR(H29/D29,"")) -> 0.5660997 | K29: =IF(H29="","",IF(D29=0,"",H29-D29)) -> -5814264 | L29: =IF(G29="","—",IF(D29=0,"予算未入力",IF(H29>=D29,"◎ ペース内","▲ 遅れ"))) -> ▲ 遅れ | M29: 9 | N29: 9 | O29: 29 | P29: 19 | Q29: 37 | R29: =IFERROR(M29/O29,"") -> 0.31034483 | S29: =IFERROR(G29/M29,"") -> 20928.889 | T29: =IFERROR(N29/M29,"") -> 1 | U29: =IFERROR(P29/O29,"") -> 0.65517241 | W29: 44059 | X29: 0
A30: 46196 | B30: =MID("日月火水木金土",WEEKDAY(A30),1) -> 火 | C30: 500000 | D30: =SUM($C$8:C30) -> 13900000 | E30: 106630 | F30: 182910 | G30: =IF(COUNT(E30:F30)=0,"",SUM(E30:F30)) -> 289540 | H30: =IF(G30="","",SUM($G$8:G30)) -> 7875276 | I30: =IF(G30="","",IFERROR(G30/C30,"")) -> 0.57908 | J30: =IF(H30="","",IFERROR(H30/D30,"")) -> 0.56656662 | K30: =IF(H30="","",IF(D30=0,"",H30-D30)) -> -6024724 | L30: =IF(G30="","—",IF(D30=0,"予算未入力",IF(H30>=D30,"◎ ペース内","▲ 遅れ"))) -> ▲ 遅れ | M30: 11 | N30: 11 | O30: 35 | P30: 17 | Q30: 42 | R30: =IFERROR(M30/O30,"") -> 0.31428571 | S30: =IFERROR(G30/M30,"") -> 26321.818 | T30: =IFERROR(N30/M30,"") -> 1 | U30: =IFERROR(P30/O30,"") -> 0.48571429 | W30: 44051 | X30: 0 | Y30: ※要確認：旧シートの売上合計と内訳が-10円ズレ。合計289,540円に合わせクレジットを182,920→182,910に調整
A31: 46197 | B31: =MID("日月火水木金土",WEEKDAY(A31),1) -> 水 | C31: 500000 | D31: =SUM($C$8:C31) -> 14400000 | E31: 23700 | F31: 364340 | G31: =IF(COUNT(E31:F31)=0,"",SUM(E31:F31)) -> 388040 | H31: =IF(G31="","",SUM($G$8:G31)) -> 8263316 | I31: =IF(G31="","",IFERROR(G31/C31,"")) -> 0.77608 | J31: =IF(H31="","",IFERROR(H31/D31,"")) -> 0.57384139 | K31: =IF(H31="","",IF(D31=0,"",H31-D31)) -> -6136684 | L31: =IF(G31="","—",IF(D31=0,"予算未入力",IF(H31>=D31,"◎ ペース内","▲ 遅れ"))) -> ▲ 遅れ | M31: 15 | N31: 16 | O31: 33 | P31: 27 | Q31: 39 | R31: =IFERROR(M31/O31,"") -> 0.45454545 | S31: =IFERROR(G31/M31,"") -> 25869.333 | T31: =IFERROR(N31/M31,"") -> 1.0666667 | U31: =IFERROR(P31/O31,"") -> 0.81818182 | X31: 0
A32: 46198 | B32: =MID("日月火水木金土",WEEKDAY(A32),1) -> 木 | C32: 500000 | D32: =SUM($C$8:C32) -> 14900000 | E32: 100530 | F32: 189607 | G32: =IF(COUNT(E32:F32)=0,"",SUM(E32:F32)) -> 290137 | H32: =IF(G32="","",SUM($G$8:G32)) -> 8553453 | I32: =IF(G32="","",IFERROR(G32/C32,"")) -> 0.580274 | J32: =IF(H32="","",IFERROR(H32/D32,"")) -> 0.57405725 | K32: =IF(H32="","",IF(D32=0,"",H32-D32)) -> -6346547 | L32: =IF(G32="","—",IF(D32=0,"予算未入力",IF(H32>=D32,"◎ ペース内","▲ 遅れ"))) -> ▲ 遅れ | M32: 12 | N32: 14 | O32: 45 | P32: 24 | Q32: 32 | R32: =IFERROR(M32/O32,"") -> 0.26666667 | S32: =IFERROR(G32/M32,"") -> 24178.083 | T32: =IFERROR(N32/M32,"") -> 1.1666667 | U32: =IFERROR(P32/O32,"") -> 0.53333333 | W32: 44040 | X32: 0
A33: 46199 | B33: =MID("日月火水木金土",WEEKDAY(A33),1) -> 金 | C33: 600000 | D33: =SUM($C$8:C33) -> 15500000 | E33: 73230 | F33: 84220 | G33: =IF(COUNT(E33:F33)=0,"",SUM(E33:F33)) -> 157450 | H33: =IF(G33="","",SUM($G$8:G33)) -> 8710903 | I33: =IF(G33="","",IFERROR(G33/C33,"")) -> 0.26241667 | J33: =IF(H33="","",IFERROR(H33/D33,"")) -> 0.56199374 | K33: =IF(H33="","",IF(D33=0,"",H33-D33)) -> -6789097 | L33: =IF(G33="","—",IF(D33=0,"予算未入力",IF(H33>=D33,"◎ ペース内","▲ 遅れ"))) -> ▲ 遅れ | M33: 7 | N33: 7 | O33: 37 | P33: 11 | Q33: 15 | R33: =IFERROR(M33/O33,"") -> 0.18918919 | S33: =IFERROR(G33/M33,"") -> 22492.857 | T33: =IFERROR(N33/M33,"") -> 1 | U33: =IFERROR(P33/O33,"") -> 0.2972973 | W33: 44052 | X33: 0
A34: 46200 | B34: =MID("日月火水木金土",WEEKDAY(A34),1) -> 土 | C34: 900000 | D34: =SUM($C$8:C34) -> 16400000 | E34: 105850 | F34: 104440 | G34: =IF(COUNT(E34:F34)=0,"",SUM(E34:F34)) -> 210290 | H34: =IF(G34="","",SUM($G$8:G34)) -> 8921193 | I34: =IF(G34="","",IFERROR(G34/C34,"")) -> 0.23365556 | J34: =IF(H34="","",IFERROR(H34/D34,"")) -> 0.54397518 | K34: =IF(H34="","",IF(D34=0,"",H34-D34)) -> -7478807 | L34: =IF(G34="","—",IF(D34=0,"予算未入力",IF(H34>=D34,"◎ ペース内","▲ 遅れ"))) -> ▲ 遅れ | M34: 9 | N34: 10 | O34: 21 | P34: 15 | Q34: 22 | R34: =IFERROR(M34/O34,"") -> 0.42857143 | S34: =IFERROR(G34/M34,"") -> 23365.556 | T34: =IFERROR(N34/M34,"") -> 1.1111111 | U34: =IFERROR(P34/O34,"") -> 0.71428571 | W34: 44057 | X34: 0
A35: 46201 | B35: =MID("日月火水木金土",WEEKDAY(A35),1) -> 日 | C35: 900000 | D35: =SUM($C$8:C35) -> 17300000 | E35: 180260 | F35: 355030 | G35: =IF(COUNT(E35:F35)=0,"",SUM(E35:F35)) -> 535290 | H35: =IF(G35="","",SUM($G$8:G35)) -> 9456483 | I35: =IF(G35="","",IFERROR(G35/C35,"")) -> 0.59476667 | J35: =IF(H35="","",IFERROR(H35/D35,"")) -> 0.54661751 | K35: =IF(H35="","",IF(D35=0,"",H35-D35)) -> -7843517 | L35: =IF(G35="","—",IF(D35=0,"予算未入力",IF(H35>=D35,"◎ ペース内","▲ 遅れ"))) -> ▲ 遅れ | M35: 25 | N35: 27 | O35: 56 | P35: 39 | Q35: 51 | R35: =IFERROR(M35/O35,"") -> 0.44642857 | S35: =IFERROR(G35/M35,"") -> 21411.6 | T35: =IFERROR(N35/M35,"") -> 1.08 | U35: =IFERROR(P35/O35,"") -> 0.69642857 | W35: 44072 | X35: 0
A36: 46202 | B36: =MID("日月火水木金土",WEEKDAY(A36),1) -> 月 | C36: 600000 | D36: =SUM($C$8:C36) -> 17900000 | E36: 101900 | F36: 408020 | G36: =IF(COUNT(E36:F36)=0,"",SUM(E36:F36)) -> 509920 | H36: =IF(G36="","",SUM($G$8:G36)) -> 9966403 | I36: =IF(G36="","",IFERROR(G36/C36,"")) -> 0.84986667 | J36: =IF(H36="","",IFERROR(H36/D36,"")) -> 0.55678229 | K36: =IF(H36="","",IF(D36=0,"",H36-D36)) -> -7933597 | L36: =IF(G36="","—",IF(D36=0,"予算未入力",IF(H36>=D36,"◎ ペース内","▲ 遅れ"))) -> ▲ 遅れ | M36: 24 | N36: 24 | O36: 68 | P36: 35 | Q36: 48 | R36: =IFERROR(M36/O36,"") -> 0.35294118 | S36: =IFERROR(G36/M36,"") -> 21246.667 | T36: =IFERROR(N36/M36,"") -> 1 | U36: =IFERROR(P36/O36,"") -> 0.51470588 | W36: 44082 | X36: 0
A37: 46203 | B37: =MID("日月火水木金土",WEEKDAY(A37),1) -> 火 | C37: 600000 | D37: =SUM($C$8:C37) -> 18500000 | E37: 100640 | F37: 379600 | G37: =IF(COUNT(E37:F37)=0,"",SUM(E37:F37)) -> 480240 | H37: =IF(G37="","",SUM($G$8:G37)) -> 10446643 | I37: =IF(G37="","",IFERROR(G37/C37,"")) -> 0.8004 | J37: =IF(H37="","",IFERROR(H37/D37,"")) -> 0.56468341 | K37: =IF(H37="","",IF(D37=0,"",H37-D37)) -> -8053357 | L37: =IF(G37="","—",IF(D37=0,"予算未入力",IF(H37>=D37,"◎ ペース内","▲ 遅れ"))) -> ▲ 遅れ | M37: 20 | N37: 23 | O37: 58 | P37: 29 | Q37: 53 | R37: =IFERROR(M37/O37,"") -> 0.34482759 | S37: =IFERROR(G37/M37,"") -> 24012 | T37: =IFERROR(N37/M37,"") -> 1.15 | U37: =IFERROR(P37/O37,"") -> 0.5 | W37: 44070 | X37: 0
A38: 月計 | C38: =SUM(C8:C37) -> 18500000 | D38: =C38 -> 18500000 | E38: =SUM(E8:E37) -> 2397249 | F38: =SUM(F8:F37) -> 8049394 | G38: =SUM(G8:G37) -> 10446643 | H38: =G38 -> 10446643 | I38: =IFERROR(G38/C38,"") -> 0.56468341 | J38: =IFERROR(G38/C38,"") -> 0.56468341 | K38: =G38-C38 -> -8053357 | M38: =SUM(M8:M37) -> 450 | N38: =SUM(N8:N37) -> 495 | O38: =SUM(O8:O37) -> 1283 | P38: =SUM(P8:P37) -> 781 | Q38: =SUM(Q8:Q37) -> 1130 | R38: =IFERROR(M38/O38,"") -> 0.35074045 | S38: =IFERROR(G38/M38,"") -> 23214.762 | T38: =IFERROR(N38/M38,"") -> 1.1 | U38: =IFERROR(P38/O38,"") -> 0.60872954 | V38: =SUM(V8:V37) -> 0 | W38: =IFERROR(LOOKUP(9.99E+307,W8:W37),"") -> 44070 | X38: =SUM(X8:X37) -> 0 | Y38: フォロワーは月末値

Sheet 2026年07月
A1: 2026年7月 原宿店 日別売上管理
A2: 青字＋薄黄色のセルが入力欄。白セルは数式なので触らないでください。単位：円
A3: 月間予算 | C3: 当月実績 | E3: 達成率 | G3: 営業日数(/31日) | I3: 残り必要額 | K3: 残り必要日商
A4: =IF('設定'!$B$11="",SUM(C8:C38),'設定'!$B$11) -> 20000000 | C4: =SUM(G8:G38) -> 9690000 | E4: =IFERROR(C4/A4,0) -> 0.4845 | G4: =COUNTIF(G8:G38,">0") -> 30 | I4: =A4-C4 -> 10310000 | K4: =IF((31-G4)>0,(A4-C4)/(31-G4),0) -> 10310000
A5: 日次予算合計 | C5: 着地見込 | E5: 決定率 | G5: 客単価 | I5: セット率 | K5: 試着率
A6: =SUM(C8:C38) -> 20000000 | C6: =IFERROR(C4/G4*31,0) -> 10013000 | E6: =IFERROR(M39/O39,0) -> 0.36566524 | G6: =IFERROR(G39/M39,0) -> 22746.479 | I6: =IFERROR(N39/M39,0) -> 1.0516432 | K6: =IFERROR(P39/O39,0) -> 0.54334764
A7: 日付 | B7: 曜 | C7: 日次予算 | D7: 累計予算 | E7: 現金 | F7: クレジット | G7: 実績合計 | H7: 累計実績 | I7: 日次達成 | J7: 累計達成 | K7: 累計予実差 | L7: ペース | M7: 購入人数 | N7: 販売点数 | O7: 来客数 | P7: 試着組数 | Q7: 試着個数 | R7: 決定率 | S7: 客単価 | T7: セット率 | U7: 試着率 | V7: クロス クーポン | W7: インスタ フォロワー | X7: 経費 | Y7: メモ | AA7: 曜日 | AB7: 平均日商 | AC7: 日数 | AD7: 決定率 | AE7: 客単価
A8: 46204 | B8: =MID("日月火水木金土",WEEKDAY(A8),1) -> 水 | C8: 550000 | D8: =SUM($C$8:C8) -> 550000 | E8: 97070 | F8: 292640 | G8: =IF(COUNT(E8:F8)=0,"",SUM(E8:F8)) -> 389710 | H8: =IF(G8="","",SUM($G$8:G8)) -> 389710 | I8: =IF(G8="","",IFERROR(G8/C8,"")) -> 0.70856364 | J8: =IF(H8="","",IFERROR(H8/D8,"")) -> 0.70856364 | K8: =IF(H8="","",IF(D8=0,"",H8-D8)) -> -160290 | L8: =IF(G8="","—",IF(D8=0,"予算未入力",IF(H8>=D8,"◎ ペース内","▲ 遅れ"))) -> ▲ 遅れ | M8: 16 | N8: 18 | O8: 44 | P8: 25 | Q8: 47 | R8: =IFERROR(M8/O8,"") -> 0.36363636 | S8: =IFERROR(G8/M8,"") -> 24356.875 | T8: =IFERROR(N8/M8,"") -> 1.125 | U8: =IFERROR(P8/O8,"") -> 0.56818182 | W8: 44074 | X8: 0 | AA8: 月 | AB8: =IFERROR(AVERAGEIFS($G$8:$G$38,$B$8:$B$38,AA8,$G$8:$G$38,">0"),0) -> 234885.25 | AC8: =COUNTIFS($B$8:$B$38,AA8,$G$8:$G$38,">0") -> 4 | AD8: =IFERROR(SUMIF($B$8:$B$38,AA8,$M$8:$M$38)/SUMIF($B$8:$B$38,AA8,$O$8:$O$38),0) -> 0.35964912 | AE8: =IFERROR(SUMIF($B$8:$B$38,AA8,$G$8:$G$38)/SUMIF($B$8:$B$38,AA8,$M$8:$M$38),0) -> 22915.634
A9: 46205 | B9: =MID("日月火水木金土",WEEKDAY(A9),1) -> 木 | C9: 550000 | D9: =SUM($C$8:C9) -> 1100000 | E9: 0 | F9: 193700 | G9: =IF(COUNT(E9:F9)=0,"",SUM(E9:F9)) -> 193700 | H9: =IF(G9="","",SUM($G$8:G9)) -> 583410 | I9: =IF(G9="","",IFERROR(G9/C9,"")) -> 0.35218182 | J9: =IF(H9="","",IFERROR(H9/D9,"")) -> 0.53037273 | K9: =IF(H9="","",IF(D9=0,"",H9-D9)) -> -516590 | L9: =IF(G9="","—",IF(D9=0,"予算未入力",IF(H9>=D9,"◎ ペース内","▲ 遅れ"))) -> ▲ 遅れ | M9: 8 | N9: 10 | O9: 29 | P9: 18 | Q9: 30 | R9: =IFERROR(M9/O9,"") -> 0.27586207 | S9: =IFERROR(G9/M9,"") -> 24212.5 | T9: =IFERROR(N9/M9,"") -> 1.25 | U9: =IFERROR(P9/O9,"") -> 0.62068966 | W9: 44071 | X9: 0 | AA9: 火 | AB9: =IFERROR(AVERAGEIFS($G$8:$G$38,$B$8:$B$38,AA9,$G$8:$G$38,">0"),0) -> 260905.25 | AC9: =COUNTIFS($B$8:$B$38,AA9,$G$8:$G$38,">0") -> 4 | AD9: =IFERROR(SUMIF($B$8:$B$38,AA9,$M$8:$M$38)/SUMIF($B$8:$B$38,AA9,$O$8:$O$38),0) -> 0.29375 | AE9: =IFERROR(SUMIF($B$8:$B$38,AA9,$G$8:$G$38)/SUMIF($B$8:$B$38,AA9,$M$8:$M$38),0) -> 22204.702
A10: 46206 | B10: =MID("日月火水木金土",WEEKDAY(A10),1) -> 金 | C10: 550000 | D10: =SUM($C$8:C10) -> 1650000 | E10: 26010 | F10: 418910 | G10: =IF(COUNT(E10:F10)=0,"",SUM(E10:F10)) -> 444920 | H10: =IF(G10="","",SUM($G$8:G10)) -> 1028330 | I10: =IF(G10="","",IFERROR(G10/C10,"")) -> 0.80894545 | J10: =IF(H10="","",IFERROR(H10/D10,"")) -> 0.6232303 | K10: =IF(H10="","",IF(D10=0,"",H10-D10)) -> -621670 | L10: =IF(G10="","—",IF(D10=0,"予算未入力",IF(H10>=D10,"◎ ペース内","▲ 遅れ"))) -> ▲ 遅れ | M10: 19 | N10: 21 | O10: 52 | P10: 32 | Q10: 56 | R10: =IFERROR(M10/O10,"") -> 0.36538462 | S10: =IFERROR(G10/M10,"") -> 23416.842 | T10: =IFERROR(N10/M10,"") -> 1.1052632 | U10: =IFERROR(P10/O10,"") -> 0.61538462 | X10: 0 | AA10: 水 | AB10: =IFERROR(AVERAGEIFS($G$8:$G$38,$B$8:$B$38,AA10,$G$8:$G$38,">0"),0) -> 314029 | AC10: =COUNTIFS($B$8:$B$38,AA10,$G$8:$G$38,">0") -> 5 | AD10: =IFERROR(SUMIF($B$8:$B$38,AA10,$M$8:$M$38)/SUMIF($B$8:$B$38,AA10,$O$8:$O$38),0) -> 0.38888889 | AE10: =IFERROR(SUMIF($B$8:$B$38,AA10,$G$8:$G$38)/SUMIF($B$8:$B$38,AA10,$M$8:$M$38),0) -> 22430.643
A11: 46207 | B11: =MID("日月火水木金土",WEEKDAY(A11),1) -> 土 | C11: 750000 | D11: =SUM($C$8:C11) -> 2400000 | E11: 138350 | F11: 515280 | G11: =IF(COUNT(E11:F11)=0,"",SUM(E11:F11)) -> 653630 | H11: =IF(G11="","",SUM($G$8:G11)) -> 1681960 | I11: =IF(G11="","",IFERROR(G11/C11,"")) -> 0.87150667 | J11: =IF(H11="","",IFERROR(H11/D11,"")) -> 0.70081667 | K11: =IF(H11="","",IF(D11=0,"",H11-D11)) -> -718040 | L11: =IF(G11="","—",IF(D11=0,"予算未入力",IF(H11>=D11,"◎ ペース内","▲ 遅れ"))) -> ▲ 遅れ | M11: 30 | N11: 30 | O11: 48 | P11: 31 | Q11: 55 | R11: =IFERROR(M11/O11,"") -> 0.625 | S11: =IFERROR(G11/M11,"") -> 21787.667 | T11: =IFERROR(N11/M11,"") -> 1 | U11: =IFERROR(P11/O11,"") -> 0.64583333 | X11: 0 | AA11: 木 | AB11: =IFERROR(AVERAGEIFS($G$8:$G$38,$B$8:$B$38,AA11,$G$8:$G$38,">0"),0) -> 192022.8 | AC11: =COUNTIFS($B$8:$B$38,AA11,$G$8:$G$38,">0") -> 5 | AD11: =IFERROR(SUMIF($B$8:$B$38,AA11,$M$8:$M$38)/SUMIF($B$8:$B$38,AA11,$O$8:$O$38),0) -> 0.30701754 | AE11: =IFERROR(SUMIF($B$8:$B$38,AA11,$G$8:$G$38)/SUMIF($B$8:$B$38,AA11,$M$8:$M$38),0) -> 27431.829
A12: 46208 | B12: =MID("日月火水木金土",WEEKDAY(A12),1) -> 日 | C12: 750000 | D12: =SUM($C$8:C12) -> 3150000 | E12: 108888 | F12: 546440 | G12: =IF(COUNT(E12:F12)=0,"",SUM(E12:F12)) -> 655328 | H12: =IF(G12="","",SUM($G$8:G12)) -> 2337288 | I12: =IF(G12="","",IFERROR(G12/C12,"")) -> 0.87377067 | J12: =IF(H12="","",IFERROR(H12/D12,"")) -> 0.74199619 | K12: =IF(H12="","",IF(D12=0,"",H12-D12)) -> -812712 | L12: =IF(G12="","—",IF(D12=0,"予算未入力",IF(H12>=D12,"◎ ペース内","▲ 遅れ"))) -> ▲ 遅れ | M12: 30 | N12: 32 | O12: 102 | P12: 54 | Q12: 75 | R12: =IFERROR(M12/O12,"") -> 0.29411765 | S12: =IFERROR(G12/M12,"") -> 21844.267 | T12: =IFERROR(N12/M12,"") -> 1.0666667 | U12: =IFERROR(P12/O12,"") -> 0.52941176 | W12: 44119 | X12: 0 | AA12: 金 | AB12: =IFERROR(AVERAGEIFS($G$8:$G$38,$B$8:$B$38,AA12,$G$8:$G$38,">0"),0) -> 330919.75 | AC12: =COUNTIFS($B$8:$B$38,AA12,$G$8:$G$38,">0") -> 4 | AD12: =IFERROR(SUMIF($B$8:$B$38,AA12,$M$8:$M$38)/SUMIF($B$8:$B$38,AA12,$O$8:$O$38),0) -> 0.41549296 | AE12: =IFERROR(SUMIF($B$8:$B$38,AA12,$G$8:$G$38)/SUMIF($B$8:$B$38,AA12,$M$8:$M$38),0) -> 22435.237
A13: 46209 | B13: =MID("日月火水木金土",WEEKDAY(A13),1) -> 月 | C13: 550000 | D13: =SUM($C$8:C13) -> 3700000 | E13: 134850 | F13: 229690 | G13: =IF(COUNT(E13:F13)=0,"",SUM(E13:F13)) -> 364540 | H13: =IF(G13="","",SUM($G$8:G13)) -> 2701828 | I13: =IF(G13="","",IFERROR(G13/C13,"")) -> 0.6628 | J13: =IF(H13="","",IFERROR(H13/D13,"")) -> 0.73022378 | K13: =IF(H13="","",IF(D13=0,"",H13-D13)) -> -998172 | L13: =IF(G13="","—",IF(D13=0,"予算未入力",IF(H13>=D13,"◎ ペース内","▲ 遅れ"))) -> ▲ 遅れ | M13: 15 | N13: 17 | O13: 35 | P13: 18 | Q13: 29 | R13: =IFERROR(M13/O13,"") -> 0.42857143 | S13: =IFERROR(G13/M13,"") -> 24302.667 | T13: =IFERROR(N13/M13,"") -> 1.1333333 | U13: =IFERROR(P13/O13,"") -> 0.51428571 | W13: 44121 | X13: 0 | AA13: 土 | AB13: =IFERROR(AVERAGEIFS($G$8:$G$38,$B$8:$B$38,AA13,$G$8:$G$38,">0"),0) -> 561593.75 | AC13: =COUNTIFS($B$8:$B$38,AA13,$G$8:$G$38,">0") -> 4 | AD13: =IFERROR(SUMIF($B$8:$B$38,AA13,$M$8:$M$38)/SUMIF($B$8:$B$38,AA13,$O$8:$O$38),0) -> 0.45535714 | AE13: =IFERROR(SUMIF($B$8:$B$38,AA13,$G$8:$G$38)/SUMIF($B$8:$B$38,AA13,$M$8:$M$38),0) -> 22023.284
A14: 46210 | B14: =MID("日月火水木金土",WEEKDAY(A14),1) -> 火 | C14: 550000 | D14: =SUM($C$8:C14) -> 4250000 | E14: 62530 | F14: 259960 | G14: =IF(COUNT(E14:F14)=0,"",SUM(E14:F14)) -> 322490 | H14: =IF(G14="","",SUM($G$8:G14)) -> 3024318 | I14: =IF(G14="","",IFERROR(G14/C14,"")) -> 0.58634545 | J14: =IF(H14="","",IFERROR(H14/D14,"")) -> 0.71160424 | K14: =IF(H14="","",IF(D14=0,"",H14-D14)) -> -1225682 | L14: =IF(G14="","—",IF(D14=0,"予算未入力",IF(H14>=D14,"◎ ペース内","▲ 遅れ"))) -> ▲ 遅れ | M14: 15 | N14: 15 | O14: 52 | P14: 20 | Q14: 40 | R14: =IFERROR(M14/O14,"") -> 0.28846154 | S14: =IFERROR(G14/M14,"") -> 21499.333 | T14: =IFERROR(N14/M14,"") -> 1 | U14: =IFERROR(P14/O14,"") -> 0.38461538 | W14: 44119 | X14: 0 | AA14: 日 | AB14: =IFERROR(AVERAGEIFS($G$8:$G$38,$B$8:$B$38,AA14,$G$8:$G$38,">0"),0) -> 401631.25 | AC14: =COUNTIFS($B$8:$B$38,AA14,$G$8:$G$38,">0") -> 4 | AD14: =IFERROR(SUMIF($B$8:$B$38,AA14,$M$8:$M$38)/SUMIF($B$8:$B$38,AA14,$O$8:$O$38),0) -> 0.31168831 | AE14: =IFERROR(SUMIF($B$8:$B$38,AA14,$G$8:$G$38)/SUMIF($B$8:$B$38,AA14,$M$8:$M$38),0) -> 22312.847
A15: 46211 | B15: =MID("日月火水木金土",WEEKDAY(A15),1) -> 水 | C15: 550000 | D15: =SUM($C$8:C15) -> 4800000 | E15: 71967 | F15: 231070 | G15: =IF(COUNT(E15:F15)=0,"",SUM(E15:F15)) -> 303037 | H15: =IF(G15="","",SUM($G$8:G15)) -> 3327355 | I15: =IF(G15="","",IFERROR(G15/C15,"")) -> 0.55097636 | J15: =IF(H15="","",IFERROR(H15/D15,"")) -> 0.69319896 | K15: =IF(H15="","",IF(D15=0,"",H15-D15)) -> -1472645 | L15: =IF(G15="","—",IF(D15=0,"予算未入力",IF(H15>=D15,"◎ ペース内","▲ 遅れ"))) -> ▲ 遅れ | M15: 14 | N15: 14 | O15: 28 | P15: 22 | Q15: 46 | R15: =IFERROR(M15/O15,"") -> 0.5 | S15: =IFERROR(G15/M15,"") -> 21645.5 | T15: =IFERROR(N15/M15,"") -> 1 | U15: =IFERROR(P15/O15,"") -> 0.78571429 | X15: 0
A16: 46212 | B16: =MID("日月火水木金土",WEEKDAY(A16),1) -> 木 | C16: 550000 | D16: =SUM($C$8:C16) -> 5350000 | E16: 0 | F16: 254080 | G16: =IF(COUNT(E16:F16)=0,"",SUM(E16:F16)) -> 254080 | H16: =IF(G16="","",SUM($G$8:G16)) -> 3581435 | I16: =IF(G16="","",IFERROR(G16/C16,"")) -> 0.46196364 | J16: =IF(H16="","",IFERROR(H16/D16,"")) -> 0.6694271 | K16: =IF(H16="","",IF(D16=0,"",H16-D16)) -> -1768565 | L16: =IF(G16="","—",IF(D16=0,"予算未入力",IF(H16>=D16,"◎ ペース内","▲ 遅れ"))) -> ▲ 遅れ | M16: 11 | N16: 11 | O16: 41 | P16: 18 | Q16: 48 | R16: =IFERROR(M16/O16,"") -> 0.26829268 | S16: =IFERROR(G16/M16,"") -> 23098.182 | T16: =IFERROR(N16/M16,"") -> 1 | U16: =IFERROR(P16/O16,"") -> 0.43902439 | W16: 44118 | X16: 0 | AA16: ※実績入力後に曜日別の傾向が出ます
A17: 46213 | B17: =MID("日月火水木金土",WEEKDAY(A17),1) -> 金 | C17: 550000 | D17: =SUM($C$8:C17) -> 5900000 | E17: 45420 | F17: 361700 | G17: =IF(COUNT(E17:F17)=0,"",SUM(E17:F17)) -> 407120 | H17: =IF(G17="","",SUM($G$8:G17)) -> 3988555 | I17: =IF(G17="","",IFERROR(G17/C17,"")) -> 0.74021818 | J17: =IF(H17="","",IFERROR(H17/D17,"")) -> 0.67602627 | K17: =IF(H17="","",IF(D17=0,"",H17-D17)) -> -1911445 | L17: =IF(G17="","—",IF(D17=0,"予算未入力",IF(H17>=D17,"◎ ペース内","▲ 遅れ"))) -> ▲ 遅れ | M17: 16 | N17: 16 | O17: 31 | P17: 23 | Q17: 35 | R17: =IFERROR(M17/O17,"") -> 0.51612903 | S17: =IFERROR(G17/M17,"") -> 25445 | T17: =IFERROR(N17/M17,"") -> 1 | U17: =IFERROR(P17/O17,"") -> 0.74193548 | W17: 44115 | X17: 0
A18: 46214 | B18: =MID("日月火水木金土",WEEKDAY(A18),1) -> 土 | C18: 750000 | D18: =SUM($C$8:C18) -> 6650000 | E18: 193350 | F18: 527417 | G18: =IF(COUNT(E18:F18)=0,"",SUM(E18:F18)) -> 720767 | H18: =IF(G18="","",SUM($G$8:G18)) -> 4709322 | I18: =IF(G18="","",IFERROR(G18/C18,"")) -> 0.96102267 | J18: =IF(H18="","",IFERROR(H18/D18,"")) -> 0.70816872 | K18: =IF(H18="","",IF(D18=0,"",H18-D18)) -> -1940678 | L18: =IF(G18="","—",IF(D18=0,"予算未入力",IF(H18>=D18,"◎ ペース内","▲ 遅れ"))) -> ▲ 遅れ | M18: 31 | N18: 34 | O18: 76 | P18: 35 | Q18: 74 | R18: =IFERROR(M18/O18,"") -> 0.40789474 | S18: =IFERROR(G18/M18,"") -> 23250.548 | T18: =IFERROR(N18/M18,"") -> 1.0967742 | U18: =IFERROR(P18/O18,"") -> 0.46052632 | X18: 0 | AA18: ■ 週次サマリー（火曜〜翌月曜） | AH18: 第1火曜 | AI18: =$A$8+MOD(2-WEEKDAY($A$8,2)+7,7) -> 46210
A19: 46215 | B19: =MID("日月火水木金土",WEEKDAY(A19),1) -> 日 | C19: 750000 | D19: =SUM($C$8:C19) -> 7400000 | E19: 38220 | F19: 356070 | G19: =IF(COUNT(E19:F19)=0,"",SUM(E19:F19)) -> 394290 | H19: =IF(G19="","",SUM($G$8:G19)) -> 5103612 | I19: =IF(G19="","",IFERROR(G19/C19,"")) -> 0.52572 | J19: =IF(H19="","",IFERROR(H19/D19,"")) -> 0.6896773 | K19: =IF(H19="","",IF(D19=0,"",H19-D19)) -> -2296388 | L19: =IF(G19="","—",IF(D19=0,"予算未入力",IF(H19>=D19,"◎ ペース内","▲ 遅れ"))) -> ▲ 遅れ | M19: 15 | N19: 15 | O19: 51 | P19: 22 | Q19: 28 | R19: =IFERROR(M19/O19,"") -> 0.29411765 | S19: =IFERROR(G19/M19,"") -> 26286 | T19: =IFERROR(N19/M19,"") -> 1 | U19: =IFERROR(P19/O19,"") -> 0.43137255 | W19: 44126 | X19: 0 | AA19: 週 | AB19: 期間 | AC19: 売上 | AD19: 決定率 | AE19: 客単価 | AF19: セット率 | AG19: 試着率
A20: 46216 | B20: =MID("日月火水木金土",WEEKDAY(A20),1) -> 月 | C20: 550000 | D20: =SUM($C$8:C20) -> 7950000 | E20: 64020 | F20: 116336 | G20: =IF(COUNT(E20:F20)=0,"",SUM(E20:F20)) -> 180356 | H20: =IF(G20="","",SUM($G$8:G20)) -> 5283968 | I20: =IF(G20="","",IFERROR(G20/C20,"")) -> 0.32792 | J20: =IF(H20="","",IFERROR(H20/D20,"")) -> 0.66465006 | K20: =IF(H20="","",IF(D20=0,"",H20-D20)) -> -2666032 | L20: =IF(G20="","—",IF(D20=0,"予算未入力",IF(H20>=D20,"◎ ペース内","▲ 遅れ"))) -> ▲ 遅れ | M20: 9 | N20: 9 | O20: 29 | P20: 11 | Q20: 32 | R20: =IFERROR(M20/O20,"") -> 0.31034483 | S20: =IFERROR(G20/M20,"") -> 20039.556 | T20: =IFERROR(N20/M20,"") -> 1 | U20: =IFERROR(P20/O20,"") -> 0.37931034 | W20: 44151 | X20: 0 | AA20: 1 | AB20: =IF($AI$18+7*(1-1)>$A$38,"",TEXT($AI$18+7*(1-1),"m/d")&"-"&TEXT($AI$18+7*(1-1)+6,"m/d")) -> 7/7-7/13 | AC20: =IF($AB20="","",(SUMIFS($G$8:$G$38,$A$8:$A$38,">="&$AI$18+7*(1-1),$A$8:$A$38,"<="&$AI$18+7*(1-1)+6)+SUMIFS('2026年08月'!$G$8:$G$38,'2026年08月'!$A$8:$A$38,">="&$AI$18+7*(1-1),'2026年08月'!$A$8:$A$38,"<="&$AI$18+7*(1-1)+6))) -> 2582140 | AD20: =IF($AB20="","",IFERROR((SUMIFS($M$8:$M$38,$A$8:$A$38,">="&$AI$18+7*(1-1),$A$8:$A$38,"<="&$AI$18+7*(1-1)+6)+SUMIFS('2026年08月'!$M$8:$M$38,'2026年08月'!$A$8:$A$38,">="&$AI$18+7*(1-1),'2026年08月'!$A$8:$A$38,"<="&$AI$18+7*(1-1)+6))/(SUMIFS($O$8:$O$38,$A$8:$A$38,">="&$AI$18+7*(1-1),$A$8:$A$38,"<="&$AI$18+7*(1-1)+6)+SUMIFS('2026年08月'!$O$8:$O$38,'2026年08月'!$A$8:$A$38,">="&$AI$18+7*(1-1),'2026年08月'!$A$8:$A$38,"<="&$AI$18+7*(1-1)+6)),"")) -> 0.36038961 | AE20: =IF($AB20="","",IFERROR((SUMIFS($G$8:$G$38,$A$8:$A$38,">="&$AI$18+7*(1-1),$A$8:$A$38,"<="&$AI$18+7*(1-1)+6)+SUMIFS('2026年08月'!$G$8:$G$38,'2026年08月'!$A$8:$A$38,">="&$AI$18+7*(1-1),'2026年08月'!$A$8:$A$38,"<="&$AI$18+7*(1-1)+6))/(SUMIFS($M$8:$M$38,$A$8:$A$38,">="&$AI$18+7*(1-1),$A$8:$A$38,"<="&$AI$18+7*(1-1)+6)+SUMIFS('2026年08月'!$M$8:$M$38,'2026年08月'!$A$8:$A$38,">="&$AI$18+7*(1-1),'2026年08月'!$A$8:$A$38,"<="&$AI$18+7*(1-1)+6)),"")) -> 23262.523 | AF20: =IF($AB20="","",IFERROR((SUMIFS($N$8:$N$38,$A$8:$A$38,">="&$AI$18+7*(1-1),$A$8:$A$38,"<="&$AI$18+7*(1-1)+6)+SUMIFS('2026年08月'!$N$8:$N$38,'2026年08月'!$A$8:$A$38,">="&$AI$18+7*(1-1),'2026年08月'!$A$8:$A$38,"<="&$AI$18+7*(1-1)+6))/(SUMIFS($M$8:$M$38,$A$8:$A$38,">="&$AI$18+7*(1-1),$A$8:$A$38,"<="&$AI$18+7*(1-1)+6)+SUMIFS('2026年08月'!$M$8:$M$38,'2026年08月'!$A$8:$A$38,">="&$AI$18+7*(1-1),'2026年08月'!$A$8:$A$38,"<="&$AI$18+7*(1-1)+6)),"")) -> 1.027027 | AG20: =IF($AB20="","",IFERROR((SUMIFS($P$8:$P$38,$A$8:$A$38,">="&$AI$18+7*(1-1),$A$8:$A$38,"<="&$AI$18+7*(1-1)+6)+SUMIFS('2026年08月'!$P$8:$P$38,'2026年08月'!$A$8:$A$38,">="&$AI$18+7*(1-1),'2026年08月'!$A$8:$A$38,"<="&$AI$18+7*(1-1)+6))/(SUMIFS($O$8:$O$38,$A$8:$A$38,">="&$AI$18+7*(1-1),$A$8:$A$38,"<="&$AI$18+7*(1-1)+6)+SUMIFS('2026年08月'!$O$8:$O$38,'2026年08月'!$A$8:$A$38,">="&$AI$18+7*(1-1),'2026年08月'!$A$8:$A$38,"<="&$AI$18+7*(1-1)+6)),"")) -> 0.49025974
A21: 46217 | B21: =MID("日月火水木金土",WEEKDAY(A21),1) -> 火 | C21: 550000 | D21: =SUM($C$8:C21) -> 8500000 | E21: 96240 | F21: 201170 | G21: =IF(COUNT(E21:F21)=0,"",SUM(E21:F21)) -> 297410 | H21: =IF(G21="","",SUM($G$8:G21)) -> 5581378 | I21: =IF(G21="","",IFERROR(G21/C21,"")) -> 0.54074545 | J21: =IF(H21="","",IFERROR(H21/D21,"")) -> 0.65663271 | K21: =IF(H21="","",IF(D21=0,"",H21-D21)) -> -2918622 | L21: =IF(G21="","—",IF(D21=0,"予算未入力",IF(H21>=D21,"◎ ペース内","▲ 遅れ"))) -> ▲ 遅れ | M21: 12 | N21: 15 | O21: 36 | P21: 12 | Q21: 19 | R21: =IFERROR(M21/O21,"") -> 0.33333333 | S21: =IFERROR(G21/M21,"") -> 24784.167 | T21: =IFERROR(N21/M21,"") -> 1.25 | U21: =IFERROR(P21/O21,"") -> 0.33333333 | W21: 44157 | X21: 0 | AA21: 2 | AB21: =IF($AI$18+7*(2-1)>$A$38,"",TEXT($AI$18+7*(2-1),"m/d")&"-"&TEXT($AI$18+7*(2-1)+6,"m/d")) -> 7/14-7/20 | AC21: =IF($AB21="","",(SUMIFS($G$8:$G$38,$A$8:$A$38,">="&$AI$18+7*(2-1),$A$8:$A$38,"<="&$AI$18+7*(2-1)+6)+SUMIFS('2026年08月'!$G$8:$G$38,'2026年08月'!$A$8:$A$38,">="&$AI$18+7*(2-1),'2026年08月'!$A$8:$A$38,"<="&$AI$18+7*(2-1)+6))) -> 2374619 | AD21: =IF($AB21="","",IFERROR((SUMIFS($M$8:$M$38,$A$8:$A$38,">="&$AI$18+7*(2-1),$A$8:$A$38,"<="&$AI$18+7*(2-1)+6)+SUMIFS('2026年08月'!$M$8:$M$38,'2026年08月'!$A$8:$A$38,">="&$AI$18+7*(2-1),'2026年08月'!$A$8:$A$38,"<="&$AI$18+7*(2-1)+6))/(SUMIFS($O$8:$O$38,$A$8:$A$38,">="&$AI$18+7*(2-1),$A$8:$A$38,"<="&$AI$18+7*(2-1)+6)+SUMIFS('2026年08月'!$O$8:$O$38,'2026年08月'!$A$8:$A$38,">="&$AI$18+7*(2-1),'2026年08月'!$A$8:$A$38,"<="&$AI$18+7*(2-1)+6)),"")) -> 0.42741935 | AE21: =IF($AB21="","",IFERROR((SUMIFS($G$8:$G$38,$A$8:$A$38,">="&$AI$18+7*(2-1),$A$8:$A$38,"<="&$AI$18+7*(2-1)+6)+SUMIFS('2026年08月'!$G$8:$G$38,'2026年08月'!$A$8:$A$38,">="&$AI$18+7*(2-1),'2026年08月'!$A$8:$A$38,"<="&$AI$18+7*(2-1)+6))/(SUMIFS($M$8:$M$38,$A$8:$A$38,">="&$AI$18+7*(2-1),$A$8:$A$38,"<="&$AI$18+7*(2-1)+6)+SUMIFS('2026年08月'!$M$8:$M$38,'2026年08月'!$A$8:$A$38,">="&$AI$18+7*(2-1),'2026年08月'!$A$8:$A$38,"<="&$AI$18+7*(2-1)+6)),"")) -> 22402.066 | AF21: =IF($AB21="","",IFERROR((SUMIFS($N$8:$N$38,$A$8:$A$38,">="&$AI$18+7*(2-1),$A$8:$A$38,"<="&$AI$18+7*(2-1)+6)+SUMIFS('2026年08月'!$N$8:$N$38,'2026年08月'!$A$8:$A$38,">="&$AI$18+7*(2-1),'2026年08月'!$A$8:$A$38,"<="&$AI$18+7*(2-1)+6))/(SUMIFS($M$8:$M$38,$A$8:$A$38,">="&$AI$18+7*(2-1),$A$8:$A$38,"<="&$AI$18+7*(2-1)+6)+SUMIFS('2026年08月'!$M$8:$M$38,'2026年08月'!$A$8:$A$38,">="&$AI$18+7*(2-1),'2026年08月'!$A$8:$A$38,"<="&$AI$18+7*(2-1)+6)),"")) -> 1.0660377 | AG21: =IF($AB21="","",IFERROR((SUMIFS($P$8:$P$38,$A$8:$A$38,">="&$AI$18+7*(2-1),$A$8:$A$38,"<="&$AI$18+7*(2-1)+6)+SUMIFS('2026年08月'!$P$8:$P$38,'2026年08月'!$A$8:$A$38,">="&$AI$18+7*(2-1),'2026年08月'!$A$8:$A$38,"<="&$AI$18+7*(2-1)+6))/(SUMIFS($O$8:$O$38,$A$8:$A$38,">="&$AI$18+7*(2-1),$A$8:$A$38,"<="&$AI$18+7*(2-1)+6)+SUMIFS('2026年08月'!$O$8:$O$38,'2026年08月'!$A$8:$A$38,">="&$AI$18+7*(2-1),'2026年08月'!$A$8:$A$38,"<="&$AI$18+7*(2-1)+6)),"")) -> 0.66129032
A22: 46218 | B22: =MID("日月火水木金土",WEEKDAY(A22),1) -> 水 | C22: 550000 | D22: =SUM($C$8:C22) -> 9050000 | E22: 152940 | F22: 200180 | G22: =IF(COUNT(E22:F22)=0,"",SUM(E22:F22)) -> 353120 | H22: =IF(G22="","",SUM($G$8:G22)) -> 5934498 | I22: =IF(G22="","",IFERROR(G22/C22,"")) -> 0.64203636 | J22: =IF(H22="","",IFERROR(H22/D22,"")) -> 0.65574564 | K22: =IF(H22="","",IF(D22=0,"",H22-D22)) -> -3115502 | L22: =IF(G22="","—",IF(D22=0,"予算未入力",IF(H22>=D22,"◎ ペース内","▲ 遅れ"))) -> ▲ 遅れ | M22: 16 | N22: 18 | O22: 40 | P22: 27 | Q22: 36 | R22: =IFERROR(M22/O22,"") -> 0.4 | S22: =IFERROR(G22/M22,"") -> 22070 | T22: =IFERROR(N22/M22,"") -> 1.125 | U22: =IFERROR(P22/O22,"") -> 0.675 | W22: 44154 | X22: 0 | AA22: 3 | AB22: =IF($AI$18+7*(3-1)>$A$38,"",TEXT($AI$18+7*(3-1),"m/d")&"-"&TEXT($AI$18+7*(3-1)+6,"m/d")) -> 7/21-7/27 | AC22: =IF($AB22="","",(SUMIFS($G$8:$G$38,$A$8:$A$38,">="&$AI$18+7*(3-1),$A$8:$A$38,"<="&$AI$18+7*(3-1)+6)+SUMIFS('2026年08月'!$G$8:$G$38,'2026年08月'!$A$8:$A$38,">="&$AI$18+7*(3-1),'2026年08月'!$A$8:$A$38,"<="&$AI$18+7*(3-1)+6))) -> 1490502 | AD22: =IF($AB22="","",IFERROR((SUMIFS($M$8:$M$38,$A$8:$A$38,">="&$AI$18+7*(3-1),$A$8:$A$38,"<="&$AI$18+7*(3-1)+6)+SUMIFS('2026年08月'!$M$8:$M$38,'2026年08月'!$A$8:$A$38,">="&$AI$18+7*(3-1),'2026年08月'!$A$8:$A$38,"<="&$AI$18+7*(3-1)+6))/(SUMIFS($O$8:$O$38,$A$8:$A$38,">="&$AI$18+7*(3-1),$A$8:$A$38,"<="&$AI$18+7*(3-1)+6)+SUMIFS('2026年08月'!$O$8:$O$38,'2026年08月'!$A$8:$A$38,">="&$AI$18+7*(3-1),'2026年08月'!$A$8:$A$38,"<="&$AI$18+7*(3-1)+6)),"")) -> 0.32876712 | AE22: =IF($AB22="","",IFERROR((SUMIFS($G$8:$G$38,$A$8:$A$38,">="&$AI$18+7*(3-1),$A$8:$A$38,"<="&$AI$18+7*(3-1)+6)+SUMIFS('2026年08月'!$G$8:$G$38,'2026年08月'!$A$8:$A$38,">="&$AI$18+7*(3-1),'2026年08月'!$A$8:$A$38,"<="&$AI$18+7*(3-1)+6))/(SUMIFS($M$8:$M$38,$A$8:$A$38,">="&$AI$18+7*(3-1),$A$8:$A$38,"<="&$AI$18+7*(3-1)+6)+SUMIFS('2026年08月'!$M$8:$M$38,'2026年08月'!$A$8:$A$38,">="&$AI$18+7*(3-1),'2026年08月'!$A$8:$A$38,"<="&$AI$18+7*(3-1)+6)),"")) -> 20701.417 | AF22: =IF($AB22="","",IFERROR((SUMIFS($N$8:$N$38,$A$8:$A$38,">="&$AI$18+7*(3-1),$A$8:$A$38,"<="&$AI$18+7*(3-1)+6)+SUMIFS('2026年08月'!$N$8:$N$38,'2026年08月'!$A$8:$A$38,">="&$AI$18+7*(3-1),'2026年08月'!$A$8:$A$38,"<="&$AI$18+7*(3-1)+6))/(SUMIFS($M$8:$M$38,$A$8:$A$38,">="&$AI$18+7*(3-1),$A$8:$A$38,"<="&$AI$18+7*(3-1)+6)+SUMIFS('2026年08月'!$M$8:$M$38,'2026年08月'!$A$8:$A$38,">="&$AI$18+7*(3-1),'2026年08月'!$A$8:$A$38,"<="&$AI$18+7*(3-1)+6)),"")) -> 1.0138889 | AG22: =IF($AB22="","",IFERROR((SUMIFS($P$8:$P$38,$A$8:$A$38,">="&$AI$18+7*(3-1),$A$8:$A$38,"<="&$AI$18+7*(3-1)+6)+SUMIFS('2026年08月'!$P$8:$P$38,'2026年08月'!$A$8:$A$38,">="&$AI$18+7*(3-1),'2026年08月'!$A$8:$A$38,"<="&$AI$18+7*(3-1)+6))/(SUMIFS($O$8:$O$38,$A$8:$A$38,">="&$AI$18+7*(3-1),$A$8:$A$38,"<="&$AI$18+7*(3-1)+6)+SUMIFS('2026年08月'!$O$8:$O$38,'2026年08月'!$A$8:$A$38,">="&$AI$18+7*(3-1),'2026年08月'!$A$8:$A$38,"<="&$AI$18+7*(3-1)+6)),"")) -> 0.51141553
A23: 46219 | B23: =MID("日月火水木金土",WEEKDAY(A23),1) -> 木 | C23: 550000 | D23: =SUM($C$8:C23) -> 9600000 | E23: 67920 | F23: 179943 | G23: =IF(COUNT(E23:F23)=0,"",SUM(E23:F23)) -> 247863 | H23: =IF(G23="","",SUM($G$8:G23)) -> 6182361 | I23: =IF(G23="","",IFERROR(G23/C23,"")) -> 0.45066 | J23: =IF(H23="","",IFERROR(H23/D23,"")) -> 0.64399594 | K23: =IF(H23="","",IF(D23=0,"",H23-D23)) -> -3417639 | L23: =IF(G23="","—",IF(D23=0,"予算未入力",IF(H23>=D23,"◎ ペース内","▲ 遅れ"))) -> ▲ 遅れ | M23: 9 | N23: 11 | O23: 26 | P23: 11 | Q23: 15 | R23: =IFERROR(M23/O23,"") -> 0.34615385 | S23: =IFERROR(G23/M23,"") -> 27540.333 | T23: =IFERROR(N23/M23,"") -> 1.2222222 | U23: =IFERROR(P23/O23,"") -> 0.42307692 | W23: 44153 | X23: 0 | AA23: 4 | AB23: =IF($AI$18+7*(4-1)>$A$38,"",TEXT($AI$18+7*(4-1),"m/d")&"-"&TEXT($AI$18+7*(4-1)+6,"m/d")) -> 7/28-8/3 | AC23: =IF($AB23="","",(SUMIFS($G$8:$G$38,$A$8:$A$38,">="&$AI$18+7*(4-1),$A$8:$A$38,"<="&$AI$18+7*(4-1)+6)+SUMIFS('2026年08月'!$G$8:$G$38,'2026年08月'!$A$8:$A$38,">="&$AI$18+7*(4-1),'2026年08月'!$A$8:$A$38,"<="&$AI$18+7*(4-1)+6))) -> 1293630 | AD23: =IF($AB23="","",IFERROR((SUMIFS($M$8:$M$38,$A$8:$A$38,">="&$AI$18+7*(4-1),$A$8:$A$38,"<="&$AI$18+7*(4-1)+6)+SUMIFS('2026年08月'!$M$8:$M$38,'2026年08月'!$A$8:$A$38,">="&$AI$18+7*(4-1),'2026年08月'!$A$8:$A$38,"<="&$AI$18+7*(4-1)+6))/(SUMIFS($O$8:$O$38,$A$8:$A$38,">="&$AI$18+7*(4-1),$A$8:$A$38,"<="&$AI$18+7*(4-1)+6)+SUMIFS('2026年08月'!$O$8:$O$38,'2026年08月'!$A$8:$A$38,">="&$AI$18+7*(4-1),'2026年08月'!$A$8:$A$38,"<="&$AI$18+7*(4-1)+6)),"")) -> 0.27604167 | AE23: =IF($AB23="","",IFERROR((SUMIFS($G$8:$G$38,$A$8:$A$38,">="&$AI$18+7*(4-1),$A$8:$A$38,"<="&$AI$18+7*(4-1)+6)+SUMIFS('2026年08月'!$G$8:$G$38,'2026年08月'!$A$8:$A$38,">="&$AI$18+7*(4-1),'2026年08月'!$A$8:$A$38,"<="&$AI$18+7*(4-1)+6))/(SUMIFS($M$8:$M$38,$A$8:$A$38,">="&$AI$18+7*(4-1),$A$8:$A$38,"<="&$AI$18+7*(4-1)+6)+SUMIFS('2026年08月'!$M$8:$M$38,'2026年08月'!$A$8:$A$38,">="&$AI$18+7*(4-1),'2026年08月'!$A$8:$A$38,"<="&$AI$18+7*(4-1)+6)),"")) -> 24408.113 | AF23: =IF($AB23="","",IFERROR((SUMIFS($N$8:$N$38,$A$8:$A$38,">="&$AI$18+7*(4-1),$A$8:$A$38,"<="&$AI$18+7*(4-1)+6)+SUMIFS('2026年08月'!$N$8:$N$38,'2026年08月'!$A$8:$A$38,">="&$AI$18+7*(4-1),'2026年08月'!$A$8:$A$38,"<="&$AI$18+7*(4-1)+6))/(SUMIFS($M$8:$M$38,$A$8:$A$38,">="&$AI$18+7*(4-1),$A$8:$A$38,"<="&$AI$18+7*(4-1)+6)+SUMIFS('2026年08月'!$M$8:$M$38,'2026年08月'!$A$8:$A$38,">="&$AI$18+7*(4-1),'2026年08月'!$A$8:$A$38,"<="&$AI$18+7*(4-1)+6)),"")) -> 1.1132075 | AG23: =IF($AB23="","",IFERROR((SUMIFS($P$8:$P$38,$A$8:$A$38,">="&$AI$18+7*(4-1),$A$8:$A$38,"<="&$AI$18+7*(4-1)+6)+SUMIFS('2026年08月'!$P$8:$P$38,'2026年08月'!$A$8:$A$38,">="&$AI$18+7*(4-1),'2026年08月'!$A$8:$A$38,"<="&$AI$18+7*(4-1)+6))/(SUMIFS($O$8:$O$38,$A$8:$A$38,">="&$AI$18+7*(4-1),$A$8:$A$38,"<="&$AI$18+7*(4-1)+6)+SUMIFS('2026年08月'!$O$8:$O$38,'2026年08月'!$A$8:$A$38,">="&$AI$18+7*(4-1),'2026年08月'!$A$8:$A$38,"<="&$AI$18+7*(4-1)+6)),"")) -> 0.421875
A24: 46220 | B24: =MID("日月火水木金土",WEEKDAY(A24),1) -> 金 | C24: 550000 | D24: =SUM($C$8:C24) -> 10150000 | E24: 69840 | F24: 175760 | G24: =IF(COUNT(E24:F24)=0,"",SUM(E24:F24)) -> 245600 | H24: =IF(G24="","",SUM($G$8:G24)) -> 6427961 | I24: =IF(G24="","",IFERROR(G24/C24,"")) -> 0.44654545 | J24: =IF(H24="","",IFERROR(H24/D24,"")) -> 0.63329665 | K24: =IF(H24="","",IF(D24=0,"",H24-D24)) -> -3722039 | L24: =IF(G24="","—",IF(D24=0,"予算未入力",IF(H24>=D24,"◎ ペース内","▲ 遅れ"))) -> ▲ 遅れ | M24: 12 | N24: 12 | O24: 22 | P24: 19 | Q24: 26 | R24: =IFERROR(M24/O24,"") -> 0.54545455 | S24: =IFERROR(G24/M24,"") -> 20466.667 | T24: =IFERROR(N24/M24,"") -> 1 | U24: =IFERROR(P24/O24,"") -> 0.86363636 | W24: 44162 | X24: 0 | AA24: 5 | AB24: =IF($AI$18+7*(5-1)>$A$38,"",TEXT($AI$18+7*(5-1),"m/d")&"-"&TEXT($AI$18+7*(5-1)+6,"m/d")) | AC24: =IF($AB24="","",(SUMIFS($G$8:$G$38,$A$8:$A$38,">="&$AI$18+7*(5-1),$A$8:$A$38,"<="&$AI$18+7*(5-1)+6)+SUMIFS('2026年08月'!$G$8:$G$38,'2026年08月'!$A$8:$A$38,">="&$AI$18+7*(5-1),'2026年08月'!$A$8:$A$38,"<="&$AI$18+7*(5-1)+6))) | AD24: =IF($AB24="","",IFERROR((SUMIFS($M$8:$M$38,$A$8:$A$38,">="&$AI$18+7*(5-1),$A$8:$A$38,"<="&$AI$18+7*(5-1)+6)+SUMIFS('2026年08月'!$M$8:$M$38,'2026年08月'!$A$8:$A$38,">="&$AI$18+7*(5-1),'2026年08月'!$A$8:$A$38,"<="&$AI$18+7*(5-1)+6))/(SUMIFS($O$8:$O$38,$A$8:$A$38,">="&$AI$18+7*(5-1),$A$8:$A$38,"<="&$AI$18+7*(5-1)+6)+SUMIFS('2026年08月'!$O$8:$O$38,'2026年08月'!$A$8:$A$38,">="&$AI$18+7*(5-1),'2026年08月'!$A$8:$A$38,"<="&$AI$18+7*(5-1)+6)),"")) | AE24: =IF($AB24="","",IFERROR((SUMIFS($G$8:$G$38,$A$8:$A$38,">="&$AI$18+7*(5-1),$A$8:$A$38,"<="&$AI$18+7*(5-1)+6)+SUMIFS('2026年08月'!$G$8:$G$38,'2026年08月'!$A$8:$A$38,">="&$AI$18+7*(5-1),'2026年08月'!$A$8:$A$38,"<="&$AI$18+7*(5-1)+6))/(SUMIFS($M$8:$M$38,$A$8:$A$38,">="&$AI$18+7*(5-1),$A$8:$A$38,"<="&$AI$18+7*(5-1)+6)+SUMIFS('2026年08月'!$M$8:$M$38,'2026年08月'!$A$8:$A$38,">="&$AI$18+7*(5-1),'2026年08月'!$A$8:$A$38,"<="&$AI$18+7*(5-1)+6)),"")) | AF24: =IF($AB24="","",IFERROR((SUMIFS($N$8:$N$38,$A$8:$A$38,">="&$AI$18+7*(5-1),$A$8:$A$38,"<="&$AI$18+7*(5-1)+6)+SUMIFS('2026年08月'!$N$8:$N$38,'2026年08月'!$A$8:$A$38,">="&$AI$18+7*(5-1),'2026年08月'!$A$8:$A$38,"<="&$AI$18+7*(5-1)+6))/(SUMIFS($M$8:$M$38,$A$8:$A$38,">="&$AI$18+7*(5-1),$A$8:$A$38,"<="&$AI$18+7*(5-1)+6)+SUMIFS('2026年08月'!$M$8:$M$38,'2026年08月'!$A$8:$A$38,">="&$AI$18+7*(5-1),'2026年08月'!$A$8:$A$38,"<="&$AI$18+7*(5-1)+6)),"")) | AG24: =IF($AB24="","",IFERROR((SUMIFS($P$8:$P$38,$A$8:$A$38,">="&$AI$18+7*(5-1),$A$8:$A$38,"<="&$AI$18+7*(5-1)+6)+SUMIFS('2026年08月'!$P$8:$P$38,'2026年08月'!$A$8:$A$38,">="&$AI$18+7*(5-1),'2026年08月'!$A$8:$A$38,"<="&$AI$18+7*(5-1)+6))/(SUMIFS($O$8:$O$38,$A$8:$A$38,">="&$AI$18+7*(5-1),$A$8:$A$38,"<="&$AI$18+7*(5-1)+6)+SUMIFS('2026年08月'!$O$8:$O$38,'2026年08月'!$A$8:$A$38,">="&$AI$18+7*(5-1),'2026年08月'!$A$8:$A$38,"<="&$AI$18+7*(5-1)+6)),""))
A25: 46221 | B25: =MID("日月火水木金土",WEEKDAY(A25),1) -> 土 | C25: 900000 | D25: =SUM($C$8:C25) -> 11050000 | E25: 85320 | F25: 417728 | G25: =IF(COUNT(E25:F25)=0,"",SUM(E25:F25)) -> 503048 | H25: =IF(G25="","",SUM($G$8:G25)) -> 6931009 | I25: =IF(G25="","",IFERROR(G25/C25,"")) -> 0.55894222 | J25: =IF(H25="","",IFERROR(H25/D25,"")) -> 0.62724063 | K25: =IF(H25="","",IF(D25=0,"",H25-D25)) -> -4118991 | L25: =IF(G25="","—",IF(D25=0,"予算未入力",IF(H25>=D25,"◎ ペース内","▲ 遅れ"))) -> ▲ 遅れ | M25: 25 | N25: 25 | O25: 47 | P25: 39 | Q25: 45 | R25: =IFERROR(M25/O25,"") -> 0.53191489 | S25: =IFERROR(G25/M25,"") -> 20121.92 | T25: =IFERROR(N25/M25,"") -> 1 | U25: =IFERROR(P25/O25,"") -> 0.82978723 | X25: 0 | AA25: 6 | AB25: =IF($AI$18+7*(6-1)>$A$38,"",TEXT($AI$18+7*(6-1),"m/d")&"-"&TEXT($AI$18+7*(6-1)+6,"m/d")) | AC25: =IF($AB25="","",(SUMIFS($G$8:$G$38,$A$8:$A$38,">="&$AI$18+7*(6-1),$A$8:$A$38,"<="&$AI$18+7*(6-1)+6)+SUMIFS('2026年08月'!$G$8:$G$38,'2026年08月'!$A$8:$A$38,">="&$AI$18+7*(6-1),'2026年08月'!$A$8:$A$38,"<="&$AI$18+7*(6-1)+6))) | AD25: =IF($AB25="","",IFERROR((SUMIFS($M$8:$M$38,$A$8:$A$38,">="&$AI$18+7*(6-1),$A$8:$A$38,"<="&$AI$18+7*(6-1)+6)+SUMIFS('2026年08月'!$M$8:$M$38,'2026年08月'!$A$8:$A$38,">="&$AI$18+7*(6-1),'2026年08月'!$A$8:$A$38,"<="&$AI$18+7*(6-1)+6))/(SUMIFS($O$8:$O$38,$A$8:$A$38,">="&$AI$18+7*(6-1),$A$8:$A$38,"<="&$AI$18+7*(6-1)+6)+SUMIFS('2026年08月'!$O$8:$O$38,'2026年08月'!$A$8:$A$38,">="&$AI$18+7*(6-1),'2026年08月'!$A$8:$A$38,"<="&$AI$18+7*(6-1)+6)),"")) | AE25: =IF($AB25="","",IFERROR((SUMIFS($G$8:$G$38,$A$8:$A$38,">="&$AI$18+7*(6-1),$A$8:$A$38,"<="&$AI$18+7*(6-1)+6)+SUMIFS('2026年08月'!$G$8:$G$38,'2026年08月'!$A$8:$A$38,">="&$AI$18+7*(6-1),'2026年08月'!$A$8:$A$38,"<="&$AI$18+7*(6-1)+6))/(SUMIFS($M$8:$M$38,$A$8:$A$38,">="&$AI$18+7*(6-1),$A$8:$A$38,"<="&$AI$18+7*(6-1)+6)+SUMIFS('2026年08月'!$M$8:$M$38,'2026年08月'!$A$8:$A$38,">="&$AI$18+7*(6-1),'2026年08月'!$A$8:$A$38,"<="&$AI$18+7*(6-1)+6)),"")) | AF25: =IF($AB25="","",IFERROR((SUMIFS($N$8:$N$38,$A$8:$A$38,">="&$AI$18+7*(6-1),$A$8:$A$38,"<="&$AI$18+7*(6-1)+6)+SUMIFS('2026年08月'!$N$8:$N$38,'2026年08月'!$A$8:$A$38,">="&$AI$18+7*(6-1),'2026年08月'!$A$8:$A$38,"<="&$AI$18+7*(6-1)+6))/(SUMIFS($M$8:$M$38,$A$8:$A$38,">="&$AI$18+7*(6-1),$A$8:$A$38,"<="&$AI$18+7*(6-1)+6)+SUMIFS('2026年08月'!$M$8:$M$38,'2026年08月'!$A$8:$A$38,">="&$AI$18+7*(6-1),'2026年08月'!$A$8:$A$38,"<="&$AI$18+7*(6-1)+6)),"")) | AG25: =IF($AB25="","",IFERROR((SUMIFS($P$8:$P$38,$A$8:$A$38,">="&$AI$18+7*(6-1),$A$8:$A$38,"<="&$AI$18+7*(6-1)+6)+SUMIFS('2026年08月'!$P$8:$P$38,'2026年08月'!$A$8:$A$38,">="&$AI$18+7*(6-1),'2026年08月'!$A$8:$A$38,"<="&$AI$18+7*(6-1)+6))/(SUMIFS($O$8:$O$38,$A$8:$A$38,">="&$AI$18+7*(6-1),$A$8:$A$38,"<="&$AI$18+7*(6-1)+6)+SUMIFS('2026年08月'!$O$8:$O$38,'2026年08月'!$A$8:$A$38,">="&$AI$18+7*(6-1),'2026年08月'!$A$8:$A$38,"<="&$AI$18+7*(6-1)+6)),""))
A26: 46222 | B26: =MID("日月火水木金土",WEEKDAY(A26),1) -> 日 | C26: 900000 | D26: =SUM($C$8:C26) -> 11950000 | E26: 38820 | F26: 413063 | G26: =IF(COUNT(E26:F26)=0,"",SUM(E26:F26)) -> 451883 | H26: =IF(G26="","",SUM($G$8:G26)) -> 7382892 | I26: =IF(G26="","",IFERROR(G26/C26,"")) -> 0.50209222 | J26: =IF(H26="","",IFERROR(H26/D26,"")) -> 0.61781523 | K26: =IF(H26="","",IF(D26=0,"",H26-D26)) -> -4567108 | L26: =IF(G26="","—",IF(D26=0,"予算未入力",IF(H26>=D26,"◎ ペース内","▲ 遅れ"))) -> ▲ 遅れ | M26: 20 | N26: 20 | O26: 42 | P26: 26 | Q26: 33 | R26: =IFERROR(M26/O26,"") -> 0.47619048 | S26: =IFERROR(G26/M26,"") -> 22594.15 | T26: =IFERROR(N26/M26,"") -> 1 | U26: =IFERROR(P26/O26,"") -> 0.61904762 | X26: 0 | AA26: ※期間ラベルは第1火曜から自動生成。決定率・客単価・セット率・試着率は「週合計÷週合計」
A27: 46223 | B27: =MID("日月火水木金土",WEEKDAY(A27),1) -> 月 | C27: 900000 | D27: =SUM($C$8:C27) -> 12850000 | E27: 49820 | F27: 225875 | G27: =IF(COUNT(E27:F27)=0,"",SUM(E27:F27)) -> 275695 | H27: =IF(G27="","",SUM($G$8:G27)) -> 7658587 | I27: =IF(G27="","",IFERROR(G27/C27,"")) -> 0.30632778 | J27: =IF(H27="","",IFERROR(H27/D27,"")) -> 0.59599899 | K27: =IF(H27="","",IF(D27=0,"",H27-D27)) -> -5191413 | L27: =IF(G27="","—",IF(D27=0,"予算未入力",IF(H27>=D27,"◎ ペース内","▲ 遅れ"))) -> ▲ 遅れ | M27: 12 | N27: 12 | O27: 35 | P27: 30 | Q27: 40 | R27: =IFERROR(M27/O27,"") -> 0.34285714 | S27: =IFERROR(G27/M27,"") -> 22974.583 | T27: =IFERROR(N27/M27,"") -> 1 | U27: =IFERROR(P27/O27,"") -> 0.85714286 | W27: 44152 | X27: 0 | AA27: ※最終週は翌月にまたぐため、2026年08月シートの実績も自動で合算します
A28: 46224 | B28: =MID("日月火水木金土",WEEKDAY(A28),1) -> 火 | C28: 600000 | D28: =SUM($C$8:C28) -> 13450000 | E28: 57080 | F28: 133772 | G28: =IF(COUNT(E28:F28)=0,"",SUM(E28:F28)) -> 190852 | H28: =IF(G28="","",SUM($G$8:G28)) -> 7849439 | I28: =IF(G28="","",IFERROR(G28/C28,"")) -> 0.31808667 | J28: =IF(H28="","",IFERROR(H28/D28,"")) -> 0.58360141 | K28: =IF(H28="","",IF(D28=0,"",H28-D28)) -> -5600561 | L28: =IF(G28="","—",IF(D28=0,"予算未入力",IF(H28>=D28,"◎ ペース内","▲ 遅れ"))) -> ▲ 遅れ | M28: 9 | N28: 9 | O28: 24 | P28: 13 | Q28: 20 | R28: =IFERROR(M28/O28,"") -> 0.375 | S28: =IFERROR(G28/M28,"") -> 21205.778 | T28: =IFERROR(N28/M28,"") -> 1 | U28: =IFERROR(P28/O28,"") -> 0.54166667 | X28: 0 | AA28: ※月初の月曜まで（例：6/1）は前月シートの最終週に含まれます
A29: 46225 | B29: =MID("日月火水木金土",WEEKDAY(A29),1) -> 水 | C29: 600000 | D29: =SUM($C$8:C29) -> 14050000 | E29: 69577 | F29: 258696 | G29: =IF(COUNT(E29:F29)=0,"",SUM(E29:F29)) -> 328273 | H29: =IF(G29="","",SUM($G$8:G29)) -> 8177712 | I29: =IF(G29="","",IFERROR(G29/C29,"")) -> 0.54712167 | J29: =IF(H29="","",IFERROR(H29/D29,"")) -> 0.58204356 | K29: =IF(H29="","",IF(D29=0,"",H29-D29)) -> -5872288 | L29: =IF(G29="","—",IF(D29=0,"予算未入力",IF(H29>=D29,"◎ ペース内","▲ 遅れ"))) -> ▲ 遅れ | M29: 16 | N29: 16 | O29: 36 | P29: 24 | Q29: 46 | R29: =IFERROR(M29/O29,"") -> 0.44444444 | S29: =IFERROR(G29/M29,"") -> 20517.062 | T29: =IFERROR(N29/M29,"") -> 1 | U29: =IFERROR(P29/O29,"") -> 0.66666667 | W29: 44145 | X29: 0
A30: 46226 | B30: =MID("日月火水木金土",WEEKDAY(A30),1) -> 木 | C30: 600000 | D30: =SUM($C$8:C30) -> 14650000 | E30: 44220 | F30: 108214 | G30: =IF(COUNT(E30:F30)=0,"",SUM(E30:F30)) -> 152434 | H30: =IF(G30="","",SUM($G$8:G30)) -> 8330146 | I30: =IF(G30="","",IFERROR(G30/C30,"")) -> 0.25405667 | J30: =IF(H30="","",IFERROR(H30/D30,"")) -> 0.56861065 | K30: =IF(H30="","",IF(D30=0,"",H30-D30)) -> -6319854 | L30: =IF(G30="","—",IF(D30=0,"予算未入力",IF(H30>=D30,"◎ ペース内","▲ 遅れ"))) -> ▲ 遅れ | M30: 7 | N30: 7 | O30: 18 | P30: 12 | Q30: 17 | R30: =IFERROR(M30/O30,"") -> 0.38888889 | S30: =IFERROR(G30/M30,"") -> 21776.286 | T30: =IFERROR(N30/M30,"") -> 1 | U30: =IFERROR(P30/O30,"") -> 0.66666667 | X30: 0
A31: 46227 | B31: =MID("日月火水木金土",WEEKDAY(A31),1) -> 金 | C31: 600000 | D31: =SUM($C$8:C31) -> 15250000 | E31: 38938 | F31: 187101 | G31: =IF(COUNT(E31:F31)=0,"",SUM(E31:F31)) -> 226039 | H31: =IF(G31="","",SUM($G$8:G31)) -> 8556185 | I31: =IF(G31="","",IFERROR(G31/C31,"")) -> 0.37673167 | J31: =IF(H31="","",IFERROR(H31/D31,"")) -> 0.56106131 | K31: =IF(H31="","",IF(D31=0,"",H31-D31)) -> -6693815 | L31: =IF(G31="","—",IF(D31=0,"予算未入力",IF(H31>=D31,"◎ ペース内","▲ 遅れ"))) -> ▲ 遅れ | M31: 12 | N31: 13 | O31: 37 | P31: 19 | Q31: 36 | R31: =IFERROR(M31/O31,"") -> 0.32432432 | S31: =IFERROR(G31/M31,"") -> 18836.583 | T31: =IFERROR(N31/M31,"") -> 1.0833333 | U31: =IFERROR(P31/O31,"") -> 0.51351351 | X31: 0
A32: 46228 | B32: =MID("日月火水木金土",WEEKDAY(A32),1) -> 土 | C32: 850000 | D32: =SUM($C$8:C32) -> 16100000 | E32: 157010 | F32: 211920 | G32: =IF(COUNT(E32:F32)=0,"",SUM(E32:F32)) -> 368930 | H32: =IF(G32="","",SUM($G$8:G32)) -> 8925115 | I32: =IF(G32="","",IFERROR(G32/C32,"")) -> 0.43403529 | J32: =IF(H32="","",IFERROR(H32/D32,"")) -> 0.55435497 | K32: =IF(H32="","",IF(D32=0,"",H32-D32)) -> -7174885 | L32: =IF(G32="","—",IF(D32=0,"予算未入力",IF(H32>=D32,"◎ ペース内","▲ 遅れ"))) -> ▲ 遅れ | M32: 16 | N32: 16 | O32: 53 | P32: 26 | Q32: 39 | R32: =IFERROR(M32/O32,"") -> 0.30188679 | S32: =IFERROR(G32/M32,"") -> 23058.125 | T32: =IFERROR(N32/M32,"") -> 1 | U32: =IFERROR(P32/O32,"") -> 0.49056604 | W32: 44136 | X32: 0
A33: 46229 | B33: =MID("日月火水木金土",WEEKDAY(A33),1) -> 日 | C33: 900000 | D33: =SUM($C$8:C33) -> 17000000 | E33: 63130 | F33: 41894 | G33: =IF(COUNT(E33:F33)=0,"",SUM(E33:F33)) -> 105024 | H33: =IF(G33="","",SUM($G$8:G33)) -> 9030139 | I33: =IF(G33="","",IFERROR(G33/C33,"")) -> 0.11669333 | J33: =IF(H33="","",IFERROR(H33/D33,"")) -> 0.53118465 | K33: =IF(H33="","",IF(D33=0,"",H33-D33)) -> -7969861 | L33: =IF(G33="","—",IF(D33=0,"予算未入力",IF(H33>=D33,"◎ ペース内","▲ 遅れ"))) -> ▲ 遅れ | M33: 7 | N33: 7 | O33: 36 | P33: 11 | Q33: 24 | R33: =IFERROR(M33/O33,"") -> 0.19444444 | S33: =IFERROR(G33/M33,"") -> 15003.429 | T33: =IFERROR(N33/M33,"") -> 1 | U33: =IFERROR(P33/O33,"") -> 0.30555556 | W33: 44123 | X33: 0
A34: 46230 | B34: =MID("日月火水木金土",WEEKDAY(A34),1) -> 月 | C34: 600000 | D34: =SUM($C$8:C34) -> 17600000 | E34: 68130 | F34: 50820 | G34: =IF(COUNT(E34:F34)=0,"",SUM(E34:F34)) -> 118950 | H34: =IF(G34="","",SUM($G$8:G34)) -> 9149089 | I34: =IF(G34="","",IFERROR(G34/C34,"")) -> 0.19825 | J34: =IF(H34="","",IFERROR(H34/D34,"")) -> 0.5198346 | K34: =IF(H34="","",IF(D34=0,"",H34-D34)) -> -8450911 | L34: =IF(G34="","—",IF(D34=0,"予算未入力",IF(H34>=D34,"◎ ペース内","▲ 遅れ"))) -> ▲ 遅れ | M34: 5 | N34: 5 | O34: 15 | P34: 7 | Q34: 13 | R34: =IFERROR(M34/O34,"") -> 0.33333333 | S34: =IFERROR(G34/M34,"") -> 23790 | T34: =IFERROR(N34/M34,"") -> 1 | U34: =IFERROR(P34/O34,"") -> 0.46666667 | W34: 44123 | X34: 0
A35: 46231 | B35: =MID("日月火水木金土",WEEKDAY(A35),1) -> 火 | C35: 600000 | D35: =SUM($C$8:C35) -> 18200000 | E35: 63630 | F35: 169239 | G35: =IF(COUNT(E35:F35)=0,"",SUM(E35:F35)) -> 232869 | H35: =IF(G35="","",SUM($G$8:G35)) -> 9381958 | I35: =IF(G35="","",IFERROR(G35/C35,"")) -> 0.388115 | J35: =IF(H35="","",IFERROR(H35/D35,"")) -> 0.5154922 | K35: =IF(H35="","",IF(D35=0,"",H35-D35)) -> -8818042 | L35: =IF(G35="","—",IF(D35=0,"予算未入力",IF(H35>=D35,"◎ ペース内","▲ 遅れ"))) -> ▲ 遅れ | M35: 11 | N35: 12 | O35: 48 | P35: 14 | Q35: 18 | R35: =IFERROR(M35/O35,"") -> 0.22916667 | S35: =IFERROR(G35/M35,"") -> 21169.909 | T35: =IFERROR(N35/M35,"") -> 1.0909091 | U35: =IFERROR(P35/O35,"") -> 0.29166667 | X35: 0
A36: 46232 | B36: =MID("日月火水木金土",WEEKDAY(A36),1) -> 水 | C36: 600000 | D36: =SUM($C$8:C36) -> 18800000 | E36: 74130 | F36: 121875 | G36: =IF(COUNT(E36:F36)=0,"",SUM(E36:F36)) -> 196005 | H36: =IF(G36="","",SUM($G$8:G36)) -> 9577963 | I36: =IF(G36="","",IFERROR(G36/C36,"")) -> 0.326675 | J36: =IF(H36="","",IFERROR(H36/D36,"")) -> 0.50946612 | K36: =IF(H36="","",IF(D36=0,"",H36-D36)) -> -9222037 | L36: =IF(G36="","—",IF(D36=0,"予算未入力",IF(H36>=D36,"◎ ペース内","▲ 遅れ"))) -> ▲ 遅れ | M36: 8 | N36: 8 | O36: 32 | P36: 14 | Q36: 27 | R36: =IFERROR(M36/O36,"") -> 0.25 | S36: =IFERROR(G36/M36,"") -> 24500.625 | T36: =IFERROR(N36/M36,"") -> 1 | U36: =IFERROR(P36/O36,"") -> 0.4375 | X36: 0
A37: 46233 | B37: =MID("日月火水木金土",WEEKDAY(A37),1) -> 木 | C37: 600000 | D37: =SUM($C$8:C37) -> 19400000 | E37: 0 | F37: 112037 | G37: =IF(COUNT(E37:F37)=0,"",SUM(E37:F37)) -> 112037 | H37: =IF(G37="","",SUM($G$8:G37)) -> 9690000 | I37: =IF(G37="","",IFERROR(G37/C37,"")) -> 0.18672833 | J37: =IF(H37="","",IFERROR(H37/D37,"")) -> 0.49948454 | K37: =IF(H37="","",IF(D37=0,"",H37-D37)) -> -9710000 | L37: =IF(G37="","—",IF(D37=0,"予算未入力",IF(H37>=D37,"◎ ペース内","▲ 遅れ"))) -> ▲ 遅れ | R37: =IFERROR(M37/O37,"") | S37: =IFERROR(G37/M37,"") | T37: =IFERROR(N37/M37,"") | U37: =IFERROR(P37/O37,"") | X37: 0
A38: 46234 | B38: =MID("日月火水木金土",WEEKDAY(A38),1) -> 金 | C38: 600000 | D38: =SUM($C$8:C38) -> 20000000 | G38: =IF(COUNT(E38:F38)=0,"",SUM(E38:F38)) | H38: =IF(G38="","",SUM($G$8:G38)) | I38: =IF(G38="","",IFERROR(G38/C38,"")) | J38: =IF(H38="","",IFERROR(H38/D38,"")) | K38: =IF(H38="","",IF(D38=0,"",H38-D38)) | L38: =IF(G38="","—",IF(D38=0,"予算未入力",IF(H38>=D38,"◎ ペース内","▲ 遅れ"))) -> — | R38: =IFERROR(M38/O38,"") | S38: =IFERROR(G38/M38,"") | T38: =IFERROR(N38/M38,"") | U38: =IFERROR(P38/O38,"") | X38: 0
A39: 月計 | C39: =SUM(C8:C38) -> 20000000 | D39: =C39 -> 20000000 | E39: =SUM(E8:E38) -> 2177420 | F39: =SUM(F8:F38) -> 7512580 | G39: =SUM(G8:G38) -> 9690000 | H39: =G39 -> 9690000 | I39: =IFERROR(G39/C39,"") -> 0.4845 | J39: =IFERROR(G39/C39,"") -> 0.4845 | K39: =G39-C39 -> -10310000 | M39: =SUM(M8:M38) -> 426 | N39: =SUM(N8:N38) -> 448 | O39: =SUM(O8:O38) -> 1165 | P39: =SUM(P8:P38) -> 633 | Q39: =SUM(Q8:Q38) -> 1049 | R39: =IFERROR(M39/O39,"") -> 0.36566524 | S39: =IFERROR(G39/M39,"") -> 22746.479 | T39: =IFERROR(N39/M39,"") -> 1.0516432 | U39: =IFERROR(P39/O39,"") -> 0.54334764 | V39: =SUM(V8:V38) -> 0 | W39: =IFERROR(LOOKUP(9.99E+307,W8:W38),"") -> 44123 | X39: =SUM(X8:X38) -> 0 | Y39: フォロワーは月末値

Sheet 2026年08月
A1: 2026年8月 原宿店 日別売上管理
A2: 青字＋薄黄色のセルが入力欄。白セルは数式なので触らないでください。単位：円
A3: 月間予算 | C3: 当月実績 | E3: 達成率 | G3: 営業日数(/31日) | I3: 残り必要額 | K3: 残り必要日商
A4: =IF('設定'!$B$12="",SUM(C8:C38),'設定'!$B$12) -> 24660000 | C4: =SUM(G8:G38) -> 8510877 | E4: =IFERROR(C4/A4,0) -> 0.34512883 | G4: =COUNTIF(G8:G38,">0") -> 31 | I4: =A4-C4 -> 16149123 | K4: =IF((31-G4)>0,(A4-C4)/(31-G4),0) -> 0
A5: 日次予算合計 | C5: 着地見込 | E5: 決定率 | G5: 客単価 | I5: セット率 | K5: 試着率
A6: =SUM(C8:C38) -> 24660000 | C6: =IFERROR(C4/G4*31,0) -> 8510877 | E6: =IFERROR(M39/O39,0) -> 0.39752832 | G6: =IFERROR(G39/M39,0) -> 22048.904 | I6: =IFERROR(N39/M39,0) -> 1.119171 | K6: =IFERROR(P39/O39,0) -> 0.54479918
A7: 日付 | B7: 曜 | C7: 日次予算 | D7: 累計予算 | E7: 現金 | F7: クレジット | G7: 実績合計 | H7: 累計実績 | I7: 日次達成 | J7: 累計達成 | K7: 累計予実差 | L7: ペース | M7: 購入人数 | N7: 販売点数 | O7: 来客数 | P7: 試着組数 | Q7: 試着個数 | R7: 決定率 | S7: 客単価 | T7: セット率 | U7: 試着率 | V7: クロス クーポン | W7: インスタ フォロワー | X7: 経費 | Y7: メモ | AA7: 曜日 | AB7: 平均日商 | AC7: 日数 | AD7: 決定率 | AE7: 客単価
A8: 46235 | B8: =MID("日月火水木金土",WEEKDAY(A8),1) -> 土 | C8: 920000 | D8: =SUM($C$8:C8) -> 920000 | E8: 80538 | F8: 103699 | G8: =IF(COUNT(E8:F8)=0,"",SUM(E8:F8)) -> 184237 | H8: =IF(G8="","",SUM($G$8:G8)) -> 184237 | I8: =IF(G8="","",IFERROR(G8/C8,"")) -> 0.20025761 | J8: =IF(H8="","",IFERROR(H8/D8,"")) -> 0.20025761 | K8: =IF(H8="","",IF(D8=0,"",H8-D8)) -> -735763 | L8: =IF(G8="","—",IF(D8=0,"予算未入力",IF(H8>=D8,"◎ ペース内","▲ 遅れ"))) -> ▲ 遅れ | M8: 9 | N8: 9 | O8: 41 | P8: 18 | Q8: 23 | R8: =IFERROR(M8/O8,"") -> 0.2195122 | S8: =IFERROR(G8/M8,"") -> 20470.778 | T8: =IFERROR(N8/M8,"") -> 1 | U8: =IFERROR(P8/O8,"") -> 0.43902439 | W8: 44031 | X8: 0 | AA8: 月 | AB8: =IFERROR(AVERAGEIFS($G$8:$G$38,$B$8:$B$38,AA8,$G$8:$G$38,">0"),0) -> 169276.4 | AC8: =COUNTIFS($B$8:$B$38,AA8,$G$8:$G$38,">0") -> 5 | AD8: =IFERROR(SUMIF($B$8:$B$38,AA8,$M$8:$M$38)/SUMIF($B$8:$B$38,AA8,$O$8:$O$38),0) -> 0.26388889 | AE8: =IFERROR(SUMIF($B$8:$B$38,AA8,$G$8:$G$38)/SUMIF($B$8:$B$38,AA8,$M$8:$M$38),0) -> 22273.211
A9: 46236 | B9: =MID("日月火水木金土",WEEKDAY(A9),1) -> 日 | C9: 920000 | D9: =SUM($C$8:C9) -> 1840000 | E9: 23810 | F9: 314060 | G9: =IF(COUNT(E9:F9)=0,"",SUM(E9:F9)) -> 337870 | H9: =IF(G9="","",SUM($G$8:G9)) -> 522107 | I9: =IF(G9="","",IFERROR(G9/C9,"")) -> 0.36725 | J9: =IF(H9="","",IFERROR(H9/D9,"")) -> 0.2837538 | K9: =IF(H9="","",IF(D9=0,"",H9-D9)) -> -1317893 | L9: =IF(G9="","—",IF(D9=0,"予算未入力",IF(H9>=D9,"◎ ペース内","▲ 遅れ"))) -> ▲ 遅れ | M9: 15 | N9: 16 | O9: 42 | P9: 20 | Q9: 31 | R9: =IFERROR(M9/O9,"") -> 0.35714286 | S9: =IFERROR(G9/M9,"") -> 22524.667 | T9: =IFERROR(N9/M9,"") -> 1.0666667 | U9: =IFERROR(P9/O9,"") -> 0.47619048 | W9: 44017 | AA9: 火 | AB9: =IFERROR(AVERAGEIFS($G$8:$G$38,$B$8:$B$38,AA9,$G$8:$G$38,">0"),0) -> 209119.75 | AC9: =COUNTIFS($B$8:$B$38,AA9,$G$8:$G$38,">0") -> 4 | AD9: =IFERROR(SUMIF($B$8:$B$38,AA9,$M$8:$M$38)/SUMIF($B$8:$B$38,AA9,$O$8:$O$38),0) -> 0.48275862 | AE9: =IFERROR(SUMIF($B$8:$B$38,AA9,$G$8:$G$38)/SUMIF($B$8:$B$38,AA9,$M$8:$M$38),0) -> 19916.167
A10: 46237 | B10: =MID("日月火水木金土",WEEKDAY(A10),1) -> 月 | C10: 600000 | D10: =SUM($C$8:C10) -> 2440000 | E10: 16500 | F10: 214112 | G10: =IF(COUNT(E10:F10)=0,"",SUM(E10:F10)) -> 230612 | H10: =IF(G10="","",SUM($G$8:G10)) -> 752719 | I10: =IF(G10="","",IFERROR(G10/C10,"")) -> 0.38435333 | J10: =IF(H10="","",IFERROR(H10/D10,"")) -> 0.30849139 | K10: =IF(H10="","",IF(D10=0,"",H10-D10)) -> -1687281 | L10: =IF(G10="","—",IF(D10=0,"予算未入力",IF(H10>=D10,"◎ ペース内","▲ 遅れ"))) -> ▲ 遅れ | M10: 10 | N10: 14 | O10: 29 | P10: 15 | Q10: 19 | R10: =IFERROR(M10/O10,"") -> 0.34482759 | S10: =IFERROR(G10/M10,"") -> 23061.2 | T10: =IFERROR(N10/M10,"") -> 1.4 | U10: =IFERROR(P10/O10,"") -> 0.51724138 | W10: 43992 | AA10: 水 | AB10: =IFERROR(AVERAGEIFS($G$8:$G$38,$B$8:$B$38,AA10,$G$8:$G$38,">0"),0) -> 378254.5 | AC10: =COUNTIFS($B$8:$B$38,AA10,$G$8:$G$38,">0") -> 4 | AD10: =IFERROR(SUMIF($B$8:$B$38,AA10,$M$8:$M$38)/SUMIF($B$8:$B$38,AA10,$O$8:$O$38),0) -> 0.45454545 | AE10: =IFERROR(SUMIF($B$8:$B$38,AA10,$G$8:$G$38)/SUMIF($B$8:$B$38,AA10,$M$8:$M$38),0) -> 25216.967
A11: 46238 | B11: =MID("日月火水木金土",WEEKDAY(A11),1) -> 火 | C11: 600000 | D11: =SUM($C$8:C11) -> 3040000 | E11: 19410 | F11: 135514 | G11: =IF(COUNT(E11:F11)=0,"",SUM(E11:F11)) -> 154924 | H11: =IF(G11="","",SUM($G$8:G11)) -> 907643 | I11: =IF(G11="","",IFERROR(G11/C11,"")) -> 0.25820667 | J11: =IF(H11="","",IFERROR(H11/D11,"")) -> 0.29856678 | K11: =IF(H11="","",IF(D11=0,"",H11-D11)) -> -2132357 | L11: =IF(G11="","—",IF(D11=0,"予算未入力",IF(H11>=D11,"◎ ペース内","▲ 遅れ"))) -> ▲ 遅れ | M11: 8 | N11: 8 | O11: 31 | P11: 14 | Q11: 16 | R11: =IFERROR(M11/O11,"") -> 0.25806452 | S11: =IFERROR(G11/M11,"") -> 19365.5 | T11: =IFERROR(N11/M11,"") -> 1 | U11: =IFERROR(P11/O11,"") -> 0.4516129 | W11: 43974 | AA11: 木 | AB11: =IFERROR(AVERAGEIFS($G$8:$G$38,$B$8:$B$38,AA11,$G$8:$G$38,">0"),0) -> 237435.25 | AC11: =COUNTIFS($B$8:$B$38,AA11,$G$8:$G$38,">0") -> 4 | AD11: =IFERROR(SUMIF($B$8:$B$38,AA11,$M$8:$M$38)/SUMIF($B$8:$B$38,AA11,$O$8:$O$38),0) -> 0.3220339 | AE11: =IFERROR(SUMIF($B$8:$B$38,AA11,$G$8:$G$38)/SUMIF($B$8:$B$38,AA11,$M$8:$M$38),0) -> 24993.184
A12: 46239 | B12: =MID("日月火水木金土",WEEKDAY(A12),1) -> 水 | C12: 600000 | D12: =SUM($C$8:C12) -> 3640000 | E12: 44000 | F12: 252083 | G12: =IF(COUNT(E12:F12)=0,"",SUM(E12:F12)) -> 296083 | H12: =IF(G12="","",SUM($G$8:G12)) -> 1203726 | I12: =IF(G12="","",IFERROR(G12/C12,"")) -> 0.49347167 | J12: =IF(H12="","",IFERROR(H12/D12,"")) -> 0.33069396 | K12: =IF(H12="","",IF(D12=0,"",H12-D12)) -> -2436274 | L12: =IF(G12="","—",IF(D12=0,"予算未入力",IF(H12>=D12,"◎ ペース内","▲ 遅れ"))) -> ▲ 遅れ | M12: 12 | N12: 15 | O12: 26 | P12: 13 | Q12: 20 | R12: =IFERROR(M12/O12,"") -> 0.46153846 | S12: =IFERROR(G12/M12,"") -> 24673.583 | T12: =IFERROR(N12/M12,"") -> 1.25 | U12: =IFERROR(P12/O12,"") -> 0.5 | W12: 43958 | AA12: 金 | AB12: =IFERROR(AVERAGEIFS($G$8:$G$38,$B$8:$B$38,AA12,$G$8:$G$38,">0"),0) -> 271458.5 | AC12: =COUNTIFS($B$8:$B$38,AA12,$G$8:$G$38,">0") -> 4 | AD12: =IFERROR(SUMIF($B$8:$B$38,AA12,$M$8:$M$38)/SUMIF($B$8:$B$38,AA12,$O$8:$O$38),0) -> 0.44615385 | AE12: =IFERROR(SUMIF($B$8:$B$38,AA12,$G$8:$G$38)/SUMIF($B$8:$B$38,AA12,$M$8:$M$38),0) -> 18721.276
A13: 46240 | B13: =MID("日月火水木金土",WEEKDAY(A13),1) -> 木 | C13: 600000 | D13: =SUM($C$8:C13) -> 4240000 | E13: 40162 | F13: 117846 | G13: =IF(COUNT(E13:F13)=0,"",SUM(E13:F13)) -> 158008 | H13: =IF(G13="","",SUM($G$8:G13)) -> 1361734 | I13: =IF(G13="","",IFERROR(G13/C13,"")) -> 0.26334667 | J13: =IF(H13="","",IFERROR(H13/D13,"")) -> 0.32116368 | K13: =IF(H13="","",IF(D13=0,"",H13-D13)) -> -2878266 | L13: =IF(G13="","—",IF(D13=0,"予算未入力",IF(H13>=D13,"◎ ペース内","▲ 遅れ"))) -> ▲ 遅れ | M13: 8 | N13: 8 | O13: 24 | P13: 10 | Q13: 15 | R13: =IFERROR(M13/O13,"") -> 0.33333333 | S13: =IFERROR(G13/M13,"") -> 19751 | T13: =IFERROR(N13/M13,"") -> 1 | U13: =IFERROR(P13/O13,"") -> 0.41666667 | W13: 43948 | AA13: 土 | AB13: =IFERROR(AVERAGEIFS($G$8:$G$38,$B$8:$B$38,AA13,$G$8:$G$38,">0"),0) -> 311607.6 | AC13: =COUNTIFS($B$8:$B$38,AA13,$G$8:$G$38,">0") -> 5 | AD13: =IFERROR(SUMIF($B$8:$B$38,AA13,$M$8:$M$38)/SUMIF($B$8:$B$38,AA13,$O$8:$O$38),0) -> 0.42774566 | AE13: =IFERROR(SUMIF($B$8:$B$38,AA13,$G$8:$G$38)/SUMIF($B$8:$B$38,AA13,$M$8:$M$38),0) -> 21054.568
A14: 46241 | B14: =MID("日月火水木金土",WEEKDAY(A14),1) -> 金 | C14: 600000 | D14: =SUM($C$8:C14) -> 4840000 | E14: 42808 | F14: 127519 | G14: =IF(COUNT(E14:F14)=0,"",SUM(E14:F14)) -> 170327 | H14: =IF(G14="","",SUM($G$8:G14)) -> 1532061 | I14: =IF(G14="","",IFERROR(G14/C14,"")) -> 0.28387833 | J14: =IF(H14="","",IFERROR(H14/D14,"")) -> 0.31654153 | K14: =IF(H14="","",IF(D14=0,"",H14-D14)) -> -3307939 | L14: =IF(G14="","—",IF(D14=0,"予算未入力",IF(H14>=D14,"◎ ペース内","▲ 遅れ"))) -> ▲ 遅れ | M14: 8 | N14: 8 | O14: 29 | P14: 15 | Q14: 20 | R14: =IFERROR(M14/O14,"") -> 0.27586207 | S14: =IFERROR(G14/M14,"") -> 21290.875 | T14: =IFERROR(N14/M14,"") -> 1 | U14: =IFERROR(P14/O14,"") -> 0.51724138 | W14: 43928 | AA14: 日 | AB14: =IFERROR(AVERAGEIFS($G$8:$G$38,$B$8:$B$38,AA14,$G$8:$G$38,">0"),0) -> 344277 | AC14: =COUNTIFS($B$8:$B$38,AA14,$G$8:$G$38,">0") -> 5 | AD14: =IFERROR(SUMIF($B$8:$B$38,AA14,$M$8:$M$38)/SUMIF($B$8:$B$38,AA14,$O$8:$O$38),0) -> 0.40641711 | AE14: =IFERROR(SUMIF($B$8:$B$38,AA14,$G$8:$G$38)/SUMIF($B$8:$B$38,AA14,$M$8:$M$38),0) -> 22649.803
A15: 46242 | B15: =MID("日月火水木金土",WEEKDAY(A15),1) -> 土 | C15: 920000 | D15: =SUM($C$8:C15) -> 5760000 | E15: 67030 | F15: 236986 | G15: =IF(COUNT(E15:F15)=0,"",SUM(E15:F15)) -> 304016 | H15: =IF(G15="","",SUM($G$8:G15)) -> 1836077 | I15: =IF(G15="","",IFERROR(G15/C15,"")) -> 0.33045217 | J15: =IF(H15="","",IFERROR(H15/D15,"")) -> 0.31876337 | K15: =IF(H15="","",IF(D15=0,"",H15-D15)) -> -3923923 | L15: =IF(G15="","—",IF(D15=0,"予算未入力",IF(H15>=D15,"◎ ペース内","▲ 遅れ"))) -> ▲ 遅れ | M15: 14 | N15: 14 | O15: 41 | P15: 25 | Q15: 29 | R15: =IFERROR(M15/O15,"") -> 0.34146341 | S15: =IFERROR(G15/M15,"") -> 21715.429 | T15: =IFERROR(N15/M15,"") -> 1 | U15: =IFERROR(P15/O15,"") -> 0.6097561 | W15: 43905
A16: 46243 | B16: =MID("日月火水木金土",WEEKDAY(A16),1) -> 日 | C16: 920000 | D16: =SUM($C$8:C16) -> 6680000 | E16: 47620 | F16: 270241 | G16: =IF(COUNT(E16:F16)=0,"",SUM(E16:F16)) -> 317861 | H16: =IF(G16="","",SUM($G$8:G16)) -> 2153938 | I16: =IF(G16="","",IFERROR(G16/C16,"")) -> 0.34550109 | J16: =IF(H16="","",IFERROR(H16/D16,"")) -> 0.32244581 | K16: =IF(H16="","",IF(D16=0,"",H16-D16)) -> -4526062 | L16: =IF(G16="","—",IF(D16=0,"予算未入力",IF(H16>=D16,"◎ ペース内","▲ 遅れ"))) -> ▲ 遅れ | M16: 12 | N16: 15 | O16: 40 | P16: 18 | Q16: 22 | R16: =IFERROR(M16/O16,"") -> 0.3 | S16: =IFERROR(G16/M16,"") -> 26488.417 | T16: =IFERROR(N16/M16,"") -> 1.25 | U16: =IFERROR(P16/O16,"") -> 0.45 | W16: 43888 | AA16: ※実績入力後に曜日別の傾向が出ます
A17: 46244 | B17: =MID("日月火水木金土",WEEKDAY(A17),1) -> 月 | C17: 700000 | D17: =SUM($C$8:C17) -> 7380000 | E17: 90116 | F17: 84218 | G17: =IF(COUNT(E17:F17)=0,"",SUM(E17:F17)) -> 174334 | H17: =IF(G17="","",SUM($G$8:G17)) -> 2328272 | I17: =IF(G17="","",IFERROR(G17/C17,"")) -> 0.24904857 | J17: =IF(H17="","",IFERROR(H17/D17,"")) -> 0.31548401 | K17: =IF(H17="","",IF(D17=0,"",H17-D17)) -> -5051728 | L17: =IF(G17="","—",IF(D17=0,"予算未入力",IF(H17>=D17,"◎ ペース内","▲ 遅れ"))) -> ▲ 遅れ | M17: 8 | N17: 8 | O17: 39 | P17: 24 | Q17: 23 | R17: =IFERROR(M17/O17,"") -> 0.20512821 | S17: =IFERROR(G17/M17,"") -> 21791.75 | T17: =IFERROR(N17/M17,"") -> 1 | U17: =IFERROR(P17/O17,"") -> 0.61538462 | W17: 43877
A18: 46245 | B18: =MID("日月火水木金土",WEEKDAY(A18),1) -> 火 | C18: 920000 | D18: =SUM($C$8:C18) -> 8300000 | E18: 24800 | F18: 151100 | G18: =IF(COUNT(E18:F18)=0,"",SUM(E18:F18)) -> 175900 | H18: =IF(G18="","",SUM($G$8:G18)) -> 2504172 | I18: =IF(G18="","",IFERROR(G18/C18,"")) -> 0.19119565 | J18: =IF(H18="","",IFERROR(H18/D18,"")) -> 0.30170747 | K18: =IF(H18="","",IF(D18=0,"",H18-D18)) -> -5795828 | L18: =IF(G18="","—",IF(D18=0,"予算未入力",IF(H18>=D18,"◎ ペース内","▲ 遅れ"))) -> ▲ 遅れ | M18: 12 | N18: 10 | O18: 19 | P18: 9 | Q18: 15 | R18: =IFERROR(M18/O18,"") -> 0.63157895 | S18: =IFERROR(G18/M18,"") -> 14658.333 | T18: =IFERROR(N18/M18,"") -> 0.83333333 | U18: =IFERROR(P18/O18,"") -> 0.47368421 | W18: 43859 | AA18: ■ 週次サマリー（火曜〜翌月曜） | AH18: 第1火曜 | AI18: =$A$8+MOD(2-WEEKDAY($A$8,2)+7,7) -> 46238
A19: 46246 | B19: =MID("日月火水木金土",WEEKDAY(A19),1) -> 水 | C19: 720000 | D19: =SUM($C$8:C19) -> 9020000 | E19: 68740 | F19: 337140 | G19: =IF(COUNT(E19:F19)=0,"",SUM(E19:F19)) -> 405880 | H19: =IF(G19="","",SUM($G$8:G19)) -> 2910052 | I19: =IF(G19="","",IFERROR(G19/C19,"")) -> 0.56372222 | J19: =IF(H19="","",IFERROR(H19/D19,"")) -> 0.32262217 | K19: =IF(H19="","",IF(D19=0,"",H19-D19)) -> -6109948 | L19: =IF(G19="","—",IF(D19=0,"予算未入力",IF(H19>=D19,"◎ ペース内","▲ 遅れ"))) -> ▲ 遅れ | M19: 18 | N19: 23 | O19: 32 | P19: 24 | Q19: 29 | R19: =IFERROR(M19/O19,"") -> 0.5625 | S19: =IFERROR(G19/M19,"") -> 22548.889 | T19: =IFERROR(N19/M19,"") -> 1.2777778 | U19: =IFERROR(P19/O19,"") -> 0.75 | W19: 43848 | AA19: 週 | AB19: 期間 | AC19: 売上 | AD19: 決定率 | AE19: 客単価 | AF19: セット率 | AG19: 試着率
A20: 46247 | B20: =MID("日月火水木金土",WEEKDAY(A20),1) -> 木 | C20: 1120000 | D20: =SUM($C$8:C20) -> 10140000 | E20: 14960 | F20: 102116 | G20: =IF(COUNT(E20:F20)=0,"",SUM(E20:F20)) -> 117076 | H20: =IF(G20="","",SUM($G$8:G20)) -> 3027128 | I20: =IF(G20="","",IFERROR(G20/C20,"")) -> 0.10453214 | J20: =IF(H20="","",IFERROR(H20/D20,"")) -> 0.29853333 | K20: =IF(H20="","",IF(D20=0,"",H20-D20)) -> -7112872 | L20: =IF(G20="","—",IF(D20=0,"予算未入力",IF(H20>=D20,"◎ ペース内","▲ 遅れ"))) -> ▲ 遅れ | M20: 6 | N20: 6 | O20: 34 | P20: 10 | Q20: 14 | R20: =IFERROR(M20/O20,"") -> 0.17647059 | S20: =IFERROR(G20/M20,"") -> 19512.667 | T20: =IFERROR(N20/M20,"") -> 1 | U20: =IFERROR(P20/O20,"") -> 0.29411765 | W20: 43848 | AA20: 1 | AB20: =IF($AI$18+7*(1-1)>$A$38,"",TEXT($AI$18+7*(1-1),"m/d")&"-"&TEXT($AI$18+7*(1-1)+6,"m/d")) -> 8/4-8/10 | AC20: =IF($AB20="","",(SUMIFS($G$8:$G$38,$A$8:$A$38,">="&$AI$18+7*(1-1),$A$8:$A$38,"<="&$AI$18+7*(1-1)+6)+SUMIFS('2026年09月'!$G$8:$G$37,'2026年09月'!$A$8:$A$37,">="&$AI$18+7*(1-1),'2026年09月'!$A$8:$A$37,"<="&$AI$18+7*(1-1)+6))) -> 1575553 | AD20: =IF($AB20="","",IFERROR((SUMIFS($M$8:$M$38,$A$8:$A$38,">="&$AI$18+7*(1-1),$A$8:$A$38,"<="&$AI$18+7*(1-1)+6)+SUMIFS('2026年09月'!$M$8:$M$37,'2026年09月'!$A$8:$A$37,">="&$AI$18+7*(1-1),'2026年09月'!$A$8:$A$37,"<="&$AI$18+7*(1-1)+6))/(SUMIFS($O$8:$O$38,$A$8:$A$38,">="&$AI$18+7*(1-1),$A$8:$A$38,"<="&$AI$18+7*(1-1)+6)+SUMIFS('2026年09月'!$O$8:$O$37,'2026年09月'!$A$8:$A$37,">="&$AI$18+7*(1-1),'2026年09月'!$A$8:$A$37,"<="&$AI$18+7*(1-1)+6)),"")) -> 0.30434783 | AE20: =IF($AB20="","",IFERROR((SUMIFS($G$8:$G$38,$A$8:$A$38,">="&$AI$18+7*(1-1),$A$8:$A$38,"<="&$AI$18+7*(1-1)+6)+SUMIFS('2026年09月'!$G$8:$G$37,'2026年09月'!$A$8:$A$37,">="&$AI$18+7*(1-1),'2026年09月'!$A$8:$A$37,"<="&$AI$18+7*(1-1)+6))/(SUMIFS($M$8:$M$38,$A$8:$A$38,">="&$AI$18+7*(1-1),$A$8:$A$38,"<="&$AI$18+7*(1-1)+6)+SUMIFS('2026年09月'!$M$8:$M$37,'2026年09月'!$A$8:$A$37,">="&$AI$18+7*(1-1),'2026年09月'!$A$8:$A$37,"<="&$AI$18+7*(1-1)+6)),"")) -> 22507.9 | AF20: =IF($AB20="","",IFERROR((SUMIFS($N$8:$N$38,$A$8:$A$38,">="&$AI$18+7*(1-1),$A$8:$A$38,"<="&$AI$18+7*(1-1)+6)+SUMIFS('2026年09月'!$N$8:$N$37,'2026年09月'!$A$8:$A$37,">="&$AI$18+7*(1-1),'2026年09月'!$A$8:$A$37,"<="&$AI$18+7*(1-1)+6))/(SUMIFS($M$8:$M$38,$A$8:$A$38,">="&$AI$18+7*(1-1),$A$8:$A$38,"<="&$AI$18+7*(1-1)+6)+SUMIFS('2026年09月'!$M$8:$M$37,'2026年09月'!$A$8:$A$37,">="&$AI$18+7*(1-1),'2026年09月'!$A$8:$A$37,"<="&$AI$18+7*(1-1)+6)),"")) -> 1.0857143 | AG20: =IF($AB20="","",IFERROR((SUMIFS($P$8:$P$38,$A$8:$A$38,">="&$AI$18+7*(1-1),$A$8:$A$38,"<="&$AI$18+7*(1-1)+6)+SUMIFS('2026年09月'!$P$8:$P$37,'2026年09月'!$A$8:$A$37,">="&$AI$18+7*(1-1),'2026年09月'!$A$8:$A$37,"<="&$AI$18+7*(1-1)+6))/(SUMIFS($O$8:$O$38,$A$8:$A$38,">="&$AI$18+7*(1-1),$A$8:$A$38,"<="&$AI$18+7*(1-1)+6)+SUMIFS('2026年09月'!$O$8:$O$37,'2026年09月'!$A$8:$A$37,">="&$AI$18+7*(1-1),'2026年09月'!$A$8:$A$37,"<="&$AI$18+7*(1-1)+6)),"")) -> 0.5173913
A21: 46248 | B21: =MID("日月火水木金土",WEEKDAY(A21),1) -> 金 | C21: 1120000 | D21: =SUM($C$8:C21) -> 11260000 | E21: 28270 | F21: 273659 | G21: =IF(COUNT(E21:F21)=0,"",SUM(E21:F21)) -> 301929 | H21: =IF(G21="","",SUM($G$8:G21)) -> 3329057 | I21: =IF(G21="","",IFERROR(G21/C21,"")) -> 0.26957946 | J21: =IF(H21="","",IFERROR(H21/D21,"")) -> 0.29565337 | K21: =IF(H21="","",IF(D21=0,"",H21-D21)) -> -7930943 | L21: =IF(G21="","—",IF(D21=0,"予算未入力",IF(H21>=D21,"◎ ペース内","▲ 遅れ"))) -> ▲ 遅れ | M21: 19 | N21: 19 | O21: 37 | P21: 24 | Q21: 35 | R21: =IFERROR(M21/O21,"") -> 0.51351351 | S21: =IFERROR(G21/M21,"") -> 15891 | T21: =IFERROR(N21/M21,"") -> 1 | U21: =IFERROR(P21/O21,"") -> 0.64864865 | AA21: 2 | AB21: =IF($AI$18+7*(2-1)>$A$38,"",TEXT($AI$18+7*(2-1),"m/d")&"-"&TEXT($AI$18+7*(2-1)+6,"m/d")) -> 8/11-8/17 | AC21: =IF($AB21="","",(SUMIFS($G$8:$G$38,$A$8:$A$38,">="&$AI$18+7*(2-1),$A$8:$A$38,"<="&$AI$18+7*(2-1)+6)+SUMIFS('2026年09月'!$G$8:$G$37,'2026年09月'!$A$8:$A$37,">="&$AI$18+7*(2-1),'2026年09月'!$A$8:$A$37,"<="&$AI$18+7*(2-1)+6))) -> 1936201 | AD21: =IF($AB21="","",IFERROR((SUMIFS($M$8:$M$38,$A$8:$A$38,">="&$AI$18+7*(2-1),$A$8:$A$38,"<="&$AI$18+7*(2-1)+6)+SUMIFS('2026年09月'!$M$8:$M$37,'2026年09月'!$A$8:$A$37,">="&$AI$18+7*(2-1),'2026年09月'!$A$8:$A$37,"<="&$AI$18+7*(2-1)+6))/(SUMIFS($O$8:$O$38,$A$8:$A$38,">="&$AI$18+7*(2-1),$A$8:$A$38,"<="&$AI$18+7*(2-1)+6)+SUMIFS('2026年09月'!$O$8:$O$37,'2026年09月'!$A$8:$A$37,">="&$AI$18+7*(2-1),'2026年09月'!$A$8:$A$37,"<="&$AI$18+7*(2-1)+6)),"")) -> 0.44843049 | AE21: =IF($AB21="","",IFERROR((SUMIFS($G$8:$G$38,$A$8:$A$38,">="&$AI$18+7*(2-1),$A$8:$A$38,"<="&$AI$18+7*(2-1)+6)+SUMIFS('2026年09月'!$G$8:$G$37,'2026年09月'!$A$8:$A$37,">="&$AI$18+7*(2-1),'2026年09月'!$A$8:$A$37,"<="&$AI$18+7*(2-1)+6))/(SUMIFS($M$8:$M$38,$A$8:$A$38,">="&$AI$18+7*(2-1),$A$8:$A$38,"<="&$AI$18+7*(2-1)+6)+SUMIFS('2026年09月'!$M$8:$M$37,'2026年09月'!$A$8:$A$37,">="&$AI$18+7*(2-1),'2026年09月'!$A$8:$A$37,"<="&$AI$18+7*(2-1)+6)),"")) -> 19362.01 | AF21: =IF($AB21="","",IFERROR((SUMIFS($N$8:$N$38,$A$8:$A$38,">="&$AI$18+7*(2-1),$A$8:$A$38,"<="&$AI$18+7*(2-1)+6)+SUMIFS('2026年09月'!$N$8:$N$37,'2026年09月'!$A$8:$A$37,">="&$AI$18+7*(2-1),'2026年09月'!$A$8:$A$37,"<="&$AI$18+7*(2-1)+6))/(SUMIFS($M$8:$M$38,$A$8:$A$38,">="&$AI$18+7*(2-1),$A$8:$A$38,"<="&$AI$18+7*(2-1)+6)+SUMIFS('2026年09月'!$M$8:$M$37,'2026年09月'!$A$8:$A$37,">="&$AI$18+7*(2-1),'2026年09月'!$A$8:$A$37,"<="&$AI$18+7*(2-1)+6)),"")) -> 1.04 | AG21: =IF($AB21="","",IFERROR((SUMIFS($P$8:$P$38,$A$8:$A$38,">="&$AI$18+7*(2-1),$A$8:$A$38,"<="&$AI$18+7*(2-1)+6)+SUMIFS('2026年09月'!$P$8:$P$37,'2026年09月'!$A$8:$A$37,">="&$AI$18+7*(2-1),'2026年09月'!$A$8:$A$37,"<="&$AI$18+7*(2-1)+6))/(SUMIFS($O$8:$O$38,$A$8:$A$38,">="&$AI$18+7*(2-1),$A$8:$A$38,"<="&$AI$18+7*(2-1)+6)+SUMIFS('2026年09月'!$O$8:$O$37,'2026年09月'!$A$8:$A$37,">="&$AI$18+7*(2-1),'2026年09月'!$A$8:$A$37,"<="&$AI$18+7*(2-1)+6)),"")) -> 0.53363229
A22: 46249 | B22: =MID("日月火水木金土",WEEKDAY(A22),1) -> 土 | C22: 1120000 | D22: =SUM($C$8:C22) -> 12380000 | E22: 165190 | F22: 252259 | G22: =IF(COUNT(E22:F22)=0,"",SUM(E22:F22)) -> 417449 | H22: =IF(G22="","",SUM($G$8:G22)) -> 3746506 | I22: =IF(G22="","",IFERROR(G22/C22,"")) -> 0.37272232 | J22: =IF(H22="","",IFERROR(H22/D22,"")) -> 0.30262569 | K22: =IF(H22="","",IF(D22=0,"",H22-D22)) -> -8633494 | L22: =IF(G22="","—",IF(D22=0,"予算未入力",IF(H22>=D22,"◎ ペース内","▲ 遅れ"))) -> ▲ 遅れ | M22: 19 | N22: 19 | O22: 37 | P22: 19 | Q22: 49 | R22: =IFERROR(M22/O22,"") -> 0.51351351 | S22: =IFERROR(G22/M22,"") -> 21971 | T22: =IFERROR(N22/M22,"") -> 1 | U22: =IFERROR(P22/O22,"") -> 0.51351351 | W22: 43805 | AA22: 3 | AB22: =IF($AI$18+7*(3-1)>$A$38,"",TEXT($AI$18+7*(3-1),"m/d")&"-"&TEXT($AI$18+7*(3-1)+6,"m/d")) -> 8/18-8/24 | AC22: =IF($AB22="","",(SUMIFS($G$8:$G$38,$A$8:$A$38,">="&$AI$18+7*(3-1),$A$8:$A$38,"<="&$AI$18+7*(3-1)+6)+SUMIFS('2026年09月'!$G$8:$G$37,'2026年09月'!$A$8:$A$37,">="&$AI$18+7*(3-1),'2026年09月'!$A$8:$A$37,"<="&$AI$18+7*(3-1)+6))) -> 2009000 | AD22: =IF($AB22="","",IFERROR((SUMIFS($M$8:$M$38,$A$8:$A$38,">="&$AI$18+7*(3-1),$A$8:$A$38,"<="&$AI$18+7*(3-1)+6)+SUMIFS('2026年09月'!$M$8:$M$37,'2026年09月'!$A$8:$A$37,">="&$AI$18+7*(3-1),'2026年09月'!$A$8:$A$37,"<="&$AI$18+7*(3-1)+6))/(SUMIFS($O$8:$O$38,$A$8:$A$38,">="&$AI$18+7*(3-1),$A$8:$A$38,"<="&$AI$18+7*(3-1)+6)+SUMIFS('2026年09月'!$O$8:$O$37,'2026年09月'!$A$8:$A$37,">="&$AI$18+7*(3-1),'2026年09月'!$A$8:$A$37,"<="&$AI$18+7*(3-1)+6)),"")) -> 0.47894737 | AE22: =IF($AB22="","",IFERROR((SUMIFS($G$8:$G$38,$A$8:$A$38,">="&$AI$18+7*(3-1),$A$8:$A$38,"<="&$AI$18+7*(3-1)+6)+SUMIFS('2026年09月'!$G$8:$G$37,'2026年09月'!$A$8:$A$37,">="&$AI$18+7*(3-1),'2026年09月'!$A$8:$A$37,"<="&$AI$18+7*(3-1)+6))/(SUMIFS($M$8:$M$38,$A$8:$A$38,">="&$AI$18+7*(3-1),$A$8:$A$38,"<="&$AI$18+7*(3-1)+6)+SUMIFS('2026年09月'!$M$8:$M$37,'2026年09月'!$A$8:$A$37,">="&$AI$18+7*(3-1),'2026年09月'!$A$8:$A$37,"<="&$AI$18+7*(3-1)+6)),"")) -> 22076.923 | AF22: =IF($AB22="","",IFERROR((SUMIFS($N$8:$N$38,$A$8:$A$38,">="&$AI$18+7*(3-1),$A$8:$A$38,"<="&$AI$18+7*(3-1)+6)+SUMIFS('2026年09月'!$N$8:$N$37,'2026年09月'!$A$8:$A$37,">="&$AI$18+7*(3-1),'2026年09月'!$A$8:$A$37,"<="&$AI$18+7*(3-1)+6))/(SUMIFS($M$8:$M$38,$A$8:$A$38,">="&$AI$18+7*(3-1),$A$8:$A$38,"<="&$AI$18+7*(3-1)+6)+SUMIFS('2026年09月'!$M$8:$M$37,'2026年09月'!$A$8:$A$37,">="&$AI$18+7*(3-1),'2026年09月'!$A$8:$A$37,"<="&$AI$18+7*(3-1)+6)),"")) -> 1.0879121 | AG22: =IF($AB22="","",IFERROR((SUMIFS($P$8:$P$38,$A$8:$A$38,">="&$AI$18+7*(3-1),$A$8:$A$38,"<="&$AI$18+7*(3-1)+6)+SUMIFS('2026年09月'!$P$8:$P$37,'2026年09月'!$A$8:$A$37,">="&$AI$18+7*(3-1),'2026年09月'!$A$8:$A$37,"<="&$AI$18+7*(3-1)+6))/(SUMIFS($O$8:$O$38,$A$8:$A$38,">="&$AI$18+7*(3-1),$A$8:$A$38,"<="&$AI$18+7*(3-1)+6)+SUMIFS('2026年09月'!$O$8:$O$37,'2026年09月'!$A$8:$A$37,">="&$AI$18+7*(3-1),'2026年09月'!$A$8:$A$37,"<="&$AI$18+7*(3-1)+6)),"")) -> 0.6
A23: 46250 | B23: =MID("日月火水木金土",WEEKDAY(A23),1) -> 日 | C23: 1120000 | D23: =SUM($C$8:C23) -> 13500000 | E23: 134682 | F23: 234071 | G23: =IF(COUNT(E23:F23)=0,"",SUM(E23:F23)) -> 368753 | H23: =IF(G23="","",SUM($G$8:G23)) -> 4115259 | I23: =IF(G23="","",IFERROR(G23/C23,"")) -> 0.32924375 | J23: =IF(H23="","",IFERROR(H23/D23,"")) -> 0.304834 | K23: =IF(H23="","",IF(D23=0,"",H23-D23)) -> -9384741 | L23: =IF(G23="","—",IF(D23=0,"予算未入力",IF(H23>=D23,"◎ ペース内","▲ 遅れ"))) -> ▲ 遅れ | M23: 18 | N23: 19 | O23: 35 | P23: 23 | Q23: 49 | R23: =IFERROR(M23/O23,"") -> 0.51428571 | S23: =IFERROR(G23/M23,"") -> 20486.278 | T23: =IFERROR(N23/M23,"") -> 1.0555556 | U23: =IFERROR(P23/O23,"") -> 0.65714286 | W23: 43785 | AA23: 4 | AB23: =IF($AI$18+7*(4-1)>$A$38,"",TEXT($AI$18+7*(4-1),"m/d")&"-"&TEXT($AI$18+7*(4-1)+6,"m/d")) -> 8/25-8/31 | AC23: =IF($AB23="","",(SUMIFS($G$8:$G$38,$A$8:$A$38,">="&$AI$18+7*(4-1),$A$8:$A$38,"<="&$AI$18+7*(4-1)+6)+SUMIFS('2026年09月'!$G$8:$G$37,'2026年09月'!$A$8:$A$37,">="&$AI$18+7*(4-1),'2026年09月'!$A$8:$A$37,"<="&$AI$18+7*(4-1)+6))) -> 2237404 | AD23: =IF($AB23="","",IFERROR((SUMIFS($M$8:$M$38,$A$8:$A$38,">="&$AI$18+7*(4-1),$A$8:$A$38,"<="&$AI$18+7*(4-1)+6)+SUMIFS('2026年09月'!$M$8:$M$37,'2026年09月'!$A$8:$A$37,">="&$AI$18+7*(4-1),'2026年09月'!$A$8:$A$37,"<="&$AI$18+7*(4-1)+6))/(SUMIFS($O$8:$O$38,$A$8:$A$38,">="&$AI$18+7*(4-1),$A$8:$A$38,"<="&$AI$18+7*(4-1)+6)+SUMIFS('2026年09月'!$O$8:$O$37,'2026年09月'!$A$8:$A$37,">="&$AI$18+7*(4-1),'2026年09月'!$A$8:$A$37,"<="&$AI$18+7*(4-1)+6)),"")) -> 0.4212963 | AE23: =IF($AB23="","",IFERROR((SUMIFS($G$8:$G$38,$A$8:$A$38,">="&$AI$18+7*(4-1),$A$8:$A$38,"<="&$AI$18+7*(4-1)+6)+SUMIFS('2026年09月'!$G$8:$G$37,'2026年09月'!$A$8:$A$37,">="&$AI$18+7*(4-1),'2026年09月'!$A$8:$A$37,"<="&$AI$18+7*(4-1)+6))/(SUMIFS($M$8:$M$38,$A$8:$A$38,">="&$AI$18+7*(4-1),$A$8:$A$38,"<="&$AI$18+7*(4-1)+6)+SUMIFS('2026年09月'!$M$8:$M$37,'2026年09月'!$A$8:$A$37,">="&$AI$18+7*(4-1),'2026年09月'!$A$8:$A$37,"<="&$AI$18+7*(4-1)+6)),"")) -> 24586.857 | AF23: =IF($AB23="","",IFERROR((SUMIFS($N$8:$N$38,$A$8:$A$38,">="&$AI$18+7*(4-1),$A$8:$A$38,"<="&$AI$18+7*(4-1)+6)+SUMIFS('2026年09月'!$N$8:$N$37,'2026年09月'!$A$8:$A$37,">="&$AI$18+7*(4-1),'2026年09月'!$A$8:$A$37,"<="&$AI$18+7*(4-1)+6))/(SUMIFS($M$8:$M$38,$A$8:$A$38,">="&$AI$18+7*(4-1),$A$8:$A$38,"<="&$AI$18+7*(4-1)+6)+SUMIFS('2026年09月'!$M$8:$M$37,'2026年09月'!$A$8:$A$37,">="&$AI$18+7*(4-1),'2026年09月'!$A$8:$A$37,"<="&$AI$18+7*(4-1)+6)),"")) -> 1.2527473 | AG23: =IF($AB23="","",IFERROR((SUMIFS($P$8:$P$38,$A$8:$A$38,">="&$AI$18+7*(4-1),$A$8:$A$38,"<="&$AI$18+7*(4-1)+6)+SUMIFS('2026年09月'!$P$8:$P$37,'2026年09月'!$A$8:$A$37,">="&$AI$18+7*(4-1),'2026年09月'!$A$8:$A$37,"<="&$AI$18+7*(4-1)+6))/(SUMIFS($O$8:$O$38,$A$8:$A$38,">="&$AI$18+7*(4-1),$A$8:$A$38,"<="&$AI$18+7*(4-1)+6)+SUMIFS('2026年09月'!$O$8:$O$37,'2026年09月'!$A$8:$A$37,">="&$AI$18+7*(4-1),'2026年09月'!$A$8:$A$37,"<="&$AI$18+7*(4-1)+6)),"")) -> 0.57407407
A24: 46251 | B24: =MID("日月火水木金土",WEEKDAY(A24),1) -> 月 | C24: 680000 | D24: =SUM($C$8:C24) -> 14180000 | E24: 24310 | F24: 124904 | G24: =IF(COUNT(E24:F24)=0,"",SUM(E24:F24)) -> 149214 | H24: =IF(G24="","",SUM($G$8:G24)) -> 4264473 | I24: =IF(G24="","",IFERROR(G24/C24,"")) -> 0.21943235 | J24: =IF(H24="","",IFERROR(H24/D24,"")) -> 0.30073858 | K24: =IF(H24="","",IF(D24=0,"",H24-D24)) -> -9915527 | L24: =IF(G24="","—",IF(D24=0,"予算未入力",IF(H24>=D24,"◎ ペース内","▲ 遅れ"))) -> ▲ 遅れ | M24: 8 | N24: 8 | O24: 29 | P24: 10 | Q24: 13 | R24: =IFERROR(M24/O24,"") -> 0.27586207 | S24: =IFERROR(G24/M24,"") -> 18651.75 | T24: =IFERROR(N24/M24,"") -> 1 | U24: =IFERROR(P24/O24,"") -> 0.34482759 | AA24: 5 | AB24: =IF($AI$18+7*(5-1)>$A$38,"",TEXT($AI$18+7*(5-1),"m/d")&"-"&TEXT($AI$18+7*(5-1)+6,"m/d")) | AC24: =IF($AB24="","",(SUMIFS($G$8:$G$38,$A$8:$A$38,">="&$AI$18+7*(5-1),$A$8:$A$38,"<="&$AI$18+7*(5-1)+6)+SUMIFS('2026年09月'!$G$8:$G$37,'2026年09月'!$A$8:$A$37,">="&$AI$18+7*(5-1),'2026年09月'!$A$8:$A$37,"<="&$AI$18+7*(5-1)+6))) | AD24: =IF($AB24="","",IFERROR((SUMIFS($M$8:$M$38,$A$8:$A$38,">="&$AI$18+7*(5-1),$A$8:$A$38,"<="&$AI$18+7*(5-1)+6)+SUMIFS('2026年09月'!$M$8:$M$37,'2026年09月'!$A$8:$A$37,">="&$AI$18+7*(5-1),'2026年09月'!$A$8:$A$37,"<="&$AI$18+7*(5-1)+6))/(SUMIFS($O$8:$O$38,$A$8:$A$38,">="&$AI$18+7*(5-1),$A$8:$A$38,"<="&$AI$18+7*(5-1)+6)+SUMIFS('2026年09月'!$O$8:$O$37,'2026年09月'!$A$8:$A$37,">="&$AI$18+7*(5-1),'2026年09月'!$A$8:$A$37,"<="&$AI$18+7*(5-1)+6)),"")) | AE24: =IF($AB24="","",IFERROR((SUMIFS($G$8:$G$38,$A$8:$A$38,">="&$AI$18+7*(5-1),$A$8:$A$38,"<="&$AI$18+7*(5-1)+6)+SUMIFS('2026年09月'!$G$8:$G$37,'2026年09月'!$A$8:$A$37,">="&$AI$18+7*(5-1),'2026年09月'!$A$8:$A$37,"<="&$AI$18+7*(5-1)+6))/(SUMIFS($M$8:$M$38,$A$8:$A$38,">="&$AI$18+7*(5-1),$A$8:$A$38,"<="&$AI$18+7*(5-1)+6)+SUMIFS('2026年09月'!$M$8:$M$37,'2026年09月'!$A$8:$A$37,">="&$AI$18+7*(5-1),'2026年09月'!$A$8:$A$37,"<="&$AI$18+7*(5-1)+6)),"")) | AF24: =IF($AB24="","",IFERROR((SUMIFS($N$8:$N$38,$A$8:$A$38,">="&$AI$18+7*(5-1),$A$8:$A$38,"<="&$AI$18+7*(5-1)+6)+SUMIFS('2026年09月'!$N$8:$N$37,'2026年09月'!$A$8:$A$37,">="&$AI$18+7*(5-1),'2026年09月'!$A$8:$A$37,"<="&$AI$18+7*(5-1)+6))/(SUMIFS($M$8:$M$38,$A$8:$A$38,">="&$AI$18+7*(5-1),$A$8:$A$38,"<="&$AI$18+7*(5-1)+6)+SUMIFS('2026年09月'!$M$8:$M$37,'2026年09月'!$A$8:$A$37,">="&$AI$18+7*(5-1),'2026年09月'!$A$8:$A$37,"<="&$AI$18+7*(5-1)+6)),"")) | AG24: =IF($AB24="","",IFERROR((SUMIFS($P$8:$P$38,$A$8:$A$38,">="&$AI$18+7*(5-1),$A$8:$A$38,"<="&$AI$18+7*(5-1)+6)+SUMIFS('2026年09月'!$P$8:$P$37,'2026年09月'!$A$8:$A$37,">="&$AI$18+7*(5-1),'2026年09月'!$A$8:$A$37,"<="&$AI$18+7*(5-1)+6))/(SUMIFS($O$8:$O$38,$A$8:$A$38,">="&$AI$18+7*(5-1),$A$8:$A$38,"<="&$AI$18+7*(5-1)+6)+SUMIFS('2026年09月'!$O$8:$O$37,'2026年09月'!$A$8:$A$37,">="&$AI$18+7*(5-1),'2026年09月'!$A$8:$A$37,"<="&$AI$18+7*(5-1)+6)),""))
A25: 46252 | B25: =MID("日月火水木金土",WEEKDAY(A25),1) -> 火 | C25: 680000 | D25: =SUM($C$8:C25) -> 14860000 | E25: 3570 | F25: 159541 | G25: =IF(COUNT(E25:F25)=0,"",SUM(E25:F25)) -> 163111 | H25: =IF(G25="","",SUM($G$8:G25)) -> 4427584 | I25: =IF(G25="","",IFERROR(G25/C25,"")) -> 0.23986912 | J25: =IF(H25="","",IFERROR(H25/D25,"")) -> 0.29795316 | K25: =IF(H25="","",IF(D25=0,"",H25-D25)) -> -10432416 | L25: =IF(G25="","—",IF(D25=0,"予算未入力",IF(H25>=D25,"◎ ペース内","▲ 遅れ"))) -> ▲ 遅れ | M25: 9 | N25: 10 | O25: 15 | P25: 8 | Q25: 15 | R25: =IFERROR(M25/O25,"") -> 0.6 | S25: =IFERROR(G25/M25,"") -> 18123.444 | T25: =IFERROR(N25/M25,"") -> 1.1111111 | U25: =IFERROR(P25/O25,"") -> 0.53333333 | W25: 43764 | AA25: 6 | AB25: =IF($AI$18+7*(6-1)>$A$38,"",TEXT($AI$18+7*(6-1),"m/d")&"-"&TEXT($AI$18+7*(6-1)+6,"m/d")) | AC25: =IF($AB25="","",(SUMIFS($G$8:$G$38,$A$8:$A$38,">="&$AI$18+7*(6-1),$A$8:$A$38,"<="&$AI$18+7*(6-1)+6)+SUMIFS('2026年09月'!$G$8:$G$37,'2026年09月'!$A$8:$A$37,">="&$AI$18+7*(6-1),'2026年09月'!$A$8:$A$37,"<="&$AI$18+7*(6-1)+6))) | AD25: =IF($AB25="","",IFERROR((SUMIFS($M$8:$M$38,$A$8:$A$38,">="&$AI$18+7*(6-1),$A$8:$A$38,"<="&$AI$18+7*(6-1)+6)+SUMIFS('2026年09月'!$M$8:$M$37,'2026年09月'!$A$8:$A$37,">="&$AI$18+7*(6-1),'2026年09月'!$A$8:$A$37,"<="&$AI$18+7*(6-1)+6))/(SUMIFS($O$8:$O$38,$A$8:$A$38,">="&$AI$18+7*(6-1),$A$8:$A$38,"<="&$AI$18+7*(6-1)+6)+SUMIFS('2026年09月'!$O$8:$O$37,'2026年09月'!$A$8:$A$37,">="&$AI$18+7*(6-1),'2026年09月'!$A$8:$A$37,"<="&$AI$18+7*(6-1)+6)),"")) | AE25: =IF($AB25="","",IFERROR((SUMIFS($G$8:$G$38,$A$8:$A$38,">="&$AI$18+7*(6-1),$A$8:$A$38,"<="&$AI$18+7*(6-1)+6)+SUMIFS('2026年09月'!$G$8:$G$37,'2026年09月'!$A$8:$A$37,">="&$AI$18+7*(6-1),'2026年09月'!$A$8:$A$37,"<="&$AI$18+7*(6-1)+6))/(SUMIFS($M$8:$M$38,$A$8:$A$38,">="&$AI$18+7*(6-1),$A$8:$A$38,"<="&$AI$18+7*(6-1)+6)+SUMIFS('2026年09月'!$M$8:$M$37,'2026年09月'!$A$8:$A$37,">="&$AI$18+7*(6-1),'2026年09月'!$A$8:$A$37,"<="&$AI$18+7*(6-1)+6)),"")) | AF25: =IF($AB25="","",IFERROR((SUMIFS($N$8:$N$38,$A$8:$A$38,">="&$AI$18+7*(6-1),$A$8:$A$38,"<="&$AI$18+7*(6-1)+6)+SUMIFS('2026年09月'!$N$8:$N$37,'2026年09月'!$A$8:$A$37,">="&$AI$18+7*(6-1),'2026年09月'!$A$8:$A$37,"<="&$AI$18+7*(6-1)+6))/(SUMIFS($M$8:$M$38,$A$8:$A$38,">="&$AI$18+7*(6-1),$A$8:$A$38,"<="&$AI$18+7*(6-1)+6)+SUMIFS('2026年09月'!$M$8:$M$37,'2026年09月'!$A$8:$A$37,">="&$AI$18+7*(6-1),'2026年09月'!$A$8:$A$37,"<="&$AI$18+7*(6-1)+6)),"")) | AG25: =IF($AB25="","",IFERROR((SUMIFS($P$8:$P$38,$A$8:$A$38,">="&$AI$18+7*(6-1),$A$8:$A$38,"<="&$AI$18+7*(6-1)+6)+SUMIFS('2026年09月'!$P$8:$P$37,'2026年09月'!$A$8:$A$37,">="&$AI$18+7*(6-1),'2026年09月'!$A$8:$A$37,"<="&$AI$18+7*(6-1)+6))/(SUMIFS($O$8:$O$38,$A$8:$A$38,">="&$AI$18+7*(6-1),$A$8:$A$38,"<="&$AI$18+7*(6-1)+6)+SUMIFS('2026年09月'!$O$8:$O$37,'2026年09月'!$A$8:$A$37,">="&$AI$18+7*(6-1),'2026年09月'!$A$8:$A$37,"<="&$AI$18+7*(6-1)+6)),""))
A26: 46253 | B26: =MID("日月火水木金土",WEEKDAY(A26),1) -> 水 | C26: 680000 | D26: =SUM($C$8:C26) -> 15540000 | E26: 142246 | F26: 173512 | G26: =IF(COUNT(E26:F26)=0,"",SUM(E26:F26)) -> 315758 | H26: =IF(G26="","",SUM($G$8:G26)) -> 4743342 | I26: =IF(G26="","",IFERROR(G26/C26,"")) -> 0.46435 | J26: =IF(H26="","",IFERROR(H26/D26,"")) -> 0.30523436 | K26: =IF(H26="","",IF(D26=0,"",H26-D26)) -> -10796658 | L26: =IF(G26="","—",IF(D26=0,"予算未入力",IF(H26>=D26,"◎ ペース内","▲ 遅れ"))) -> ▲ 遅れ | M26: 15 | N26: 16 | O26: 31 | P26: 24 | Q26: 31 | R26: =IFERROR(M26/O26,"") -> 0.48387097 | S26: =IFERROR(G26/M26,"") -> 21050.533 | T26: =IFERROR(N26/M26,"") -> 1.0666667 | U26: =IFERROR(P26/O26,"") -> 0.77419355 | W26: 43764 | AA26: ※期間ラベルは第1火曜から自動生成。決定率・客単価・セット率・試着率は「週合計÷週合計」
A27: 46254 | B27: =MID("日月火水木金土",WEEKDAY(A27),1) -> 木 | C27: 680000 | D27: =SUM($C$8:C27) -> 16220000 | E27: 113773 | F27: 331755 | G27: =IF(COUNT(E27:F27)=0,"",SUM(E27:F27)) -> 445528 | H27: =IF(G27="","",SUM($G$8:G27)) -> 5188870 | I27: =IF(G27="","",IFERROR(G27/C27,"")) -> 0.65518824 | J27: =IF(H27="","",IFERROR(H27/D27,"")) -> 0.31990567 | K27: =IF(H27="","",IF(D27=0,"",H27-D27)) -> -11031130 | L27: =IF(G27="","—",IF(D27=0,"予算未入力",IF(H27>=D27,"◎ ペース内","▲ 遅れ"))) -> ▲ 遅れ | M27: 16 | N27: 19 | O27: 33 | P27: 17 | Q27: 31 | R27: =IFERROR(M27/O27,"") -> 0.48484848 | S27: =IFERROR(G27/M27,"") -> 27845.5 | T27: =IFERROR(N27/M27,"") -> 1.1875 | U27: =IFERROR(P27/O27,"") -> 0.51515152 | AA27: ※最終週は翌月にまたぐため、2026年09月シートの実績も自動で合算します
A28: 46255 | B28: =MID("日月火水木金土",WEEKDAY(A28),1) -> 金 | C28: 680000 | D28: =SUM($C$8:C28) -> 16900000 | E28: 87995 | F28: 214961 | G28: =IF(COUNT(E28:F28)=0,"",SUM(E28:F28)) -> 302956 | H28: =IF(G28="","",SUM($G$8:G28)) -> 5491826 | I28: =IF(G28="","",IFERROR(G28/C28,"")) -> 0.44552353 | J28: =IF(H28="","",IFERROR(H28/D28,"")) -> 0.32496012 | K28: =IF(H28="","",IF(D28=0,"",H28-D28)) -> -11408174 | L28: =IF(G28="","—",IF(D28=0,"予算未入力",IF(H28>=D28,"◎ ペース内","▲ 遅れ"))) -> ▲ 遅れ | M28: 17 | N28: 17 | O28: 28 | P28: 17 | Q28: 24 | R28: =IFERROR(M28/O28,"") -> 0.60714286 | S28: =IFERROR(G28/M28,"") -> 17820.941 | T28: =IFERROR(N28/M28,"") -> 1 | U28: =IFERROR(P28/O28,"") -> 0.60714286 | W28: 43744 | AA28: ※月初の月曜まで（例：6/1）は前月シートの最終週に含まれます
A29: 46256 | B29: =MID("日月火水木金土",WEEKDAY(A29),1) -> 土 | C29: 920000 | D29: =SUM($C$8:C29) -> 17820000 | E29: 47620 | F29: 176584 | G29: =IF(COUNT(E29:F29)=0,"",SUM(E29:F29)) -> 224204 | H29: =IF(G29="","",SUM($G$8:G29)) -> 5716030 | I29: =IF(G29="","",IFERROR(G29/C29,"")) -> 0.2437 | J29: =IF(H29="","",IFERROR(H29/D29,"")) -> 0.32076487 | K29: =IF(H29="","",IF(D29=0,"",H29-D29)) -> -12103970 | L29: =IF(G29="","—",IF(D29=0,"予算未入力",IF(H29>=D29,"◎ ペース内","▲ 遅れ"))) -> ▲ 遅れ | M29: 11 | N29: 12 | O29: 23 | P29: 16 | Q29: 24 | R29: =IFERROR(M29/O29,"") -> 0.47826087 | S29: =IFERROR(G29/M29,"") -> 20382.182 | T29: =IFERROR(N29/M29,"") -> 1.0909091 | U29: =IFERROR(P29/O29,"") -> 0.69565217 | W29: 43742
A30: 46257 | B30: =MID("日月火水木金土",WEEKDAY(A30),1) -> 日 | C30: 920000 | D30: =SUM($C$8:C30) -> 18740000 | E30: 101380 | F30: 241728 | G30: =IF(COUNT(E30:F30)=0,"",SUM(E30:F30)) -> 343108 | H30: =IF(G30="","",SUM($G$8:G30)) -> 6059138 | I30: =IF(G30="","",IFERROR(G30/C30,"")) -> 0.37294348 | J30: =IF(H30="","",IFERROR(H30/D30,"")) -> 0.32332647 | K30: =IF(H30="","",IF(D30=0,"",H30-D30)) -> -12680862 | L30: =IF(G30="","—",IF(D30=0,"予算未入力",IF(H30>=D30,"◎ ペース内","▲ 遅れ"))) -> ▲ 遅れ | M30: 15 | N30: 15 | O30: 37 | P30: 18 | Q30: 25 | R30: =IFERROR(M30/O30,"") -> 0.40540541 | S30: =IFERROR(G30/M30,"") -> 22873.867 | T30: =IFERROR(N30/M30,"") -> 1 | U30: =IFERROR(P30/O30,"") -> 0.48648649 | W30: 43735
A31: 46258 | B31: =MID("日月火水木金土",WEEKDAY(A31),1) -> 月 | C31: 680000 | D31: =SUM($C$8:C31) -> 19420000 | E31: 120050 | F31: 94285 | G31: =IF(COUNT(E31:F31)=0,"",SUM(E31:F31)) -> 214335 | H31: =IF(G31="","",SUM($G$8:G31)) -> 6273473 | I31: =IF(G31="","",IFERROR(G31/C31,"")) -> 0.31519853 | J31: =IF(H31="","",IFERROR(H31/D31,"")) -> 0.32304186 | K31: =IF(H31="","",IF(D31=0,"",H31-D31)) -> -13146527 | L31: =IF(G31="","—",IF(D31=0,"予算未入力",IF(H31>=D31,"◎ ペース内","▲ 遅れ"))) -> ▲ 遅れ | M31: 8 | N31: 10 | O31: 23 | P31: 14 | Q31: 23 | R31: =IFERROR(M31/O31,"") -> 0.34782609 | S31: =IFERROR(G31/M31,"") -> 26791.875 | T31: =IFERROR(N31/M31,"") -> 1.25 | U31: =IFERROR(P31/O31,"") -> 0.60869565 | W31: 43715
A32: 46259 | B32: =MID("日月火水木金土",WEEKDAY(A32),1) -> 火 | C32: 680000 | D32: =SUM($C$8:C32) -> 20100000 | E32: 67700 | F32: 274844 | G32: =IF(COUNT(E32:F32)=0,"",SUM(E32:F32)) -> 342544 | H32: =IF(G32="","",SUM($G$8:G32)) -> 6616017 | I32: =IF(G32="","",IFERROR(G32/C32,"")) -> 0.50374118 | J32: =IF(H32="","",IFERROR(H32/D32,"")) -> 0.32915507 | K32: =IF(H32="","",IF(D32=0,"",H32-D32)) -> -13483983 | L32: =IF(G32="","—",IF(D32=0,"予算未入力",IF(H32>=D32,"◎ ペース内","▲ 遅れ"))) -> ▲ 遅れ | M32: 13 | N32: 14 | O32: 22 | P32: 19 | Q32: 43 | R32: =IFERROR(M32/O32,"") -> 0.59090909 | S32: =IFERROR(G32/M32,"") -> 26349.538 | T32: =IFERROR(N32/M32,"") -> 1.0769231 | U32: =IFERROR(P32/O32,"") -> 0.86363636 | W32: 43702
A33: 46260 | B33: =MID("日月火水木金土",WEEKDAY(A33),1) -> 水 | C33: 680000 | D33: =SUM($C$8:C33) -> 20780000 | E33: 242210 | F33: 253087 | G33: =IF(COUNT(E33:F33)=0,"",SUM(E33:F33)) -> 495297 | H33: =IF(G33="","",SUM($G$8:G33)) -> 7111314 | I33: =IF(G33="","",IFERROR(G33/C33,"")) -> 0.72837794 | J33: =IF(H33="","",IFERROR(H33/D33,"")) -> 0.34221915 | K33: =IF(H33="","",IF(D33=0,"",H33-D33)) -> -13668686 | L33: =IF(G33="","—",IF(D33=0,"予算未入力",IF(H33>=D33,"◎ ペース内","▲ 遅れ"))) -> ▲ 遅れ | M33: 15 | N33: 29 | O33: 43 | P33: 22 | Q33: 33 | R33: =IFERROR(M33/O33,"") -> 0.34883721 | S33: =IFERROR(G33/M33,"") -> 33019.8 | T33: =IFERROR(N33/M33,"") -> 1.9333333 | U33: =IFERROR(P33/O33,"") -> 0.51162791 | W33: 43692
A34: 46261 | B34: =MID("日月火水木金土",WEEKDAY(A34),1) -> 木 | C34: 680000 | D34: =SUM($C$8:C34) -> 21460000 | E34: 87276 | F34: 141853 | G34: =IF(COUNT(E34:F34)=0,"",SUM(E34:F34)) -> 229129 | H34: =IF(G34="","",SUM($G$8:G34)) -> 7340443 | I34: =IF(G34="","",IFERROR(G34/C34,"")) -> 0.33695441 | J34: =IF(H34="","",IFERROR(H34/D34,"")) -> 0.34205233 | K34: =IF(H34="","",IF(D34=0,"",H34-D34)) -> -14119557 | L34: =IF(G34="","—",IF(D34=0,"予算未入力",IF(H34>=D34,"◎ ペース内","▲ 遅れ"))) -> ▲ 遅れ | M34: 8 | N34: 12 | O34: 27 | P34: 15 | Q34: 28 | R34: =IFERROR(M34/O34,"") -> 0.2962963 | S34: =IFERROR(G34/M34,"") -> 28641.125 | T34: =IFERROR(N34/M34,"") -> 1.5 | U34: =IFERROR(P34/O34,"") -> 0.55555556 | W34: 43690
A35: 46262 | B35: =MID("日月火水木金土",WEEKDAY(A35),1) -> 金 | C35: 680000 | D35: =SUM($C$8:C35) -> 22140000 | E35: 87770 | F35: 222852 | G35: =IF(COUNT(E35:F35)=0,"",SUM(E35:F35)) -> 310622 | H35: =IF(G35="","",SUM($G$8:G35)) -> 7651065 | I35: =IF(G35="","",IFERROR(G35/C35,"")) -> 0.45679706 | J35: =IF(H35="","",IFERROR(H35/D35,"")) -> 0.34557656 | K35: =IF(H35="","",IF(D35=0,"",H35-D35)) -> -14488935 | L35: =IF(G35="","—",IF(D35=0,"予算未入力",IF(H35>=D35,"◎ ペース内","▲ 遅れ"))) -> ▲ 遅れ | M35: 14 | N35: 15 | O35: 36 | P35: 17 | Q35: 22 | R35: =IFERROR(M35/O35,"") -> 0.38888889 | S35: =IFERROR(G35/M35,"") -> 22187.286 | T35: =IFERROR(N35/M35,"") -> 1.0714286 | U35: =IFERROR(P35/O35,"") -> 0.47222222 | W35: 43674
A36: 46263 | B36: =MID("日月火水木金土",WEEKDAY(A36),1) -> 土 | C36: 920000 | D36: =SUM($C$8:C36) -> 23060000 | E36: 45590 | F36: 382542 | G36: =IF(COUNT(E36:F36)=0,"",SUM(E36:F36)) -> 428132 | H36: =IF(G36="","",SUM($G$8:G36)) -> 8079197 | I36: =IF(G36="","",IFERROR(G36/C36,"")) -> 0.46536087 | J36: =IF(H36="","",IFERROR(H36/D36,"")) -> 0.35035546 | K36: =IF(H36="","",IF(D36=0,"",H36-D36)) -> -14980803 | L36: =IF(G36="","—",IF(D36=0,"予算未入力",IF(H36>=D36,"◎ ペース内","▲ 遅れ"))) -> ▲ 遅れ | M36: 21 | N36: 22 | O36: 31 | P36: 20 | Q36: 30 | R36: =IFERROR(M36/O36,"") -> 0.67741935 | S36: =IFERROR(G36/M36,"") -> 20387.238 | T36: =IFERROR(N36/M36,"") -> 1.047619 | U36: =IFERROR(P36/O36,"") -> 0.64516129 | W36: 43662
A37: 46264 | B37: =MID("日月火水木金土",WEEKDAY(A37),1) -> 日 | C37: 920000 | D37: =SUM($C$8:C37) -> 23980000 | E37: 93589 | F37: 260204 | G37: =IF(COUNT(E37:F37)=0,"",SUM(E37:F37)) -> 353793 | H37: =IF(G37="","",SUM($G$8:G37)) -> 8432990 | I37: =IF(G37="","",IFERROR(G37/C37,"")) -> 0.38455761 | J37: =IF(H37="","",IFERROR(H37/D37,"")) -> 0.35166764 | K37: =IF(H37="","",IF(D37=0,"",H37-D37)) -> -15547010 | L37: =IF(G37="","—",IF(D37=0,"予算未入力",IF(H37>=D37,"◎ ペース内","▲ 遅れ"))) -> ▲ 遅れ | M37: 16 | N37: 18 | O37: 33 | P37: 23 | Q37: 43 | R37: =IFERROR(M37/O37,"") -> 0.48484848 | S37: =IFERROR(G37/M37,"") -> 22112.062 | T37: =IFERROR(N37/M37,"") -> 1.125 | U37: =IFERROR(P37/O37,"") -> 0.6969697 | W37: 43651
