Workbook

Sheet ダッシュボード
A1: OLD ORDER 名古屋店 売上管理ダッシュボード 2026年4月〜2027年3月
A2: 各月シートの入力欄を埋めると、ここに自動集計されます。単位：円
A4: 年間予算 | C4: 当期実績(YTD) | E4: 年間予算進捗 | G4: 経過月 達成率 | I4: 残り必要額
A5: =IF('設定'!$B$5=0,SUM(B8:B19),'設定'!$B$5) -> 142952527 | C5: =SUM(C8:C19) -> 34259237 | E5: =IFERROR(C5/A5,0) -> 0.23965464 | G5: =IFERROR(SUMIFS($C$8:$C$19,$C$8:$C$19,">0",$B$8:$B$19,">0")/SUMIFS($B$8:$B$19,$C$8:$C$19,">0",$B$8:$B$19,">0"),0) -> 0.43392198 | I5: =A5-C5 -> 108693290
A7: 月 | B7: 月間予算 | C7: 当月実績 | D7: 達成率 | E7: 予実差 | F7: 前年実績 | G7: 前年比 | H7: 購入人数 | I7: 来客数 | J7: 決定率 | K7: 客単価 | L7: 累計予算 | M7: 累計実績 | N7: 累計達成率
A8: 2026年4月 | B8: ='2026年04月'!$A$4 -> 6927491 | C8: ='2026年04月'!$C$4 -> 6331814 | D8: =IF(C8=0,"",IFERROR(C8/B8,"")) -> 0.91401259 | E8: =C8-B8 -> -595677 | F8: =IF('設定'!C8="","",'設定'!C8) | G8: =IF(OR(F8="",C8=0),"",IFERROR(C8/F8,"")) | H8: ='2026年04月'!$N$38 -> 306 | I8: ='2026年04月'!$P$38 -> 938 | J8: =IFERROR(H8/I8,0) -> 0.32622601 | K8: =IFERROR(C8/H8,0) -> 20692.203 | L8: =IF(C8=0,"",SUM($B$8:B8)) -> 6927491 | M8: =IF(C8=0,"",SUM($C$8:C8)) -> 6331814 | N8: =IF(M8="","",IFERROR(M8/L8,0)) -> 0.91401259
A9: 2026年5月 | B9: ='2026年05月'!$A$4 -> 6625036 | C9: ='2026年05月'!$C$4 -> 6030095 | D9: =IF(C9=0,"",IFERROR(C9/B9,"")) -> 0.91019807 | E9: =C9-B9 -> -594941 | F9: =IF('設定'!C9="","",'設定'!C9) | G9: =IF(OR(F9="",C9=0),"",IFERROR(C9/F9,"")) | H9: ='2026年05月'!$N$39 -> 285 | I9: ='2026年05月'!$P$39 -> 1055 | J9: =IFERROR(H9/I9,0) -> 0.27014218 | K9: =IFERROR(C9/H9,0) -> 21158.228 | L9: =IF(C9=0,"",SUM($B$8:B9)) -> 13552527 | M9: =IF(C9=0,"",SUM($C$8:C9)) -> 12361909 | N9: =IF(M9="","",IFERROR(M9/L9,0)) -> 0.9121479
A10: 2026年6月 | B10: ='2026年06月'!$A$4 -> 9000000 | C10: ='2026年06月'!$C$4 -> 5200406 | D10: =IF(C10=0,"",IFERROR(C10/B10,"")) -> 0.57782289 | E10: =C10-B10 -> -3799594 | F10: =IF('設定'!C10="","",'設定'!C10) | G10: =IF(OR(F10="",C10=0),"",IFERROR(C10/F10,"")) | H10: ='2026年06月'!$N$38 -> 240 | I10: ='2026年06月'!$P$38 -> 834 | J10: =IFERROR(H10/I10,0) -> 0.28776978 | K10: =IFERROR(C10/H10,0) -> 21668.358 | L10: =IF(C10=0,"",SUM($B$8:B10)) -> 22552527 | M10: =IF(C10=0,"",SUM($C$8:C10)) -> 17562315 | N10: =IF(M10="","",IFERROR(M10/L10,0)) -> 0.77872936
A11: 2026年7月 | B11: ='2026年07月'!$A$4 -> 14000000 | C11: ='2026年07月'!$C$4 -> 5575024 | D11: =IF(C11=0,"",IFERROR(C11/B11,"")) -> 0.398216 | E11: =C11-B11 -> -8424976 | F11: =IF('設定'!C11="","",'設定'!C11) | G11: =IF(OR(F11="",C11=0),"",IFERROR(C11/F11,"")) | H11: ='2026年07月'!$O$39 -> 241 | I11: ='2026年07月'!$Q$39 -> 793 | J11: =IFERROR(H11/I11,0) -> 0.30390921 | K11: =IFERROR(C11/H11,0) -> 23132.88 | L11: =IF(C11=0,"",SUM($B$8:B11)) -> 36552527 | M11: =IF(C11=0,"",SUM($C$8:C11)) -> 23137339 | N11: =IF(M11="","",IFERROR(M11/L11,0)) -> 0.63298877
A12: 2026年8月 | B12: ='2026年08月'!$A$4 -> 17400000 | C12: ='2026年08月'!$C$4 -> 4585980 | D12: =IF(C12=0,"",IFERROR(C12/B12,"")) -> 0.26356207 | E12: =C12-B12 -> -12814020 | F12: =IF('設定'!C12="","",'設定'!C12) | G12: =IF(OR(F12="",C12=0),"",IFERROR(C12/F12,"")) | H12: ='2026年08月'!$O$39 -> 208 | I12: ='2026年08月'!$Q$39 -> 790 | J12: =IFERROR(H12/I12,0) -> 0.26329114 | K12: =IFERROR(C12/H12,0) -> 22047.981 | L12: =IF(C12=0,"",SUM($B$8:B12)) -> 53952527 | M12: =IF(C12=0,"",SUM($C$8:C12)) -> 27723319 | N12: =IF(M12="","",IFERROR(M12/L12,0)) -> 0.51384653
A13: 2026年9月 | B13: ='2026年09月'!$A$4 -> 14000000 | C13: ='2026年09月'!$C$4 -> 4640983 | D13: =IF(C13=0,"",IFERROR(C13/B13,"")) -> 0.33149879 | E13: =C13-B13 -> -9359017 | F13: =IF('設定'!C13="","",'設定'!C13) | G13: =IF(OR(F13="",C13=0),"",IFERROR(C13/F13,"")) | H13: ='2026年09月'!$O$38 -> 201 | I13: ='2026年09月'!$Q$38 -> 708 | J13: =IFERROR(H13/I13,0) -> 0.28389831 | K13: =IFERROR(C13/H13,0) -> 23089.468 | L13: =IF(C13=0,"",SUM($B$8:B13)) -> 67952527 | M13: =IF(C13=0,"",SUM($C$8:C13)) -> 32364302 | N13: =IF(M13="","",IFERROR(M13/L13,0)) -> 0.47627812
A14: 2026年10月 | B14: ='2026年10月'!$A$4 -> 11000000 | C14: ='2026年10月'!$C$4 -> 1894935 | D14: =IF(C14=0,"",IFERROR(C14/B14,"")) -> 0.17226682 | E14: =C14-B14 -> -9105065 | F14: =IF('設定'!C14="","",'設定'!C14) | G14: =IF(OR(F14="",C14=0),"",IFERROR(C14/F14,"")) | H14: ='2026年10月'!$O$39 -> 83 | I14: ='2026年10月'!$Q$39 -> 379 | J14: =IFERROR(H14/I14,0) -> 0.21899736 | K14: =IFERROR(C14/H14,0) -> 22830.542 | L14: =IF(C14=0,"",SUM($B$8:B14)) -> 78952527 | M14: =IF(C14=0,"",SUM($C$8:C14)) -> 34259237 | N14: =IF(M14="","",IFERROR(M14/L14,0)) -> 0.43392198
A15: 2026年11月 | B15: ='2026年11月'!$A$4 -> 12000000 | C15: ='2026年11月'!$C$4 -> 0 | D15: =IF(C15=0,"",IFERROR(C15/B15,"")) | E15: =C15-B15 -> -12000000 | F15: =IF('設定'!C15="","",'設定'!C15) -> 3642505 | G15: =IF(OR(F15="",C15=0),"",IFERROR(C15/F15,"")) | H15: ='2026年11月'!$O$38 -> 0 | I15: ='2026年11月'!$Q$38 -> 0 | J15: =IFERROR(H15/I15,0) -> 0 | K15: =IFERROR(C15/H15,0) -> 0 | L15: =IF(C15=0,"",SUM($B$8:B15)) | M15: =IF(C15=0,"",SUM($C$8:C15)) | N15: =IF(M15="","",IFERROR(M15/L15,0))
A16: 2026年12月 | B16: ='2026年12月'!$A$4 -> 14000000 | C16: ='2026年12月'!$C$4 -> 0 | D16: =IF(C16=0,"",IFERROR(C16/B16,"")) | E16: =C16-B16 -> -14000000 | F16: =IF('設定'!C16="","",'設定'!C16) -> 9172615 | G16: =IF(OR(F16="",C16=0),"",IFERROR(C16/F16,"")) | H16: ='2026年12月'!$O$39 -> 0 | I16: ='2026年12月'!$Q$39 -> 0 | J16: =IFERROR(H16/I16,0) -> 0 | K16: =IFERROR(C16/H16,0) -> 0 | L16: =IF(C16=0,"",SUM($B$8:B16)) | M16: =IF(C16=0,"",SUM($C$8:C16)) | N16: =IF(M16="","",IFERROR(M16/L16,0))
A17: 2027年1月 | B17: ='2027年01月'!$A$4 -> 15000000 | C17: ='2027年01月'!$C$4 -> 0 | D17: =IF(C17=0,"",IFERROR(C17/B17,"")) | E17: =C17-B17 -> -15000000 | F17: =IF('設定'!C17="","",'設定'!C17) -> 6528886 | G17: =IF(OR(F17="",C17=0),"",IFERROR(C17/F17,"")) | H17: ='2027年01月'!$O$39 -> 0 | I17: ='2027年01月'!$Q$39 -> 0 | J17: =IFERROR(H17/I17,0) -> 0 | K17: =IFERROR(C17/H17,0) -> 0 | L17: =IF(C17=0,"",SUM($B$8:B17)) | M17: =IF(C17=0,"",SUM($C$8:C17)) | N17: =IF(M17="","",IFERROR(M17/L17,0))
A18: 2027年2月 | B18: ='2027年02月'!$A$4 -> 12000000 | C18: ='2027年02月'!$C$4 -> 0 | D18: =IF(C18=0,"",IFERROR(C18/B18,"")) | E18: =C18-B18 -> -12000000 | F18: =IF('設定'!C18="","",'設定'!C18) -> 4592978 | G18: =IF(OR(F18="",C18=0),"",IFERROR(C18/F18,"")) | H18: ='2027年02月'!$O$36 -> 0 | I18: ='2027年02月'!$Q$36 -> 0 | J18: =IFERROR(H18/I18,0) -> 0 | K18: =IFERROR(C18/H18,0) -> 0 | L18: =IF(C18=0,"",SUM($B$8:B18)) | M18: =IF(C18=0,"",SUM($C$8:C18)) | N18: =IF(M18="","",IFERROR(M18/L18,0))
A19: 2027年3月 | B19: ='2027年03月'!$A$4 -> 11000000 | C19: ='2027年03月'!$C$4 -> 0 | D19: =IF(C19=0,"",IFERROR(C19/B19,"")) | E19: =C19-B19 -> -11000000 | F19: =IF('設定'!C19="","",'設定'!C19) -> 5167827 | G19: =IF(OR(F19="",C19=0),"",IFERROR(C19/F19,"")) | H19: ='2027年03月'!$O$39 -> 0 | I19: ='2027年03月'!$Q$39 -> 0 | J19: =IFERROR(H19/I19,0) -> 0 | K19: =IFERROR(C19/H19,0) -> 0 | L19: =IF(C19=0,"",SUM($B$8:B19)) | M19: =IF(C19=0,"",SUM($C$8:C19)) | N19: =IF(M19="","",IFERROR(M19/L19,0))
A20: 合計 | B20: =SUM(B8:B19) -> 142952527 | C20: =SUM(C8:C19) -> 34259237 | D20: =IFERROR(C20/B20,0) -> 0.23965464 | E20: =SUM(E8:E19) -> -108693290 | F20: =SUM(F8:F19) -> 29104811 | G20: =IFERROR(C20/F20,0) -> 1.1770988 | H20: =SUM(H8:H19) -> 1564 | I20: =SUM(I8:I19) -> 5497 | J20: =IFERROR(H20/I20,0) -> 0.28451883 | K20: =IFERROR(C20/H20,0) -> 21904.883
A22: ※前年実績は「設定」シートの青字セルに入力。元データが無い月は空欄です。
A23: ※「経過月 達成率」は予算と実績の両方が入っている月だけで計算します。
A24: 【グラフ】

Sheet 2026年04月
A1: 2026年4月 名古屋店 日別売上管理
A2: 青字＋薄黄色のセルが入力欄。白セルは数式なので触らないでください。単位：円
A3: 月間予算 | C3: 当月実績 | E3: 達成率 | G3: 営業日数(/30日) | I3: 残り必要額 | K3: 残り必要日商
A4: =IF('設定'!$B$8="",SUM(C8:C37),'設定'!$B$8) -> 6927491 | C4: =SUM(H8:H37) -> 6331814 | E4: =IFERROR(C4/A4,0) -> 0.91401259 | G4: =COUNTIF(H8:H37,">0") -> 30 | I4: =A4-C4 -> 595677 | K4: =IF((30-G4)>0,(A4-C4)/(30-G4),0) -> 0
A5: 日次予算合計 | C5: 着地見込 | E5: 決定率 | G5: 客単価 | I5: セット率 | K5: 試着率
A6: =SUM(C8:C37) -> 10200000 | C6: =IFERROR(C4/G4*30,0) -> 6331814 | E6: =IFERROR(N38/P38,0) -> 0.32622601 | G6: =IFERROR(H38/N38,0) -> 20692.203 | I6: =IFERROR(O38/N38,0) -> 1.1045752 | K6: =IFERROR(Q38/P38,0) -> 0.47547974
A7: 日付 | B7: 曜 | C7: 日次予算 | D7: 累計予算 | E7: 現金 | F7: クレジット | G7: 内訳差額 (要確認) | H7: 実績合計 | I7: 累計実績 | J7: 日次達成 | K7: 累計達成 | L7: 累計予実差 | M7: ペース | N7: 購入人数 | O7: 販売点数 | P7: 来客数 | Q7: 試着組数 | R7: 試着個数 | S7: 決定率 | T7: 客単価 | U7: セット率 | V7: 試着率 | W7: クロス クーポン | X7: インスタ フォロワー | Y7: 経費 | Z7: メモ | AB7: 曜日 | AC7: 平均日商 | AD7: 日数 | AE7: 決定率 | AF7: 客単価
A8: 46113 | B8: =MID("日月火水木金土",WEEKDAY(A8),1) -> 水 | C8: 200000 | D8: =SUM($C$8:C8) -> 200000 | E8: 60638 | F8: 107470 | G8: -17706 | H8: =IF(COUNT(E8:G8)=0,"",SUM(E8:G8)) -> 150402 | I8: =IF(H8="","",SUM($H$8:H8)) -> 150402 | J8: =IF(H8="","",IFERROR(H8/C8,"")) -> 0.75201 | K8: =IF(I8="","",IFERROR(I8/D8,"")) -> 0.75201 | L8: =IF(I8="","",IF(D8=0,"",I8-D8)) -> -49598 | M8: =IF(H8="","—",IF(D8=0,"予算未入力",IF(I8>=D8,"◎ ペース内","▲ 遅れ"))) -> ▲ 遅れ | N8: 8 | O8: 8 | P8: 20 | Q8: 13 | S8: =IFERROR(N8/P8,"") -> 0.4 | T8: =IFERROR(H8/N8,"") -> 18800.25 | U8: =IFERROR(O8/N8,"") -> 1 | V8: =IFERROR(Q8/P8,"") -> 0.65 | X8: 8054 | Y8: 0 | AB8: 月 | AC8: =IFERROR(AVERAGEIFS($H$8:$H$37,$B$8:$B$37,AB8,$H$8:$H$37,">0"),0) -> 146293.25 | AD8: =COUNTIFS($B$8:$B$37,AB8,$H$8:$H$37,">0") -> 4 | AE8: =IFERROR(SUMIF($B$8:$B$37,AB8,$N$8:$N$37)/SUMIF($B$8:$B$37,AB8,$P$8:$P$37),0) -> 0.26126126 | AF8: =IFERROR(SUMIF($B$8:$B$37,AB8,$H$8:$H$37)/SUMIF($B$8:$B$37,AB8,$N$8:$N$37),0) -> 20178.379
A9: 46114 | B9: =MID("日月火水木金土",WEEKDAY(A9),1) -> 木 | C9: 200000 | D9: =SUM($C$8:C9) -> 400000 | E9: 40392 | F9: 236347 | G9: 21879 | H9: =IF(COUNT(E9:G9)=0,"",SUM(E9:G9)) -> 298618 | I9: =IF(H9="","",SUM($H$8:H9)) -> 449020 | J9: =IF(H9="","",IFERROR(H9/C9,"")) -> 1.49309 | K9: =IF(I9="","",IFERROR(I9/D9,"")) -> 1.12255 | L9: =IF(I9="","",IF(D9=0,"",I9-D9)) -> 49020 | M9: =IF(H9="","—",IF(D9=0,"予算未入力",IF(I9>=D9,"◎ ペース内","▲ 遅れ"))) -> ◎ ペース内 | N9: 13 | O9: 15 | P9: 33 | Q9: 13 | S9: =IFERROR(N9/P9,"") -> 0.39393939 | T9: =IFERROR(H9/N9,"") -> 22970.615 | U9: =IFERROR(O9/N9,"") -> 1.1538462 | V9: =IFERROR(Q9/P9,"") -> 0.39393939 | X9: 8108 | Y9: 0 | AB9: 火 | AC9: =IFERROR(AVERAGEIFS($H$8:$H$37,$B$8:$B$37,AB9,$H$8:$H$37,">0"),0) -> 107222 | AD9: =COUNTIFS($B$8:$B$37,AB9,$H$8:$H$37,">0") -> 4 | AE9: =IFERROR(SUMIF($B$8:$B$37,AB9,$N$8:$N$37)/SUMIF($B$8:$B$37,AB9,$P$8:$P$37),0) -> 0.25609756 | AF9: =IFERROR(SUMIF($B$8:$B$37,AB9,$H$8:$H$37)/SUMIF($B$8:$B$37,AB9,$N$8:$N$37),0) -> 20423.238
A10: 46115 | B10: =MID("日月火水木金土",WEEKDAY(A10),1) -> 金 | C10: 200000 | D10: =SUM($C$8:C10) -> 600000 | E10: 64598 | F10: 67348 | G10: 30860 | H10: =IF(COUNT(E10:G10)=0,"",SUM(E10:G10)) -> 162806 | I10: =IF(H10="","",SUM($H$8:H10)) -> 611826 | J10: =IF(H10="","",IFERROR(H10/C10,"")) -> 0.81403 | K10: =IF(I10="","",IFERROR(I10/D10,"")) -> 1.01971 | L10: =IF(I10="","",IF(D10=0,"",I10-D10)) -> 11826 | M10: =IF(H10="","—",IF(D10=0,"予算未入力",IF(I10>=D10,"◎ ペース内","▲ 遅れ"))) -> ◎ ペース内 | N10: 8 | O10: 8 | P10: 36 | Q10: 8 | S10: =IFERROR(N10/P10,"") -> 0.22222222 | T10: =IFERROR(H10/N10,"") -> 20350.75 | U10: =IFERROR(O10/N10,"") -> 1 | V10: =IFERROR(Q10/P10,"") -> 0.22222222 | X10: 8167 | Y10: 0 | AB10: 水 | AC10: =IFERROR(AVERAGEIFS($H$8:$H$37,$B$8:$B$37,AB10,$H$8:$H$37,">0"),0) -> 205001.8 | AD10: =COUNTIFS($B$8:$B$37,AB10,$H$8:$H$37,">0") -> 5 | AE10: =IFERROR(SUMIF($B$8:$B$37,AB10,$N$8:$N$37)/SUMIF($B$8:$B$37,AB10,$P$8:$P$37),0) -> 0.38059701 | AF10: =IFERROR(SUMIF($B$8:$B$37,AB10,$H$8:$H$37)/SUMIF($B$8:$B$37,AB10,$N$8:$N$37),0) -> 20098.216
A11: 46116 | B11: =MID("日月火水木金土",WEEKDAY(A11),1) -> 土 | C11: 500000 | D11: =SUM($C$8:C11) -> 1100000 | E11: 43430 | F11: 269270 | G11: -8261 | H11: =IF(COUNT(E11:G11)=0,"",SUM(E11:G11)) -> 304439 | I11: =IF(H11="","",SUM($H$8:H11)) -> 916265 | J11: =IF(H11="","",IFERROR(H11/C11,"")) -> 0.608878 | K11: =IF(I11="","",IFERROR(I11/D11,"")) -> 0.83296818 | L11: =IF(I11="","",IF(D11=0,"",I11-D11)) -> -183735 | M11: =IF(H11="","—",IF(D11=0,"予算未入力",IF(I11>=D11,"◎ ペース内","▲ 遅れ"))) -> ▲ 遅れ | N11: 14 | O11: 26 | P11: 43 | Q11: 38 | S11: =IFERROR(N11/P11,"") -> 0.3255814 | T11: =IFERROR(H11/N11,"") -> 21745.643 | U11: =IFERROR(O11/N11,"") -> 1.8571429 | V11: =IFERROR(Q11/P11,"") -> 0.88372093 | X11: 8220 | Y11: 0 | AB11: 木 | AC11: =IFERROR(AVERAGEIFS($H$8:$H$37,$B$8:$B$37,AB11,$H$8:$H$37,">0"),0) -> 223738.4 | AD11: =COUNTIFS($B$8:$B$37,AB11,$H$8:$H$37,">0") -> 5 | AE11: =IFERROR(SUMIF($B$8:$B$37,AB11,$N$8:$N$37)/SUMIF($B$8:$B$37,AB11,$P$8:$P$37),0) -> 0.3630137 | AF11: =IFERROR(SUMIF($B$8:$B$37,AB11,$H$8:$H$37)/SUMIF($B$8:$B$37,AB11,$N$8:$N$37),0) -> 21107.396
A12: 46117 | B12: =MID("日月火水木金土",WEEKDAY(A12),1) -> 日 | C12: 400000 | D12: =SUM($C$8:C12) -> 1500000 | E12: 72199 | F12: 144030 | G12: 101108 | H12: =IF(COUNT(E12:G12)=0,"",SUM(E12:G12)) -> 317337 | I12: =IF(H12="","",SUM($H$8:H12)) -> 1233602 | J12: =IF(H12="","",IFERROR(H12/C12,"")) -> 0.7933425 | K12: =IF(I12="","",IFERROR(I12/D12,"")) -> 0.82240133 | L12: =IF(I12="","",IF(D12=0,"",I12-D12)) -> -266398 | M12: =IF(H12="","—",IF(D12=0,"予算未入力",IF(I12>=D12,"◎ ペース内","▲ 遅れ"))) -> ▲ 遅れ | N12: 15 | O12: 15 | P12: 51 | Q12: 31 | S12: =IFERROR(N12/P12,"") -> 0.29411765 | T12: =IFERROR(H12/N12,"") -> 21155.8 | U12: =IFERROR(O12/N12,"") -> 1 | V12: =IFERROR(Q12/P12,"") -> 0.60784314 | X12: 8287 | Y12: 0 | AB12: 金 | AC12: =IFERROR(AVERAGEIFS($H$8:$H$37,$B$8:$B$37,AB12,$H$8:$H$37,">0"),0) -> 168889.75 | AD12: =COUNTIFS($B$8:$B$37,AB12,$H$8:$H$37,">0") -> 4 | AE12: =IFERROR(SUMIF($B$8:$B$37,AB12,$N$8:$N$37)/SUMIF($B$8:$B$37,AB12,$P$8:$P$37),0) -> 0.28695652 | AF12: =IFERROR(SUMIF($B$8:$B$37,AB12,$H$8:$H$37)/SUMIF($B$8:$B$37,AB12,$N$8:$N$37),0) -> 20471.485
A13: 46118 | B13: =MID("日月火水木金土",WEEKDAY(A13),1) -> 月 | C13: 300000 | D13: =SUM($C$8:C13) -> 1800000 | E13: 23810 | F13: 150520 | G13: 4780 | H13: =IF(COUNT(E13:G13)=0,"",SUM(E13:G13)) -> 179110 | I13: =IF(H13="","",SUM($H$8:H13)) -> 1412712 | J13: =IF(H13="","",IFERROR(H13/C13,"")) -> 0.59703333 | K13: =IF(I13="","",IFERROR(I13/D13,"")) -> 0.78484 | L13: =IF(I13="","",IF(D13=0,"",I13-D13)) -> -387288 | M13: =IF(H13="","—",IF(D13=0,"予算未入力",IF(I13>=D13,"◎ ペース内","▲ 遅れ"))) -> ▲ 遅れ | N13: 8 | O13: 9 | P13: 21 | Q13: 8 | S13: =IFERROR(N13/P13,"") -> 0.38095238 | T13: =IFERROR(H13/N13,"") -> 22388.75 | U13: =IFERROR(O13/N13,"") -> 1.125 | V13: =IFERROR(Q13/P13,"") -> 0.38095238 | X13: 8332 | Y13: 0 | AB13: 土 | AC13: =IFERROR(AVERAGEIFS($H$8:$H$37,$B$8:$B$37,AB13,$H$8:$H$37,">0"),0) -> 277896.75 | AD13: =COUNTIFS($B$8:$B$37,AB13,$H$8:$H$37,">0") -> 4 | AE13: =IFERROR(SUMIF($B$8:$B$37,AB13,$N$8:$N$37)/SUMIF($B$8:$B$37,AB13,$P$8:$P$37),0) -> 0.28108108 | AF13: =IFERROR(SUMIF($B$8:$B$37,AB13,$H$8:$H$37)/SUMIF($B$8:$B$37,AB13,$N$8:$N$37),0) -> 21376.673
A14: 46119 | B14: =MID("日月火水木金土",WEEKDAY(A14),1) -> 火 | C14: 300000 | D14: =SUM($C$8:C14) -> 2100000 | E14: 0 | F14: 14520 | G14: -1320 | H14: =IF(COUNT(E14:G14)=0,"",SUM(E14:G14)) -> 13200 | I14: =IF(H14="","",SUM($H$8:H14)) -> 1425912 | J14: =IF(H14="","",IFERROR(H14/C14,"")) -> 0.044 | K14: =IF(I14="","",IFERROR(I14/D14,"")) -> 0.67900571 | L14: =IF(I14="","",IF(D14=0,"",I14-D14)) -> -674088 | M14: =IF(H14="","—",IF(D14=0,"予算未入力",IF(I14>=D14,"◎ ペース内","▲ 遅れ"))) -> ▲ 遅れ | N14: 1 | O14: 1 | P14: 8 | Q14: 3 | S14: =IFERROR(N14/P14,"") -> 0.125 | T14: =IFERROR(H14/N14,"") -> 13200 | U14: =IFERROR(O14/N14,"") -> 1 | V14: =IFERROR(Q14/P14,"") -> 0.375 | X14: 8329 | Y14: 0 | AB14: 日 | AC14: =IFERROR(AVERAGEIFS($H$8:$H$37,$B$8:$B$37,AB14,$H$8:$H$37,">0"),0) -> 346726.5 | AD14: =COUNTIFS($B$8:$B$37,AB14,$H$8:$H$37,">0") -> 4 | AE14: =IFERROR(SUMIF($B$8:$B$37,AB14,$N$8:$N$37)/SUMIF($B$8:$B$37,AB14,$P$8:$P$37),0) -> 0.40606061 | AF14: =IFERROR(SUMIF($B$8:$B$37,AB14,$H$8:$H$37)/SUMIF($B$8:$B$37,AB14,$N$8:$N$37),0) -> 20700.09
A15: 46120 | B15: =MID("日月火水木金土",WEEKDAY(A15),1) -> 水 | C15: 300000 | D15: =SUM($C$8:C15) -> 2400000 | E15: 21610 | F15: 50320 | G15: 15074 | H15: =IF(COUNT(E15:G15)=0,"",SUM(E15:G15)) -> 87004 | I15: =IF(H15="","",SUM($H$8:H15)) -> 1512916 | J15: =IF(H15="","",IFERROR(H15/C15,"")) -> 0.29001333 | K15: =IF(I15="","",IFERROR(I15/D15,"")) -> 0.63038167 | L15: =IF(I15="","",IF(D15=0,"",I15-D15)) -> -887084 | M15: =IF(H15="","—",IF(D15=0,"予算未入力",IF(I15>=D15,"◎ ペース内","▲ 遅れ"))) -> ▲ 遅れ | N15: 4 | O15: 4 | P15: 18 | Q15: 10 | S15: =IFERROR(N15/P15,"") -> 0.22222222 | T15: =IFERROR(H15/N15,"") -> 21751 | U15: =IFERROR(O15/N15,"") -> 1 | V15: =IFERROR(Q15/P15,"") -> 0.55555556 | X15: 8331 | Y15: 0
A16: 46121 | B16: =MID("日月火水木金土",WEEKDAY(A16),1) -> 木 | C16: 300000 | D16: =SUM($C$8:C16) -> 2700000 | E16: 21500 | F16: 23810 | G16: 43321 | H16: =IF(COUNT(E16:G16)=0,"",SUM(E16:G16)) -> 88631 | I16: =IF(H16="","",SUM($H$8:H16)) -> 1601547 | J16: =IF(H16="","",IFERROR(H16/C16,"")) -> 0.29543667 | K16: =IF(I16="","",IFERROR(I16/D16,"")) -> 0.59316556 | L16: =IF(I16="","",IF(D16=0,"",I16-D16)) -> -1098453 | M16: =IF(H16="","—",IF(D16=0,"予算未入力",IF(I16>=D16,"◎ ペース内","▲ 遅れ"))) -> ▲ 遅れ | N16: 4 | O16: 5 | P16: 16 | Q16: 12 | S16: =IFERROR(N16/P16,"") -> 0.25 | T16: =IFERROR(H16/N16,"") -> 22157.75 | U16: =IFERROR(O16/N16,"") -> 1.25 | V16: =IFERROR(Q16/P16,"") -> 0.75 | X16: 8324 | Y16: 0 | AB16: ※実績入力後に曜日別の傾向が出ます
A17: 46122 | B17: =MID("日月火水木金土",WEEKDAY(A17),1) -> 金 | C17: 300000 | D17: =SUM($C$8:C17) -> 3000000 | E17: 23700 | F17: 97730 | G17: -12428 | H17: =IF(COUNT(E17:G17)=0,"",SUM(E17:G17)) -> 109002 | I17: =IF(H17="","",SUM($H$8:H17)) -> 1710549 | J17: =IF(H17="","",IFERROR(H17/C17,"")) -> 0.36334 | K17: =IF(I17="","",IFERROR(I17/D17,"")) -> 0.570183 | L17: =IF(I17="","",IF(D17=0,"",I17-D17)) -> -1289451 | M17: =IF(H17="","—",IF(D17=0,"予算未入力",IF(I17>=D17,"◎ ペース内","▲ 遅れ"))) -> ▲ 遅れ | N17: 5 | O17: 5 | P17: 24 | Q17: 14 | S17: =IFERROR(N17/P17,"") -> 0.20833333 | T17: =IFERROR(H17/N17,"") -> 21800.4 | U17: =IFERROR(O17/N17,"") -> 1 | V17: =IFERROR(Q17/P17,"") -> 0.58333333 | X17: 8317 | Y17: 0
A18: 46123 | B18: =MID("日月火水木金土",WEEKDAY(A18),1) -> 土 | C18: 500000 | D18: =SUM($C$8:C18) -> 3500000 | E18: 117140 | F18: 144350 | G18: -3476 | H18: =IF(COUNT(E18:G18)=0,"",SUM(E18:G18)) -> 258014 | I18: =IF(H18="","",SUM($H$8:H18)) -> 1968563 | J18: =IF(H18="","",IFERROR(H18/C18,"")) -> 0.516028 | K18: =IF(I18="","",IFERROR(I18/D18,"")) -> 0.56244657 | L18: =IF(I18="","",IF(D18=0,"",I18-D18)) -> -1531437 | M18: =IF(H18="","—",IF(D18=0,"予算未入力",IF(I18>=D18,"◎ ペース内","▲ 遅れ"))) -> ▲ 遅れ | N18: 12 | O18: 12 | P18: 43 | Q18: 30 | S18: =IFERROR(N18/P18,"") -> 0.27906977 | T18: =IFERROR(H18/N18,"") -> 21501.167 | U18: =IFERROR(O18/N18,"") -> 1 | V18: =IFERROR(Q18/P18,"") -> 0.69767442 | X18: 8315 | Y18: 0 | AB18: ■ 週次サマリー（火曜〜翌月曜） | AI18: 第1火曜 | AJ18: =$A$8+MOD(2-WEEKDAY($A$8,2)+7,7) -> 46119
A19: 46124 | B19: =MID("日月火水木金土",WEEKDAY(A19),1) -> 日 | C19: 400000 | D19: =SUM($C$8:C19) -> 3900000 | E19: 90630 | F19: 62030 | G19: -14652 | H19: =IF(COUNT(E19:G19)=0,"",SUM(E19:G19)) -> 138008 | I19: =IF(H19="","",SUM($H$8:H19)) -> 2106571 | J19: =IF(H19="","",IFERROR(H19/C19,"")) -> 0.34502 | K19: =IF(I19="","",IFERROR(I19/D19,"")) -> 0.54014641 | L19: =IF(I19="","",IF(D19=0,"",I19-D19)) -> -1793429 | M19: =IF(H19="","—",IF(D19=0,"予算未入力",IF(I19>=D19,"◎ ペース内","▲ 遅れ"))) -> ▲ 遅れ | N19: 7 | O19: 7 | P19: 33 | Q19: 20 | S19: =IFERROR(N19/P19,"") -> 0.21212121 | T19: =IFERROR(H19/N19,"") -> 19715.429 | U19: =IFERROR(O19/N19,"") -> 1 | V19: =IFERROR(Q19/P19,"") -> 0.60606061 | X19: 8308 | Y19: 0 | AB19: 週 | AC19: 期間 | AD19: 売上 | AE19: 決定率 | AF19: 客単価 | AG19: セット率 | AH19: 試着率
A20: 46125 | B20: =MID("日月火水木金土",WEEKDAY(A20),1) -> 月 | C20: 300000 | D20: =SUM($C$8:C20) -> 4200000 | E20: 35910 | F20: 64620 | G20: -9528 | H20: =IF(COUNT(E20:G20)=0,"",SUM(E20:G20)) -> 91002 | I20: =IF(H20="","",SUM($H$8:H20)) -> 2197573 | J20: =IF(H20="","",IFERROR(H20/C20,"")) -> 0.30334 | K20: =IF(I20="","",IFERROR(I20/D20,"")) -> 0.52323167 | L20: =IF(I20="","",IF(D20=0,"",I20-D20)) -> -2002427 | M20: =IF(H20="","—",IF(D20=0,"予算未入力",IF(I20>=D20,"◎ ペース内","▲ 遅れ"))) -> ▲ 遅れ | N20: 5 | O20: 5 | P20: 28 | Q20: 8 | S20: =IFERROR(N20/P20,"") -> 0.17857143 | T20: =IFERROR(H20/N20,"") -> 18200.4 | U20: =IFERROR(O20/N20,"") -> 1 | V20: =IFERROR(Q20/P20,"") -> 0.28571429 | X20: 8304 | Y20: 0 | AB20: 1 | AC20: =IF($AJ$18+7*(1-1)>$A$37,"",TEXT($AJ$18+7*(1-1),"m/d")&"-"&TEXT($AJ$18+7*(1-1)+6,"m/d")) -> 4/7-4/13 | AD20: =IF($AC20="","",(SUMIFS($H$8:$H$37,$A$8:$A$37,">="&$AJ$18+7*(1-1),$A$8:$A$37,"<="&$AJ$18+7*(1-1)+6)+SUMIFS('2026年05月'!$H$8:$H$38,'2026年05月'!$A$8:$A$38,">="&$AJ$18+7*(1-1),'2026年05月'!$A$8:$A$38,"<="&$AJ$18+7*(1-1)+6))) -> 784861 | AE20: =IF($AC20="","",IFERROR((SUMIFS($N$8:$N$37,$A$8:$A$37,">="&$AJ$18+7*(1-1),$A$8:$A$37,"<="&$AJ$18+7*(1-1)+6)+SUMIFS('2026年05月'!$N$8:$N$38,'2026年05月'!$A$8:$A$38,">="&$AJ$18+7*(1-1),'2026年05月'!$A$8:$A$38,"<="&$AJ$18+7*(1-1)+6))/(SUMIFS($P$8:$P$37,$A$8:$A$37,">="&$AJ$18+7*(1-1),$A$8:$A$37,"<="&$AJ$18+7*(1-1)+6)+SUMIFS('2026年05月'!$P$8:$P$38,'2026年05月'!$A$8:$A$38,">="&$AJ$18+7*(1-1),'2026年05月'!$A$8:$A$38,"<="&$AJ$18+7*(1-1)+6)),"")) -> 0.22352941 | AF20: =IF($AC20="","",IFERROR((SUMIFS($H$8:$H$37,$A$8:$A$37,">="&$AJ$18+7*(1-1),$A$8:$A$37,"<="&$AJ$18+7*(1-1)+6)+SUMIFS('2026年05月'!$H$8:$H$38,'2026年05月'!$A$8:$A$38,">="&$AJ$18+7*(1-1),'2026年05月'!$A$8:$A$38,"<="&$AJ$18+7*(1-1)+6))/(SUMIFS($N$8:$N$37,$A$8:$A$37,">="&$AJ$18+7*(1-1),$A$8:$A$37,"<="&$AJ$18+7*(1-1)+6)+SUMIFS('2026年05月'!$N$8:$N$38,'2026年05月'!$A$8:$A$38,">="&$AJ$18+7*(1-1),'2026年05月'!$A$8:$A$38,"<="&$AJ$18+7*(1-1)+6)),"")) -> 20654.237 | AG20: =IF($AC20="","",IFERROR((SUMIFS($O$8:$O$37,$A$8:$A$37,">="&$AJ$18+7*(1-1),$A$8:$A$37,"<="&$AJ$18+7*(1-1)+6)+SUMIFS('2026年05月'!$O$8:$O$38,'2026年05月'!$A$8:$A$38,">="&$AJ$18+7*(1-1),'2026年05月'!$A$8:$A$38,"<="&$AJ$18+7*(1-1)+6))/(SUMIFS($N$8:$N$37,$A$8:$A$37,">="&$AJ$18+7*(1-1),$A$8:$A$37,"<="&$AJ$18+7*(1-1)+6)+SUMIFS('2026年05月'!$N$8:$N$38,'2026年05月'!$A$8:$A$38,">="&$AJ$18+7*(1-1),'2026年05月'!$A$8:$A$38,"<="&$AJ$18+7*(1-1)+6)),"")) -> 1.0263158 | AH20: =IF($AC20="","",IFERROR((SUMIFS($Q$8:$Q$37,$A$8:$A$37,">="&$AJ$18+7*(1-1),$A$8:$A$37,"<="&$AJ$18+7*(1-1)+6)+SUMIFS('2026年05月'!$Q$8:$Q$38,'2026年05月'!$A$8:$A$38,">="&$AJ$18+7*(1-1),'2026年05月'!$A$8:$A$38,"<="&$AJ$18+7*(1-1)+6))/(SUMIFS($P$8:$P$37,$A$8:$A$37,">="&$AJ$18+7*(1-1),$A$8:$A$37,"<="&$AJ$18+7*(1-1)+6)+SUMIFS('2026年05月'!$P$8:$P$38,'2026年05月'!$A$8:$A$38,">="&$AJ$18+7*(1-1),'2026年05月'!$A$8:$A$38,"<="&$AJ$18+7*(1-1)+6)),"")) -> 0.57058824
A21: 46126 | B21: =MID("日月火水木金土",WEEKDAY(A21),1) -> 火 | C21: 300000 | D21: =SUM($C$8:C21) -> 4500000 | E21: 0 | F21: 44110 | G21: 39392 | H21: =IF(COUNT(E21:G21)=0,"",SUM(E21:G21)) -> 83502 | I21: =IF(H21="","",SUM($H$8:H21)) -> 2281075 | J21: =IF(H21="","",IFERROR(H21/C21,"")) -> 0.27834 | K21: =IF(I21="","",IFERROR(I21/D21,"")) -> 0.50690556 | L21: =IF(I21="","",IF(D21=0,"",I21-D21)) -> -2218925 | M21: =IF(H21="","—",IF(D21=0,"予算未入力",IF(I21>=D21,"◎ ペース内","▲ 遅れ"))) -> ▲ 遅れ | N21: 4 | O21: 4 | P21: 25 | Q21: 13 | S21: =IFERROR(N21/P21,"") -> 0.16 | T21: =IFERROR(H21/N21,"") -> 20875.5 | U21: =IFERROR(O21/N21,"") -> 1 | V21: =IFERROR(Q21/P21,"") -> 0.52 | X21: 8301 | Y21: 0 | AB21: 2 | AC21: =IF($AJ$18+7*(2-1)>$A$37,"",TEXT($AJ$18+7*(2-1),"m/d")&"-"&TEXT($AJ$18+7*(2-1)+6,"m/d")) -> 4/14-4/20 | AD21: =IF($AC21="","",(SUMIFS($H$8:$H$37,$A$8:$A$37,">="&$AJ$18+7*(2-1),$A$8:$A$37,"<="&$AJ$18+7*(2-1)+6)+SUMIFS('2026年05月'!$H$8:$H$38,'2026年05月'!$A$8:$A$38,">="&$AJ$18+7*(2-1),'2026年05月'!$A$8:$A$38,"<="&$AJ$18+7*(2-1)+6))) -> 1329465 | AE21: =IF($AC21="","",IFERROR((SUMIFS($N$8:$N$37,$A$8:$A$37,">="&$AJ$18+7*(2-1),$A$8:$A$37,"<="&$AJ$18+7*(2-1)+6)+SUMIFS('2026年05月'!$N$8:$N$38,'2026年05月'!$A$8:$A$38,">="&$AJ$18+7*(2-1),'2026年05月'!$A$8:$A$38,"<="&$AJ$18+7*(2-1)+6))/(SUMIFS($P$8:$P$37,$A$8:$A$37,">="&$AJ$18+7*(2-1),$A$8:$A$37,"<="&$AJ$18+7*(2-1)+6)+SUMIFS('2026年05月'!$P$8:$P$38,'2026年05月'!$A$8:$A$38,">="&$AJ$18+7*(2-1),'2026年05月'!$A$8:$A$38,"<="&$AJ$18+7*(2-1)+6)),"")) -> 0.33668342 | AF21: =IF($AC21="","",IFERROR((SUMIFS($H$8:$H$37,$A$8:$A$37,">="&$AJ$18+7*(2-1),$A$8:$A$37,"<="&$AJ$18+7*(2-1)+6)+SUMIFS('2026年05月'!$H$8:$H$38,'2026年05月'!$A$8:$A$38,">="&$AJ$18+7*(2-1),'2026年05月'!$A$8:$A$38,"<="&$AJ$18+7*(2-1)+6))/(SUMIFS($N$8:$N$37,$A$8:$A$37,">="&$AJ$18+7*(2-1),$A$8:$A$37,"<="&$AJ$18+7*(2-1)+6)+SUMIFS('2026年05月'!$N$8:$N$38,'2026年05月'!$A$8:$A$38,">="&$AJ$18+7*(2-1),'2026年05月'!$A$8:$A$38,"<="&$AJ$18+7*(2-1)+6)),"")) -> 19842.761 | AG21: =IF($AC21="","",IFERROR((SUMIFS($O$8:$O$37,$A$8:$A$37,">="&$AJ$18+7*(2-1),$A$8:$A$37,"<="&$AJ$18+7*(2-1)+6)+SUMIFS('2026年05月'!$O$8:$O$38,'2026年05月'!$A$8:$A$38,">="&$AJ$18+7*(2-1),'2026年05月'!$A$8:$A$38,"<="&$AJ$18+7*(2-1)+6))/(SUMIFS($N$8:$N$37,$A$8:$A$37,">="&$AJ$18+7*(2-1),$A$8:$A$37,"<="&$AJ$18+7*(2-1)+6)+SUMIFS('2026年05月'!$N$8:$N$38,'2026年05月'!$A$8:$A$38,">="&$AJ$18+7*(2-1),'2026年05月'!$A$8:$A$38,"<="&$AJ$18+7*(2-1)+6)),"")) -> 1.0298507 | AH21: =IF($AC21="","",IFERROR((SUMIFS($Q$8:$Q$37,$A$8:$A$37,">="&$AJ$18+7*(2-1),$A$8:$A$37,"<="&$AJ$18+7*(2-1)+6)+SUMIFS('2026年05月'!$Q$8:$Q$38,'2026年05月'!$A$8:$A$38,">="&$AJ$18+7*(2-1),'2026年05月'!$A$8:$A$38,"<="&$AJ$18+7*(2-1)+6))/(SUMIFS($P$8:$P$37,$A$8:$A$37,">="&$AJ$18+7*(2-1),$A$8:$A$37,"<="&$AJ$18+7*(2-1)+6)+SUMIFS('2026年05月'!$P$8:$P$38,'2026年05月'!$A$8:$A$38,">="&$AJ$18+7*(2-1),'2026年05月'!$A$8:$A$38,"<="&$AJ$18+7*(2-1)+6)),"")) -> 0.44221106
A22: 46127 | B22: =MID("日月火水木金土",WEEKDAY(A22),1) -> 水 | C22: 300000 | D22: =SUM($C$8:C22) -> 4800000 | E22: 23810 | F22: 99030 | G22: -11830 | H22: =IF(COUNT(E22:G22)=0,"",SUM(E22:G22)) -> 111010 | I22: =IF(H22="","",SUM($H$8:H22)) -> 2392085 | J22: =IF(H22="","",IFERROR(H22/C22,"")) -> 0.37003333 | K22: =IF(I22="","",IFERROR(I22/D22,"")) -> 0.49835104 | L22: =IF(I22="","",IF(D22=0,"",I22-D22)) -> -2407915 | M22: =IF(H22="","—",IF(D22=0,"予算未入力",IF(I22>=D22,"◎ ペース内","▲ 遅れ"))) -> ▲ 遅れ | N22: 6 | O22: 6 | P22: 17 | Q22: 5 | R22: 11 | S22: =IFERROR(N22/P22,"") -> 0.35294118 | T22: =IFERROR(H22/N22,"") -> 18501.667 | U22: =IFERROR(O22/N22,"") -> 1 | V22: =IFERROR(Q22/P22,"") -> 0.29411765 | X22: 8301 | Y22: 0 | AB22: 3 | AC22: =IF($AJ$18+7*(3-1)>$A$37,"",TEXT($AJ$18+7*(3-1),"m/d")&"-"&TEXT($AJ$18+7*(3-1)+6,"m/d")) -> 4/21-4/27 | AD22: =IF($AC22="","",(SUMIFS($H$8:$H$37,$A$8:$A$37,">="&$AJ$18+7*(3-1),$A$8:$A$37,"<="&$AJ$18+7*(3-1)+6)+SUMIFS('2026年05月'!$H$8:$H$38,'2026年05月'!$A$8:$A$38,">="&$AJ$18+7*(3-1),'2026年05月'!$A$8:$A$38,"<="&$AJ$18+7*(3-1)+6))) -> 1685356 | AE22: =IF($AC22="","",IFERROR((SUMIFS($N$8:$N$37,$A$8:$A$37,">="&$AJ$18+7*(3-1),$A$8:$A$37,"<="&$AJ$18+7*(3-1)+6)+SUMIFS('2026年05月'!$N$8:$N$38,'2026年05月'!$A$8:$A$38,">="&$AJ$18+7*(3-1),'2026年05月'!$A$8:$A$38,"<="&$AJ$18+7*(3-1)+6))/(SUMIFS($P$8:$P$37,$A$8:$A$37,">="&$AJ$18+7*(3-1),$A$8:$A$37,"<="&$AJ$18+7*(3-1)+6)+SUMIFS('2026年05月'!$P$8:$P$38,'2026年05月'!$A$8:$A$38,">="&$AJ$18+7*(3-1),'2026年05月'!$A$8:$A$38,"<="&$AJ$18+7*(3-1)+6)),"")) -> 0.32916667 | AF22: =IF($AC22="","",IFERROR((SUMIFS($H$8:$H$37,$A$8:$A$37,">="&$AJ$18+7*(3-1),$A$8:$A$37,"<="&$AJ$18+7*(3-1)+6)+SUMIFS('2026年05月'!$H$8:$H$38,'2026年05月'!$A$8:$A$38,">="&$AJ$18+7*(3-1),'2026年05月'!$A$8:$A$38,"<="&$AJ$18+7*(3-1)+6))/(SUMIFS($N$8:$N$37,$A$8:$A$37,">="&$AJ$18+7*(3-1),$A$8:$A$37,"<="&$AJ$18+7*(3-1)+6)+SUMIFS('2026年05月'!$N$8:$N$38,'2026年05月'!$A$8:$A$38,">="&$AJ$18+7*(3-1),'2026年05月'!$A$8:$A$38,"<="&$AJ$18+7*(3-1)+6)),"")) -> 21333.62 | AG22: =IF($AC22="","",IFERROR((SUMIFS($O$8:$O$37,$A$8:$A$37,">="&$AJ$18+7*(3-1),$A$8:$A$37,"<="&$AJ$18+7*(3-1)+6)+SUMIFS('2026年05月'!$O$8:$O$38,'2026年05月'!$A$8:$A$38,">="&$AJ$18+7*(3-1),'2026年05月'!$A$8:$A$38,"<="&$AJ$18+7*(3-1)+6))/(SUMIFS($N$8:$N$37,$A$8:$A$37,">="&$AJ$18+7*(3-1),$A$8:$A$37,"<="&$AJ$18+7*(3-1)+6)+SUMIFS('2026年05月'!$N$8:$N$38,'2026年05月'!$A$8:$A$38,">="&$AJ$18+7*(3-1),'2026年05月'!$A$8:$A$38,"<="&$AJ$18+7*(3-1)+6)),"")) -> 1.1265823 | AH22: =IF($AC22="","",IFERROR((SUMIFS($Q$8:$Q$37,$A$8:$A$37,">="&$AJ$18+7*(3-1),$A$8:$A$37,"<="&$AJ$18+7*(3-1)+6)+SUMIFS('2026年05月'!$Q$8:$Q$38,'2026年05月'!$A$8:$A$38,">="&$AJ$18+7*(3-1),'2026年05月'!$A$8:$A$38,"<="&$AJ$18+7*(3-1)+6))/(SUMIFS($P$8:$P$37,$A$8:$A$37,">="&$AJ$18+7*(3-1),$A$8:$A$37,"<="&$AJ$18+7*(3-1)+6)+SUMIFS('2026年05月'!$P$8:$P$38,'2026年05月'!$A$8:$A$38,">="&$AJ$18+7*(3-1),'2026年05月'!$A$8:$A$38,"<="&$AJ$18+7*(3-1)+6)),"")) -> 0.40416667
A23: 46128 | B23: =MID("日月火水木金土",WEEKDAY(A23),1) -> 木 | C23: 300000 | D23: =SUM($C$8:C23) -> 5100000 | E23: 23810 | F23: 104100 | G23: 6299 | H23: =IF(COUNT(E23:G23)=0,"",SUM(E23:G23)) -> 134209 | I23: =IF(H23="","",SUM($H$8:H23)) -> 2526294 | J23: =IF(H23="","",IFERROR(H23/C23,"")) -> 0.44736333 | K23: =IF(I23="","",IFERROR(I23/D23,"")) -> 0.49535176 | L23: =IF(I23="","",IF(D23=0,"",I23-D23)) -> -2573706 | M23: =IF(H23="","—",IF(D23=0,"予算未入力",IF(I23>=D23,"◎ ペース内","▲ 遅れ"))) -> ▲ 遅れ | N23: 8 | O23: 9 | P23: 24 | Q23: 11 | R23: 19 | S23: =IFERROR(N23/P23,"") -> 0.33333333 | T23: =IFERROR(H23/N23,"") -> 16776.125 | U23: =IFERROR(O23/N23,"") -> 1.125 | V23: =IFERROR(Q23/P23,"") -> 0.45833333 | X23: 8304 | Y23: 0 | AB23: 4 | AC23: =IF($AJ$18+7*(4-1)>$A$37,"",TEXT($AJ$18+7*(4-1),"m/d")&"-"&TEXT($AJ$18+7*(4-1)+6,"m/d")) -> 4/28-5/4 | AD23: =IF($AC23="","",(SUMIFS($H$8:$H$37,$A$8:$A$37,">="&$AJ$18+7*(4-1),$A$8:$A$37,"<="&$AJ$18+7*(4-1)+6)+SUMIFS('2026年05月'!$H$8:$H$38,'2026年05月'!$A$8:$A$38,">="&$AJ$18+7*(4-1),'2026年05月'!$A$8:$A$38,"<="&$AJ$18+7*(4-1)+6))) -> 2560005 | AE23: =IF($AC23="","",IFERROR((SUMIFS($N$8:$N$37,$A$8:$A$37,">="&$AJ$18+7*(4-1),$A$8:$A$37,"<="&$AJ$18+7*(4-1)+6)+SUMIFS('2026年05月'!$N$8:$N$38,'2026年05月'!$A$8:$A$38,">="&$AJ$18+7*(4-1),'2026年05月'!$A$8:$A$38,"<="&$AJ$18+7*(4-1)+6))/(SUMIFS($P$8:$P$37,$A$8:$A$37,">="&$AJ$18+7*(4-1),$A$8:$A$37,"<="&$AJ$18+7*(4-1)+6)+SUMIFS('2026年05月'!$P$8:$P$38,'2026年05月'!$A$8:$A$38,">="&$AJ$18+7*(4-1),'2026年05月'!$A$8:$A$38,"<="&$AJ$18+7*(4-1)+6)),"")) -> 0.38819876 | AF23: =IF($AC23="","",IFERROR((SUMIFS($H$8:$H$37,$A$8:$A$37,">="&$AJ$18+7*(4-1),$A$8:$A$37,"<="&$AJ$18+7*(4-1)+6)+SUMIFS('2026年05月'!$H$8:$H$38,'2026年05月'!$A$8:$A$38,">="&$AJ$18+7*(4-1),'2026年05月'!$A$8:$A$38,"<="&$AJ$18+7*(4-1)+6))/(SUMIFS($N$8:$N$37,$A$8:$A$37,">="&$AJ$18+7*(4-1),$A$8:$A$37,"<="&$AJ$18+7*(4-1)+6)+SUMIFS('2026年05月'!$N$8:$N$38,'2026年05月'!$A$8:$A$38,">="&$AJ$18+7*(4-1),'2026年05月'!$A$8:$A$38,"<="&$AJ$18+7*(4-1)+6)),"")) -> 20480.04 | AG23: =IF($AC23="","",IFERROR((SUMIFS($O$8:$O$37,$A$8:$A$37,">="&$AJ$18+7*(4-1),$A$8:$A$37,"<="&$AJ$18+7*(4-1)+6)+SUMIFS('2026年05月'!$O$8:$O$38,'2026年05月'!$A$8:$A$38,">="&$AJ$18+7*(4-1),'2026年05月'!$A$8:$A$38,"<="&$AJ$18+7*(4-1)+6))/(SUMIFS($N$8:$N$37,$A$8:$A$37,">="&$AJ$18+7*(4-1),$A$8:$A$37,"<="&$AJ$18+7*(4-1)+6)+SUMIFS('2026年05月'!$N$8:$N$38,'2026年05月'!$A$8:$A$38,">="&$AJ$18+7*(4-1),'2026年05月'!$A$8:$A$38,"<="&$AJ$18+7*(4-1)+6)),"")) -> 1.072 | AH23: =IF($AC23="","",IFERROR((SUMIFS($Q$8:$Q$37,$A$8:$A$37,">="&$AJ$18+7*(4-1),$A$8:$A$37,"<="&$AJ$18+7*(4-1)+6)+SUMIFS('2026年05月'!$Q$8:$Q$38,'2026年05月'!$A$8:$A$38,">="&$AJ$18+7*(4-1),'2026年05月'!$A$8:$A$38,"<="&$AJ$18+7*(4-1)+6))/(SUMIFS($P$8:$P$37,$A$8:$A$37,">="&$AJ$18+7*(4-1),$A$8:$A$37,"<="&$AJ$18+7*(4-1)+6)+SUMIFS('2026年05月'!$P$8:$P$38,'2026年05月'!$A$8:$A$38,">="&$AJ$18+7*(4-1),'2026年05月'!$A$8:$A$38,"<="&$AJ$18+7*(4-1)+6)),"")) -> 0.41304348
A24: 46129 | B24: =MID("日月火水木金土",WEEKDAY(A24),1) -> 金 | C24: 300000 | D24: =SUM($C$8:C24) -> 5400000 | E24: 65930 | F24: 103050 | G24: 5058 | H24: =IF(COUNT(E24:G24)=0,"",SUM(E24:G24)) -> 174038 | I24: =IF(H24="","",SUM($H$8:H24)) -> 2700332 | J24: =IF(H24="","",IFERROR(H24/C24,"")) -> 0.58012667 | K24: =IF(I24="","",IFERROR(I24/D24,"")) -> 0.50006148 | L24: =IF(I24="","",IF(D24=0,"",I24-D24)) -> -2699668 | M24: =IF(H24="","—",IF(D24=0,"予算未入力",IF(I24>=D24,"◎ ペース内","▲ 遅れ"))) -> ▲ 遅れ | N24: 9 | O24: 9 | P24: 21 | Q24: 5 | R24: 7 | S24: =IFERROR(N24/P24,"") -> 0.42857143 | T24: =IFERROR(H24/N24,"") -> 19337.556 | U24: =IFERROR(O24/N24,"") -> 1 | V24: =IFERROR(Q24/P24,"") -> 0.23809524 | X24: 8378 | Y24: 0 | AB24: 5 | AC24: =IF($AJ$18+7*(5-1)>$A$37,"",TEXT($AJ$18+7*(5-1),"m/d")&"-"&TEXT($AJ$18+7*(5-1)+6,"m/d")) | AD24: =IF($AC24="","",(SUMIFS($H$8:$H$37,$A$8:$A$37,">="&$AJ$18+7*(5-1),$A$8:$A$37,"<="&$AJ$18+7*(5-1)+6)+SUMIFS('2026年05月'!$H$8:$H$38,'2026年05月'!$A$8:$A$38,">="&$AJ$18+7*(5-1),'2026年05月'!$A$8:$A$38,"<="&$AJ$18+7*(5-1)+6))) | AE24: =IF($AC24="","",IFERROR((SUMIFS($N$8:$N$37,$A$8:$A$37,">="&$AJ$18+7*(5-1),$A$8:$A$37,"<="&$AJ$18+7*(5-1)+6)+SUMIFS('2026年05月'!$N$8:$N$38,'2026年05月'!$A$8:$A$38,">="&$AJ$18+7*(5-1),'2026年05月'!$A$8:$A$38,"<="&$AJ$18+7*(5-1)+6))/(SUMIFS($P$8:$P$37,$A$8:$A$37,">="&$AJ$18+7*(5-1),$A$8:$A$37,"<="&$AJ$18+7*(5-1)+6)+SUMIFS('2026年05月'!$P$8:$P$38,'2026年05月'!$A$8:$A$38,">="&$AJ$18+7*(5-1),'2026年05月'!$A$8:$A$38,"<="&$AJ$18+7*(5-1)+6)),"")) | AF24: =IF($AC24="","",IFERROR((SUMIFS($H$8:$H$37,$A$8:$A$37,">="&$AJ$18+7*(5-1),$A$8:$A$37,"<="&$AJ$18+7*(5-1)+6)+SUMIFS('2026年05月'!$H$8:$H$38,'2026年05月'!$A$8:$A$38,">="&$AJ$18+7*(5-1),'2026年05月'!$A$8:$A$38,"<="&$AJ$18+7*(5-1)+6))/(SUMIFS($N$8:$N$37,$A$8:$A$37,">="&$AJ$18+7*(5-1),$A$8:$A$37,"<="&$AJ$18+7*(5-1)+6)+SUMIFS('2026年05月'!$N$8:$N$38,'2026年05月'!$A$8:$A$38,">="&$AJ$18+7*(5-1),'2026年05月'!$A$8:$A$38,"<="&$AJ$18+7*(5-1)+6)),"")) | AG24: =IF($AC24="","",IFERROR((SUMIFS($O$8:$O$37,$A$8:$A$37,">="&$AJ$18+7*(5-1),$A$8:$A$37,"<="&$AJ$18+7*(5-1)+6)+SUMIFS('2026年05月'!$O$8:$O$38,'2026年05月'!$A$8:$A$38,">="&$AJ$18+7*(5-1),'2026年05月'!$A$8:$A$38,"<="&$AJ$18+7*(5-1)+6))/(SUMIFS($N$8:$N$37,$A$8:$A$37,">="&$AJ$18+7*(5-1),$A$8:$A$37,"<="&$AJ$18+7*(5-1)+6)+SUMIFS('2026年05月'!$N$8:$N$38,'2026年05月'!$A$8:$A$38,">="&$AJ$18+7*(5-1),'2026年05月'!$A$8:$A$38,"<="&$AJ$18+7*(5-1)+6)),"")) | AH24: =IF($AC24="","",IFERROR((SUMIFS($Q$8:$Q$37,$A$8:$A$37,">="&$AJ$18+7*(5-1),$A$8:$A$37,"<="&$AJ$18+7*(5-1)+6)+SUMIFS('2026年05月'!$Q$8:$Q$38,'2026年05月'!$A$8:$A$38,">="&$AJ$18+7*(5-1),'2026年05月'!$A$8:$A$38,"<="&$AJ$18+7*(5-1)+6))/(SUMIFS($P$8:$P$37,$A$8:$A$37,">="&$AJ$18+7*(5-1),$A$8:$A$37,"<="&$AJ$18+7*(5-1)+6)+SUMIFS('2026年05月'!$P$8:$P$38,'2026年05月'!$A$8:$A$38,">="&$AJ$18+7*(5-1),'2026年05月'!$A$8:$A$38,"<="&$AJ$18+7*(5-1)+6)),""))
A25: 46130 | B25: =MID("日月火水木金土",WEEKDAY(A25),1) -> 土 | C25: 500000 | D25: =SUM($C$8:C25) -> 5900000 | E25: 65330 | F25: 116640 | G25: 4041 | H25: =IF(COUNT(E25:G25)=0,"",SUM(E25:G25)) -> 186011 | I25: =IF(H25="","",SUM($H$8:H25)) -> 2886343 | J25: =IF(H25="","",IFERROR(H25/C25,"")) -> 0.372022 | K25: =IF(I25="","",IFERROR(I25/D25,"")) -> 0.48921068 | L25: =IF(I25="","",IF(D25=0,"",I25-D25)) -> -3013657 | M25: =IF(H25="","—",IF(D25=0,"予算未入力",IF(I25>=D25,"◎ ペース内","▲ 遅れ"))) -> ▲ 遅れ | N25: 9 | O25: 9 | P25: 36 | Q25: 17 | R25: 40 | S25: =IFERROR(N25/P25,"") -> 0.25 | T25: =IFERROR(H25/N25,"") -> 20667.889 | U25: =IFERROR(O25/N25,"") -> 1 | V25: =IFERROR(Q25/P25,"") -> 0.47222222 | X25: 8485 | Y25: 0 | AB25: 6 | AC25: =IF($AJ$18+7*(6-1)>$A$37,"",TEXT($AJ$18+7*(6-1),"m/d")&"-"&TEXT($AJ$18+7*(6-1)+6,"m/d")) | AD25: =IF($AC25="","",(SUMIFS($H$8:$H$37,$A$8:$A$37,">="&$AJ$18+7*(6-1),$A$8:$A$37,"<="&$AJ$18+7*(6-1)+6)+SUMIFS('2026年05月'!$H$8:$H$38,'2026年05月'!$A$8:$A$38,">="&$AJ$18+7*(6-1),'2026年05月'!$A$8:$A$38,"<="&$AJ$18+7*(6-1)+6))) | AE25: =IF($AC25="","",IFERROR((SUMIFS($N$8:$N$37,$A$8:$A$37,">="&$AJ$18+7*(6-1),$A$8:$A$37,"<="&$AJ$18+7*(6-1)+6)+SUMIFS('2026年05月'!$N$8:$N$38,'2026年05月'!$A$8:$A$38,">="&$AJ$18+7*(6-1),'2026年05月'!$A$8:$A$38,"<="&$AJ$18+7*(6-1)+6))/(SUMIFS($P$8:$P$37,$A$8:$A$37,">="&$AJ$18+7*(6-1),$A$8:$A$37,"<="&$AJ$18+7*(6-1)+6)+SUMIFS('2026年05月'!$P$8:$P$38,'2026年05月'!$A$8:$A$38,">="&$AJ$18+7*(6-1),'2026年05月'!$A$8:$A$38,"<="&$AJ$18+7*(6-1)+6)),"")) | AF25: =IF($AC25="","",IFERROR((SUMIFS($H$8:$H$37,$A$8:$A$37,">="&$AJ$18+7*(6-1),$A$8:$A$37,"<="&$AJ$18+7*(6-1)+6)+SUMIFS('2026年05月'!$H$8:$H$38,'2026年05月'!$A$8:$A$38,">="&$AJ$18+7*(6-1),'2026年05月'!$A$8:$A$38,"<="&$AJ$18+7*(6-1)+6))/(SUMIFS($N$8:$N$37,$A$8:$A$37,">="&$AJ$18+7*(6-1),$A$8:$A$37,"<="&$AJ$18+7*(6-1)+6)+SUMIFS('2026年05月'!$N$8:$N$38,'2026年05月'!$A$8:$A$38,">="&$AJ$18+7*(6-1),'2026年05月'!$A$8:$A$38,"<="&$AJ$18+7*(6-1)+6)),"")) | AG25: =IF($AC25="","",IFERROR((SUMIFS($O$8:$O$37,$A$8:$A$37,">="&$AJ$18+7*(6-1),$A$8:$A$37,"<="&$AJ$18+7*(6-1)+6)+SUMIFS('2026年05月'!$O$8:$O$38,'2026年05月'!$A$8:$A$38,">="&$AJ$18+7*(6-1),'2026年05月'!$A$8:$A$38,"<="&$AJ$18+7*(6-1)+6))/(SUMIFS($N$8:$N$37,$A$8:$A$37,">="&$AJ$18+7*(6-1),$A$8:$A$37,"<="&$AJ$18+7*(6-1)+6)+SUMIFS('2026年05月'!$N$8:$N$38,'2026年05月'!$A$8:$A$38,">="&$AJ$18+7*(6-1),'2026年05月'!$A$8:$A$38,"<="&$AJ$18+7*(6-1)+6)),"")) | AH25: =IF($AC25="","",IFERROR((SUMIFS($Q$8:$Q$37,$A$8:$A$37,">="&$AJ$18+7*(6-1),$A$8:$A$37,"<="&$AJ$18+7*(6-1)+6)+SUMIFS('2026年05月'!$Q$8:$Q$38,'2026年05月'!$A$8:$A$38,">="&$AJ$18+7*(6-1),'2026年05月'!$A$8:$A$38,"<="&$AJ$18+7*(6-1)+6))/(SUMIFS($P$8:$P$37,$A$8:$A$37,">="&$AJ$18+7*(6-1),$A$8:$A$37,"<="&$AJ$18+7*(6-1)+6)+SUMIFS('2026年05月'!$P$8:$P$38,'2026年05月'!$A$8:$A$38,">="&$AJ$18+7*(6-1),'2026年05月'!$A$8:$A$38,"<="&$AJ$18+7*(6-1)+6)),""))
A26: 46131 | B26: =MID("日月火水木金土",WEEKDAY(A26),1) -> 日 | C26: 400000 | D26: =SUM($C$8:C26) -> 6300000 | E26: 205280 | F26: 233470 | G26: -11208 | H26: =IF(COUNT(E26:G26)=0,"",SUM(E26:G26)) -> 427542 | I26: =IF(H26="","",SUM($H$8:H26)) -> 3313885 | J26: =IF(H26="","",IFERROR(H26/C26,"")) -> 1.068855 | K26: =IF(I26="","",IFERROR(I26/D26,"")) -> 0.52601349 | L26: =IF(I26="","",IF(D26=0,"",I26-D26)) -> -2986115 | M26: =IF(H26="","—",IF(D26=0,"予算未入力",IF(I26>=D26,"◎ ペース内","▲ 遅れ"))) -> ▲ 遅れ | N26: 21 | O26: 21 | P26: 42 | Q26: 26 | R26: 39 | S26: =IFERROR(N26/P26,"") -> 0.5 | T26: =IFERROR(H26/N26,"") -> 20359.143 | U26: =IFERROR(O26/N26,"") -> 1 | V26: =IFERROR(Q26/P26,"") -> 0.61904762 | X26: 8572 | Y26: 0 | AB26: ※期間ラベルは第1火曜から自動生成。決定率・客単価・セット率・試着率は「週合計÷週合計」
A27: 46132 | B27: =MID("日月火水木金土",WEEKDAY(A27),1) -> 月 | C27: 300000 | D27: =SUM($C$8:C27) -> 6600000 | E27: 120710 | F27: 92220 | G27: 223 | H27: =IF(COUNT(E27:G27)=0,"",SUM(E27:G27)) -> 213153 | I27: =IF(H27="","",SUM($H$8:H27)) -> 3527038 | J27: =IF(H27="","",IFERROR(H27/C27,"")) -> 0.71051 | K27: =IF(I27="","",IFERROR(I27/D27,"")) -> 0.5343997 | L27: =IF(I27="","",IF(D27=0,"",I27-D27)) -> -3072962 | M27: =IF(H27="","—",IF(D27=0,"予算未入力",IF(I27>=D27,"◎ ペース内","▲ 遅れ"))) -> ▲ 遅れ | N27: 10 | O27: 11 | P27: 34 | Q27: 11 | R27: 19 | S27: =IFERROR(N27/P27,"") -> 0.29411765 | T27: =IFERROR(H27/N27,"") -> 21315.3 | U27: =IFERROR(O27/N27,"") -> 1.1 | V27: =IFERROR(Q27/P27,"") -> 0.32352941 | X27: 8640 | Y27: 0 | AB27: ※最終週は翌月にまたぐため、2026年05月シートの実績も自動で合算します
A28: 46133 | B28: =MID("日月火水木金土",WEEKDAY(A28),1) -> 火 | C28: 300000 | D28: =SUM($C$8:C28) -> 6900000 | E28: 26510 | F28: 72430 | G28: 25300 | H28: =IF(COUNT(E28:G28)=0,"",SUM(E28:G28)) -> 124240 | I28: =IF(H28="","",SUM($H$8:H28)) -> 3651278 | J28: =IF(H28="","",IFERROR(H28/C28,"")) -> 0.41413333 | K28: =IF(I28="","",IFERROR(I28/D28,"")) -> 0.52917072 | L28: =IF(I28="","",IF(D28=0,"",I28-D28)) -> -3248722 | M28: =IF(H28="","—",IF(D28=0,"予算未入力",IF(I28>=D28,"◎ ペース内","▲ 遅れ"))) -> ▲ 遅れ | N28: 5 | O28: 5 | P28: 23 | Q28: 10 | R28: 13 | S28: =IFERROR(N28/P28,"") -> 0.2173913 | T28: =IFERROR(H28/N28,"") -> 24848 | U28: =IFERROR(O28/N28,"") -> 1 | V28: =IFERROR(Q28/P28,"") -> 0.43478261 | X28: 8722 | Y28: 0 | AB28: ※月初の月曜まで（例：6/1）は前月シートの最終週に含まれます
A29: 46134 | B29: =MID("日月火水木金土",WEEKDAY(A29),1) -> 水 | C29: 300000 | D29: =SUM($C$8:C29) -> 7200000 | E29: 72040 | F29: 106250 | G29: -16983 | H29: =IF(COUNT(E29:G29)=0,"",SUM(E29:G29)) -> 161307 | I29: =IF(H29="","",SUM($H$8:H29)) -> 3812585 | J29: =IF(H29="","",IFERROR(H29/C29,"")) -> 0.53769 | K29: =IF(I29="","",IFERROR(I29/D29,"")) -> 0.52952569 | L29: =IF(I29="","",IF(D29=0,"",I29-D29)) -> -3387415 | M29: =IF(H29="","—",IF(D29=0,"予算未入力",IF(I29>=D29,"◎ ペース内","▲ 遅れ"))) -> ▲ 遅れ | N29: 6 | O29: 10 | P29: 23 | Q29: 6 | R29: 11 | S29: =IFERROR(N29/P29,"") -> 0.26086957 | T29: =IFERROR(H29/N29,"") -> 26884.5 | U29: =IFERROR(O29/N29,"") -> 1.6666667 | V29: =IFERROR(Q29/P29,"") -> 0.26086957 | X29: 8794 | Y29: 0
A30: 46135 | B30: =MID("日月火水木金土",WEEKDAY(A30),1) -> 木 | C30: 300000 | D30: =SUM($C$8:C30) -> 7500000 | E30: 97440 | F30: 62420 | G30: 41186 | H30: =IF(COUNT(E30:G30)=0,"",SUM(E30:G30)) -> 201046 | I30: =IF(H30="","",SUM($H$8:H30)) -> 4013631 | J30: =IF(H30="","",IFERROR(H30/C30,"")) -> 0.67015333 | K30: =IF(I30="","",IFERROR(I30/D30,"")) -> 0.5351508 | L30: =IF(I30="","",IF(D30=0,"",I30-D30)) -> -3486369 | M30: =IF(H30="","—",IF(D30=0,"予算未入力",IF(I30>=D30,"◎ ペース内","▲ 遅れ"))) -> ▲ 遅れ | N30: 10 | O30: 11 | P30: 30 | Q30: 12 | R30: 21 | S30: =IFERROR(N30/P30,"") -> 0.33333333 | T30: =IFERROR(H30/N30,"") -> 20104.6 | U30: =IFERROR(O30/N30,"") -> 1.1 | V30: =IFERROR(Q30/P30,"") -> 0.4 | X30: 8853 | Y30: 0
A31: 46136 | B31: =MID("日月火水木金土",WEEKDAY(A31),1) -> 金 | C31: 300000 | D31: =SUM($C$8:C31) -> 7800000 | E31: 21610 | F31: 232510 | G31: -24407 | H31: =IF(COUNT(E31:G31)=0,"",SUM(E31:G31)) -> 229713 | I31: =IF(H31="","",SUM($H$8:H31)) -> 4243344 | J31: =IF(H31="","",IFERROR(H31/C31,"")) -> 0.76571 | K31: =IF(I31="","",IFERROR(I31/D31,"")) -> 0.54401846 | L31: =IF(I31="","",IF(D31=0,"",I31-D31)) -> -3556656 | M31: =IF(H31="","—",IF(D31=0,"予算未入力",IF(I31>=D31,"◎ ペース内","▲ 遅れ"))) -> ▲ 遅れ | N31: 11 | O31: 13 | P31: 34 | Q31: 14 | R31: 25 | S31: =IFERROR(N31/P31,"") -> 0.32352941 | T31: =IFERROR(H31/N31,"") -> 20883 | U31: =IFERROR(O31/N31,"") -> 1.1818182 | V31: =IFERROR(Q31/P31,"") -> 0.41176471 | X31: 8942 | Y31: 0
A32: 46137 | B32: =MID("日月火水木金土",WEEKDAY(A32),1) -> 土 | C32: 600000 | D32: =SUM($C$8:C32) -> 8400000 | E32: 121140 | F32: 158980 | G32: 83003 | H32: =IF(COUNT(E32:G32)=0,"",SUM(E32:G32)) -> 363123 | I32: =IF(H32="","",SUM($H$8:H32)) -> 4606467 | J32: =IF(H32="","",IFERROR(H32/C32,"")) -> 0.605205 | K32: =IF(I32="","",IFERROR(I32/D32,"")) -> 0.54838893 | L32: =IF(I32="","",IF(D32=0,"",I32-D32)) -> -3793533 | M32: =IF(H32="","—",IF(D32=0,"予算未入力",IF(I32>=D32,"◎ ペース内","▲ 遅れ"))) -> ▲ 遅れ | N32: 17 | O32: 18 | P32: 63 | Q32: 23 | R32: 40 | S32: =IFERROR(N32/P32,"") -> 0.26984127 | T32: =IFERROR(H32/N32,"") -> 21360.176 | U32: =IFERROR(O32/N32,"") -> 1.0588235 | V32: =IFERROR(Q32/P32,"") -> 0.36507937 | X32: 8988 | Y32: 0
A33: 46138 | B33: =MID("日月火水木金土",WEEKDAY(A33),1) -> 日 | C33: 400000 | D33: =SUM($C$8:C33) -> 8800000 | E33: 147770 | F33: 324611 | G33: 31638 | H33: =IF(COUNT(E33:G33)=0,"",SUM(E33:G33)) -> 504019 | I33: =IF(H33="","",SUM($H$8:H33)) -> 5110486 | J33: =IF(H33="","",IFERROR(H33/C33,"")) -> 1.2600475 | K33: =IF(I33="","",IFERROR(I33/D33,"")) -> 0.58073705 | L33: =IF(I33="","",IF(D33=0,"",I33-D33)) -> -3689514 | M33: =IF(H33="","—",IF(D33=0,"予算未入力",IF(I33>=D33,"◎ ペース内","▲ 遅れ"))) -> ▲ 遅れ | N33: 24 | O33: 26 | P33: 39 | Q33: 23 | R33: 49 | S33: =IFERROR(N33/P33,"") -> 0.61538462 | T33: =IFERROR(H33/N33,"") -> 21000.792 | U33: =IFERROR(O33/N33,"") -> 1.0833333 | V33: =IFERROR(Q33/P33,"") -> 0.58974359 | X33: 9035 | Y33: 0
A34: 46139 | B34: =MID("日月火水木金土",WEEKDAY(A34),1) -> 月 | C34: 300000 | D34: =SUM($C$8:C34) -> 9100000 | E34: 36900 | F34: 75830 | G34: -10822 | H34: =IF(COUNT(E34:G34)=0,"",SUM(E34:G34)) -> 101908 | I34: =IF(H34="","",SUM($H$8:H34)) -> 5212394 | J34: =IF(H34="","",IFERROR(H34/C34,"")) -> 0.33969333 | K34: =IF(I34="","",IFERROR(I34/D34,"")) -> 0.57279055 | L34: =IF(I34="","",IF(D34=0,"",I34-D34)) -> -3887606 | M34: =IF(H34="","—",IF(D34=0,"予算未入力",IF(I34>=D34,"◎ ペース内","▲ 遅れ"))) -> ▲ 遅れ | N34: 6 | O34: 6 | P34: 28 | Q34: 9 | R34: 18 | S34: =IFERROR(N34/P34,"") -> 0.21428571 | T34: =IFERROR(H34/N34,"") -> 16984.667 | U34: =IFERROR(O34/N34,"") -> 1 | V34: =IFERROR(Q34/P34,"") -> 0.32142857 | X34: 9033 | Y34: 0
A35: 46140 | B35: =MID("日月火水木金土",WEEKDAY(A35),1) -> 火 | C35: 300000 | D35: =SUM($C$8:C35) -> 9400000 | E35: 33050 | F35: 131650 | G35: 43246 | H35: =IF(COUNT(E35:G35)=0,"",SUM(E35:G35)) -> 207946 | I35: =IF(H35="","",SUM($H$8:H35)) -> 5420340 | J35: =IF(H35="","",IFERROR(H35/C35,"")) -> 0.69315333 | K35: =IF(I35="","",IFERROR(I35/D35,"")) -> 0.57663191 | L35: =IF(I35="","",IF(D35=0,"",I35-D35)) -> -3979660 | M35: =IF(H35="","—",IF(D35=0,"予算未入力",IF(I35>=D35,"◎ ペース内","▲ 遅れ"))) -> ▲ 遅れ | N35: 11 | O35: 11 | P35: 26 | Q35: 10 | R35: 16 | S35: =IFERROR(N35/P35,"") -> 0.42307692 | T35: =IFERROR(H35/N35,"") -> 18904.182 | U35: =IFERROR(O35/N35,"") -> 1 | V35: =IFERROR(Q35/P35,"") -> 0.38461538 | X35: 9029 | Y35: 0
A36: 46141 | B36: =MID("日月火水木金土",WEEKDAY(A36),1) -> 水 | C36: 500000 | D36: =SUM($C$8:C36) -> 9900000 | E36: 90900 | F36: 402270 | G36: 22116 | H36: =IF(COUNT(E36:G36)=0,"",SUM(E36:G36)) -> 515286 | I36: =IF(H36="","",SUM($H$8:H36)) -> 5935626 | J36: =IF(H36="","",IFERROR(H36/C36,"")) -> 1.030572 | K36: =IF(I36="","",IFERROR(I36/D36,"")) -> 0.59955818 | L36: =IF(I36="","",IF(D36=0,"",I36-D36)) -> -3964374 | M36: =IF(H36="","—",IF(D36=0,"予算未入力",IF(I36>=D36,"◎ ペース内","▲ 遅れ"))) -> ▲ 遅れ | N36: 27 | O36: 27 | P36: 56 | Q36: 27 | R36: 51 | S36: =IFERROR(N36/P36,"") -> 0.48214286 | T36: =IFERROR(H36/N36,"") -> 19084.667 | U36: =IFERROR(O36/N36,"") -> 1 | V36: =IFERROR(Q36/P36,"") -> 0.48214286 | X36: 9024 | Y36: 2510
A37: 46142 | B37: =MID("日月火水木金土",WEEKDAY(A37),1) -> 木 | C37: 300000 | D37: =SUM($C$8:C37) -> 10200000 | E37: 276802 | F37: 92120 | G37: 27266 | H37: =IF(COUNT(E37:G37)=0,"",SUM(E37:G37)) -> 396188 | I37: =IF(H37="","",SUM($H$8:H37)) -> 6331814 | J37: =IF(H37="","",IFERROR(H37/C37,"")) -> 1.3206267 | K37: =IF(I37="","",IFERROR(I37/D37,"")) -> 0.62076608 | L37: =IF(I37="","",IF(D37=0,"",I37-D37)) -> -3868186 | M37: =IF(H37="","—",IF(D37=0,"予算未入力",IF(I37>=D37,"◎ ペース内","▲ 遅れ"))) -> ▲ 遅れ | N37: 18 | O37: 22 | P37: 43 | Q37: 16 | R37: 28 | S37: =IFERROR(N37/P37,"") -> 0.41860465 | T37: =IFERROR(H37/N37,"") -> 22010.444 | U37: =IFERROR(O37/N37,"") -> 1.2222222 | V37: =IFERROR(Q37/P37,"") -> 0.37209302 | X37: 9024 | Y37: 0
A38: 月計 | C38: =SUM(C8:C37) -> 10200000 | D38: =C38 -> 10200000 | E38: =SUM(E8:E37) -> 2044589 | F38: =SUM(F8:F37) -> 3884056 | G38: =SUM(G8:G37) -> 403169 | H38: =SUM(H8:H37) -> 6331814 | I38: =H38 -> 6331814 | J38: =IFERROR(H38/C38,"") -> 0.62076608 | K38: =IFERROR(H38/C38,"") -> 0.62076608 | L38: =H38-C38 -> -3868186 | N38: =SUM(N8:N37) -> 306 | O38: =SUM(O8:O37) -> 338 | P38: =SUM(P8:P37) -> 938 | Q38: =SUM(Q8:Q37) -> 446 | R38: =SUM(R8:R37) -> 407 | S38: =IFERROR(N38/P38,"") -> 0.32622601 | T38: =IFERROR(H38/N38,"") -> 20692.203 | U38: =IFERROR(O38/N38,"") -> 1.1045752 | V38: =IFERROR(Q38/P38,"") -> 0.47547974 | W38: =SUM(W8:W37) -> 0 | X38: =IFERROR(LOOKUP(9.99E+307,X8:X37),"") -> 9024 | Y38: =SUM(Y8:Y37) -> 2510 | Z38: フォロワーは月末値

Sheet 2026年05月
A1: 2026年5月 名古屋店 日別売上管理
A2: 青字＋薄黄色のセルが入力欄。白セルは数式なので触らないでください。単位：円
A3: 月間予算 | C3: 当月実績 | E3: 達成率 | G3: 営業日数(/31日) | I3: 残り必要額 | K3: 残り必要日商
A4: =IF('設定'!$B$9="",SUM(C8:C38),'設定'!$B$9) -> 6625036 | C4: =SUM(H8:H38) -> 6030095 | E4: =IFERROR(C4/A4,0) -> 0.91019807 | G4: =COUNTIF(H8:H38,">0") -> 31 | I4: =A4-C4 -> 594941 | K4: =IF((31-G4)>0,(A4-C4)/(31-G4),0) -> 0
A5: 日次予算合計 | C5: 着地見込 | E5: 決定率 | G5: 客単価 | I5: セット率 | K5: 試着率
A6: =SUM(C8:C38) -> 11200000 | C6: =IFERROR(C4/G4*31,0) -> 6030095 | E6: =IFERROR(N39/P39,0) -> 0.27014218 | G6: =IFERROR(H39/N39,0) -> 21158.228 | I6: =IFERROR(O39/N39,0) -> 1.0982456 | K6: =IFERROR(Q39/P39,0) -> 0.33649289
A7: 日付 | B7: 曜 | C7: 日次予算 | D7: 累計予算 | E7: 現金 | F7: クレジット | G7: 内訳差額 (要確認) | H7: 実績合計 | I7: 累計実績 | J7: 日次達成 | K7: 累計達成 | L7: 累計予実差 | M7: ペース | N7: 購入人数 | O7: 販売点数 | P7: 来客数 | Q7: 試着組数 | R7: 試着個数 | S7: 決定率 | T7: 客単価 | U7: セット率 | V7: 試着率 | W7: クロス クーポン | X7: インスタ フォロワー | Y7: 経費 | Z7: メモ | AB7: 曜日 | AC7: 平均日商 | AD7: 日数 | AE7: 決定率 | AF7: 客単価
A8: 46143 | B8: =MID("日月火水木金土",WEEKDAY(A8),1) -> 金 | C8: 300000 | D8: =SUM($C$8:C8) -> 300000 | E8: 71430 | F8: 52020 | G8: 48010 | H8: =IF(COUNT(E8:G8)=0,"",SUM(E8:G8)) -> 171460 | I8: =IF(H8="","",SUM($H$8:H8)) -> 171460 | J8: =IF(H8="","",IFERROR(H8/C8,"")) -> 0.57153333 | K8: =IF(I8="","",IFERROR(I8/D8,"")) -> 0.57153333 | L8: =IF(I8="","",IF(D8=0,"",I8-D8)) -> -128540 | M8: =IF(H8="","—",IF(D8=0,"予算未入力",IF(I8>=D8,"◎ ペース内","▲ 遅れ"))) -> ▲ 遅れ | N8: 7 | O8: 7 | P8: 38 | Q8: 7 | R8: 12 | S8: =IFERROR(N8/P8,"") -> 0.18421053 | T8: =IFERROR(H8/N8,"") -> 24494.286 | U8: =IFERROR(O8/N8,"") -> 1 | V8: =IFERROR(Q8/P8,"") -> 0.18421053 | X8: 9026 | Y8: 0 | AB8: 月 | AC8: =IFERROR(AVERAGEIFS($H$8:$H$38,$B$8:$B$38,AB8,$H$8:$H$38,">0"),0) -> 247403.5 | AD8: =COUNTIFS($B$8:$B$38,AB8,$H$8:$H$38,">0") -> 4 | AE8: =IFERROR(SUMIF($B$8:$B$38,AB8,$N$8:$N$38)/SUMIF($B$8:$B$38,AB8,$P$8:$P$38),0) -> 0.32432432 | AF8: =IFERROR(SUMIF($B$8:$B$38,AB8,$H$8:$H$38)/SUMIF($B$8:$B$38,AB8,$N$8:$N$38),0) -> 20616.958
A9: 46144 | B9: =MID("日月火水木金土",WEEKDAY(A9),1) -> 土 | C9: 800000 | D9: =SUM($C$8:C9) -> 1100000 | E9: 69730 | F9: 174859 | G9: 2574 | H9: =IF(COUNT(E9:G9)=0,"",SUM(E9:G9)) -> 247163 | I9: =IF(H9="","",SUM($H$8:H9)) -> 418623 | J9: =IF(H9="","",IFERROR(H9/C9,"")) -> 0.30895375 | K9: =IF(I9="","",IFERROR(I9/D9,"")) -> 0.38056636 | L9: =IF(I9="","",IF(D9=0,"",I9-D9)) -> -681377 | M9: =IF(H9="","—",IF(D9=0,"予算未入力",IF(I9>=D9,"◎ ペース内","▲ 遅れ"))) -> ▲ 遅れ | N9: 12 | O9: 13 | P9: 50 | Q9: 19 | R9: 30 | S9: =IFERROR(N9/P9,"") -> 0.24 | T9: =IFERROR(H9/N9,"") -> 20596.917 | U9: =IFERROR(O9/N9,"") -> 1.0833333 | V9: =IFERROR(Q9/P9,"") -> 0.38 | X9: 9026 | Y9: 0 | AB9: 火 | AC9: =IFERROR(AVERAGEIFS($H$8:$H$38,$B$8:$B$38,AB9,$H$8:$H$38,">0"),0) -> 157339.25 | AD9: =COUNTIFS($B$8:$B$38,AB9,$H$8:$H$38,">0") -> 4 | AE9: =IFERROR(SUMIF($B$8:$B$38,AB9,$N$8:$N$38)/SUMIF($B$8:$B$38,AB9,$P$8:$P$38),0) -> 0.2265625 | AF9: =IFERROR(SUMIF($B$8:$B$38,AB9,$H$8:$H$38)/SUMIF($B$8:$B$38,AB9,$N$8:$N$38),0) -> 21701.966
A10: 46145 | B10: =MID("日月火水木金土",WEEKDAY(A10),1) -> 日 | C10: 800000 | D10: =SUM($C$8:C10) -> 1900000 | E10: 90828 | F10: 340770 | G10: 18135 | H10: =IF(COUNT(E10:G10)=0,"",SUM(E10:G10)) -> 449733 | I10: =IF(H10="","",SUM($H$8:H10)) -> 868356 | J10: =IF(H10="","",IFERROR(H10/C10,"")) -> 0.56216625 | K10: =IF(I10="","",IFERROR(I10/D10,"")) -> 0.45702947 | L10: =IF(I10="","",IF(D10=0,"",I10-D10)) -> -1031644 | M10: =IF(H10="","—",IF(D10=0,"予算未入力",IF(I10>=D10,"◎ ペース内","▲ 遅れ"))) -> ▲ 遅れ | N10: 23 | O10: 25 | P10: 43 | Q10: 24 | R10: 52 | S10: =IFERROR(N10/P10,"") -> 0.53488372 | T10: =IFERROR(H10/N10,"") -> 19553.609 | U10: =IFERROR(O10/N10,"") -> 1.0869565 | V10: =IFERROR(Q10/P10,"") -> 0.55813953 | X10: 9026 | Y10: 0 | AB10: 水 | AC10: =IFERROR(AVERAGEIFS($H$8:$H$38,$B$8:$B$38,AB10,$H$8:$H$38,">0"),0) -> 150081.25 | AD10: =COUNTIFS($B$8:$B$38,AB10,$H$8:$H$38,">0") -> 4 | AE10: =IFERROR(SUMIF($B$8:$B$38,AB10,$N$8:$N$38)/SUMIF($B$8:$B$38,AB10,$P$8:$P$38),0) -> 0.23853211 | AF10: =IFERROR(SUMIF($B$8:$B$38,AB10,$H$8:$H$38)/SUMIF($B$8:$B$38,AB10,$N$8:$N$38),0) -> 23089.423
A11: 46146 | B11: =MID("日月火水木金土",WEEKDAY(A11),1) -> 月 | C11: 800000 | D11: =SUM($C$8:C11) -> 2700000 | E11: 191540 | F11: 326020 | G11: 54669 | H11: =IF(COUNT(E11:G11)=0,"",SUM(E11:G11)) -> 572229 | I11: =IF(H11="","",SUM($H$8:H11)) -> 1440585 | J11: =IF(H11="","",IFERROR(H11/C11,"")) -> 0.71528625 | K11: =IF(I11="","",IFERROR(I11/D11,"")) -> 0.53355 | L11: =IF(I11="","",IF(D11=0,"",I11-D11)) -> -1259415 | M11: =IF(H11="","—",IF(D11=0,"予算未入力",IF(I11>=D11,"◎ ペース内","▲ 遅れ"))) -> ▲ 遅れ | N11: 27 | O11: 29 | P11: 66 | Q11: 30 | R11: 44 | S11: =IFERROR(N11/P11,"") -> 0.40909091 | T11: =IFERROR(H11/N11,"") -> 21193.667 | U11: =IFERROR(O11/N11,"") -> 1.0740741 | V11: =IFERROR(Q11/P11,"") -> 0.45454545 | X11: 9029 | Y11: 0 | AB11: 木 | AC11: =IFERROR(AVERAGEIFS($H$8:$H$38,$B$8:$B$38,AB11,$H$8:$H$38,">0"),0) -> 93831.25 | AD11: =COUNTIFS($B$8:$B$38,AB11,$H$8:$H$38,">0") -> 4 | AE11: =IFERROR(SUMIF($B$8:$B$38,AB11,$N$8:$N$38)/SUMIF($B$8:$B$38,AB11,$P$8:$P$38),0) -> 0.27941176 | AF11: =IFERROR(SUMIF($B$8:$B$38,AB11,$H$8:$H$38)/SUMIF($B$8:$B$38,AB11,$N$8:$N$38),0) -> 19753.947
A12: 46147 | B12: =MID("日月火水木金土",WEEKDAY(A12),1) -> 火 | C12: 800000 | D12: =SUM($C$8:C12) -> 3500000 | E12: 24310 | F12: 170369 | G12: 26553 | H12: =IF(COUNT(E12:G12)=0,"",SUM(E12:G12)) -> 221232 | I12: =IF(H12="","",SUM($H$8:H12)) -> 1661817 | J12: =IF(H12="","",IFERROR(H12/C12,"")) -> 0.27654 | K12: =IF(I12="","",IFERROR(I12/D12,"")) -> 0.47480486 | L12: =IF(I12="","",IF(D12=0,"",I12-D12)) -> -1838183 | M12: =IF(H12="","—",IF(D12=0,"予算未入力",IF(I12>=D12,"◎ ペース内","▲ 遅れ"))) -> ▲ 遅れ | N12: 10 | O12: 12 | P12: 65 | Q12: 14 | R12: 27 | S12: =IFERROR(N12/P12,"") -> 0.15384615 | T12: =IFERROR(H12/N12,"") -> 22123.2 | U12: =IFERROR(O12/N12,"") -> 1.2 | V12: =IFERROR(Q12/P12,"") -> 0.21538462 | X12: 9024 | Y12: 0 | AB12: 金 | AC12: =IFERROR(AVERAGEIFS($H$8:$H$38,$B$8:$B$38,AB12,$H$8:$H$38,">0"),0) -> 114059.4 | AD12: =COUNTIFS($B$8:$B$38,AB12,$H$8:$H$38,">0") -> 5 | AE12: =IFERROR(SUMIF($B$8:$B$38,AB12,$N$8:$N$38)/SUMIF($B$8:$B$38,AB12,$P$8:$P$38),0) -> 0.19852941 | AF12: =IFERROR(SUMIF($B$8:$B$38,AB12,$H$8:$H$38)/SUMIF($B$8:$B$38,AB12,$N$8:$N$38),0) -> 21122.111
A13: 46148 | B13: =MID("日月火水木金土",WEEKDAY(A13),1) -> 水 | C13: 700000 | D13: =SUM($C$8:C13) -> 4200000 | E13: 143150 | F13: 145510 | G13: -7852 | H13: =IF(COUNT(E13:G13)=0,"",SUM(E13:G13)) -> 280808 | I13: =IF(H13="","",SUM($H$8:H13)) -> 1942625 | J13: =IF(H13="","",IFERROR(H13/C13,"")) -> 0.40115429 | K13: =IF(I13="","",IFERROR(I13/D13,"")) -> 0.46252976 | L13: =IF(I13="","",IF(D13=0,"",I13-D13)) -> -2257375 | M13: =IF(H13="","—",IF(D13=0,"予算未入力",IF(I13>=D13,"◎ ペース内","▲ 遅れ"))) -> ▲ 遅れ | N13: 12 | O13: 14 | P13: 47 | Q13: 14 | R13: 17 | S13: =IFERROR(N13/P13,"") -> 0.25531915 | T13: =IFERROR(H13/N13,"") -> 23400.667 | U13: =IFERROR(O13/N13,"") -> 1.1666667 | V13: =IFERROR(Q13/P13,"") -> 0.29787234 | X13: 9023 | Y13: 0 | AB13: 土 | AC13: =IFERROR(AVERAGEIFS($H$8:$H$38,$B$8:$B$38,AB13,$H$8:$H$38,">0"),0) -> 266354 | AD13: =COUNTIFS($B$8:$B$38,AB13,$H$8:$H$38,">0") -> 5 | AE13: =IFERROR(SUMIF($B$8:$B$38,AB13,$N$8:$N$38)/SUMIF($B$8:$B$38,AB13,$P$8:$P$38),0) -> 0.24313725 | AF13: =IFERROR(SUMIF($B$8:$B$38,AB13,$H$8:$H$38)/SUMIF($B$8:$B$38,AB13,$N$8:$N$38),0) -> 21480.161
A14: 46149 | B14: =MID("日月火水木金土",WEEKDAY(A14),1) -> 木 | C14: 200000 | D14: =SUM($C$8:C14) -> 4400000 | E14: 23920 | F14: 102779 | G14: -11994 | H14: =IF(COUNT(E14:G14)=0,"",SUM(E14:G14)) -> 114705 | I14: =IF(H14="","",SUM($H$8:H14)) -> 2057330 | J14: =IF(H14="","",IFERROR(H14/C14,"")) -> 0.573525 | K14: =IF(I14="","",IFERROR(I14/D14,"")) -> 0.467575 | L14: =IF(I14="","",IF(D14=0,"",I14-D14)) -> -2342670 | M14: =IF(H14="","—",IF(D14=0,"予算未入力",IF(I14>=D14,"◎ ペース内","▲ 遅れ"))) -> ▲ 遅れ | N14: 6 | O14: 7 | P14: 18 | Q14: 5 | R14: 10 | S14: =IFERROR(N14/P14,"") -> 0.33333333 | T14: =IFERROR(H14/N14,"") -> 19117.5 | U14: =IFERROR(O14/N14,"") -> 1.1666667 | V14: =IFERROR(Q14/P14,"") -> 0.27777778 | X14: 9013 | Y14: 0 | AB14: 日 | AC14: =IFERROR(AVERAGEIFS($H$8:$H$38,$B$8:$B$38,AB14,$H$8:$H$38,">0"),0) -> 306681.4 | AD14: =COUNTIFS($B$8:$B$38,AB14,$H$8:$H$38,">0") -> 5 | AE14: =IFERROR(SUMIF($B$8:$B$38,AB14,$N$8:$N$38)/SUMIF($B$8:$B$38,AB14,$P$8:$P$38),0) -> 0.3507109 | AF14: =IFERROR(SUMIF($B$8:$B$38,AB14,$H$8:$H$38)/SUMIF($B$8:$B$38,AB14,$N$8:$N$38),0) -> 20721.716
A15: 46150 | B15: =MID("日月火水木金土",WEEKDAY(A15),1) -> 金 | C15: 200000 | D15: =SUM($C$8:C15) -> 4600000 | E15: 63620 | F15: 0 | G15: -6116 | H15: =IF(COUNT(E15:G15)=0,"",SUM(E15:G15)) -> 57504 | I15: =IF(H15="","",SUM($H$8:H15)) -> 2114834 | J15: =IF(H15="","",IFERROR(H15/C15,"")) -> 0.28752 | K15: =IF(I15="","",IFERROR(I15/D15,"")) -> 0.45974652 | L15: =IF(I15="","",IF(D15=0,"",I15-D15)) -> -2485166 | M15: =IF(H15="","—",IF(D15=0,"予算未入力",IF(I15>=D15,"◎ ペース内","▲ 遅れ"))) -> ▲ 遅れ | N15: 3 | O15: 3 | P15: 26 | Q15: 3 | R15: 5 | S15: =IFERROR(N15/P15,"") -> 0.11538462 | T15: =IFERROR(H15/N15,"") -> 19168 | U15: =IFERROR(O15/N15,"") -> 1 | V15: =IFERROR(Q15/P15,"") -> 0.11538462 | X15: 9013 | Y15: 0
A16: 46151 | B16: =MID("日月火水木金土",WEEKDAY(A16),1) -> 土 | C16: 500000 | D16: =SUM($C$8:C16) -> 5100000 | E16: 43610 | F16: 83370 | G16: 9624 | H16: =IF(COUNT(E16:G16)=0,"",SUM(E16:G16)) -> 136604 | I16: =IF(H16="","",SUM($H$8:H16)) -> 2251438 | J16: =IF(H16="","",IFERROR(H16/C16,"")) -> 0.273208 | K16: =IF(I16="","",IFERROR(I16/D16,"")) -> 0.44145843 | L16: =IF(I16="","",IF(D16=0,"",I16-D16)) -> -2848562 | M16: =IF(H16="","—",IF(D16=0,"予算未入力",IF(I16>=D16,"◎ ペース内","▲ 遅れ"))) -> ▲ 遅れ | N16: 6 | O16: 7 | P16: 41 | Q16: 11 | R16: 15 | S16: =IFERROR(N16/P16,"") -> 0.14634146 | T16: =IFERROR(H16/N16,"") -> 22767.333 | U16: =IFERROR(O16/N16,"") -> 1.1666667 | V16: =IFERROR(Q16/P16,"") -> 0.26829268 | X16: 9010 | Y16: 0 | AB16: ※実績入力後に曜日別の傾向が出ます
A17: 46152 | B17: =MID("日月火水木金土",WEEKDAY(A17),1) -> 日 | C17: 400000 | D17: =SUM($C$8:C17) -> 5500000 | E17: 22000 | F17: 206599 | G17: -21789 | H17: =IF(COUNT(E17:G17)=0,"",SUM(E17:G17)) -> 206810 | I17: =IF(H17="","",SUM($H$8:H17)) -> 2458248 | J17: =IF(H17="","",IFERROR(H17/C17,"")) -> 0.517025 | K17: =IF(I17="","",IFERROR(I17/D17,"")) -> 0.44695418 | L17: =IF(I17="","",IF(D17=0,"",I17-D17)) -> -3041752 | M17: =IF(H17="","—",IF(D17=0,"予算未入力",IF(I17>=D17,"◎ ペース内","▲ 遅れ"))) -> ▲ 遅れ | N17: 9 | O17: 10 | P17: 41 | Q17: 10 | R17: 16 | S17: =IFERROR(N17/P17,"") -> 0.2195122 | T17: =IFERROR(H17/N17,"") -> 22978.889 | U17: =IFERROR(O17/N17,"") -> 1.1111111 | V17: =IFERROR(Q17/P17,"") -> 0.24390244 | X17: 9004 | Y17: 0
A18: 46153 | B18: =MID("日月火水木金土",WEEKDAY(A18),1) -> 月 | C18: 200000 | D18: =SUM($C$8:C18) -> 5700000 | E18: 29470 | F18: 85597 | G18: -11200 | H18: =IF(COUNT(E18:G18)=0,"",SUM(E18:G18)) -> 103867 | I18: =IF(H18="","",SUM($H$8:H18)) -> 2562115 | J18: =IF(H18="","",IFERROR(H18/C18,"")) -> 0.519335 | K18: =IF(I18="","",IFERROR(I18/D18,"")) -> 0.44949386 | L18: =IF(I18="","",IF(D18=0,"",I18-D18)) -> -3137885 | M18: =IF(H18="","—",IF(D18=0,"予算未入力",IF(I18>=D18,"◎ ペース内","▲ 遅れ"))) -> ▲ 遅れ | N18: 6 | O18: 6 | P18: 28 | Q18: 15 | R18: 26 | S18: =IFERROR(N18/P18,"") -> 0.21428571 | T18: =IFERROR(H18/N18,"") -> 17311.167 | U18: =IFERROR(O18/N18,"") -> 1 | V18: =IFERROR(Q18/P18,"") -> 0.53571429 | X18: 9002 | Y18: 0 | AB18: ■ 週次サマリー（火曜〜翌月曜） | AI18: 第1火曜 | AJ18: =$A$8+MOD(2-WEEKDAY($A$8,2)+7,7) -> 46147
A19: 46154 | B19: =MID("日月火水木金土",WEEKDAY(A19),1) -> 火 | C19: 200000 | D19: =SUM($C$8:C19) -> 5900000 | E19: 41410 | F19: 85140 | G19: 1456 | H19: =IF(COUNT(E19:G19)=0,"",SUM(E19:G19)) -> 128006 | I19: =IF(H19="","",SUM($H$8:H19)) -> 2690121 | J19: =IF(H19="","",IFERROR(H19/C19,"")) -> 0.64003 | K19: =IF(I19="","",IFERROR(I19/D19,"")) -> 0.45595271 | L19: =IF(I19="","",IF(D19=0,"",I19-D19)) -> -3209879 | M19: =IF(H19="","—",IF(D19=0,"予算未入力",IF(I19>=D19,"◎ ペース内","▲ 遅れ"))) -> ▲ 遅れ | N19: 6 | O19: 6 | P19: 20 | Q19: 6 | R19: 13 | S19: =IFERROR(N19/P19,"") -> 0.3 | T19: =IFERROR(H19/N19,"") -> 21334.333 | U19: =IFERROR(O19/N19,"") -> 1 | V19: =IFERROR(Q19/P19,"") -> 0.3 | X19: 9007 | Y19: 0 | AB19: 週 | AC19: 期間 | AD19: 売上 | AE19: 決定率 | AF19: 客単価 | AG19: セット率 | AH19: 試着率
A20: 46155 | B20: =MID("日月火水木金土",WEEKDAY(A20),1) -> 水 | C20: 200000 | D20: =SUM($C$8:C20) -> 6100000 | E20: 74630 | F20: 91230 | G20: -15853 | H20: =IF(COUNT(E20:G20)=0,"",SUM(E20:G20)) -> 150007 | I20: =IF(H20="","",SUM($H$8:H20)) -> 2840128 | J20: =IF(H20="","",IFERROR(H20/C20,"")) -> 0.750035 | K20: =IF(I20="","",IFERROR(I20/D20,"")) -> 0.46559475 | L20: =IF(I20="","",IF(D20=0,"",I20-D20)) -> -3259872 | M20: =IF(H20="","—",IF(D20=0,"予算未入力",IF(I20>=D20,"◎ ペース内","▲ 遅れ"))) -> ▲ 遅れ | N20: 7 | O20: 7 | P20: 20 | Q20: 7 | R20: 17 | S20: =IFERROR(N20/P20,"") -> 0.35 | T20: =IFERROR(H20/N20,"") -> 21429.571 | U20: =IFERROR(O20/N20,"") -> 1 | V20: =IFERROR(Q20/P20,"") -> 0.35 | X20: 9002 | Y20: 0 | AB20: 1 | AC20: =IF($AJ$18+7*(1-1)>$A$38,"",TEXT($AJ$18+7*(1-1),"m/d")&"-"&TEXT($AJ$18+7*(1-1)+6,"m/d")) -> 5/5-5/11 | AD20: =IF($AC20="","",(SUMIFS($H$8:$H$38,$A$8:$A$38,">="&$AJ$18+7*(1-1),$A$8:$A$38,"<="&$AJ$18+7*(1-1)+6)+SUMIFS('2026年06月'!$H$8:$H$37,'2026年06月'!$A$8:$A$37,">="&$AJ$18+7*(1-1),'2026年06月'!$A$8:$A$37,"<="&$AJ$18+7*(1-1)+6))) -> 1121530 | AE20: =IF($AC20="","",IFERROR((SUMIFS($N$8:$N$38,$A$8:$A$38,">="&$AJ$18+7*(1-1),$A$8:$A$38,"<="&$AJ$18+7*(1-1)+6)+SUMIFS('2026年06月'!$N$8:$N$37,'2026年06月'!$A$8:$A$37,">="&$AJ$18+7*(1-1),'2026年06月'!$A$8:$A$37,"<="&$AJ$18+7*(1-1)+6))/(SUMIFS($P$8:$P$38,$A$8:$A$38,">="&$AJ$18+7*(1-1),$A$8:$A$38,"<="&$AJ$18+7*(1-1)+6)+SUMIFS('2026年06月'!$P$8:$P$37,'2026年06月'!$A$8:$A$37,">="&$AJ$18+7*(1-1),'2026年06月'!$A$8:$A$37,"<="&$AJ$18+7*(1-1)+6)),"")) -> 0.19548872 | AF20: =IF($AC20="","",IFERROR((SUMIFS($H$8:$H$38,$A$8:$A$38,">="&$AJ$18+7*(1-1),$A$8:$A$38,"<="&$AJ$18+7*(1-1)+6)+SUMIFS('2026年06月'!$H$8:$H$37,'2026年06月'!$A$8:$A$37,">="&$AJ$18+7*(1-1),'2026年06月'!$A$8:$A$37,"<="&$AJ$18+7*(1-1)+6))/(SUMIFS($N$8:$N$38,$A$8:$A$38,">="&$AJ$18+7*(1-1),$A$8:$A$38,"<="&$AJ$18+7*(1-1)+6)+SUMIFS('2026年06月'!$N$8:$N$37,'2026年06月'!$A$8:$A$37,">="&$AJ$18+7*(1-1),'2026年06月'!$A$8:$A$37,"<="&$AJ$18+7*(1-1)+6)),"")) -> 21567.885 | AG20: =IF($AC20="","",IFERROR((SUMIFS($O$8:$O$38,$A$8:$A$38,">="&$AJ$18+7*(1-1),$A$8:$A$38,"<="&$AJ$18+7*(1-1)+6)+SUMIFS('2026年06月'!$O$8:$O$37,'2026年06月'!$A$8:$A$37,">="&$AJ$18+7*(1-1),'2026年06月'!$A$8:$A$37,"<="&$AJ$18+7*(1-1)+6))/(SUMIFS($N$8:$N$38,$A$8:$A$38,">="&$AJ$18+7*(1-1),$A$8:$A$38,"<="&$AJ$18+7*(1-1)+6)+SUMIFS('2026年06月'!$N$8:$N$37,'2026年06月'!$A$8:$A$37,">="&$AJ$18+7*(1-1),'2026年06月'!$A$8:$A$37,"<="&$AJ$18+7*(1-1)+6)),"")) -> 1.1346154 | AH20: =IF($AC20="","",IFERROR((SUMIFS($Q$8:$Q$38,$A$8:$A$38,">="&$AJ$18+7*(1-1),$A$8:$A$38,"<="&$AJ$18+7*(1-1)+6)+SUMIFS('2026年06月'!$Q$8:$Q$37,'2026年06月'!$A$8:$A$37,">="&$AJ$18+7*(1-1),'2026年06月'!$A$8:$A$37,"<="&$AJ$18+7*(1-1)+6))/(SUMIFS($P$8:$P$38,$A$8:$A$38,">="&$AJ$18+7*(1-1),$A$8:$A$38,"<="&$AJ$18+7*(1-1)+6)+SUMIFS('2026年06月'!$P$8:$P$37,'2026年06月'!$A$8:$A$37,">="&$AJ$18+7*(1-1),'2026年06月'!$A$8:$A$37,"<="&$AJ$18+7*(1-1)+6)),"")) -> 0.27067669
A21: 46156 | B21: =MID("日月火水木金土",WEEKDAY(A21),1) -> 木 | C21: 200000 | D21: =SUM($C$8:C21) -> 6300000 | E21: 23810 | F21: 47900 | G21: 12794 | H21: =IF(COUNT(E21:G21)=0,"",SUM(E21:G21)) -> 84504 | I21: =IF(H21="","",SUM($H$8:H21)) -> 2924632 | J21: =IF(H21="","",IFERROR(H21/C21,"")) -> 0.42252 | K21: =IF(I21="","",IFERROR(I21/D21,"")) -> 0.4642273 | L21: =IF(I21="","",IF(D21=0,"",I21-D21)) -> -3375368 | M21: =IF(H21="","—",IF(D21=0,"予算未入力",IF(I21>=D21,"◎ ペース内","▲ 遅れ"))) -> ▲ 遅れ | N21: 4 | O21: 4 | P21: 18 | Q21: 6 | R21: 11 | S21: =IFERROR(N21/P21,"") -> 0.22222222 | T21: =IFERROR(H21/N21,"") -> 21126 | U21: =IFERROR(O21/N21,"") -> 1 | V21: =IFERROR(Q21/P21,"") -> 0.33333333 | X21: 9000 | Y21: 0 | AB21: 2 | AC21: =IF($AJ$18+7*(2-1)>$A$38,"",TEXT($AJ$18+7*(2-1),"m/d")&"-"&TEXT($AJ$18+7*(2-1)+6,"m/d")) -> 5/12-5/18 | AD21: =IF($AC21="","",(SUMIFS($H$8:$H$38,$A$8:$A$38,">="&$AJ$18+7*(2-1),$A$8:$A$38,"<="&$AJ$18+7*(2-1)+6)+SUMIFS('2026年06月'!$H$8:$H$37,'2026年06月'!$A$8:$A$37,">="&$AJ$18+7*(2-1),'2026年06月'!$A$8:$A$37,"<="&$AJ$18+7*(2-1)+6))) -> 1165587 | AE21: =IF($AC21="","",IFERROR((SUMIFS($N$8:$N$38,$A$8:$A$38,">="&$AJ$18+7*(2-1),$A$8:$A$38,"<="&$AJ$18+7*(2-1)+6)+SUMIFS('2026年06月'!$N$8:$N$37,'2026年06月'!$A$8:$A$37,">="&$AJ$18+7*(2-1),'2026年06月'!$A$8:$A$37,"<="&$AJ$18+7*(2-1)+6))/(SUMIFS($P$8:$P$38,$A$8:$A$38,">="&$AJ$18+7*(2-1),$A$8:$A$38,"<="&$AJ$18+7*(2-1)+6)+SUMIFS('2026年06月'!$P$8:$P$37,'2026年06月'!$A$8:$A$37,">="&$AJ$18+7*(2-1),'2026年06月'!$A$8:$A$37,"<="&$AJ$18+7*(2-1)+6)),"")) -> 0.28717949 | AF21: =IF($AC21="","",IFERROR((SUMIFS($H$8:$H$38,$A$8:$A$38,">="&$AJ$18+7*(2-1),$A$8:$A$38,"<="&$AJ$18+7*(2-1)+6)+SUMIFS('2026年06月'!$H$8:$H$37,'2026年06月'!$A$8:$A$37,">="&$AJ$18+7*(2-1),'2026年06月'!$A$8:$A$37,"<="&$AJ$18+7*(2-1)+6))/(SUMIFS($N$8:$N$38,$A$8:$A$38,">="&$AJ$18+7*(2-1),$A$8:$A$38,"<="&$AJ$18+7*(2-1)+6)+SUMIFS('2026年06月'!$N$8:$N$37,'2026年06月'!$A$8:$A$37,">="&$AJ$18+7*(2-1),'2026年06月'!$A$8:$A$37,"<="&$AJ$18+7*(2-1)+6)),"")) -> 20814.054 | AG21: =IF($AC21="","",IFERROR((SUMIFS($O$8:$O$38,$A$8:$A$38,">="&$AJ$18+7*(2-1),$A$8:$A$38,"<="&$AJ$18+7*(2-1)+6)+SUMIFS('2026年06月'!$O$8:$O$37,'2026年06月'!$A$8:$A$37,">="&$AJ$18+7*(2-1),'2026年06月'!$A$8:$A$37,"<="&$AJ$18+7*(2-1)+6))/(SUMIFS($N$8:$N$38,$A$8:$A$38,">="&$AJ$18+7*(2-1),$A$8:$A$38,"<="&$AJ$18+7*(2-1)+6)+SUMIFS('2026年06月'!$N$8:$N$37,'2026年06月'!$A$8:$A$37,">="&$AJ$18+7*(2-1),'2026年06月'!$A$8:$A$37,"<="&$AJ$18+7*(2-1)+6)),"")) -> 1.0357143 | AH21: =IF($AC21="","",IFERROR((SUMIFS($Q$8:$Q$38,$A$8:$A$38,">="&$AJ$18+7*(2-1),$A$8:$A$38,"<="&$AJ$18+7*(2-1)+6)+SUMIFS('2026年06月'!$Q$8:$Q$37,'2026年06月'!$A$8:$A$37,">="&$AJ$18+7*(2-1),'2026年06月'!$A$8:$A$37,"<="&$AJ$18+7*(2-1)+6))/(SUMIFS($P$8:$P$38,$A$8:$A$38,">="&$AJ$18+7*(2-1),$A$8:$A$38,"<="&$AJ$18+7*(2-1)+6)+SUMIFS('2026年06月'!$P$8:$P$37,'2026年06月'!$A$8:$A$37,">="&$AJ$18+7*(2-1),'2026年06月'!$A$8:$A$37,"<="&$AJ$18+7*(2-1)+6)),"")) -> 0.32307692
A22: 46157 | B22: =MID("日月火水木金土",WEEKDAY(A22),1) -> 金 | C22: 200000 | D22: =SUM($C$8:C22) -> 6500000 | E22: 0 | F22: 104750 | G22: -10237 | H22: =IF(COUNT(E22:G22)=0,"",SUM(E22:G22)) -> 94513 | I22: =IF(H22="","",SUM($H$8:H22)) -> 3019145 | J22: =IF(H22="","",IFERROR(H22/C22,"")) -> 0.472565 | K22: =IF(I22="","",IFERROR(I22/D22,"")) -> 0.46448385 | L22: =IF(I22="","",IF(D22=0,"",I22-D22)) -> -3480855 | M22: =IF(H22="","—",IF(D22=0,"予算未入力",IF(I22>=D22,"◎ ペース内","▲ 遅れ"))) -> ▲ 遅れ | N22: 5 | O22: 5 | P22: 23 | Q22: 6 | R22: 8 | S22: =IFERROR(N22/P22,"") -> 0.2173913 | T22: =IFERROR(H22/N22,"") -> 18902.6 | U22: =IFERROR(O22/N22,"") -> 1 | V22: =IFERROR(Q22/P22,"") -> 0.26086957 | X22: 9002 | Y22: 0 | AB22: 3 | AC22: =IF($AJ$18+7*(3-1)>$A$38,"",TEXT($AJ$18+7*(3-1),"m/d")&"-"&TEXT($AJ$18+7*(3-1)+6,"m/d")) -> 5/19-5/25 | AD22: =IF($AC22="","",(SUMIFS($H$8:$H$38,$A$8:$A$38,">="&$AJ$18+7*(3-1),$A$8:$A$38,"<="&$AJ$18+7*(3-1)+6)+SUMIFS('2026年06月'!$H$8:$H$37,'2026年06月'!$A$8:$A$37,">="&$AJ$18+7*(3-1),'2026年06月'!$A$8:$A$37,"<="&$AJ$18+7*(3-1)+6))) -> 1182303 | AE22: =IF($AC22="","",IFERROR((SUMIFS($N$8:$N$38,$A$8:$A$38,">="&$AJ$18+7*(3-1),$A$8:$A$38,"<="&$AJ$18+7*(3-1)+6)+SUMIFS('2026年06月'!$N$8:$N$37,'2026年06月'!$A$8:$A$37,">="&$AJ$18+7*(3-1),'2026年06月'!$A$8:$A$37,"<="&$AJ$18+7*(3-1)+6))/(SUMIFS($P$8:$P$38,$A$8:$A$38,">="&$AJ$18+7*(3-1),$A$8:$A$38,"<="&$AJ$18+7*(3-1)+6)+SUMIFS('2026年06月'!$P$8:$P$37,'2026年06月'!$A$8:$A$37,">="&$AJ$18+7*(3-1),'2026年06月'!$A$8:$A$37,"<="&$AJ$18+7*(3-1)+6)),"")) -> 0.285 | AF22: =IF($AC22="","",IFERROR((SUMIFS($H$8:$H$38,$A$8:$A$38,">="&$AJ$18+7*(3-1),$A$8:$A$38,"<="&$AJ$18+7*(3-1)+6)+SUMIFS('2026年06月'!$H$8:$H$37,'2026年06月'!$A$8:$A$37,">="&$AJ$18+7*(3-1),'2026年06月'!$A$8:$A$37,"<="&$AJ$18+7*(3-1)+6))/(SUMIFS($N$8:$N$38,$A$8:$A$38,">="&$AJ$18+7*(3-1),$A$8:$A$38,"<="&$AJ$18+7*(3-1)+6)+SUMIFS('2026年06月'!$N$8:$N$37,'2026年06月'!$A$8:$A$37,">="&$AJ$18+7*(3-1),'2026年06月'!$A$8:$A$37,"<="&$AJ$18+7*(3-1)+6)),"")) -> 20742.158 | AG22: =IF($AC22="","",IFERROR((SUMIFS($O$8:$O$38,$A$8:$A$38,">="&$AJ$18+7*(3-1),$A$8:$A$38,"<="&$AJ$18+7*(3-1)+6)+SUMIFS('2026年06月'!$O$8:$O$37,'2026年06月'!$A$8:$A$37,">="&$AJ$18+7*(3-1),'2026年06月'!$A$8:$A$37,"<="&$AJ$18+7*(3-1)+6))/(SUMIFS($N$8:$N$38,$A$8:$A$38,">="&$AJ$18+7*(3-1),$A$8:$A$38,"<="&$AJ$18+7*(3-1)+6)+SUMIFS('2026年06月'!$N$8:$N$37,'2026年06月'!$A$8:$A$37,">="&$AJ$18+7*(3-1),'2026年06月'!$A$8:$A$37,"<="&$AJ$18+7*(3-1)+6)),"")) -> 1.0877193 | AH22: =IF($AC22="","",IFERROR((SUMIFS($Q$8:$Q$38,$A$8:$A$38,">="&$AJ$18+7*(3-1),$A$8:$A$38,"<="&$AJ$18+7*(3-1)+6)+SUMIFS('2026年06月'!$Q$8:$Q$37,'2026年06月'!$A$8:$A$37,">="&$AJ$18+7*(3-1),'2026年06月'!$A$8:$A$37,"<="&$AJ$18+7*(3-1)+6))/(SUMIFS($P$8:$P$38,$A$8:$A$38,">="&$AJ$18+7*(3-1),$A$8:$A$38,"<="&$AJ$18+7*(3-1)+6)+SUMIFS('2026年06月'!$P$8:$P$37,'2026年06月'!$A$8:$A$37,">="&$AJ$18+7*(3-1),'2026年06月'!$A$8:$A$37,"<="&$AJ$18+7*(3-1)+6)),"")) -> 0.395
A23: 46158 | B23: =MID("日月火水木金土",WEEKDAY(A23),1) -> 土 | C23: 500000 | D23: =SUM($C$8:C23) -> 7000000 | E23: 71430 | F23: 138630 | G23: 67958 | H23: =IF(COUNT(E23:G23)=0,"",SUM(E23:G23)) -> 278018 | I23: =IF(H23="","",SUM($H$8:H23)) -> 3297163 | J23: =IF(H23="","",IFERROR(H23/C23,"")) -> 0.556036 | K23: =IF(I23="","",IFERROR(I23/D23,"")) -> 0.47102329 | L23: =IF(I23="","",IF(D23=0,"",I23-D23)) -> -3702837 | M23: =IF(H23="","—",IF(D23=0,"予算未入力",IF(I23>=D23,"◎ ペース内","▲ 遅れ"))) -> ▲ 遅れ | N23: 13 | O23: 13 | P23: 42 | Q23: 13 | R23: 21 | S23: =IFERROR(N23/P23,"") -> 0.30952381 | T23: =IFERROR(H23/N23,"") -> 21386 | U23: =IFERROR(O23/N23,"") -> 1 | V23: =IFERROR(Q23/P23,"") -> 0.30952381 | X23: 8999 | Y23: 0 | AB23: 4 | AC23: =IF($AJ$18+7*(4-1)>$A$38,"",TEXT($AJ$18+7*(4-1),"m/d")&"-"&TEXT($AJ$18+7*(4-1)+6,"m/d")) -> 5/26-6/1 | AD23: =IF($AC23="","",(SUMIFS($H$8:$H$38,$A$8:$A$38,">="&$AJ$18+7*(4-1),$A$8:$A$38,"<="&$AJ$18+7*(4-1)+6)+SUMIFS('2026年06月'!$H$8:$H$37,'2026年06月'!$A$8:$A$37,">="&$AJ$18+7*(4-1),'2026年06月'!$A$8:$A$37,"<="&$AJ$18+7*(4-1)+6))) -> 1266653 | AE23: =IF($AC23="","",IFERROR((SUMIFS($N$8:$N$38,$A$8:$A$38,">="&$AJ$18+7*(4-1),$A$8:$A$38,"<="&$AJ$18+7*(4-1)+6)+SUMIFS('2026年06月'!$N$8:$N$37,'2026年06月'!$A$8:$A$37,">="&$AJ$18+7*(4-1),'2026年06月'!$A$8:$A$37,"<="&$AJ$18+7*(4-1)+6))/(SUMIFS($P$8:$P$38,$A$8:$A$38,">="&$AJ$18+7*(4-1),$A$8:$A$38,"<="&$AJ$18+7*(4-1)+6)+SUMIFS('2026年06月'!$P$8:$P$37,'2026年06月'!$A$8:$A$37,">="&$AJ$18+7*(4-1),'2026年06月'!$A$8:$A$37,"<="&$AJ$18+7*(4-1)+6)),"")) -> 0.25877193 | AF23: =IF($AC23="","",IFERROR((SUMIFS($H$8:$H$38,$A$8:$A$38,">="&$AJ$18+7*(4-1),$A$8:$A$38,"<="&$AJ$18+7*(4-1)+6)+SUMIFS('2026年06月'!$H$8:$H$37,'2026年06月'!$A$8:$A$37,">="&$AJ$18+7*(4-1),'2026年06月'!$A$8:$A$37,"<="&$AJ$18+7*(4-1)+6))/(SUMIFS($N$8:$N$38,$A$8:$A$38,">="&$AJ$18+7*(4-1),$A$8:$A$38,"<="&$AJ$18+7*(4-1)+6)+SUMIFS('2026年06月'!$N$8:$N$37,'2026年06月'!$A$8:$A$37,">="&$AJ$18+7*(4-1),'2026年06月'!$A$8:$A$37,"<="&$AJ$18+7*(4-1)+6)),"")) -> 21468.695 | AG23: =IF($AC23="","",IFERROR((SUMIFS($O$8:$O$38,$A$8:$A$38,">="&$AJ$18+7*(4-1),$A$8:$A$38,"<="&$AJ$18+7*(4-1)+6)+SUMIFS('2026年06月'!$O$8:$O$37,'2026年06月'!$A$8:$A$37,">="&$AJ$18+7*(4-1),'2026年06月'!$A$8:$A$37,"<="&$AJ$18+7*(4-1)+6))/(SUMIFS($N$8:$N$38,$A$8:$A$38,">="&$AJ$18+7*(4-1),$A$8:$A$38,"<="&$AJ$18+7*(4-1)+6)+SUMIFS('2026年06月'!$N$8:$N$37,'2026年06月'!$A$8:$A$37,">="&$AJ$18+7*(4-1),'2026年06月'!$A$8:$A$37,"<="&$AJ$18+7*(4-1)+6)),"")) -> 1.1694915 | AH23: =IF($AC23="","",IFERROR((SUMIFS($Q$8:$Q$38,$A$8:$A$38,">="&$AJ$18+7*(4-1),$A$8:$A$38,"<="&$AJ$18+7*(4-1)+6)+SUMIFS('2026年06月'!$Q$8:$Q$37,'2026年06月'!$A$8:$A$37,">="&$AJ$18+7*(4-1),'2026年06月'!$A$8:$A$37,"<="&$AJ$18+7*(4-1)+6))/(SUMIFS($P$8:$P$38,$A$8:$A$38,">="&$AJ$18+7*(4-1),$A$8:$A$38,"<="&$AJ$18+7*(4-1)+6)+SUMIFS('2026年06月'!$P$8:$P$37,'2026年06月'!$A$8:$A$37,">="&$AJ$18+7*(4-1),'2026年06月'!$A$8:$A$37,"<="&$AJ$18+7*(4-1)+6)),"")) -> 0.30263158
A24: 46159 | B24: =MID("日月火水木金土",WEEKDAY(A24),1) -> 日 | C24: 400000 | D24: =SUM($C$8:C24) -> 7400000 | E24: 103440 | F24: 166960 | G24: 14637 | H24: =IF(COUNT(E24:G24)=0,"",SUM(E24:G24)) -> 285037 | I24: =IF(H24="","",SUM($H$8:H24)) -> 3582200 | J24: =IF(H24="","",IFERROR(H24/C24,"")) -> 0.7125925 | K24: =IF(I24="","",IFERROR(I24/D24,"")) -> 0.48408108 | L24: =IF(I24="","",IF(D24=0,"",I24-D24)) -> -3817800 | M24: =IF(H24="","—",IF(D24=0,"予算未入力",IF(I24>=D24,"◎ ペース内","▲ 遅れ"))) -> ▲ 遅れ | N24: 14 | O24: 15 | P24: 40 | Q24: 18 | R24: 32 | S24: =IFERROR(N24/P24,"") -> 0.35 | T24: =IFERROR(H24/N24,"") -> 20359.786 | U24: =IFERROR(O24/N24,"") -> 1.0714286 | V24: =IFERROR(Q24/P24,"") -> 0.45 | X24: 8996 | Y24: 0 | AB24: 5 | AC24: =IF($AJ$18+7*(5-1)>$A$38,"",TEXT($AJ$18+7*(5-1),"m/d")&"-"&TEXT($AJ$18+7*(5-1)+6,"m/d")) | AD24: =IF($AC24="","",(SUMIFS($H$8:$H$38,$A$8:$A$38,">="&$AJ$18+7*(5-1),$A$8:$A$38,"<="&$AJ$18+7*(5-1)+6)+SUMIFS('2026年06月'!$H$8:$H$37,'2026年06月'!$A$8:$A$37,">="&$AJ$18+7*(5-1),'2026年06月'!$A$8:$A$37,"<="&$AJ$18+7*(5-1)+6))) | AE24: =IF($AC24="","",IFERROR((SUMIFS($N$8:$N$38,$A$8:$A$38,">="&$AJ$18+7*(5-1),$A$8:$A$38,"<="&$AJ$18+7*(5-1)+6)+SUMIFS('2026年06月'!$N$8:$N$37,'2026年06月'!$A$8:$A$37,">="&$AJ$18+7*(5-1),'2026年06月'!$A$8:$A$37,"<="&$AJ$18+7*(5-1)+6))/(SUMIFS($P$8:$P$38,$A$8:$A$38,">="&$AJ$18+7*(5-1),$A$8:$A$38,"<="&$AJ$18+7*(5-1)+6)+SUMIFS('2026年06月'!$P$8:$P$37,'2026年06月'!$A$8:$A$37,">="&$AJ$18+7*(5-1),'2026年06月'!$A$8:$A$37,"<="&$AJ$18+7*(5-1)+6)),"")) | AF24: =IF($AC24="","",IFERROR((SUMIFS($H$8:$H$38,$A$8:$A$38,">="&$AJ$18+7*(5-1),$A$8:$A$38,"<="&$AJ$18+7*(5-1)+6)+SUMIFS('2026年06月'!$H$8:$H$37,'2026年06月'!$A$8:$A$37,">="&$AJ$18+7*(5-1),'2026年06月'!$A$8:$A$37,"<="&$AJ$18+7*(5-1)+6))/(SUMIFS($N$8:$N$38,$A$8:$A$38,">="&$AJ$18+7*(5-1),$A$8:$A$38,"<="&$AJ$18+7*(5-1)+6)+SUMIFS('2026年06月'!$N$8:$N$37,'2026年06月'!$A$8:$A$37,">="&$AJ$18+7*(5-1),'2026年06月'!$A$8:$A$37,"<="&$AJ$18+7*(5-1)+6)),"")) | AG24: =IF($AC24="","",IFERROR((SUMIFS($O$8:$O$38,$A$8:$A$38,">="&$AJ$18+7*(5-1),$A$8:$A$38,"<="&$AJ$18+7*(5-1)+6)+SUMIFS('2026年06月'!$O$8:$O$37,'2026年06月'!$A$8:$A$37,">="&$AJ$18+7*(5-1),'2026年06月'!$A$8:$A$37,"<="&$AJ$18+7*(5-1)+6))/(SUMIFS($N$8:$N$38,$A$8:$A$38,">="&$AJ$18+7*(5-1),$A$8:$A$38,"<="&$AJ$18+7*(5-1)+6)+SUMIFS('2026年06月'!$N$8:$N$37,'2026年06月'!$A$8:$A$37,">="&$AJ$18+7*(5-1),'2026年06月'!$A$8:$A$37,"<="&$AJ$18+7*(5-1)+6)),"")) | AH24: =IF($AC24="","",IFERROR((SUMIFS($Q$8:$Q$38,$A$8:$A$38,">="&$AJ$18+7*(5-1),$A$8:$A$38,"<="&$AJ$18+7*(5-1)+6)+SUMIFS('2026年06月'!$Q$8:$Q$37,'2026年06月'!$A$8:$A$37,">="&$AJ$18+7*(5-1),'2026年06月'!$A$8:$A$37,"<="&$AJ$18+7*(5-1)+6))/(SUMIFS($P$8:$P$38,$A$8:$A$38,">="&$AJ$18+7*(5-1),$A$8:$A$38,"<="&$AJ$18+7*(5-1)+6)+SUMIFS('2026年06月'!$P$8:$P$37,'2026年06月'!$A$8:$A$37,">="&$AJ$18+7*(5-1),'2026年06月'!$A$8:$A$37,"<="&$AJ$18+7*(5-1)+6)),""))
A25: 46160 | B25: =MID("日月火水木金土",WEEKDAY(A25),1) -> 月 | C25: 200000 | D25: =SUM($C$8:C25) -> 7600000 | E25: 44220 | F25: 116540 | G25: -15258 | H25: =IF(COUNT(E25:G25)=0,"",SUM(E25:G25)) -> 145502 | I25: =IF(H25="","",SUM($H$8:H25)) -> 3727702 | J25: =IF(H25="","",IFERROR(H25/C25,"")) -> 0.72751 | K25: =IF(I25="","",IFERROR(I25/D25,"")) -> 0.49048711 | L25: =IF(I25="","",IF(D25=0,"",I25-D25)) -> -3872298 | M25: =IF(H25="","—",IF(D25=0,"予算未入力",IF(I25>=D25,"◎ ペース内","▲ 遅れ"))) -> ▲ 遅れ | N25: 7 | O25: 8 | P25: 32 | Q25: 7 | R25: 15 | S25: =IFERROR(N25/P25,"") -> 0.21875 | T25: =IFERROR(H25/N25,"") -> 20786 | U25: =IFERROR(O25/N25,"") -> 1.1428571 | V25: =IFERROR(Q25/P25,"") -> 0.21875 | X25: 8993 | Y25: 0 | AB25: 6 | AC25: =IF($AJ$18+7*(6-1)>$A$38,"",TEXT($AJ$18+7*(6-1),"m/d")&"-"&TEXT($AJ$18+7*(6-1)+6,"m/d")) | AD25: =IF($AC25="","",(SUMIFS($H$8:$H$38,$A$8:$A$38,">="&$AJ$18+7*(6-1),$A$8:$A$38,"<="&$AJ$18+7*(6-1)+6)+SUMIFS('2026年06月'!$H$8:$H$37,'2026年06月'!$A$8:$A$37,">="&$AJ$18+7*(6-1),'2026年06月'!$A$8:$A$37,"<="&$AJ$18+7*(6-1)+6))) | AE25: =IF($AC25="","",IFERROR((SUMIFS($N$8:$N$38,$A$8:$A$38,">="&$AJ$18+7*(6-1),$A$8:$A$38,"<="&$AJ$18+7*(6-1)+6)+SUMIFS('2026年06月'!$N$8:$N$37,'2026年06月'!$A$8:$A$37,">="&$AJ$18+7*(6-1),'2026年06月'!$A$8:$A$37,"<="&$AJ$18+7*(6-1)+6))/(SUMIFS($P$8:$P$38,$A$8:$A$38,">="&$AJ$18+7*(6-1),$A$8:$A$38,"<="&$AJ$18+7*(6-1)+6)+SUMIFS('2026年06月'!$P$8:$P$37,'2026年06月'!$A$8:$A$37,">="&$AJ$18+7*(6-1),'2026年06月'!$A$8:$A$37,"<="&$AJ$18+7*(6-1)+6)),"")) | AF25: =IF($AC25="","",IFERROR((SUMIFS($H$8:$H$38,$A$8:$A$38,">="&$AJ$18+7*(6-1),$A$8:$A$38,"<="&$AJ$18+7*(6-1)+6)+SUMIFS('2026年06月'!$H$8:$H$37,'2026年06月'!$A$8:$A$37,">="&$AJ$18+7*(6-1),'2026年06月'!$A$8:$A$37,"<="&$AJ$18+7*(6-1)+6))/(SUMIFS($N$8:$N$38,$A$8:$A$38,">="&$AJ$18+7*(6-1),$A$8:$A$38,"<="&$AJ$18+7*(6-1)+6)+SUMIFS('2026年06月'!$N$8:$N$37,'2026年06月'!$A$8:$A$37,">="&$AJ$18+7*(6-1),'2026年06月'!$A$8:$A$37,"<="&$AJ$18+7*(6-1)+6)),"")) | AG25: =IF($AC25="","",IFERROR((SUMIFS($O$8:$O$38,$A$8:$A$38,">="&$AJ$18+7*(6-1),$A$8:$A$38,"<="&$AJ$18+7*(6-1)+6)+SUMIFS('2026年06月'!$O$8:$O$37,'2026年06月'!$A$8:$A$37,">="&$AJ$18+7*(6-1),'2026年06月'!$A$8:$A$37,"<="&$AJ$18+7*(6-1)+6))/(SUMIFS($N$8:$N$38,$A$8:$A$38,">="&$AJ$18+7*(6-1),$A$8:$A$38,"<="&$AJ$18+7*(6-1)+6)+SUMIFS('2026年06月'!$N$8:$N$37,'2026年06月'!$A$8:$A$37,">="&$AJ$18+7*(6-1),'2026年06月'!$A$8:$A$37,"<="&$AJ$18+7*(6-1)+6)),"")) | AH25: =IF($AC25="","",IFERROR((SUMIFS($Q$8:$Q$38,$A$8:$A$38,">="&$AJ$18+7*(6-1),$A$8:$A$38,"<="&$AJ$18+7*(6-1)+6)+SUMIFS('2026年06月'!$Q$8:$Q$37,'2026年06月'!$A$8:$A$37,">="&$AJ$18+7*(6-1),'2026年06月'!$A$8:$A$37,"<="&$AJ$18+7*(6-1)+6))/(SUMIFS($P$8:$P$38,$A$8:$A$38,">="&$AJ$18+7*(6-1),$A$8:$A$38,"<="&$AJ$18+7*(6-1)+6)+SUMIFS('2026年06月'!$P$8:$P$37,'2026年06月'!$A$8:$A$37,">="&$AJ$18+7*(6-1),'2026年06月'!$A$8:$A$37,"<="&$AJ$18+7*(6-1)+6)),""))
A26: 46161 | B26: =MID("日月火水木金土",WEEKDAY(A26),1) -> 火 | C26: 200000 | D26: =SUM($C$8:C26) -> 7800000 | E26: 960 | F26: 143040 | G26: 8609 | H26: =IF(COUNT(E26:G26)=0,"",SUM(E26:G26)) -> 152609 | I26: =IF(H26="","",SUM($H$8:H26)) -> 3880311 | J26: =IF(H26="","",IFERROR(H26/C26,"")) -> 0.763045 | K26: =IF(I26="","",IFERROR(I26/D26,"")) -> 0.49747577 | L26: =IF(I26="","",IF(D26=0,"",I26-D26)) -> -3919689 | M26: =IF(H26="","—",IF(D26=0,"予算未入力",IF(I26>=D26,"◎ ペース内","▲ 遅れ"))) -> ▲ 遅れ | N26: 7 | O26: 8 | P26: 24 | Q26: 10 | R26: 17 | S26: =IFERROR(N26/P26,"") -> 0.29166667 | T26: =IFERROR(H26/N26,"") -> 21801.286 | U26: =IFERROR(O26/N26,"") -> 1.1428571 | V26: =IFERROR(Q26/P26,"") -> 0.41666667 | X26: 8994 | Y26: 0 | AB26: ※期間ラベルは第1火曜から自動生成。決定率・客単価・セット率・試着率は「週合計÷週合計」
A27: 46162 | B27: =MID("日月火水木金土",WEEKDAY(A27),1) -> 水 | C27: 200000 | D27: =SUM($C$8:C27) -> 8000000 | E27: 0 | F27: 47620 | G27: -4616 | H27: =IF(COUNT(E27:G27)=0,"",SUM(E27:G27)) -> 43004 | I27: =IF(H27="","",SUM($H$8:H27)) -> 3923315 | J27: =IF(H27="","",IFERROR(H27/C27,"")) -> 0.21502 | K27: =IF(I27="","",IFERROR(I27/D27,"")) -> 0.49041438 | L27: =IF(I27="","",IF(D27=0,"",I27-D27)) -> -4076685 | M27: =IF(H27="","—",IF(D27=0,"予算未入力",IF(I27>=D27,"◎ ペース内","▲ 遅れ"))) -> ▲ 遅れ | N27: 2 | O27: 2 | P27: 23 | Q27: 5 | R27: 6 | S27: =IFERROR(N27/P27,"") -> 0.086956522 | T27: =IFERROR(H27/N27,"") -> 21502 | U27: =IFERROR(O27/N27,"") -> 1 | V27: =IFERROR(Q27/P27,"") -> 0.2173913 | X27: 8994 | Y27: 0 | AB27: ※最終週は翌月にまたぐため、2026年06月シートの実績も自動で合算します
A28: 46163 | B28: =MID("日月火水木金土",WEEKDAY(A28),1) -> 木 | C28: 200000 | D28: =SUM($C$8:C28) -> 8200000 | E28: 0 | F28: 60430 | G28: 11678 | H28: =IF(COUNT(E28:G28)=0,"",SUM(E28:G28)) -> 72108 | I28: =IF(H28="","",SUM($H$8:H28)) -> 3995423 | J28: =IF(H28="","",IFERROR(H28/C28,"")) -> 0.36054 | K28: =IF(I28="","",IFERROR(I28/D28,"")) -> 0.48724671 | L28: =IF(I28="","",IF(D28=0,"",I28-D28)) -> -4204577 | M28: =IF(H28="","—",IF(D28=0,"予算未入力",IF(I28>=D28,"◎ ペース内","▲ 遅れ"))) -> ▲ 遅れ | N28: 4 | O28: 5 | P28: 12 | Q28: 7 | R28: 14 | S28: =IFERROR(N28/P28,"") -> 0.33333333 | T28: =IFERROR(H28/N28,"") -> 18027 | U28: =IFERROR(O28/N28,"") -> 1.25 | V28: =IFERROR(Q28/P28,"") -> 0.58333333 | X28: 8989 | Y28: 0 | AB28: ※月初の月曜まで（例：6/1）は前月シートの最終週に含まれます
A29: 46164 | B29: =MID("日月火水木金土",WEEKDAY(A29),1) -> 金 | C29: 200000 | D29: =SUM($C$8:C29) -> 8400000 | E29: 0 | F29: 66430 | G29: -6425 | H29: =IF(COUNT(E29:G29)=0,"",SUM(E29:G29)) -> 60005 | I29: =IF(H29="","",SUM($H$8:H29)) -> 4055428 | J29: =IF(H29="","",IFERROR(H29/C29,"")) -> 0.300025 | K29: =IF(I29="","",IFERROR(I29/D29,"")) -> 0.48278905 | L29: =IF(I29="","",IF(D29=0,"",I29-D29)) -> -4344572 | M29: =IF(H29="","—",IF(D29=0,"予算未入力",IF(I29>=D29,"◎ ペース内","▲ 遅れ"))) -> ▲ 遅れ | N29: 3 | O29: 3 | P29: 16 | Q29: 4 | R29: 5 | S29: =IFERROR(N29/P29,"") -> 0.1875 | T29: =IFERROR(H29/N29,"") -> 20001.667 | U29: =IFERROR(O29/N29,"") -> 1 | V29: =IFERROR(Q29/P29,"") -> 0.25 | X29: 8984 | Y29: 0
A30: 46165 | B30: =MID("日月火水木金土",WEEKDAY(A30),1) -> 土 | C30: 500000 | D30: =SUM($C$8:C30) -> 8900000 | E30: 98430 | F30: 277900 | G30: -20387 | H30: =IF(COUNT(E30:G30)=0,"",SUM(E30:G30)) -> 355943 | I30: =IF(H30="","",SUM($H$8:H30)) -> 4411371 | J30: =IF(H30="","",IFERROR(H30/C30,"")) -> 0.711886 | K30: =IF(I30="","",IFERROR(I30/D30,"")) -> 0.49565966 | L30: =IF(I30="","",IF(D30=0,"",I30-D30)) -> -4488629 | M30: =IF(H30="","—",IF(D30=0,"予算未入力",IF(I30>=D30,"◎ ペース内","▲ 遅れ"))) -> ▲ 遅れ | N30: 17 | O30: 19 | P30: 61 | Q30: 21 | R30: 42 | S30: =IFERROR(N30/P30,"") -> 0.27868852 | T30: =IFERROR(H30/N30,"") -> 20937.824 | U30: =IFERROR(O30/N30,"") -> 1.1176471 | V30: =IFERROR(Q30/P30,"") -> 0.3442623 | X30: 8984 | Y30: 0
A31: 46166 | B31: =MID("日月火水木金土",WEEKDAY(A31),1) -> 日 | C31: 400000 | D31: =SUM($C$8:C31) -> 9300000 | E31: 44220 | F31: 229640 | G31: 56758 | H31: =IF(COUNT(E31:G31)=0,"",SUM(E31:G31)) -> 330618 | I31: =IF(H31="","",SUM($H$8:H31)) -> 4741989 | J31: =IF(H31="","",IFERROR(H31/C31,"")) -> 0.826545 | K31: =IF(I31="","",IFERROR(I31/D31,"")) -> 0.50989129 | L31: =IF(I31="","",IF(D31=0,"",I31-D31)) -> -4558011 | M31: =IF(H31="","—",IF(D31=0,"予算未入力",IF(I31>=D31,"◎ ペース内","▲ 遅れ"))) -> ▲ 遅れ | N31: 16 | O31: 17 | P31: 42 | Q31: 23 | R31: 49 | S31: =IFERROR(N31/P31,"") -> 0.38095238 | T31: =IFERROR(H31/N31,"") -> 20663.625 | U31: =IFERROR(O31/N31,"") -> 1.0625 | V31: =IFERROR(Q31/P31,"") -> 0.54761905 | X31: 8979 | Y31: 0
A32: 46167 | B32: =MID("日月火水木金土",WEEKDAY(A32),1) -> 月 | C32: 200000 | D32: =SUM($C$8:C32) -> 9500000 | E32: 67030 | F32: 95240 | G32: 5746 | H32: =IF(COUNT(E32:G32)=0,"",SUM(E32:G32)) -> 168016 | I32: =IF(H32="","",SUM($H$8:H32)) -> 4910005 | J32: =IF(H32="","",IFERROR(H32/C32,"")) -> 0.84008 | K32: =IF(I32="","",IFERROR(I32/D32,"")) -> 0.51684263 | L32: =IF(I32="","",IF(D32=0,"",I32-D32)) -> -4589995 | M32: =IF(H32="","—",IF(D32=0,"予算未入力",IF(I32>=D32,"◎ ペース内","▲ 遅れ"))) -> ▲ 遅れ | N32: 8 | O32: 8 | P32: 22 | Q32: 9 | R32: 11 | S32: =IFERROR(N32/P32,"") -> 0.36363636 | T32: =IFERROR(H32/N32,"") -> 21002 | U32: =IFERROR(O32/N32,"") -> 1 | V32: =IFERROR(Q32/P32,"") -> 0.40909091 | X32: 8979 | Y32: 0
A33: 46168 | B33: =MID("日月火水木金土",WEEKDAY(A33),1) -> 火 | C33: 200000 | D33: =SUM($C$8:C33) -> 9700000 | E33: 47620 | F33: 71820 | G33: 8070 | H33: =IF(COUNT(E33:G33)=0,"",SUM(E33:G33)) -> 127510 | I33: =IF(H33="","",SUM($H$8:H33)) -> 5037515 | J33: =IF(H33="","",IFERROR(H33/C33,"")) -> 0.63755 | K33: =IF(I33="","",IFERROR(I33/D33,"")) -> 0.51933144 | L33: =IF(I33="","",IF(D33=0,"",I33-D33)) -> -4662485 | M33: =IF(H33="","—",IF(D33=0,"予算未入力",IF(I33>=D33,"◎ ペース内","▲ 遅れ"))) -> ▲ 遅れ | N33: 6 | O33: 6 | P33: 19 | Q33: 7 | R33: 12 | S33: =IFERROR(N33/P33,"") -> 0.31578947 | T33: =IFERROR(H33/N33,"") -> 21251.667 | U33: =IFERROR(O33/N33,"") -> 1 | V33: =IFERROR(Q33/P33,"") -> 0.36842105 | X33: 8976 | Y33: 0
A34: 46169 | B34: =MID("日月火水木金土",WEEKDAY(A34),1) -> 水 | C34: 200000 | D34: =SUM($C$8:C34) -> 9900000 | E34: 24620 | F34: 48510 | G34: 53376 | H34: =IF(COUNT(E34:G34)=0,"",SUM(E34:G34)) -> 126506 | I34: =IF(H34="","",SUM($H$8:H34)) -> 5164021 | J34: =IF(H34="","",IFERROR(H34/C34,"")) -> 0.63253 | K34: =IF(I34="","",IFERROR(I34/D34,"")) -> 0.52161828 | L34: =IF(I34="","",IF(D34=0,"",I34-D34)) -> -4735979 | M34: =IF(H34="","—",IF(D34=0,"予算未入力",IF(I34>=D34,"◎ ペース内","▲ 遅れ"))) -> ▲ 遅れ | N34: 5 | O34: 6 | P34: 19 | Q34: 5 | R34: 11 | S34: =IFERROR(N34/P34,"") -> 0.26315789 | T34: =IFERROR(H34/N34,"") -> 25301.2 | U34: =IFERROR(O34/N34,"") -> 1.2 | V34: =IFERROR(Q34/P34,"") -> 0.26315789 | X34: 8972 | Y34: 0
A35: 46170 | B35: =MID("日月火水木金土",WEEKDAY(A35),1) -> 木 | C35: 200000 | D35: =SUM($C$8:C35) -> 10100000 | E35: 0 | F35: 90840 | G35: 13168 | H35: =IF(COUNT(E35:G35)=0,"",SUM(E35:G35)) -> 104008 | I35: =IF(H35="","",SUM($H$8:H35)) -> 5268029 | J35: =IF(H35="","",IFERROR(H35/C35,"")) -> 0.52004 | K35: =IF(I35="","",IFERROR(I35/D35,"")) -> 0.52158703 | L35: =IF(I35="","",IF(D35=0,"",I35-D35)) -> -4831971 | M35: =IF(H35="","—",IF(D35=0,"予算未入力",IF(I35>=D35,"◎ ペース内","▲ 遅れ"))) -> ▲ 遅れ | N35: 5 | O35: 5 | P35: 20 | Q35: 7 | R35: 11 | S35: =IFERROR(N35/P35,"") -> 0.25 | T35: =IFERROR(H35/N35,"") -> 20801.6 | U35: =IFERROR(O35/N35,"") -> 1 | V35: =IFERROR(Q35/P35,"") -> 0.35 | X35: 8970 | Y35: 0
A36: 46171 | B36: =MID("日月火水木金土",WEEKDAY(A36),1) -> 金 | C36: 200000 | D36: =SUM($C$8:C36) -> 10300000 | E36: 0 | F36: 184980 | G36: 1835 | H36: =IF(COUNT(E36:G36)=0,"",SUM(E36:G36)) -> 186815 | I36: =IF(H36="","",SUM($H$8:H36)) -> 5454844 | J36: =IF(H36="","",IFERROR(H36/C36,"")) -> 0.934075 | K36: =IF(I36="","",IFERROR(I36/D36,"")) -> 0.5295965 | L36: =IF(I36="","",IF(D36=0,"",I36-D36)) -> -4845156 | M36: =IF(H36="","—",IF(D36=0,"予算未入力",IF(I36>=D36,"◎ ペース内","▲ 遅れ"))) -> ▲ 遅れ | N36: 9 | O36: 12 | P36: 33 | Q36: 15 | R36: 24 | S36: =IFERROR(N36/P36,"") -> 0.27272727 | T36: =IFERROR(H36/N36,"") -> 20757.222 | U36: =IFERROR(O36/N36,"") -> 1.3333333 | V36: =IFERROR(Q36/P36,"") -> 0.45454545 | X36: 8968 | Y36: 0
A37: 46172 | B37: =MID("日月火水木金土",WEEKDAY(A37),1) -> 土 | C37: 500000 | D37: =SUM($C$8:C37) -> 10800000 | E37: 90740 | F37: 257690 | G37: -34388 | H37: =IF(COUNT(E37:G37)=0,"",SUM(E37:G37)) -> 314042 | I37: =IF(H37="","",SUM($H$8:H37)) -> 5768886 | J37: =IF(H37="","",IFERROR(H37/C37,"")) -> 0.628084 | K37: =IF(I37="","",IFERROR(I37/D37,"")) -> 0.53415611 | L37: =IF(I37="","",IF(D37=0,"",I37-D37)) -> -5031114 | M37: =IF(H37="","—",IF(D37=0,"予算未入力",IF(I37>=D37,"◎ ペース内","▲ 遅れ"))) -> ▲ 遅れ | N37: 14 | O37: 15 | P37: 61 | Q37: 13 | R37: 24 | S37: =IFERROR(N37/P37,"") -> 0.2295082 | T37: =IFERROR(H37/N37,"") -> 22431.571 | U37: =IFERROR(O37/N37,"") -> 1.0714286 | V37: =IFERROR(Q37/P37,"") -> 0.21311475 | X37: 8969 | Y37: 0
A38: 46173 | B38: =MID("日月火水木金土",WEEKDAY(A38),1) -> 日 | C38: 400000 | D38: =SUM($C$8:C38) -> 11200000 | E38: 50380 | F38: 209040 | G38: 1789 | H38: =IF(COUNT(E38:G38)=0,"",SUM(E38:G38)) -> 261209 | I38: =IF(H38="","",SUM($H$8:H38)) -> 6030095 | J38: =IF(H38="","",IFERROR(H38/C38,"")) -> 0.6530225 | K38: =IF(I38="","",IFERROR(I38/D38,"")) -> 0.53840134 | L38: =IF(I38="","",IF(D38=0,"",I38-D38)) -> -5169905 | M38: =IF(H38="","—",IF(D38=0,"予算未入力",IF(I38>=D38,"◎ ペース内","▲ 遅れ"))) -> ▲ 遅れ | N38: 12 | O38: 16 | P38: 45 | Q38: 14 | R38: 26 | S38: =IFERROR(N38/P38,"") -> 0.26666667 | T38: =IFERROR(H38/N38,"") -> 21767.417 | U38: =IFERROR(O38/N38,"") -> 1.3333333 | V38: =IFERROR(Q38/P38,"") -> 0.31111111 | X38: 8961 | Y38: 0
A39: 月計 | C39: =SUM(C8:C38) -> 11200000 | D39: =C39 -> 11200000 | E39: =SUM(E8:E38) -> 1556548 | F39: =SUM(F8:F38) -> 4222223 | G39: =SUM(G8:G38) -> 251324 | H39: =SUM(H8:H38) -> 6030095 | I39: =H39 -> 6030095 | J39: =IFERROR(H39/C39,"") -> 0.53840134 | K39: =IFERROR(H39/C39,"") -> 0.53840134 | L39: =H39-C39 -> -5169905 | N39: =SUM(N8:N38) -> 285 | O39: =SUM(O8:O38) -> 313 | P39: =SUM(P8:P38) -> 1055 | Q39: =SUM(Q8:Q38) -> 355 | R39: =SUM(R8:R38) -> 623 | S39: =IFERROR(N39/P39,"") -> 0.27014218 | T39: =IFERROR(H39/N39,"") -> 21158.228 | U39: =IFERROR(O39/N39,"") -> 1.0982456 | V39: =IFERROR(Q39/P39,"") -> 0.33649289 | W39: =SUM(W8:W38) -> 0 | X39: =IFERROR(LOOKUP(9.99E+307,X8:X38),"") -> 8961 | Y39: =SUM(Y8:Y38) -> 0 | Z39: フォロワーは月末値

Sheet 2026年06月
A1: 2026年6月 名古屋店 日別売上管理
A2: 青字＋薄黄色のセルが入力欄。白セルは数式なので触らないでください。単位：円
A3: 月間予算 | C3: 当月実績 | E3: 達成率 | G3: 営業日数(/30日) | I3: 残り必要額 | K3: 残り必要日商
A4: =IF('設定'!$B$10="",SUM(C8:C37),'設定'!$B$10) -> 9000000 | C4: =SUM(H8:H37) -> 5200406 | E4: =IFERROR(C4/A4,0) -> 0.57782289 | G4: =COUNTIF(H8:H37,">0") -> 30 | I4: =A4-C4 -> 3799594 | K4: =IF((30-G4)>0,(A4-C4)/(30-G4),0) -> 0
A5: 日次予算合計 | C5: 着地見込 | E5: 決定率 | G5: 客単価 | I5: セット率 | K5: 試着率
A6: =SUM(C8:C37) -> 9500000 | C6: =IFERROR(C4/G4*30,0) -> 5200406 | E6: =IFERROR(N38/P38,0) -> 0.28776978 | G6: =IFERROR(H38/N38,0) -> 21668.358 | I6: =IFERROR(O38/N38,0) -> 1.1291667 | K6: =IFERROR(Q38/P38,0) -> 0.38129496
A7: 日付 | B7: 曜 | C7: 日次予算 | D7: 累計予算 | E7: 現金 | F7: クレジット | G7: 内訳差額 (要確認) | H7: 実績合計 | I7: 累計実績 | J7: 日次達成 | K7: 累計達成 | L7: 累計予実差 | M7: ペース | N7: 購入人数 | O7: 販売点数 | P7: 来客数 | Q7: 試着組数 | R7: 試着個数 | S7: 決定率 | T7: 客単価 | U7: セット率 | V7: 試着率 | W7: クロス クーポン | X7: インスタ フォロワー | Y7: 経費 | Z7: メモ | AB7: 曜日 | AC7: 平均日商 | AD7: 日数 | AE7: 決定率 | AF7: 客単価
A8: 46174 | B8: =MID("日月火水木金土",WEEKDAY(A8),1) -> 月 | C8: 250000 | D8: =SUM($C$8:C8) -> 250000 | E8: 49710 | F8: 67150 | G8: 29703 | H8: =IF(COUNT(E8:G8)=0,"",SUM(E8:G8)) -> 146563 | I8: =IF(H8="","",SUM($H$8:H8)) -> 146563 | J8: =IF(H8="","",IFERROR(H8/C8,"")) -> 0.586252 | K8: =IF(I8="","",IFERROR(I8/D8,"")) -> 0.586252 | L8: =IF(I8="","",IF(D8=0,"",I8-D8)) -> -103437 | M8: =IF(H8="","—",IF(D8=0,"予算未入力",IF(I8>=D8,"◎ ペース内","▲ 遅れ"))) -> ▲ 遅れ | N8: 8 | O8: 9 | P8: 31 | Q8: 8 | R8: 14 | S8: =IFERROR(N8/P8,"") -> 0.25806452 | T8: =IFERROR(H8/N8,"") -> 18320.375 | U8: =IFERROR(O8/N8,"") -> 1.125 | V8: =IFERROR(Q8/P8,"") -> 0.25806452 | X8: 8963 | Y8: 0 | AB8: 月 | AC8: =IFERROR(AVERAGEIFS($H$8:$H$37,$B$8:$B$37,AB8,$H$8:$H$37,">0"),0) -> 77027.4 | AD8: =COUNTIFS($B$8:$B$37,AB8,$H$8:$H$37,">0") -> 5 | AE8: =IFERROR(SUMIF($B$8:$B$37,AB8,$N$8:$N$37)/SUMIF($B$8:$B$37,AB8,$P$8:$P$37),0) -> 0.17475728 | AF8: =IFERROR(SUMIF($B$8:$B$37,AB8,$H$8:$H$37)/SUMIF($B$8:$B$37,AB8,$N$8:$N$37),0) -> 21396.5
A9: 46175 | B9: =MID("日月火水木金土",WEEKDAY(A9),1) -> 火 | C9: 250000 | D9: =SUM($C$8:C9) -> 500000 | E9: 0 | F9: 21500 | G9: 41502 | H9: =IF(COUNT(E9:G9)=0,"",SUM(E9:G9)) -> 63002 | I9: =IF(H9="","",SUM($H$8:H9)) -> 209565 | J9: =IF(H9="","",IFERROR(H9/C9,"")) -> 0.252008 | K9: =IF(I9="","",IFERROR(I9/D9,"")) -> 0.41913 | L9: =IF(I9="","",IF(D9=0,"",I9-D9)) -> -290435 | M9: =IF(H9="","—",IF(D9=0,"予算未入力",IF(I9>=D9,"◎ ペース内","▲ 遅れ"))) -> ▲ 遅れ | N9: 3 | O9: 3 | P9: 17 | Q9: 3 | R9: 4 | S9: =IFERROR(N9/P9,"") -> 0.17647059 | T9: =IFERROR(H9/N9,"") -> 21000.667 | U9: =IFERROR(O9/N9,"") -> 1 | V9: =IFERROR(Q9/P9,"") -> 0.17647059 | X9: 8959 | Y9: 0 | AB9: 火 | AC9: =IFERROR(AVERAGEIFS($H$8:$H$37,$B$8:$B$37,AB9,$H$8:$H$37,">0"),0) -> 150731.8 | AD9: =COUNTIFS($B$8:$B$37,AB9,$H$8:$H$37,">0") -> 5 | AE9: =IFERROR(SUMIF($B$8:$B$37,AB9,$N$8:$N$37)/SUMIF($B$8:$B$37,AB9,$P$8:$P$37),0) -> 0.29059829 | AF9: =IFERROR(SUMIF($B$8:$B$37,AB9,$H$8:$H$37)/SUMIF($B$8:$B$37,AB9,$N$8:$N$37),0) -> 22166.441
A10: 46176 | B10: =MID("日月火水木金土",WEEKDAY(A10),1) -> 水 | C10: 250000 | D10: =SUM($C$8:C10) -> 750000 | E10: 45420 | F10: 66820 | G10: 56268 | H10: =IF(COUNT(E10:G10)=0,"",SUM(E10:G10)) -> 168508 | I10: =IF(H10="","",SUM($H$8:H10)) -> 378073 | J10: =IF(H10="","",IFERROR(H10/C10,"")) -> 0.674032 | K10: =IF(I10="","",IFERROR(I10/D10,"")) -> 0.50409733 | L10: =IF(I10="","",IF(D10=0,"",I10-D10)) -> -371927 | M10: =IF(H10="","—",IF(D10=0,"予算未入力",IF(I10>=D10,"◎ ペース内","▲ 遅れ"))) -> ▲ 遅れ | N10: 7 | O10: 8 | P10: 22 | Q10: 8 | R10: 16 | S10: =IFERROR(N10/P10,"") -> 0.31818182 | T10: =IFERROR(H10/N10,"") -> 24072.571 | U10: =IFERROR(O10/N10,"") -> 1.1428571 | V10: =IFERROR(Q10/P10,"") -> 0.36363636 | X10: 8950 | Y10: 0 | AB10: 水 | AC10: =IFERROR(AVERAGEIFS($H$8:$H$37,$B$8:$B$37,AB10,$H$8:$H$37,">0"),0) -> 140237.75 | AD10: =COUNTIFS($B$8:$B$37,AB10,$H$8:$H$37,">0") -> 4 | AE10: =IFERROR(SUMIF($B$8:$B$37,AB10,$N$8:$N$37)/SUMIF($B$8:$B$37,AB10,$P$8:$P$37),0) -> 0.30769231 | AF10: =IFERROR(SUMIF($B$8:$B$37,AB10,$H$8:$H$37)/SUMIF($B$8:$B$37,AB10,$N$8:$N$37),0) -> 23372.958
A11: 46177 | B11: =MID("日月火水木金土",WEEKDAY(A11),1) -> 木 | C11: 250000 | D11: =SUM($C$8:C11) -> 1000000 | E11: 52130 | F11: 17210 | G11: -6833 | H11: =IF(COUNT(E11:G11)=0,"",SUM(E11:G11)) -> 62507 | I11: =IF(H11="","",SUM($H$8:H11)) -> 440580 | J11: =IF(H11="","",IFERROR(H11/C11,"")) -> 0.250028 | K11: =IF(I11="","",IFERROR(I11/D11,"")) -> 0.44058 | L11: =IF(I11="","",IF(D11=0,"",I11-D11)) -> -559420 | M11: =IF(H11="","—",IF(D11=0,"予算未入力",IF(I11>=D11,"◎ ペース内","▲ 遅れ"))) -> ▲ 遅れ | N11: 3 | O11: 3 | P11: 14 | Q11: 5 | R11: 6 | S11: =IFERROR(N11/P11,"") -> 0.21428571 | T11: =IFERROR(H11/N11,"") -> 20835.667 | U11: =IFERROR(O11/N11,"") -> 1 | V11: =IFERROR(Q11/P11,"") -> 0.35714286 | X11: 8948 | Y11: 0 | AB11: 木 | AC11: =IFERROR(AVERAGEIFS($H$8:$H$37,$B$8:$B$37,AB11,$H$8:$H$37,">0"),0) -> 79104.75 | AD11: =COUNTIFS($B$8:$B$37,AB11,$H$8:$H$37,">0") -> 4 | AE11: =IFERROR(SUMIF($B$8:$B$37,AB11,$N$8:$N$37)/SUMIF($B$8:$B$37,AB11,$P$8:$P$37),0) -> 0.21428571 | AF11: =IFERROR(SUMIF($B$8:$B$37,AB11,$H$8:$H$37)/SUMIF($B$8:$B$37,AB11,$N$8:$N$37),0) -> 21094.6
A12: 46178 | B12: =MID("日月火水木金土",WEEKDAY(A12),1) -> 金 | C12: 250000 | D12: =SUM($C$8:C12) -> 1250000 | E12: 41020 | F12: 19410 | G12: 17580 | H12: =IF(COUNT(E12:G12)=0,"",SUM(E12:G12)) -> 78010 | I12: =IF(H12="","",SUM($H$8:H12)) -> 518590 | J12: =IF(H12="","",IFERROR(H12/C12,"")) -> 0.31204 | K12: =IF(I12="","",IFERROR(I12/D12,"")) -> 0.414872 | L12: =IF(I12="","",IF(D12=0,"",I12-D12)) -> -731410 | M12: =IF(H12="","—",IF(D12=0,"予算未入力",IF(I12>=D12,"◎ ペース内","▲ 遅れ"))) -> ▲ 遅れ | N12: 4 | O12: 4 | P12: 12 | Q12: 5 | R12: 9 | S12: =IFERROR(N12/P12,"") -> 0.33333333 | T12: =IFERROR(H12/N12,"") -> 19502.5 | U12: =IFERROR(O12/N12,"") -> 1 | V12: =IFERROR(Q12/P12,"") -> 0.41666667 | X12: 8949 | Y12: 0 | AB12: 金 | AC12: =IFERROR(AVERAGEIFS($H$8:$H$37,$B$8:$B$37,AB12,$H$8:$H$37,">0"),0) -> 157307.25 | AD12: =COUNTIFS($B$8:$B$37,AB12,$H$8:$H$37,">0") -> 4 | AE12: =IFERROR(SUMIF($B$8:$B$37,AB12,$N$8:$N$37)/SUMIF($B$8:$B$37,AB12,$P$8:$P$37),0) -> 0.34939759 | AF12: =IFERROR(SUMIF($B$8:$B$37,AB12,$H$8:$H$37)/SUMIF($B$8:$B$37,AB12,$N$8:$N$37),0) -> 21697.552
A13: 46179 | B13: =MID("日月火水木金土",WEEKDAY(A13),1) -> 土 | C13: 500000 | D13: =SUM($C$8:C13) -> 1750000 | E13: 74130 | F13: 93540 | G13: 29340 | H13: =IF(COUNT(E13:G13)=0,"",SUM(E13:G13)) -> 197010 | I13: =IF(H13="","",SUM($H$8:H13)) -> 715600 | J13: =IF(H13="","",IFERROR(H13/C13,"")) -> 0.39402 | K13: =IF(I13="","",IFERROR(I13/D13,"")) -> 0.40891429 | L13: =IF(I13="","",IF(D13=0,"",I13-D13)) -> -1034400 | M13: =IF(H13="","—",IF(D13=0,"予算未入力",IF(I13>=D13,"◎ ペース内","▲ 遅れ"))) -> ▲ 遅れ | N13: 9 | O13: 9 | P13: 40 | Q13: 16 | R13: 22 | S13: =IFERROR(N13/P13,"") -> 0.225 | T13: =IFERROR(H13/N13,"") -> 21890 | U13: =IFERROR(O13/N13,"") -> 1 | V13: =IFERROR(Q13/P13,"") -> 0.4 | X13: 8948 | Y13: 0 | AB13: 土 | AC13: =IFERROR(AVERAGEIFS($H$8:$H$37,$B$8:$B$37,AB13,$H$8:$H$37,">0"),0) -> 315022.25 | AD13: =COUNTIFS($B$8:$B$37,AB13,$H$8:$H$37,">0") -> 4 | AE13: =IFERROR(SUMIF($B$8:$B$37,AB13,$N$8:$N$37)/SUMIF($B$8:$B$37,AB13,$P$8:$P$37),0) -> 0.31770833 | AF13: =IFERROR(SUMIF($B$8:$B$37,AB13,$H$8:$H$37)/SUMIF($B$8:$B$37,AB13,$N$8:$N$37),0) -> 20657.197
A14: 46180 | B14: =MID("日月火水木金土",WEEKDAY(A14),1) -> 日 | C14: 500000 | D14: =SUM($C$8:C14) -> 2250000 | E14: 70230 | F14: 87540 | G14: -15259 | H14: =IF(COUNT(E14:G14)=0,"",SUM(E14:G14)) -> 142511 | I14: =IF(H14="","",SUM($H$8:H14)) -> 858111 | J14: =IF(H14="","",IFERROR(H14/C14,"")) -> 0.285022 | K14: =IF(I14="","",IFERROR(I14/D14,"")) -> 0.38138267 | L14: =IF(I14="","",IF(D14=0,"",I14-D14)) -> -1391889 | M14: =IF(H14="","—",IF(D14=0,"予算未入力",IF(I14>=D14,"◎ ペース内","▲ 遅れ"))) -> ▲ 遅れ | N14: 7 | O14: 7 | P14: 40 | Q14: 20 | R14: 30 | S14: =IFERROR(N14/P14,"") -> 0.175 | T14: =IFERROR(H14/N14,"") -> 20358.714 | U14: =IFERROR(O14/N14,"") -> 1 | V14: =IFERROR(Q14/P14,"") -> 0.5 | X14: 8939 | Y14: 0 | AB14: 日 | AC14: =IFERROR(AVERAGEIFS($H$8:$H$37,$B$8:$B$37,AB14,$H$8:$H$37,">0"),0) -> 323730.5 | AD14: =COUNTIFS($B$8:$B$37,AB14,$H$8:$H$37,">0") -> 4 | AE14: =IFERROR(SUMIF($B$8:$B$37,AB14,$N$8:$N$37)/SUMIF($B$8:$B$37,AB14,$P$8:$P$37),0) -> 0.30890052 | AF14: =IFERROR(SUMIF($B$8:$B$37,AB14,$H$8:$H$37)/SUMIF($B$8:$B$37,AB14,$N$8:$N$37),0) -> 21947.831
A15: 46181 | B15: =MID("日月火水木金土",WEEKDAY(A15),1) -> 月 | C15: 250000 | D15: =SUM($C$8:C15) -> 2500000 | E15: 24310 | F15: 24310 | G15: -4620 | H15: =IF(COUNT(E15:G15)=0,"",SUM(E15:G15)) -> 44000 | I15: =IF(H15="","",SUM($H$8:H15)) -> 902111 | J15: =IF(H15="","",IFERROR(H15/C15,"")) -> 0.176 | K15: =IF(I15="","",IFERROR(I15/D15,"")) -> 0.3608444 | L15: =IF(I15="","",IF(D15=0,"",I15-D15)) -> -1597889 | M15: =IF(H15="","—",IF(D15=0,"予算未入力",IF(I15>=D15,"◎ ペース内","▲ 遅れ"))) -> ▲ 遅れ | N15: 2 | O15: 2 | P15: 24 | Q15: 4 | R15: 5 | S15: =IFERROR(N15/P15,"") -> 0.083333333 | T15: =IFERROR(H15/N15,"") -> 22000 | U15: =IFERROR(O15/N15,"") -> 1 | V15: =IFERROR(Q15/P15,"") -> 0.16666667 | X15: 8933 | Y15: 0
A16: 46182 | B16: =MID("日月火水木金土",WEEKDAY(A16),1) -> 火 | C16: 250000 | D16: =SUM($C$8:C16) -> 2750000 | E16: 40470 | F16: 126040 | G16: -15998 | H16: =IF(COUNT(E16:G16)=0,"",SUM(E16:G16)) -> 150512 | I16: =IF(H16="","",SUM($H$8:H16)) -> 1052623 | J16: =IF(H16="","",IFERROR(H16/C16,"")) -> 0.602048 | K16: =IF(I16="","",IFERROR(I16/D16,"")) -> 0.382772 | L16: =IF(I16="","",IF(D16=0,"",I16-D16)) -> -1697377 | M16: =IF(H16="","—",IF(D16=0,"予算未入力",IF(I16>=D16,"◎ ペース内","▲ 遅れ"))) -> ▲ 遅れ | N16: 6 | O16: 7 | P16: 26 | Q16: 7 | R16: 11 | S16: =IFERROR(N16/P16,"") -> 0.23076923 | T16: =IFERROR(H16/N16,"") -> 25085.333 | U16: =IFERROR(O16/N16,"") -> 1.1666667 | V16: =IFERROR(Q16/P16,"") -> 0.26923077 | X16: 8935 | Y16: 0 | AB16: ※実績入力後に曜日別の傾向が出ます
A17: 46183 | B17: =MID("日月火水木金土",WEEKDAY(A17),1) -> 水 | C17: 250000 | D17: =SUM($C$8:C17) -> 3000000 | E17: 45810 | F17: 68030 | G17: -8736 | H17: =IF(COUNT(E17:G17)=0,"",SUM(E17:G17)) -> 105104 | I17: =IF(H17="","",SUM($H$8:H17)) -> 1157727 | J17: =IF(H17="","",IFERROR(H17/C17,"")) -> 0.420416 | K17: =IF(I17="","",IFERROR(I17/D17,"")) -> 0.385909 | L17: =IF(I17="","",IF(D17=0,"",I17-D17)) -> -1842273 | M17: =IF(H17="","—",IF(D17=0,"予算未入力",IF(I17>=D17,"◎ ペース内","▲ 遅れ"))) -> ▲ 遅れ | N17: 4 | O17: 5 | P17: 18 | Q17: 4 | R17: 5 | S17: =IFERROR(N17/P17,"") -> 0.22222222 | T17: =IFERROR(H17/N17,"") -> 26276 | U17: =IFERROR(O17/N17,"") -> 1.25 | V17: =IFERROR(Q17/P17,"") -> 0.22222222 | X17: 8932 | Y17: 0
A18: 46184 | B18: =MID("日月火水木金土",WEEKDAY(A18),1) -> 木 | C18: 250000 | D18: =SUM($C$8:C18) -> 3250000 | E18: 3960 | F18: 0 | G18: -360 | H18: =IF(COUNT(E18:G18)=0,"",SUM(E18:G18)) -> 3600 | I18: =IF(H18="","",SUM($H$8:H18)) -> 1161327 | J18: =IF(H18="","",IFERROR(H18/C18,"")) -> 0.0144 | K18: =IF(I18="","",IFERROR(I18/D18,"")) -> 0.35733138 | L18: =IF(I18="","",IF(D18=0,"",I18-D18)) -> -2088673 | M18: =IF(H18="","—",IF(D18=0,"予算未入力",IF(I18>=D18,"◎ ペース内","▲ 遅れ"))) -> ▲ 遅れ | N18: 1 | O18: 1 | P18: 14 | Q18: 1 | R18: 1 | S18: =IFERROR(N18/P18,"") -> 0.071428571 | T18: =IFERROR(H18/N18,"") -> 3600 | U18: =IFERROR(O18/N18,"") -> 1 | V18: =IFERROR(Q18/P18,"") -> 0.071428571 | X18: 8928 | Y18: 0 | AB18: ■ 週次サマリー（火曜〜翌月曜） | AI18: 第1火曜 | AJ18: =$A$8+MOD(2-WEEKDAY($A$8,2)+7,7) -> 46175
A19: 46185 | B19: =MID("日月火水木金土",WEEKDAY(A19),1) -> 金 | C19: 250000 | D19: =SUM($C$8:C19) -> 3500000 | E19: 0 | F19: 122430 | G19: 9895 | H19: =IF(COUNT(E19:G19)=0,"",SUM(E19:G19)) -> 132325 | I19: =IF(H19="","",SUM($H$8:H19)) -> 1293652 | J19: =IF(H19="","",IFERROR(H19/C19,"")) -> 0.5293 | K19: =IF(I19="","",IFERROR(I19/D19,"")) -> 0.36961486 | L19: =IF(I19="","",IF(D19=0,"",I19-D19)) -> -2206348 | M19: =IF(H19="","—",IF(D19=0,"予算未入力",IF(I19>=D19,"◎ ペース内","▲ 遅れ"))) -> ▲ 遅れ | N19: 4 | O19: 6 | P19: 20 | Q19: 7 | R19: 13 | S19: =IFERROR(N19/P19,"") -> 0.2 | T19: =IFERROR(H19/N19,"") -> 33081.25 | U19: =IFERROR(O19/N19,"") -> 1.5 | V19: =IFERROR(Q19/P19,"") -> 0.35 | X19: 8924 | Y19: 0 | AB19: 週 | AC19: 期間 | AD19: 売上 | AE19: 決定率 | AF19: 客単価 | AG19: セット率 | AH19: 試着率
A20: 46186 | B20: =MID("日月火水木金土",WEEKDAY(A20),1) -> 土 | C20: 500000 | D20: =SUM($C$8:C20) -> 4000000 | E20: 201980 | F20: 184160 | G20: -14082 | H20: =IF(COUNT(E20:G20)=0,"",SUM(E20:G20)) -> 372058 | I20: =IF(H20="","",SUM($H$8:H20)) -> 1665710 | J20: =IF(H20="","",IFERROR(H20/C20,"")) -> 0.744116 | K20: =IF(I20="","",IFERROR(I20/D20,"")) -> 0.4164275 | L20: =IF(I20="","",IF(D20=0,"",I20-D20)) -> -2334290 | M20: =IF(H20="","—",IF(D20=0,"予算未入力",IF(I20>=D20,"◎ ペース内","▲ 遅れ"))) -> ▲ 遅れ | N20: 19 | O20: 19 | P20: 60 | Q20: 25 | R20: 40 | S20: =IFERROR(N20/P20,"") -> 0.31666667 | T20: =IFERROR(H20/N20,"") -> 19582 | U20: =IFERROR(O20/N20,"") -> 1 | V20: =IFERROR(Q20/P20,"") -> 0.41666667 | X20: 8923 | Y20: 0 | AB20: 1 | AC20: =IF($AJ$18+7*(1-1)>$A$37,"",TEXT($AJ$18+7*(1-1),"m/d")&"-"&TEXT($AJ$18+7*(1-1)+6,"m/d")) -> 6/2-6/8 | AD20: =IF($AC20="","",(SUMIFS($H$8:$H$37,$A$8:$A$37,">="&$AJ$18+7*(1-1),$A$8:$A$37,"<="&$AJ$18+7*(1-1)+6)+SUMIFS('2026年07月'!$I$8:$I$38,'2026年07月'!$A$8:$A$38,">="&$AJ$18+7*(1-1),'2026年07月'!$A$8:$A$38,"<="&$AJ$18+7*(1-1)+6))) -> 755548 | AE20: =IF($AC20="","",IFERROR((SUMIFS($N$8:$N$37,$A$8:$A$37,">="&$AJ$18+7*(1-1),$A$8:$A$37,"<="&$AJ$18+7*(1-1)+6)+SUMIFS('2026年07月'!$O$8:$O$38,'2026年07月'!$A$8:$A$38,">="&$AJ$18+7*(1-1),'2026年07月'!$A$8:$A$38,"<="&$AJ$18+7*(1-1)+6))/(SUMIFS($P$8:$P$37,$A$8:$A$37,">="&$AJ$18+7*(1-1),$A$8:$A$37,"<="&$AJ$18+7*(1-1)+6)+SUMIFS('2026年07月'!$Q$8:$Q$38,'2026年07月'!$A$8:$A$38,">="&$AJ$18+7*(1-1),'2026年07月'!$A$8:$A$38,"<="&$AJ$18+7*(1-1)+6)),"")) -> 0.20710059 | AF20: =IF($AC20="","",IFERROR((SUMIFS($H$8:$H$37,$A$8:$A$37,">="&$AJ$18+7*(1-1),$A$8:$A$37,"<="&$AJ$18+7*(1-1)+6)+SUMIFS('2026年07月'!$I$8:$I$38,'2026年07月'!$A$8:$A$38,">="&$AJ$18+7*(1-1),'2026年07月'!$A$8:$A$38,"<="&$AJ$18+7*(1-1)+6))/(SUMIFS($N$8:$N$37,$A$8:$A$37,">="&$AJ$18+7*(1-1),$A$8:$A$37,"<="&$AJ$18+7*(1-1)+6)+SUMIFS('2026年07月'!$O$8:$O$38,'2026年07月'!$A$8:$A$38,">="&$AJ$18+7*(1-1),'2026年07月'!$A$8:$A$38,"<="&$AJ$18+7*(1-1)+6)),"")) -> 21587.086 | AG20: =IF($AC20="","",IFERROR((SUMIFS($O$8:$O$37,$A$8:$A$37,">="&$AJ$18+7*(1-1),$A$8:$A$37,"<="&$AJ$18+7*(1-1)+6)+SUMIFS('2026年07月'!$P$8:$P$38,'2026年07月'!$A$8:$A$38,">="&$AJ$18+7*(1-1),'2026年07月'!$A$8:$A$38,"<="&$AJ$18+7*(1-1)+6))/(SUMIFS($N$8:$N$37,$A$8:$A$37,">="&$AJ$18+7*(1-1),$A$8:$A$37,"<="&$AJ$18+7*(1-1)+6)+SUMIFS('2026年07月'!$O$8:$O$38,'2026年07月'!$A$8:$A$38,">="&$AJ$18+7*(1-1),'2026年07月'!$A$8:$A$38,"<="&$AJ$18+7*(1-1)+6)),"")) -> 1.0285714 | AH20: =IF($AC20="","",IFERROR((SUMIFS($Q$8:$Q$37,$A$8:$A$37,">="&$AJ$18+7*(1-1),$A$8:$A$37,"<="&$AJ$18+7*(1-1)+6)+SUMIFS('2026年07月'!$R$8:$R$38,'2026年07月'!$A$8:$A$38,">="&$AJ$18+7*(1-1),'2026年07月'!$A$8:$A$38,"<="&$AJ$18+7*(1-1)+6))/(SUMIFS($P$8:$P$37,$A$8:$A$37,">="&$AJ$18+7*(1-1),$A$8:$A$37,"<="&$AJ$18+7*(1-1)+6)+SUMIFS('2026年07月'!$Q$8:$Q$38,'2026年07月'!$A$8:$A$38,">="&$AJ$18+7*(1-1),'2026年07月'!$A$8:$A$38,"<="&$AJ$18+7*(1-1)+6)),"")) -> 0.36094675
A21: 46187 | B21: =MID("日月火水木金土",WEEKDAY(A21),1) -> 日 | C21: 500000 | D21: =SUM($C$8:C21) -> 4500000 | E21: 178180 | F21: 121310 | G21: 10729 | H21: =IF(COUNT(E21:G21)=0,"",SUM(E21:G21)) -> 310219 | I21: =IF(H21="","",SUM($H$8:H21)) -> 1975929 | J21: =IF(H21="","",IFERROR(H21/C21,"")) -> 0.620438 | K21: =IF(I21="","",IFERROR(I21/D21,"")) -> 0.43909533 | L21: =IF(I21="","",IF(D21=0,"",I21-D21)) -> -2524071 | M21: =IF(H21="","—",IF(D21=0,"予算未入力",IF(I21>=D21,"◎ ペース内","▲ 遅れ"))) -> ▲ 遅れ | N21: 15 | O21: 17 | P21: 64 | Q21: 25 | R21: 38 | S21: =IFERROR(N21/P21,"") -> 0.234375 | T21: =IFERROR(H21/N21,"") -> 20681.267 | U21: =IFERROR(O21/N21,"") -> 1.1333333 | V21: =IFERROR(Q21/P21,"") -> 0.390625 | X21: 8921 | Y21: 0 | AB21: 2 | AC21: =IF($AJ$18+7*(2-1)>$A$37,"",TEXT($AJ$18+7*(2-1),"m/d")&"-"&TEXT($AJ$18+7*(2-1)+6,"m/d")) -> 6/9-6/15 | AD21: =IF($AC21="","",(SUMIFS($H$8:$H$37,$A$8:$A$37,">="&$AJ$18+7*(2-1),$A$8:$A$37,"<="&$AJ$18+7*(2-1)+6)+SUMIFS('2026年07月'!$I$8:$I$38,'2026年07月'!$A$8:$A$38,">="&$AJ$18+7*(2-1),'2026年07月'!$A$8:$A$38,"<="&$AJ$18+7*(2-1)+6))) -> 1134528 | AE21: =IF($AC21="","",IFERROR((SUMIFS($N$8:$N$37,$A$8:$A$37,">="&$AJ$18+7*(2-1),$A$8:$A$37,"<="&$AJ$18+7*(2-1)+6)+SUMIFS('2026年07月'!$O$8:$O$38,'2026年07月'!$A$8:$A$38,">="&$AJ$18+7*(2-1),'2026年07月'!$A$8:$A$38,"<="&$AJ$18+7*(2-1)+6))/(SUMIFS($P$8:$P$37,$A$8:$A$37,">="&$AJ$18+7*(2-1),$A$8:$A$37,"<="&$AJ$18+7*(2-1)+6)+SUMIFS('2026年07月'!$Q$8:$Q$38,'2026年07月'!$A$8:$A$38,">="&$AJ$18+7*(2-1),'2026年07月'!$A$8:$A$38,"<="&$AJ$18+7*(2-1)+6)),"")) -> 0.24074074 | AF21: =IF($AC21="","",IFERROR((SUMIFS($H$8:$H$37,$A$8:$A$37,">="&$AJ$18+7*(2-1),$A$8:$A$37,"<="&$AJ$18+7*(2-1)+6)+SUMIFS('2026年07月'!$I$8:$I$38,'2026年07月'!$A$8:$A$38,">="&$AJ$18+7*(2-1),'2026年07月'!$A$8:$A$38,"<="&$AJ$18+7*(2-1)+6))/(SUMIFS($N$8:$N$37,$A$8:$A$37,">="&$AJ$18+7*(2-1),$A$8:$A$37,"<="&$AJ$18+7*(2-1)+6)+SUMIFS('2026年07月'!$O$8:$O$38,'2026年07月'!$A$8:$A$38,">="&$AJ$18+7*(2-1),'2026年07月'!$A$8:$A$38,"<="&$AJ$18+7*(2-1)+6)),"")) -> 21817.846 | AG21: =IF($AC21="","",IFERROR((SUMIFS($O$8:$O$37,$A$8:$A$37,">="&$AJ$18+7*(2-1),$A$8:$A$37,"<="&$AJ$18+7*(2-1)+6)+SUMIFS('2026年07月'!$P$8:$P$38,'2026年07月'!$A$8:$A$38,">="&$AJ$18+7*(2-1),'2026年07月'!$A$8:$A$38,"<="&$AJ$18+7*(2-1)+6))/(SUMIFS($N$8:$N$37,$A$8:$A$37,">="&$AJ$18+7*(2-1),$A$8:$A$37,"<="&$AJ$18+7*(2-1)+6)+SUMIFS('2026年07月'!$O$8:$O$38,'2026年07月'!$A$8:$A$38,">="&$AJ$18+7*(2-1),'2026年07月'!$A$8:$A$38,"<="&$AJ$18+7*(2-1)+6)),"")) -> 1.1153846 | AH21: =IF($AC21="","",IFERROR((SUMIFS($Q$8:$Q$37,$A$8:$A$37,">="&$AJ$18+7*(2-1),$A$8:$A$37,"<="&$AJ$18+7*(2-1)+6)+SUMIFS('2026年07月'!$R$8:$R$38,'2026年07月'!$A$8:$A$38,">="&$AJ$18+7*(2-1),'2026年07月'!$A$8:$A$38,"<="&$AJ$18+7*(2-1)+6))/(SUMIFS($P$8:$P$37,$A$8:$A$37,">="&$AJ$18+7*(2-1),$A$8:$A$37,"<="&$AJ$18+7*(2-1)+6)+SUMIFS('2026年07月'!$Q$8:$Q$38,'2026年07月'!$A$8:$A$38,">="&$AJ$18+7*(2-1),'2026年07月'!$A$8:$A$38,"<="&$AJ$18+7*(2-1)+6)),"")) -> 0.34722222
A22: 46188 | B22: =MID("日月火水木金土",WEEKDAY(A22),1) -> 月 | C22: 250000 | D22: =SUM($C$8:C22) -> 4750000 | E22: 60710 | F22: 0 | H22: =IF(COUNT(E22:G22)=0,"",SUM(E22:G22)) -> 60710 | I22: =IF(H22="","",SUM($H$8:H22)) -> 2036639 | J22: =IF(H22="","",IFERROR(H22/C22,"")) -> 0.24284 | K22: =IF(I22="","",IFERROR(I22/D22,"")) -> 0.42876611 | L22: =IF(I22="","",IF(D22=0,"",I22-D22)) -> -2713361 | M22: =IF(H22="","—",IF(D22=0,"予算未入力",IF(I22>=D22,"◎ ペース内","▲ 遅れ"))) -> ▲ 遅れ | N22: 3 | O22: 3 | P22: 14 | Q22: 6 | R22: 10 | S22: =IFERROR(N22/P22,"") -> 0.21428571 | T22: =IFERROR(H22/N22,"") -> 20236.667 | U22: =IFERROR(O22/N22,"") -> 1 | V22: =IFERROR(Q22/P22,"") -> 0.42857143 | X22: 8918 | Y22: 0 | AB22: 3 | AC22: =IF($AJ$18+7*(3-1)>$A$37,"",TEXT($AJ$18+7*(3-1),"m/d")&"-"&TEXT($AJ$18+7*(3-1)+6,"m/d")) -> 6/16-6/22 | AD22: =IF($AC22="","",(SUMIFS($H$8:$H$37,$A$8:$A$37,">="&$AJ$18+7*(3-1),$A$8:$A$37,"<="&$AJ$18+7*(3-1)+6)+SUMIFS('2026年07月'!$I$8:$I$38,'2026年07月'!$A$8:$A$38,">="&$AJ$18+7*(3-1),'2026年07月'!$A$8:$A$38,"<="&$AJ$18+7*(3-1)+6))) -> 1342299 | AE22: =IF($AC22="","",IFERROR((SUMIFS($N$8:$N$37,$A$8:$A$37,">="&$AJ$18+7*(3-1),$A$8:$A$37,"<="&$AJ$18+7*(3-1)+6)+SUMIFS('2026年07月'!$O$8:$O$38,'2026年07月'!$A$8:$A$38,">="&$AJ$18+7*(3-1),'2026年07月'!$A$8:$A$38,"<="&$AJ$18+7*(3-1)+6))/(SUMIFS($P$8:$P$37,$A$8:$A$37,">="&$AJ$18+7*(3-1),$A$8:$A$37,"<="&$AJ$18+7*(3-1)+6)+SUMIFS('2026年07月'!$Q$8:$Q$38,'2026年07月'!$A$8:$A$38,">="&$AJ$18+7*(3-1),'2026年07月'!$A$8:$A$38,"<="&$AJ$18+7*(3-1)+6)),"")) -> 0.30845771 | AF22: =IF($AC22="","",IFERROR((SUMIFS($H$8:$H$37,$A$8:$A$37,">="&$AJ$18+7*(3-1),$A$8:$A$37,"<="&$AJ$18+7*(3-1)+6)+SUMIFS('2026年07月'!$I$8:$I$38,'2026年07月'!$A$8:$A$38,">="&$AJ$18+7*(3-1),'2026年07月'!$A$8:$A$38,"<="&$AJ$18+7*(3-1)+6))/(SUMIFS($N$8:$N$37,$A$8:$A$37,">="&$AJ$18+7*(3-1),$A$8:$A$37,"<="&$AJ$18+7*(3-1)+6)+SUMIFS('2026年07月'!$O$8:$O$38,'2026年07月'!$A$8:$A$38,">="&$AJ$18+7*(3-1),'2026年07月'!$A$8:$A$38,"<="&$AJ$18+7*(3-1)+6)),"")) -> 21649.984 | AG22: =IF($AC22="","",IFERROR((SUMIFS($O$8:$O$37,$A$8:$A$37,">="&$AJ$18+7*(3-1),$A$8:$A$37,"<="&$AJ$18+7*(3-1)+6)+SUMIFS('2026年07月'!$P$8:$P$38,'2026年07月'!$A$8:$A$38,">="&$AJ$18+7*(3-1),'2026年07月'!$A$8:$A$38,"<="&$AJ$18+7*(3-1)+6))/(SUMIFS($N$8:$N$37,$A$8:$A$37,">="&$AJ$18+7*(3-1),$A$8:$A$37,"<="&$AJ$18+7*(3-1)+6)+SUMIFS('2026年07月'!$O$8:$O$38,'2026年07月'!$A$8:$A$38,">="&$AJ$18+7*(3-1),'2026年07月'!$A$8:$A$38,"<="&$AJ$18+7*(3-1)+6)),"")) -> 1.1935484 | AH22: =IF($AC22="","",IFERROR((SUMIFS($Q$8:$Q$37,$A$8:$A$37,">="&$AJ$18+7*(3-1),$A$8:$A$37,"<="&$AJ$18+7*(3-1)+6)+SUMIFS('2026年07月'!$R$8:$R$38,'2026年07月'!$A$8:$A$38,">="&$AJ$18+7*(3-1),'2026年07月'!$A$8:$A$38,"<="&$AJ$18+7*(3-1)+6))/(SUMIFS($P$8:$P$37,$A$8:$A$37,">="&$AJ$18+7*(3-1),$A$8:$A$37,"<="&$AJ$18+7*(3-1)+6)+SUMIFS('2026年07月'!$Q$8:$Q$38,'2026年07月'!$A$8:$A$38,">="&$AJ$18+7*(3-1),'2026年07月'!$A$8:$A$38,"<="&$AJ$18+7*(3-1)+6)),"")) -> 0.36318408
A23: 46189 | B23: =MID("日月火水木金土",WEEKDAY(A23),1) -> 火 | C23: 250000 | D23: =SUM($C$8:C23) -> 5000000 | E23: 96350 | F23: 23810 | G23: 10446 | H23: =IF(COUNT(E23:G23)=0,"",SUM(E23:G23)) -> 130606 | I23: =IF(H23="","",SUM($H$8:H23)) -> 2167245 | J23: =IF(H23="","",IFERROR(H23/C23,"")) -> 0.522424 | K23: =IF(I23="","",IFERROR(I23/D23,"")) -> 0.433449 | L23: =IF(I23="","",IF(D23=0,"",I23-D23)) -> -2832755 | M23: =IF(H23="","—",IF(D23=0,"予算未入力",IF(I23>=D23,"◎ ペース内","▲ 遅れ"))) -> ▲ 遅れ | N23: 6 | O23: 7 | P23: 25 | Q23: 6 | R23: 10 | S23: =IFERROR(N23/P23,"") -> 0.24 | T23: =IFERROR(H23/N23,"") -> 21767.667 | U23: =IFERROR(O23/N23,"") -> 1.1666667 | V23: =IFERROR(Q23/P23,"") -> 0.24 | X23: 8915 | Y23: 813 | AB23: 4 | AC23: =IF($AJ$18+7*(4-1)>$A$37,"",TEXT($AJ$18+7*(4-1),"m/d")&"-"&TEXT($AJ$18+7*(4-1)+6,"m/d")) -> 6/23-6/29 | AD23: =IF($AC23="","",(SUMIFS($H$8:$H$37,$A$8:$A$37,">="&$AJ$18+7*(4-1),$A$8:$A$37,"<="&$AJ$18+7*(4-1)+6)+SUMIFS('2026年07月'!$I$8:$I$38,'2026年07月'!$A$8:$A$38,">="&$AJ$18+7*(4-1),'2026年07月'!$A$8:$A$38,"<="&$AJ$18+7*(4-1)+6))) -> 1699461 | AE23: =IF($AC23="","",IFERROR((SUMIFS($N$8:$N$37,$A$8:$A$37,">="&$AJ$18+7*(4-1),$A$8:$A$37,"<="&$AJ$18+7*(4-1)+6)+SUMIFS('2026年07月'!$O$8:$O$38,'2026年07月'!$A$8:$A$38,">="&$AJ$18+7*(4-1),'2026年07月'!$A$8:$A$38,"<="&$AJ$18+7*(4-1)+6))/(SUMIFS($P$8:$P$37,$A$8:$A$37,">="&$AJ$18+7*(4-1),$A$8:$A$37,"<="&$AJ$18+7*(4-1)+6)+SUMIFS('2026年07月'!$Q$8:$Q$38,'2026年07月'!$A$8:$A$38,">="&$AJ$18+7*(4-1),'2026年07月'!$A$8:$A$38,"<="&$AJ$18+7*(4-1)+6)),"")) -> 0.38888889 | AF23: =IF($AC23="","",IFERROR((SUMIFS($H$8:$H$37,$A$8:$A$37,">="&$AJ$18+7*(4-1),$A$8:$A$37,"<="&$AJ$18+7*(4-1)+6)+SUMIFS('2026年07月'!$I$8:$I$38,'2026年07月'!$A$8:$A$38,">="&$AJ$18+7*(4-1),'2026年07月'!$A$8:$A$38,"<="&$AJ$18+7*(4-1)+6))/(SUMIFS($N$8:$N$37,$A$8:$A$37,">="&$AJ$18+7*(4-1),$A$8:$A$37,"<="&$AJ$18+7*(4-1)+6)+SUMIFS('2026年07月'!$O$8:$O$38,'2026年07月'!$A$8:$A$38,">="&$AJ$18+7*(4-1),'2026年07月'!$A$8:$A$38,"<="&$AJ$18+7*(4-1)+6)),"")) -> 22070.922 | AG23: =IF($AC23="","",IFERROR((SUMIFS($O$8:$O$37,$A$8:$A$37,">="&$AJ$18+7*(4-1),$A$8:$A$37,"<="&$AJ$18+7*(4-1)+6)+SUMIFS('2026年07月'!$P$8:$P$38,'2026年07月'!$A$8:$A$38,">="&$AJ$18+7*(4-1),'2026年07月'!$A$8:$A$38,"<="&$AJ$18+7*(4-1)+6))/(SUMIFS($N$8:$N$37,$A$8:$A$37,">="&$AJ$18+7*(4-1),$A$8:$A$37,"<="&$AJ$18+7*(4-1)+6)+SUMIFS('2026年07月'!$O$8:$O$38,'2026年07月'!$A$8:$A$38,">="&$AJ$18+7*(4-1),'2026年07月'!$A$8:$A$38,"<="&$AJ$18+7*(4-1)+6)),"")) -> 1.1428571 | AH23: =IF($AC23="","",IFERROR((SUMIFS($Q$8:$Q$37,$A$8:$A$37,">="&$AJ$18+7*(4-1),$A$8:$A$37,"<="&$AJ$18+7*(4-1)+6)+SUMIFS('2026年07月'!$R$8:$R$38,'2026年07月'!$A$8:$A$38,">="&$AJ$18+7*(4-1),'2026年07月'!$A$8:$A$38,"<="&$AJ$18+7*(4-1)+6))/(SUMIFS($P$8:$P$37,$A$8:$A$37,">="&$AJ$18+7*(4-1),$A$8:$A$37,"<="&$AJ$18+7*(4-1)+6)+SUMIFS('2026年07月'!$Q$8:$Q$38,'2026年07月'!$A$8:$A$38,">="&$AJ$18+7*(4-1),'2026年07月'!$A$8:$A$38,"<="&$AJ$18+7*(4-1)+6)),"")) -> 0.45959596
A24: 46190 | B24: =MID("日月火水木金土",WEEKDAY(A24),1) -> 水 | C24: 250000 | D24: =SUM($C$8:C24) -> 5250000 | E24: 85248 | F24: 63722 | G24: 9840 | H24: =IF(COUNT(E24:G24)=0,"",SUM(E24:G24)) -> 158810 | I24: =IF(H24="","",SUM($H$8:H24)) -> 2326055 | J24: =IF(H24="","",IFERROR(H24/C24,"")) -> 0.63524 | K24: =IF(I24="","",IFERROR(I24/D24,"")) -> 0.4430581 | L24: =IF(I24="","",IF(D24=0,"",I24-D24)) -> -2923945 | M24: =IF(H24="","—",IF(D24=0,"予算未入力",IF(I24>=D24,"◎ ペース内","▲ 遅れ"))) -> ▲ 遅れ | N24: 7 | O24: 8 | P24: 21 | Q24: 10 | R24: 19 | S24: =IFERROR(N24/P24,"") -> 0.33333333 | T24: =IFERROR(H24/N24,"") -> 22687.143 | U24: =IFERROR(O24/N24,"") -> 1.1428571 | V24: =IFERROR(Q24/P24,"") -> 0.47619048 | X24: 8913 | Y24: 0 | AB24: 5 | AC24: =IF($AJ$18+7*(5-1)>$A$37,"",TEXT($AJ$18+7*(5-1),"m/d")&"-"&TEXT($AJ$18+7*(5-1)+6,"m/d")) -> 6/30-7/6 | AD24: =IF($AC24="","",(SUMIFS($H$8:$H$37,$A$8:$A$37,">="&$AJ$18+7*(5-1),$A$8:$A$37,"<="&$AJ$18+7*(5-1)+6)+SUMIFS('2026年07月'!$I$8:$I$38,'2026年07月'!$A$8:$A$38,">="&$AJ$18+7*(5-1),'2026年07月'!$A$8:$A$38,"<="&$AJ$18+7*(5-1)+6))) -> 1277407 | AE24: =IF($AC24="","",IFERROR((SUMIFS($N$8:$N$37,$A$8:$A$37,">="&$AJ$18+7*(5-1),$A$8:$A$37,"<="&$AJ$18+7*(5-1)+6)+SUMIFS('2026年07月'!$O$8:$O$38,'2026年07月'!$A$8:$A$38,">="&$AJ$18+7*(5-1),'2026年07月'!$A$8:$A$38,"<="&$AJ$18+7*(5-1)+6))/(SUMIFS($P$8:$P$37,$A$8:$A$37,">="&$AJ$18+7*(5-1),$A$8:$A$37,"<="&$AJ$18+7*(5-1)+6)+SUMIFS('2026年07月'!$Q$8:$Q$38,'2026年07月'!$A$8:$A$38,">="&$AJ$18+7*(5-1),'2026年07月'!$A$8:$A$38,"<="&$AJ$18+7*(5-1)+6)),"")) -> 0.29411765 | AF24: =IF($AC24="","",IFERROR((SUMIFS($H$8:$H$37,$A$8:$A$37,">="&$AJ$18+7*(5-1),$A$8:$A$37,"<="&$AJ$18+7*(5-1)+6)+SUMIFS('2026年07月'!$I$8:$I$38,'2026年07月'!$A$8:$A$38,">="&$AJ$18+7*(5-1),'2026年07月'!$A$8:$A$38,"<="&$AJ$18+7*(5-1)+6))/(SUMIFS($N$8:$N$37,$A$8:$A$37,">="&$AJ$18+7*(5-1),$A$8:$A$37,"<="&$AJ$18+7*(5-1)+6)+SUMIFS('2026年07月'!$O$8:$O$38,'2026年07月'!$A$8:$A$38,">="&$AJ$18+7*(5-1),'2026年07月'!$A$8:$A$38,"<="&$AJ$18+7*(5-1)+6)),"")) -> 23225.582 | AG24: =IF($AC24="","",IFERROR((SUMIFS($O$8:$O$37,$A$8:$A$37,">="&$AJ$18+7*(5-1),$A$8:$A$37,"<="&$AJ$18+7*(5-1)+6)+SUMIFS('2026年07月'!$P$8:$P$38,'2026年07月'!$A$8:$A$38,">="&$AJ$18+7*(5-1),'2026年07月'!$A$8:$A$38,"<="&$AJ$18+7*(5-1)+6))/(SUMIFS($N$8:$N$37,$A$8:$A$37,">="&$AJ$18+7*(5-1),$A$8:$A$37,"<="&$AJ$18+7*(5-1)+6)+SUMIFS('2026年07月'!$O$8:$O$38,'2026年07月'!$A$8:$A$38,">="&$AJ$18+7*(5-1),'2026年07月'!$A$8:$A$38,"<="&$AJ$18+7*(5-1)+6)),"")) -> 1.0545455 | AH24: =IF($AC24="","",IFERROR((SUMIFS($Q$8:$Q$37,$A$8:$A$37,">="&$AJ$18+7*(5-1),$A$8:$A$37,"<="&$AJ$18+7*(5-1)+6)+SUMIFS('2026年07月'!$R$8:$R$38,'2026年07月'!$A$8:$A$38,">="&$AJ$18+7*(5-1),'2026年07月'!$A$8:$A$38,"<="&$AJ$18+7*(5-1)+6))/(SUMIFS($P$8:$P$37,$A$8:$A$37,">="&$AJ$18+7*(5-1),$A$8:$A$37,"<="&$AJ$18+7*(5-1)+6)+SUMIFS('2026年07月'!$Q$8:$Q$38,'2026年07月'!$A$8:$A$38,">="&$AJ$18+7*(5-1),'2026年07月'!$A$8:$A$38,"<="&$AJ$18+7*(5-1)+6)),"")) -> 0.4171123
A25: 46191 | B25: =MID("日月火水木金土",WEEKDAY(A25),1) -> 木 | C25: 250000 | D25: =SUM($C$8:C25) -> 5500000 | E25: 0 | F25: 46310 | G25: -4310 | H25: =IF(COUNT(E25:G25)=0,"",SUM(E25:G25)) -> 42000 | I25: =IF(H25="","",SUM($H$8:H25)) -> 2368055 | J25: =IF(H25="","",IFERROR(H25/C25,"")) -> 0.168 | K25: =IF(I25="","",IFERROR(I25/D25,"")) -> 0.43055545 | L25: =IF(I25="","",IF(D25=0,"",I25-D25)) -> -3131945 | M25: =IF(H25="","—",IF(D25=0,"予算未入力",IF(I25>=D25,"◎ ペース内","▲ 遅れ"))) -> ▲ 遅れ | N25: 2 | O25: 2 | P25: 21 | Q25: 4 | R25: 6 | S25: =IFERROR(N25/P25,"") -> 0.095238095 | T25: =IFERROR(H25/N25,"") -> 21000 | U25: =IFERROR(O25/N25,"") -> 1 | V25: =IFERROR(Q25/P25,"") -> 0.19047619 | X25: 8907 | Y25: 0 | AB25: 6 | AC25: =IF($AJ$18+7*(6-1)>$A$37,"",TEXT($AJ$18+7*(6-1),"m/d")&"-"&TEXT($AJ$18+7*(6-1)+6,"m/d")) | AD25: =IF($AC25="","",(SUMIFS($H$8:$H$37,$A$8:$A$37,">="&$AJ$18+7*(6-1),$A$8:$A$37,"<="&$AJ$18+7*(6-1)+6)+SUMIFS('2026年07月'!$I$8:$I$38,'2026年07月'!$A$8:$A$38,">="&$AJ$18+7*(6-1),'2026年07月'!$A$8:$A$38,"<="&$AJ$18+7*(6-1)+6))) | AE25: =IF($AC25="","",IFERROR((SUMIFS($N$8:$N$37,$A$8:$A$37,">="&$AJ$18+7*(6-1),$A$8:$A$37,"<="&$AJ$18+7*(6-1)+6)+SUMIFS('2026年07月'!$O$8:$O$38,'2026年07月'!$A$8:$A$38,">="&$AJ$18+7*(6-1),'2026年07月'!$A$8:$A$38,"<="&$AJ$18+7*(6-1)+6))/(SUMIFS($P$8:$P$37,$A$8:$A$37,">="&$AJ$18+7*(6-1),$A$8:$A$37,"<="&$AJ$18+7*(6-1)+6)+SUMIFS('2026年07月'!$Q$8:$Q$38,'2026年07月'!$A$8:$A$38,">="&$AJ$18+7*(6-1),'2026年07月'!$A$8:$A$38,"<="&$AJ$18+7*(6-1)+6)),"")) | AF25: =IF($AC25="","",IFERROR((SUMIFS($H$8:$H$37,$A$8:$A$37,">="&$AJ$18+7*(6-1),$A$8:$A$37,"<="&$AJ$18+7*(6-1)+6)+SUMIFS('2026年07月'!$I$8:$I$38,'2026年07月'!$A$8:$A$38,">="&$AJ$18+7*(6-1),'2026年07月'!$A$8:$A$38,"<="&$AJ$18+7*(6-1)+6))/(SUMIFS($N$8:$N$37,$A$8:$A$37,">="&$AJ$18+7*(6-1),$A$8:$A$37,"<="&$AJ$18+7*(6-1)+6)+SUMIFS('2026年07月'!$O$8:$O$38,'2026年07月'!$A$8:$A$38,">="&$AJ$18+7*(6-1),'2026年07月'!$A$8:$A$38,"<="&$AJ$18+7*(6-1)+6)),"")) | AG25: =IF($AC25="","",IFERROR((SUMIFS($O$8:$O$37,$A$8:$A$37,">="&$AJ$18+7*(6-1),$A$8:$A$37,"<="&$AJ$18+7*(6-1)+6)+SUMIFS('2026年07月'!$P$8:$P$38,'2026年07月'!$A$8:$A$38,">="&$AJ$18+7*(6-1),'2026年07月'!$A$8:$A$38,"<="&$AJ$18+7*(6-1)+6))/(SUMIFS($N$8:$N$37,$A$8:$A$37,">="&$AJ$18+7*(6-1),$A$8:$A$37,"<="&$AJ$18+7*(6-1)+6)+SUMIFS('2026年07月'!$O$8:$O$38,'2026年07月'!$A$8:$A$38,">="&$AJ$18+7*(6-1),'2026年07月'!$A$8:$A$38,"<="&$AJ$18+7*(6-1)+6)),"")) | AH25: =IF($AC25="","",IFERROR((SUMIFS($Q$8:$Q$37,$A$8:$A$37,">="&$AJ$18+7*(6-1),$A$8:$A$37,"<="&$AJ$18+7*(6-1)+6)+SUMIFS('2026年07月'!$R$8:$R$38,'2026年07月'!$A$8:$A$38,">="&$AJ$18+7*(6-1),'2026年07月'!$A$8:$A$38,"<="&$AJ$18+7*(6-1)+6))/(SUMIFS($P$8:$P$37,$A$8:$A$37,">="&$AJ$18+7*(6-1),$A$8:$A$37,"<="&$AJ$18+7*(6-1)+6)+SUMIFS('2026年07月'!$Q$8:$Q$38,'2026年07月'!$A$8:$A$38,">="&$AJ$18+7*(6-1),'2026年07月'!$A$8:$A$38,"<="&$AJ$18+7*(6-1)+6)),""))
A26: 46192 | B26: =MID("日月火水木金土",WEEKDAY(A26),1) -> 金 | C26: 250000 | D26: =SUM($C$8:C26) -> 5750000 | E26: 145720 | F26: 108610 | G26: 20012 | H26: =IF(COUNT(E26:G26)=0,"",SUM(E26:G26)) -> 274342 | I26: =IF(H26="","",SUM($H$8:H26)) -> 2642397 | J26: =IF(H26="","",IFERROR(H26/C26,"")) -> 1.097368 | K26: =IF(I26="","",IFERROR(I26/D26,"")) -> 0.4595473 | L26: =IF(I26="","",IF(D26=0,"",I26-D26)) -> -3107603 | M26: =IF(H26="","—",IF(D26=0,"予算未入力",IF(I26>=D26,"◎ ペース内","▲ 遅れ"))) -> ▲ 遅れ | N26: 14 | O26: 16 | P26: 29 | Q26: 11 | R26: 15 | S26: =IFERROR(N26/P26,"") -> 0.48275862 | T26: =IFERROR(H26/N26,"") -> 19595.857 | U26: =IFERROR(O26/N26,"") -> 1.1428571 | V26: =IFERROR(Q26/P26,"") -> 0.37931034 | X26: 8904 | Y26: 0 | AB26: ※期間ラベルは第1火曜から自動生成。決定率・客単価・セット率・試着率は「週合計÷週合計」
A27: 46193 | B27: =MID("日月火水木金土",WEEKDAY(A27),1) -> 土 | C27: 500000 | D27: =SUM($C$8:C27) -> 6250000 | E27: 117660 | F27: 160410 | G27: 16448 | H27: =IF(COUNT(E27:G27)=0,"",SUM(E27:G27)) -> 294518 | I27: =IF(H27="","",SUM($H$8:H27)) -> 2936915 | J27: =IF(H27="","",IFERROR(H27/C27,"")) -> 0.589036 | K27: =IF(I27="","",IFERROR(I27/D27,"")) -> 0.4699064 | L27: =IF(I27="","",IF(D27=0,"",I27-D27)) -> -3313085 | M27: =IF(H27="","—",IF(D27=0,"予算未入力",IF(I27>=D27,"◎ ペース内","▲ 遅れ"))) -> ▲ 遅れ | N27: 15 | O27: 17 | P27: 50 | Q27: 20 | R27: 33 | S27: =IFERROR(N27/P27,"") -> 0.3 | T27: =IFERROR(H27/N27,"") -> 19634.533 | U27: =IFERROR(O27/N27,"") -> 1.1333333 | V27: =IFERROR(Q27/P27,"") -> 0.4 | X27: 8897 | Y27: 0 | AB27: ※最終週は翌月にまたぐため、2026年07月シートの実績も自動で合算します
A28: 46194 | B28: =MID("日月火水木金土",WEEKDAY(A28),1) -> 日 | C28: 500000 | D28: =SUM($C$8:C28) -> 6750000 | E28: 169110 | F28: 233340 | G28: 16071 | H28: =IF(COUNT(E28:G28)=0,"",SUM(E28:G28)) -> 418521 | I28: =IF(H28="","",SUM($H$8:H28)) -> 3355436 | J28: =IF(H28="","",IFERROR(H28/C28,"")) -> 0.837042 | K28: =IF(I28="","",IFERROR(I28/D28,"")) -> 0.49710163 | L28: =IF(I28="","",IF(D28=0,"",I28-D28)) -> -3394564 | M28: =IF(H28="","—",IF(D28=0,"予算未入力",IF(I28>=D28,"◎ ペース内","▲ 遅れ"))) -> ▲ 遅れ | N28: 17 | O28: 23 | P28: 42 | Q28: 20 | R28: 33 | S28: =IFERROR(N28/P28,"") -> 0.4047619 | T28: =IFERROR(H28/N28,"") -> 24618.882 | U28: =IFERROR(O28/N28,"") -> 1.3529412 | V28: =IFERROR(Q28/P28,"") -> 0.47619048 | X28: 8892 | Y28: 0 | AB28: ※月初の月曜まで（例：6/1）は前月シートの最終週に含まれます
A29: 46195 | B29: =MID("日月火水木金土",WEEKDAY(A29),1) -> 月 | C29: 250000 | D29: =SUM($C$8:C29) -> 7000000 | E29: 23502 | F29: 0 | H29: =IF(COUNT(E29:G29)=0,"",SUM(E29:G29)) -> 23502 | I29: =IF(H29="","",SUM($H$8:H29)) -> 3378938 | J29: =IF(H29="","",IFERROR(H29/C29,"")) -> 0.094008 | K29: =IF(I29="","",IFERROR(I29/D29,"")) -> 0.48270543 | L29: =IF(I29="","",IF(D29=0,"",I29-D29)) -> -3621062 | M29: =IF(H29="","—",IF(D29=0,"予算未入力",IF(I29>=D29,"◎ ペース内","▲ 遅れ"))) -> ▲ 遅れ | N29: 1 | O29: 1 | P29: 13 | Q29: 2 | R29: 4 | S29: =IFERROR(N29/P29,"") -> 0.076923077 | T29: =IFERROR(H29/N29,"") -> 23502 | U29: =IFERROR(O29/N29,"") -> 1 | V29: =IFERROR(Q29/P29,"") -> 0.15384615 | X29: 8888 | Y29: 0
A30: 46196 | B30: =MID("日月火水木金土",WEEKDAY(A30),1) -> 火 | C30: 250000 | D30: =SUM($C$8:C30) -> 7250000 | E30: 160040 | F30: 133832 | G30: -6340 | H30: =IF(COUNT(E30:G30)=0,"",SUM(E30:G30)) -> 287532 | I30: =IF(H30="","",SUM($H$8:H30)) -> 3666470 | J30: =IF(H30="","",IFERROR(H30/C30,"")) -> 1.150128 | K30: =IF(I30="","",IFERROR(I30/D30,"")) -> 0.50572 | L30: =IF(I30="","",IF(D30=0,"",I30-D30)) -> -3583530 | M30: =IF(H30="","—",IF(D30=0,"予算未入力",IF(I30>=D30,"◎ ペース内","▲ 遅れ"))) -> ▲ 遅れ | N30: 13 | O30: 15 | P30: 30 | Q30: 13 | R30: 24 | S30: =IFERROR(N30/P30,"") -> 0.43333333 | T30: =IFERROR(H30/N30,"") -> 22117.846 | U30: =IFERROR(O30/N30,"") -> 1.1538462 | V30: =IFERROR(Q30/P30,"") -> 0.43333333 | X30: 8884 | Y30: 0
A31: 46197 | B31: =MID("日月火水木金土",WEEKDAY(A31),1) -> 水 | C31: 250000 | D31: =SUM($C$8:C31) -> 7500000 | E31: 76830 | F31: 46910 | G31: 4789 | H31: =IF(COUNT(E31:G31)=0,"",SUM(E31:G31)) -> 128529 | I31: =IF(H31="","",SUM($H$8:H31)) -> 3794999 | J31: =IF(H31="","",IFERROR(H31/C31,"")) -> 0.514116 | K31: =IF(I31="","",IFERROR(I31/D31,"")) -> 0.50599987 | L31: =IF(I31="","",IF(D31=0,"",I31-D31)) -> -3705001 | M31: =IF(H31="","—",IF(D31=0,"予算未入力",IF(I31>=D31,"◎ ペース内","▲ 遅れ"))) -> ▲ 遅れ | N31: 6 | O31: 6 | P31: 17 | Q31: 10 | R31: 17 | S31: =IFERROR(N31/P31,"") -> 0.35294118 | T31: =IFERROR(H31/N31,"") -> 21421.5 | U31: =IFERROR(O31/N31,"") -> 1 | V31: =IFERROR(Q31/P31,"") -> 0.58823529 | X31: 8885 | Y31: 0
A32: 46198 | B32: =MID("日月火水木金土",WEEKDAY(A32),1) -> 木 | C32: 250000 | D32: =SUM($C$8:C32) -> 7750000 | E32: 51810 | F32: 124060 | G32: 32442 | H32: =IF(COUNT(E32:G32)=0,"",SUM(E32:G32)) -> 208312 | I32: =IF(H32="","",SUM($H$8:H32)) -> 4003311 | J32: =IF(H32="","",IFERROR(H32/C32,"")) -> 0.833248 | K32: =IF(I32="","",IFERROR(I32/D32,"")) -> 0.51655626 | L32: =IF(I32="","",IF(D32=0,"",I32-D32)) -> -3746689 | M32: =IF(H32="","—",IF(D32=0,"予算未入力",IF(I32>=D32,"◎ ペース内","▲ 遅れ"))) -> ▲ 遅れ | N32: 9 | O32: 12 | P32: 21 | Q32: 11 | R32: 15 | S32: =IFERROR(N32/P32,"") -> 0.42857143 | T32: =IFERROR(H32/N32,"") -> 23145.778 | U32: =IFERROR(O32/N32,"") -> 1.3333333 | V32: =IFERROR(Q32/P32,"") -> 0.52380952 | X32: 8883 | Y32: 0
A33: 46199 | B33: =MID("日月火水木金土",WEEKDAY(A33),1) -> 金 | C33: 250000 | D33: =SUM($C$8:C33) -> 8000000 | E33: 23810 | F33: 114450 | G33: 6292 | H33: =IF(COUNT(E33:G33)=0,"",SUM(E33:G33)) -> 144552 | I33: =IF(H33="","",SUM($H$8:H33)) -> 4147863 | J33: =IF(H33="","",IFERROR(H33/C33,"")) -> 0.578208 | K33: =IF(I33="","",IFERROR(I33/D33,"")) -> 0.51848288 | L33: =IF(I33="","",IF(D33=0,"",I33-D33)) -> -3852137 | M33: =IF(H33="","—",IF(D33=0,"予算未入力",IF(I33>=D33,"◎ ペース内","▲ 遅れ"))) -> ▲ 遅れ | N33: 7 | O33: 7 | P33: 22 | Q33: 9 | R33: 14 | S33: =IFERROR(N33/P33,"") -> 0.31818182 | T33: =IFERROR(H33/N33,"") -> 20650.286 | U33: =IFERROR(O33/N33,"") -> 1 | V33: =IFERROR(Q33/P33,"") -> 0.40909091 | X33: 8878 | Y33: 0
A34: 46200 | B34: =MID("日月火水木金土",WEEKDAY(A34),1) -> 土 | C34: 500000 | D34: =SUM($C$8:C34) -> 8500000 | E34: 277390 | F34: 162070 | G34: -42957 | H34: =IF(COUNT(E34:G34)=0,"",SUM(E34:G34)) -> 396503 | I34: =IF(H34="","",SUM($H$8:H34)) -> 4544366 | J34: =IF(H34="","",IFERROR(H34/C34,"")) -> 0.793006 | K34: =IF(I34="","",IFERROR(I34/D34,"")) -> 0.53463129 | L34: =IF(I34="","",IF(D34=0,"",I34-D34)) -> -3955634 | M34: =IF(H34="","—",IF(D34=0,"予算未入力",IF(I34>=D34,"◎ ペース内","▲ 遅れ"))) -> ▲ 遅れ | N34: 18 | O34: 18 | P34: 42 | Q34: 23 | R34: 36 | S34: =IFERROR(N34/P34,"") -> 0.42857143 | T34: =IFERROR(H34/N34,"") -> 22027.944 | U34: =IFERROR(O34/N34,"") -> 1 | V34: =IFERROR(Q34/P34,"") -> 0.54761905 | X34: 8876 | Y34: 0
A35: 46201 | B35: =MID("日月火水木金土",WEEKDAY(A35),1) -> 日 | C35: 500000 | D35: =SUM($C$8:C35) -> 9000000 | E35: 84230 | F35: 315620 | G35: 23821 | H35: =IF(COUNT(E35:G35)=0,"",SUM(E35:G35)) -> 423671 | I35: =IF(H35="","",SUM($H$8:H35)) -> 4968037 | J35: =IF(H35="","",IFERROR(H35/C35,"")) -> 0.847342 | K35: =IF(I35="","",IFERROR(I35/D35,"")) -> 0.55200411 | L35: =IF(I35="","",IF(D35=0,"",I35-D35)) -> -4031963 | M35: =IF(H35="","—",IF(D35=0,"予算未入力",IF(I35>=D35,"◎ ペース内","▲ 遅れ"))) -> ▲ 遅れ | N35: 20 | O35: 24 | P35: 45 | Q35: 19 | R35: 32 | S35: =IFERROR(N35/P35,"") -> 0.44444444 | T35: =IFERROR(H35/N35,"") -> 21183.55 | U35: =IFERROR(O35/N35,"") -> 1.2 | V35: =IFERROR(Q35/P35,"") -> 0.42222222 | X35: 8869 | Y35: 0
A36: 46202 | B36: =MID("日月火水木金土",WEEKDAY(A36),1) -> 月 | C36: 250000 | D36: =SUM($C$8:C36) -> 9250000 | E36: 23810 | F36: 98147 | G36: -11595 | H36: =IF(COUNT(E36:G36)=0,"",SUM(E36:G36)) -> 110362 | I36: =IF(H36="","",SUM($H$8:H36)) -> 5078399 | J36: =IF(H36="","",IFERROR(H36/C36,"")) -> 0.441448 | K36: =IF(I36="","",IFERROR(I36/D36,"")) -> 0.54901611 | L36: =IF(I36="","",IF(D36=0,"",I36-D36)) -> -4171601 | M36: =IF(H36="","—",IF(D36=0,"予算未入力",IF(I36>=D36,"◎ ペース内","▲ 遅れ"))) -> ▲ 遅れ | N36: 4 | O36: 6 | P36: 21 | Q36: 6 | R36: 9 | S36: =IFERROR(N36/P36,"") -> 0.19047619 | T36: =IFERROR(H36/N36,"") -> 27590.5 | U36: =IFERROR(O36/N36,"") -> 1.5 | V36: =IFERROR(Q36/P36,"") -> 0.28571429 | X36: 8864 | Y36: 1262
A37: 46203 | B37: =MID("日月火水木金土",WEEKDAY(A37),1) -> 火 | C37: 250000 | D37: =SUM($C$8:C37) -> 9500000 | E37: 24310 | F37: 86830 | G37: 10867 | H37: =IF(COUNT(E37:G37)=0,"",SUM(E37:G37)) -> 122007 | I37: =IF(H37="","",SUM($H$8:H37)) -> 5200406 | J37: =IF(H37="","",IFERROR(H37/C37,"")) -> 0.488028 | K37: =IF(I37="","",IFERROR(I37/D37,"")) -> 0.54741116 | L37: =IF(I37="","",IF(D37=0,"",I37-D37)) -> -4299594 | M37: =IF(H37="","—",IF(D37=0,"予算未入力",IF(I37>=D37,"◎ ペース内","▲ 遅れ"))) -> ▲ 遅れ | N37: 6 | O37: 6 | P37: 19 | Q37: 10 | R37: 17 | S37: =IFERROR(N37/P37,"") -> 0.31578947 | T37: =IFERROR(H37/N37,"") -> 20334.5 | U37: =IFERROR(O37/N37,"") -> 1 | V37: =IFERROR(Q37/P37,"") -> 0.52631579 | X37: 8863 | Y37: 0
A38: 月計 | C38: =SUM(C8:C37) -> 9500000 | D38: =C38 -> 9500000 | E38: =SUM(E8:E37) -> 2247880 | F38: =SUM(F8:F37) -> 2737571 | G38: =SUM(G8:G37) -> 214955 | H38: =SUM(H8:H37) -> 5200406 | I38: =H38 -> 5200406 | J38: =IFERROR(H38/C38,"") -> 0.54741116 | K38: =IFERROR(H38/C38,"") -> 0.54741116 | L38: =H38-C38 -> -4299594 | N38: =SUM(N8:N37) -> 240 | O38: =SUM(O8:O37) -> 271 | P38: =SUM(P8:P37) -> 834 | Q38: =SUM(Q8:Q37) -> 318 | R38: =SUM(R8:R37) -> 508 | S38: =IFERROR(N38/P38,"") -> 0.28776978 | T38: =IFERROR(H38/N38,"") -> 21668.358 | U38: =IFERROR(O38/N38,"") -> 1.1291667 | V38: =IFERROR(Q38/P38,"") -> 0.38129496 | W38: =SUM(W8:W37) -> 0 | X38: =IFERROR(LOOKUP(9.99E+307,X8:X37),"") -> 8863 | Y38: =SUM(Y8:Y37) -> 2075 | Z38: フォロワーは月末値

Sheet 2026年07月
A1: 2026年7月 名古屋店 日別売上管理
A2: 青字＋薄黄色のセルが入力欄。白セルは数式なので触らないでください。単位：円
A3: 月間予算 | C3: 当月実績 | E3: 達成率 | G3: 営業日数(/31日) | I3: 残り必要額 | K3: 残り必要日商
A4: =IF('設定'!$B$11="",SUM(C8:C38),'設定'!$B$11) -> 14000000 | C4: =SUM(I8:I38) -> 5575024 | E4: =IFERROR(C4/A4,0) -> 0.398216 | G4: =COUNTIF(I8:I38,">0") -> 29 | I4: =A4-C4 -> 8424976 | K4: =IF((31-G4)>0,(A4-C4)/(31-G4),0) -> 4212488
A5: 日次予算合計 | C5: 着地見込 | E5: 決定率 | G5: 客単価 | I5: セット率 | K5: 試着率
A6: =SUM(C8:C38) -> 13600000 | C6: =IFERROR(C4/G4*31,0) -> 5959508.4 | E6: =IFERROR(O39/Q39,0) -> 0.30390921 | G6: =IFERROR(I39/O39,0) -> 23132.88 | I6: =IFERROR(P39/O39,0) -> 1.0871369 | K6: =IFERROR(R39/Q39,0) -> 0.38461538
A7: 日付 | B7: 曜 | C7: 日次予算 | D7: 累計予算 | E7: 現金 | F7: クレジット | G7: 商品券 | H7: 内訳差額 (要確認) | I7: 実績合計 | J7: 累計実績 | K7: 日次達成 | L7: 累計達成 | M7: 累計予実差 | N7: ペース | O7: 購入人数 | P7: 販売点数 | Q7: 来客数 | R7: 試着組数 | S7: 試着個数 | T7: 決定率 | U7: 客単価 | V7: セット率 | W7: 試着率 | X7: クロス クーポン | Y7: インスタ フォロワー | Z7: 経費 | AA7: メモ | AC7: 曜日 | AD7: 平均日商 | AE7: 日数 | AF7: 決定率 | AG7: 客単価
A8: 46204 | B8: =MID("日月火水木金土",WEEKDAY(A8),1) -> 水 | C8: 300000 | D8: =SUM($C$8:C8) -> 300000 | E8: 24310 | F8: 95630 | I8: =IF(COUNT(E8:H8)=0,"",SUM(E8:H8)) -> 119940 | J8: =IF(I8="","",SUM($I$8:I8)) -> 119940 | K8: =IF(I8="","",IFERROR(I8/C8,"")) -> 0.3998 | L8: =IF(J8="","",IFERROR(J8/D8,"")) -> 0.3998 | M8: =IF(J8="","",IF(D8=0,"",J8-D8)) -> -180060 | N8: =IF(I8="","—",IF(D8=0,"予算未入力",IF(J8>=D8,"◎ ペース内","▲ 遅れ"))) -> ▲ 遅れ | O8: 4 | P8: 4 | Q8: 23 | R8: 7 | S8: 11 | T8: =IFERROR(O8/Q8,"") -> 0.17391304 | U8: =IFERROR(I8/O8,"") -> 29985 | V8: =IFERROR(P8/O8,"") -> 1 | W8: =IFERROR(R8/Q8,"") -> 0.30434783 | Y8: 8865 | Z8: 0 | AC8: 月 | AD8: =IFERROR(AVERAGEIFS($I$8:$I$38,$B$8:$B$38,AC8,$I$8:$I$38,">0"),0) -> 167774.5 | AE8: =COUNTIFS($B$8:$B$38,AC8,$I$8:$I$38,">0") -> 4 | AF8: =IFERROR(SUMIF($B$8:$B$38,AC8,$O$8:$O$38)/SUMIF($B$8:$B$38,AC8,$Q$8:$Q$38),0) -> 0.30851064 | AG8: =IFERROR(SUMIF($B$8:$B$38,AC8,$I$8:$I$38)/SUMIF($B$8:$B$38,AC8,$O$8:$O$38),0) -> 23141.31
A9: 46205 | B9: =MID("日月火水木金土",WEEKDAY(A9),1) -> 木 | C9: 300000 | D9: =SUM($C$8:C9) -> 600000 | E9: 66320 | F9: 67030 | G9: 10000 | I9: =IF(COUNT(E9:H9)=0,"",SUM(E9:H9)) -> 143350 | J9: =IF(I9="","",SUM($I$8:I9)) -> 263290 | K9: =IF(I9="","",IFERROR(I9/C9,"")) -> 0.47783333 | L9: =IF(J9="","",IFERROR(J9/D9,"")) -> 0.43881667 | M9: =IF(J9="","",IF(D9=0,"",J9-D9)) -> -336710 | N9: =IF(I9="","—",IF(D9=0,"予算未入力",IF(J9>=D9,"◎ ペース内","▲ 遅れ"))) -> ▲ 遅れ | O9: 6 | P9: 6 | Q9: 18 | R9: 11 | S9: 13 | T9: =IFERROR(O9/Q9,"") -> 0.33333333 | U9: =IFERROR(I9/O9,"") -> 23891.667 | V9: =IFERROR(P9/O9,"") -> 1 | W9: =IFERROR(R9/Q9,"") -> 0.61111111 | Y9: 8858 | Z9: 0 | AC9: 火 | AD9: =IFERROR(AVERAGEIFS($I$8:$I$38,$B$8:$B$38,AC9,$I$8:$I$38,">0"),0) -> 159862.75 | AE9: =COUNTIFS($B$8:$B$38,AC9,$I$8:$I$38,">0") -> 4 | AF9: =IFERROR(SUMIF($B$8:$B$38,AC9,$O$8:$O$38)/SUMIF($B$8:$B$38,AC9,$Q$8:$Q$38),0) -> 0.38157895 | AG9: =IFERROR(SUMIF($B$8:$B$38,AC9,$I$8:$I$38)/SUMIF($B$8:$B$38,AC9,$O$8:$O$38),0) -> 22050.034
A10: 46206 | B10: =MID("日月火水木金土",WEEKDAY(A10),1) -> 金 | C10: 300000 | D10: =SUM($C$8:C10) -> 900000 | E10: 0 | F10: 97340 | I10: =IF(COUNT(E10:H10)=0,"",SUM(E10:H10)) -> 97340 | J10: =IF(I10="","",SUM($I$8:I10)) -> 360630 | K10: =IF(I10="","",IFERROR(I10/C10,"")) -> 0.32446667 | L10: =IF(J10="","",IFERROR(J10/D10,"")) -> 0.4007 | M10: =IF(J10="","",IF(D10=0,"",J10-D10)) -> -539370 | N10: =IF(I10="","—",IF(D10=0,"予算未入力",IF(J10>=D10,"◎ ペース内","▲ 遅れ"))) -> ▲ 遅れ | O10: 5 | P10: 5 | Q10: 11 | R10: 4 | S10: 7 | T10: =IFERROR(O10/Q10,"") -> 0.45454545 | U10: =IFERROR(I10/O10,"") -> 19468 | V10: =IFERROR(P10/O10,"") -> 1 | W10: =IFERROR(R10/Q10,"") -> 0.36363636 | Y10: 8854 | Z10: 0 | AC10: 水 | AD10: =IFERROR(AVERAGEIFS($I$8:$I$38,$B$8:$B$38,AC10,$I$8:$I$38,">0"),0) -> 115760 | AE10: =COUNTIFS($B$8:$B$38,AC10,$I$8:$I$38,">0") -> 5 | AF10: =IFERROR(SUMIF($B$8:$B$38,AC10,$O$8:$O$38)/SUMIF($B$8:$B$38,AC10,$Q$8:$Q$38),0) -> 0.28235294 | AG10: =IFERROR(SUMIF($B$8:$B$38,AC10,$I$8:$I$38)/SUMIF($B$8:$B$38,AC10,$O$8:$O$38),0) -> 24116.667
A11: 46207 | B11: =MID("日月火水木金土",WEEKDAY(A11),1) -> 土 | C11: 600000 | D11: =SUM($C$8:C11) -> 1500000 | E11: 78090 | F11: 305610 | I11: =IF(COUNT(E11:H11)=0,"",SUM(E11:H11)) -> 383700 | J11: =IF(I11="","",SUM($I$8:I11)) -> 744330 | K11: =IF(I11="","",IFERROR(I11/C11,"")) -> 0.6395 | L11: =IF(J11="","",IFERROR(J11/D11,"")) -> 0.49622 | M11: =IF(J11="","",IF(D11=0,"",J11-D11)) -> -755670 | N11: =IF(I11="","—",IF(D11=0,"予算未入力",IF(J11>=D11,"◎ ペース内","▲ 遅れ"))) -> ▲ 遅れ | O11: 16 | P11: 17 | Q11: 34 | R11: 18 | S11: 27 | T11: =IFERROR(O11/Q11,"") -> 0.47058824 | U11: =IFERROR(I11/O11,"") -> 23981.25 | V11: =IFERROR(P11/O11,"") -> 1.0625 | W11: =IFERROR(R11/Q11,"") -> 0.52941176 | Y11: 8850 | Z11: 0 | AC11: 木 | AD11: =IFERROR(AVERAGEIFS($I$8:$I$38,$B$8:$B$38,AC11,$I$8:$I$38,">0"),0) -> 180234.5 | AE11: =COUNTIFS($B$8:$B$38,AC11,$I$8:$I$38,">0") -> 4 | AF11: =IFERROR(SUMIF($B$8:$B$38,AC11,$O$8:$O$38)/SUMIF($B$8:$B$38,AC11,$Q$8:$Q$38),0) -> 0.37349398 | AG11: =IFERROR(SUMIF($B$8:$B$38,AC11,$I$8:$I$38)/SUMIF($B$8:$B$38,AC11,$O$8:$O$38),0) -> 23256.065
A12: 46208 | B12: =MID("日月火水木金土",WEEKDAY(A12),1) -> 日 | C12: 600000 | D12: =SUM($C$8:C12) -> 2100000 | E12: 89520 | F12: 221630 | I12: =IF(COUNT(E12:H12)=0,"",SUM(E12:H12)) -> 311150 | J12: =IF(I12="","",SUM($I$8:I12)) -> 1055480 | K12: =IF(I12="","",IFERROR(I12/C12,"")) -> 0.51858333 | L12: =IF(J12="","",IFERROR(J12/D12,"")) -> 0.50260952 | M12: =IF(J12="","",IF(D12=0,"",J12-D12)) -> -1044520 | N12: =IF(I12="","—",IF(D12=0,"予算未入力",IF(J12>=D12,"◎ ペース内","▲ 遅れ"))) -> ▲ 遅れ | O12: 14 | P12: 16 | Q12: 68 | R12: 24 | S12: 30 | T12: =IFERROR(O12/Q12,"") -> 0.20588235 | U12: =IFERROR(I12/O12,"") -> 22225 | V12: =IFERROR(P12/O12,"") -> 1.1428571 | W12: =IFERROR(R12/Q12,"") -> 0.35294118 | Y12: 8850 | Z12: 0 | AC12: 金 | AD12: =IFERROR(AVERAGEIFS($I$8:$I$38,$B$8:$B$38,AC12,$I$8:$I$38,">0"),0) -> 115610 | AE12: =COUNTIFS($B$8:$B$38,AC12,$I$8:$I$38,">0") -> 4 | AF12: =IFERROR(SUMIF($B$8:$B$38,AC12,$O$8:$O$38)/SUMIF($B$8:$B$38,AC12,$Q$8:$Q$38),0) -> 0.28169014 | AG12: =IFERROR(SUMIF($B$8:$B$38,AC12,$I$8:$I$38)/SUMIF($B$8:$B$38,AC12,$O$8:$O$38),0) -> 23122
A13: 46209 | B13: =MID("日月火水木金土",WEEKDAY(A13),1) -> 月 | C13: 300000 | D13: =SUM($C$8:C13) -> 2400000 | E13: 25900 | F13: 74020 | I13: =IF(COUNT(E13:H13)=0,"",SUM(E13:H13)) -> 99920 | J13: =IF(I13="","",SUM($I$8:I13)) -> 1155400 | K13: =IF(I13="","",IFERROR(I13/C13,"")) -> 0.33306667 | L13: =IF(J13="","",IFERROR(J13/D13,"")) -> 0.48141667 | M13: =IF(J13="","",IF(D13=0,"",J13-D13)) -> -1244600 | N13: =IF(I13="","—",IF(D13=0,"予算未入力",IF(J13>=D13,"◎ ペース内","▲ 遅れ"))) -> ▲ 遅れ | O13: 4 | P13: 4 | Q13: 14 | R13: 4 | S13: 8 | T13: =IFERROR(O13/Q13,"") -> 0.28571429 | U13: =IFERROR(I13/O13,"") -> 24980 | V13: =IFERROR(P13/O13,"") -> 1 | W13: =IFERROR(R13/Q13,"") -> 0.28571429 | Y13: 8839 | Z13: 0 | AC13: 土 | AD13: =IFERROR(AVERAGEIFS($I$8:$I$38,$B$8:$B$38,AC13,$I$8:$I$38,">0"),0) -> 350269.25 | AE13: =COUNTIFS($B$8:$B$38,AC13,$I$8:$I$38,">0") -> 4 | AF13: =IFERROR(SUMIF($B$8:$B$38,AC13,$O$8:$O$38)/SUMIF($B$8:$B$38,AC13,$Q$8:$Q$38),0) -> 0.37654321 | AG13: =IFERROR(SUMIF($B$8:$B$38,AC13,$I$8:$I$38)/SUMIF($B$8:$B$38,AC13,$O$8:$O$38),0) -> 22968.475
A14: 46210 | B14: =MID("日月火水木金土",WEEKDAY(A14),1) -> 火 | C14: 300000 | D14: =SUM($C$8:C14) -> 2700000 | E14: 65280 | F14: 108440 | I14: =IF(COUNT(E14:H14)=0,"",SUM(E14:H14)) -> 173720 | J14: =IF(I14="","",SUM($I$8:I14)) -> 1329120 | K14: =IF(I14="","",IFERROR(I14/C14,"")) -> 0.57906667 | L14: =IF(J14="","",IFERROR(J14/D14,"")) -> 0.49226667 | M14: =IF(J14="","",IF(D14=0,"",J14-D14)) -> -1370880 | N14: =IF(I14="","—",IF(D14=0,"予算未入力",IF(J14>=D14,"◎ ペース内","▲ 遅れ"))) -> ▲ 遅れ | O14: 8 | P14: 8 | Q14: 14 | R14: 8 | S14: 15 | T14: =IFERROR(O14/Q14,"") -> 0.57142857 | U14: =IFERROR(I14/O14,"") -> 21715 | V14: =IFERROR(P14/O14,"") -> 1 | W14: =IFERROR(R14/Q14,"") -> 0.57142857 | Y14: 8841 | Z14: 0 | AC14: 日 | AD14: =IFERROR(AVERAGEIFS($I$8:$I$38,$B$8:$B$38,AC14,$I$8:$I$38,">0"),0) -> 275305 | AE14: =COUNTIFS($B$8:$B$38,AC14,$I$8:$I$38,">0") -> 4 | AF14: =IFERROR(SUMIF($B$8:$B$38,AC14,$O$8:$O$38)/SUMIF($B$8:$B$38,AC14,$Q$8:$Q$38),0) -> 0.21171171 | AG14: =IFERROR(SUMIF($B$8:$B$38,AC14,$I$8:$I$38)/SUMIF($B$8:$B$38,AC14,$O$8:$O$38),0) -> 23430.213
A15: 46211 | B15: =MID("日月火水木金土",WEEKDAY(A15),1) -> 水 | C15: 300000 | D15: =SUM($C$8:C15) -> 3000000 | E15: 47620 | F15: 50320 | I15: =IF(COUNT(E15:H15)=0,"",SUM(E15:H15)) -> 97940 | J15: =IF(I15="","",SUM($I$8:I15)) -> 1427060 | K15: =IF(I15="","",IFERROR(I15/C15,"")) -> 0.32646667 | L15: =IF(J15="","",IFERROR(J15/D15,"")) -> 0.47568667 | M15: =IF(J15="","",IF(D15=0,"",J15-D15)) -> -1572940 | N15: =IF(I15="","—",IF(D15=0,"予算未入力",IF(J15>=D15,"◎ ペース内","▲ 遅れ"))) -> ▲ 遅れ | O15: 4 | P15: 4 | Q15: 12 | R15: 5 | S15: 13 | T15: =IFERROR(O15/Q15,"") -> 0.33333333 | U15: =IFERROR(I15/O15,"") -> 24485 | V15: =IFERROR(P15/O15,"") -> 1 | W15: =IFERROR(R15/Q15,"") -> 0.41666667 | Y15: 8844 | Z15: 0
A16: 46212 | B16: =MID("日月火水木金土",WEEKDAY(A16),1) -> 木 | C16: 300000 | D16: =SUM($C$8:C16) -> 3300000 | E16: 68620 | F16: 62230 | G16: 3000 | I16: =IF(COUNT(E16:H16)=0,"",SUM(E16:H16)) -> 133850 | J16: =IF(I16="","",SUM($I$8:I16)) -> 1560910 | K16: =IF(I16="","",IFERROR(I16/C16,"")) -> 0.44616667 | L16: =IF(J16="","",IFERROR(J16/D16,"")) -> 0.47300303 | M16: =IF(J16="","",IF(D16=0,"",J16-D16)) -> -1739090 | N16: =IF(I16="","—",IF(D16=0,"予算未入力",IF(J16>=D16,"◎ ペース内","▲ 遅れ"))) -> ▲ 遅れ | O16: 6 | P16: 7 | Q16: 21 | R16: 10 | S16: 13 | T16: =IFERROR(O16/Q16,"") -> 0.28571429 | U16: =IFERROR(I16/O16,"") -> 22308.333 | V16: =IFERROR(P16/O16,"") -> 1.1666667 | W16: =IFERROR(R16/Q16,"") -> 0.47619048 | Y16: 8842 | Z16: 0 | AC16: ※実績入力後に曜日別の傾向が出ます
A17: 46213 | B17: =MID("日月火水木金土",WEEKDAY(A17),1) -> 金 | C17: 300000 | D17: =SUM($C$8:C17) -> 3600000 | E17: 50320 | F17: 54830 | I17: =IF(COUNT(E17:H17)=0,"",SUM(E17:H17)) -> 105150 | J17: =IF(I17="","",SUM($I$8:I17)) -> 1666060 | K17: =IF(I17="","",IFERROR(I17/C17,"")) -> 0.3505 | L17: =IF(J17="","",IFERROR(J17/D17,"")) -> 0.46279444 | M17: =IF(J17="","",IF(D17=0,"",J17-D17)) -> -1933940 | N17: =IF(I17="","—",IF(D17=0,"予算未入力",IF(J17>=D17,"◎ ペース内","▲ 遅れ"))) -> ▲ 遅れ | O17: 5 | P17: 5 | Q17: 24 | R17: 7 | S17: 11 | T17: =IFERROR(O17/Q17,"") -> 0.20833333 | U17: =IFERROR(I17/O17,"") -> 21030 | V17: =IFERROR(P17/O17,"") -> 1 | W17: =IFERROR(R17/Q17,"") -> 0.29166667 | Y17: 8837 | Z17: 0
A18: 46214 | B18: =MID("日月火水木金土",WEEKDAY(A18),1) -> 土 | C18: 600000 | D18: =SUM($C$8:C18) -> 4200000 | E18: 209750 | F18: 213270 | I18: =IF(COUNT(E18:H18)=0,"",SUM(E18:H18)) -> 423020 | J18: =IF(I18="","",SUM($I$8:I18)) -> 2089080 | K18: =IF(I18="","",IFERROR(I18/C18,"")) -> 0.70503333 | L18: =IF(J18="","",IFERROR(J18/D18,"")) -> 0.4974 | M18: =IF(J18="","",IF(D18=0,"",J18-D18)) -> -2110920 | N18: =IF(I18="","—",IF(D18=0,"予算未入力",IF(J18>=D18,"◎ ペース内","▲ 遅れ"))) -> ▲ 遅れ | O18: 19 | P18: 21 | Q18: 45 | R18: 14 | S18: 18 | T18: =IFERROR(O18/Q18,"") -> 0.42222222 | U18: =IFERROR(I18/O18,"") -> 22264.211 | V18: =IFERROR(P18/O18,"") -> 1.1052632 | W18: =IFERROR(R18/Q18,"") -> 0.31111111 | X18: 0 | Y18: 8840 | Z18: 0 | AC18: ■ 週次サマリー（火曜〜翌月曜） | AJ18: 第1火曜 | AK18: =$A$8+MOD(2-WEEKDAY($A$8,2)+7,7) -> 46210
A19: 46215 | B19: =MID("日月火水木金土",WEEKDAY(A19),1) -> 日 | C19: 600000 | D19: =SUM($C$8:C19) -> 4800000 | E19: 140470 | F19: 142550 | G19: 20000 | I19: =IF(COUNT(E19:H19)=0,"",SUM(E19:H19)) -> 303020 | J19: =IF(I19="","",SUM($I$8:I19)) -> 2392100 | K19: =IF(I19="","",IFERROR(I19/C19,"")) -> 0.50503333 | L19: =IF(J19="","",IFERROR(J19/D19,"")) -> 0.49835417 | M19: =IF(J19="","",IF(D19=0,"",J19-D19)) -> -2407900 | N19: =IF(I19="","—",IF(D19=0,"予算未入力",IF(J19>=D19,"◎ ペース内","▲ 遅れ"))) -> ▲ 遅れ | O19: 12 | P19: 13 | Q19: 59 | R19: 21 | S19: 28 | T19: =IFERROR(O19/Q19,"") -> 0.20338983 | U19: =IFERROR(I19/O19,"") -> 25251.667 | V19: =IFERROR(P19/O19,"") -> 1.0833333 | W19: =IFERROR(R19/Q19,"") -> 0.3559322 | X19: 0 | Y19: 8837 | Z19: 0 | AC19: 週 | AD19: 期間 | AE19: 売上 | AF19: 決定率 | AG19: 客単価 | AH19: セット率 | AI19: 試着率
A20: 46216 | B20: =MID("日月火水木金土",WEEKDAY(A20),1) -> 月 | C20: 300000 | D20: =SUM($C$8:C20) -> 5100000 | E20: 24310 | F20: 45420 | I20: =IF(COUNT(E20:H20)=0,"",SUM(E20:H20)) -> 69730 | J20: =IF(I20="","",SUM($I$8:I20)) -> 2461830 | K20: =IF(I20="","",IFERROR(I20/C20,"")) -> 0.23243333 | L20: =IF(J20="","",IFERROR(J20/D20,"")) -> 0.48271176 | M20: =IF(J20="","",IF(D20=0,"",J20-D20)) -> -2638170 | N20: =IF(I20="","—",IF(D20=0,"予算未入力",IF(J20>=D20,"◎ ペース内","▲ 遅れ"))) -> ▲ 遅れ | O20: 3 | P20: 3 | Q20: 21 | R20: 6 | S20: 7 | T20: =IFERROR(O20/Q20,"") -> 0.14285714 | U20: =IFERROR(I20/O20,"") -> 23243.333 | V20: =IFERROR(P20/O20,"") -> 1 | W20: =IFERROR(R20/Q20,"") -> 0.28571429 | X20: 0 | Y20: 8833 | Z20: 0 | AC20: 1 | AD20: =IF($AK$18+7*(1-1)>$A$38,"",TEXT($AK$18+7*(1-1),"m/d")&"-"&TEXT($AK$18+7*(1-1)+6,"m/d")) -> 7/7-7/13 | AE20: =IF($AD20="","",(SUMIFS($I$8:$I$38,$A$8:$A$38,">="&$AK$18+7*(1-1),$A$8:$A$38,"<="&$AK$18+7*(1-1)+6)+SUMIFS('2026年08月'!$I$8:$I$38,'2026年08月'!$A$8:$A$38,">="&$AK$18+7*(1-1),'2026年08月'!$A$8:$A$38,"<="&$AK$18+7*(1-1)+6))) -> 1306430 | AF20: =IF($AD20="","",IFERROR((SUMIFS($O$8:$O$38,$A$8:$A$38,">="&$AK$18+7*(1-1),$A$8:$A$38,"<="&$AK$18+7*(1-1)+6)+SUMIFS('2026年08月'!$O$8:$O$38,'2026年08月'!$A$8:$A$38,">="&$AK$18+7*(1-1),'2026年08月'!$A$8:$A$38,"<="&$AK$18+7*(1-1)+6))/(SUMIFS($Q$8:$Q$38,$A$8:$A$38,">="&$AK$18+7*(1-1),$A$8:$A$38,"<="&$AK$18+7*(1-1)+6)+SUMIFS('2026年08月'!$Q$8:$Q$38,'2026年08月'!$A$8:$A$38,">="&$AK$18+7*(1-1),'2026年08月'!$A$8:$A$38,"<="&$AK$18+7*(1-1)+6)),"")) -> 0.29081633 | AG20: =IF($AD20="","",IFERROR((SUMIFS($I$8:$I$38,$A$8:$A$38,">="&$AK$18+7*(1-1),$A$8:$A$38,"<="&$AK$18+7*(1-1)+6)+SUMIFS('2026年08月'!$I$8:$I$38,'2026年08月'!$A$8:$A$38,">="&$AK$18+7*(1-1),'2026年08月'!$A$8:$A$38,"<="&$AK$18+7*(1-1)+6))/(SUMIFS($O$8:$O$38,$A$8:$A$38,">="&$AK$18+7*(1-1),$A$8:$A$38,"<="&$AK$18+7*(1-1)+6)+SUMIFS('2026年08月'!$O$8:$O$38,'2026年08月'!$A$8:$A$38,">="&$AK$18+7*(1-1),'2026年08月'!$A$8:$A$38,"<="&$AK$18+7*(1-1)+6)),"")) -> 22919.825 | AH20: =IF($AD20="","",IFERROR((SUMIFS($P$8:$P$38,$A$8:$A$38,">="&$AK$18+7*(1-1),$A$8:$A$38,"<="&$AK$18+7*(1-1)+6)+SUMIFS('2026年08月'!$P$8:$P$38,'2026年08月'!$A$8:$A$38,">="&$AK$18+7*(1-1),'2026年08月'!$A$8:$A$38,"<="&$AK$18+7*(1-1)+6))/(SUMIFS($O$8:$O$38,$A$8:$A$38,">="&$AK$18+7*(1-1),$A$8:$A$38,"<="&$AK$18+7*(1-1)+6)+SUMIFS('2026年08月'!$O$8:$O$38,'2026年08月'!$A$8:$A$38,">="&$AK$18+7*(1-1),'2026年08月'!$A$8:$A$38,"<="&$AK$18+7*(1-1)+6)),"")) -> 1.0701754 | AI20: =IF($AD20="","",IFERROR((SUMIFS($R$8:$R$38,$A$8:$A$38,">="&$AK$18+7*(1-1),$A$8:$A$38,"<="&$AK$18+7*(1-1)+6)+SUMIFS('2026年08月'!$R$8:$R$38,'2026年08月'!$A$8:$A$38,">="&$AK$18+7*(1-1),'2026年08月'!$A$8:$A$38,"<="&$AK$18+7*(1-1)+6))/(SUMIFS($Q$8:$Q$38,$A$8:$A$38,">="&$AK$18+7*(1-1),$A$8:$A$38,"<="&$AK$18+7*(1-1)+6)+SUMIFS('2026年08月'!$Q$8:$Q$38,'2026年08月'!$A$8:$A$38,">="&$AK$18+7*(1-1),'2026年08月'!$A$8:$A$38,"<="&$AK$18+7*(1-1)+6)),"")) -> 0.3622449
A21: 46217 | B21: =MID("日月火水木金土",WEEKDAY(A21),1) -> 火 | C21: 300000 | D21: =SUM($C$8:C21) -> 5400000 | E21: 92880 | F21: 69730 | I21: =IF(COUNT(E21:H21)=0,"",SUM(E21:H21)) -> 162610 | J21: =IF(I21="","",SUM($I$8:I21)) -> 2624440 | K21: =IF(I21="","",IFERROR(I21/C21,"")) -> 0.54203333 | L21: =IF(J21="","",IFERROR(J21/D21,"")) -> 0.48600741 | M21: =IF(J21="","",IF(D21=0,"",J21-D21)) -> -2775560 | N21: =IF(I21="","—",IF(D21=0,"予算未入力",IF(J21>=D21,"◎ ペース内","▲ 遅れ"))) -> ▲ 遅れ | O21: 8 | P21: 9 | Q21: 18 | R21: 6 | S21: 10 | T21: =IFERROR(O21/Q21,"") -> 0.44444444 | U21: =IFERROR(I21/O21,"") -> 20326.25 | V21: =IFERROR(P21/O21,"") -> 1.125 | W21: =IFERROR(R21/Q21,"") -> 0.33333333 | X21: 0 | Y21: 8827 | Z21: 0 | AC21: 2 | AD21: =IF($AK$18+7*(2-1)>$A$38,"",TEXT($AK$18+7*(2-1),"m/d")&"-"&TEXT($AK$18+7*(2-1)+6,"m/d")) -> 7/14-7/20 | AE21: =IF($AD21="","",(SUMIFS($I$8:$I$38,$A$8:$A$38,">="&$AK$18+7*(2-1),$A$8:$A$38,"<="&$AK$18+7*(2-1)+6)+SUMIFS('2026年08月'!$I$8:$I$38,'2026年08月'!$A$8:$A$38,">="&$AK$18+7*(2-1),'2026年08月'!$A$8:$A$38,"<="&$AK$18+7*(2-1)+6))) -> 1758734 | AF21: =IF($AD21="","",IFERROR((SUMIFS($O$8:$O$38,$A$8:$A$38,">="&$AK$18+7*(2-1),$A$8:$A$38,"<="&$AK$18+7*(2-1)+6)+SUMIFS('2026年08月'!$O$8:$O$38,'2026年08月'!$A$8:$A$38,">="&$AK$18+7*(2-1),'2026年08月'!$A$8:$A$38,"<="&$AK$18+7*(2-1)+6))/(SUMIFS($Q$8:$Q$38,$A$8:$A$38,">="&$AK$18+7*(2-1),$A$8:$A$38,"<="&$AK$18+7*(2-1)+6)+SUMIFS('2026年08月'!$Q$8:$Q$38,'2026年08月'!$A$8:$A$38,">="&$AK$18+7*(2-1),'2026年08月'!$A$8:$A$38,"<="&$AK$18+7*(2-1)+6)),"")) -> 0.36574074 | AG21: =IF($AD21="","",IFERROR((SUMIFS($I$8:$I$38,$A$8:$A$38,">="&$AK$18+7*(2-1),$A$8:$A$38,"<="&$AK$18+7*(2-1)+6)+SUMIFS('2026年08月'!$I$8:$I$38,'2026年08月'!$A$8:$A$38,">="&$AK$18+7*(2-1),'2026年08月'!$A$8:$A$38,"<="&$AK$18+7*(2-1)+6))/(SUMIFS($O$8:$O$38,$A$8:$A$38,">="&$AK$18+7*(2-1),$A$8:$A$38,"<="&$AK$18+7*(2-1)+6)+SUMIFS('2026年08月'!$O$8:$O$38,'2026年08月'!$A$8:$A$38,">="&$AK$18+7*(2-1),'2026年08月'!$A$8:$A$38,"<="&$AK$18+7*(2-1)+6)),"")) -> 22262.456 | AH21: =IF($AD21="","",IFERROR((SUMIFS($P$8:$P$38,$A$8:$A$38,">="&$AK$18+7*(2-1),$A$8:$A$38,"<="&$AK$18+7*(2-1)+6)+SUMIFS('2026年08月'!$P$8:$P$38,'2026年08月'!$A$8:$A$38,">="&$AK$18+7*(2-1),'2026年08月'!$A$8:$A$38,"<="&$AK$18+7*(2-1)+6))/(SUMIFS($O$8:$O$38,$A$8:$A$38,">="&$AK$18+7*(2-1),$A$8:$A$38,"<="&$AK$18+7*(2-1)+6)+SUMIFS('2026年08月'!$O$8:$O$38,'2026年08月'!$A$8:$A$38,">="&$AK$18+7*(2-1),'2026年08月'!$A$8:$A$38,"<="&$AK$18+7*(2-1)+6)),"")) -> 1.0886076 | AI21: =IF($AD21="","",IFERROR((SUMIFS($R$8:$R$38,$A$8:$A$38,">="&$AK$18+7*(2-1),$A$8:$A$38,"<="&$AK$18+7*(2-1)+6)+SUMIFS('2026年08月'!$R$8:$R$38,'2026年08月'!$A$8:$A$38,">="&$AK$18+7*(2-1),'2026年08月'!$A$8:$A$38,"<="&$AK$18+7*(2-1)+6))/(SUMIFS($Q$8:$Q$38,$A$8:$A$38,">="&$AK$18+7*(2-1),$A$8:$A$38,"<="&$AK$18+7*(2-1)+6)+SUMIFS('2026年08月'!$Q$8:$Q$38,'2026年08月'!$A$8:$A$38,">="&$AK$18+7*(2-1),'2026年08月'!$A$8:$A$38,"<="&$AK$18+7*(2-1)+6)),"")) -> 0.43055556
A22: 46218 | B22: =MID("日月火水木金土",WEEKDAY(A22),1) -> 水 | C22: 300000 | D22: =SUM($C$8:C22) -> 5700000 | E22: 70010 | F22: 87440 | I22: =IF(COUNT(E22:H22)=0,"",SUM(E22:H22)) -> 157450 | J22: =IF(I22="","",SUM($I$8:I22)) -> 2781890 | K22: =IF(I22="","",IFERROR(I22/C22,"")) -> 0.52483333 | L22: =IF(J22="","",IFERROR(J22/D22,"")) -> 0.48805088 | M22: =IF(J22="","",IF(D22=0,"",J22-D22)) -> -2918110 | N22: =IF(I22="","—",IF(D22=0,"予算未入力",IF(J22>=D22,"◎ ペース内","▲ 遅れ"))) -> ▲ 遅れ | O22: 7 | P22: 8 | Q22: 20 | R22: 8 | S22: 12 | T22: =IFERROR(O22/Q22,"") -> 0.35 | U22: =IFERROR(I22/O22,"") -> 22492.857 | V22: =IFERROR(P22/O22,"") -> 1.1428571 | W22: =IFERROR(R22/Q22,"") -> 0.4 | Y22: 8826 | Z22: 0 | AC22: 3 | AD22: =IF($AK$18+7*(3-1)>$A$38,"",TEXT($AK$18+7*(3-1),"m/d")&"-"&TEXT($AK$18+7*(3-1)+6,"m/d")) -> 7/21-7/27 | AE22: =IF($AD22="","",(SUMIFS($I$8:$I$38,$A$8:$A$38,">="&$AK$18+7*(3-1),$A$8:$A$38,"<="&$AK$18+7*(3-1)+6)+SUMIFS('2026年08月'!$I$8:$I$38,'2026年08月'!$A$8:$A$38,">="&$AK$18+7*(3-1),'2026年08月'!$A$8:$A$38,"<="&$AK$18+7*(3-1)+6))) -> 1106070 | AF22: =IF($AD22="","",IFERROR((SUMIFS($O$8:$O$38,$A$8:$A$38,">="&$AK$18+7*(3-1),$A$8:$A$38,"<="&$AK$18+7*(3-1)+6)+SUMIFS('2026年08月'!$O$8:$O$38,'2026年08月'!$A$8:$A$38,">="&$AK$18+7*(3-1),'2026年08月'!$A$8:$A$38,"<="&$AK$18+7*(3-1)+6))/(SUMIFS($Q$8:$Q$38,$A$8:$A$38,">="&$AK$18+7*(3-1),$A$8:$A$38,"<="&$AK$18+7*(3-1)+6)+SUMIFS('2026年08月'!$Q$8:$Q$38,'2026年08月'!$A$8:$A$38,">="&$AK$18+7*(3-1),'2026年08月'!$A$8:$A$38,"<="&$AK$18+7*(3-1)+6)),"")) -> 0.26011561 | AG22: =IF($AD22="","",IFERROR((SUMIFS($I$8:$I$38,$A$8:$A$38,">="&$AK$18+7*(3-1),$A$8:$A$38,"<="&$AK$18+7*(3-1)+6)+SUMIFS('2026年08月'!$I$8:$I$38,'2026年08月'!$A$8:$A$38,">="&$AK$18+7*(3-1),'2026年08月'!$A$8:$A$38,"<="&$AK$18+7*(3-1)+6))/(SUMIFS($O$8:$O$38,$A$8:$A$38,">="&$AK$18+7*(3-1),$A$8:$A$38,"<="&$AK$18+7*(3-1)+6)+SUMIFS('2026年08月'!$O$8:$O$38,'2026年08月'!$A$8:$A$38,">="&$AK$18+7*(3-1),'2026年08月'!$A$8:$A$38,"<="&$AK$18+7*(3-1)+6)),"")) -> 24579.333 | AH22: =IF($AD22="","",IFERROR((SUMIFS($P$8:$P$38,$A$8:$A$38,">="&$AK$18+7*(3-1),$A$8:$A$38,"<="&$AK$18+7*(3-1)+6)+SUMIFS('2026年08月'!$P$8:$P$38,'2026年08月'!$A$8:$A$38,">="&$AK$18+7*(3-1),'2026年08月'!$A$8:$A$38,"<="&$AK$18+7*(3-1)+6))/(SUMIFS($O$8:$O$38,$A$8:$A$38,">="&$AK$18+7*(3-1),$A$8:$A$38,"<="&$AK$18+7*(3-1)+6)+SUMIFS('2026年08月'!$O$8:$O$38,'2026年08月'!$A$8:$A$38,">="&$AK$18+7*(3-1),'2026年08月'!$A$8:$A$38,"<="&$AK$18+7*(3-1)+6)),"")) -> 1.1555556 | AI22: =IF($AD22="","",IFERROR((SUMIFS($R$8:$R$38,$A$8:$A$38,">="&$AK$18+7*(3-1),$A$8:$A$38,"<="&$AK$18+7*(3-1)+6)+SUMIFS('2026年08月'!$R$8:$R$38,'2026年08月'!$A$8:$A$38,">="&$AK$18+7*(3-1),'2026年08月'!$A$8:$A$38,"<="&$AK$18+7*(3-1)+6))/(SUMIFS($Q$8:$Q$38,$A$8:$A$38,">="&$AK$18+7*(3-1),$A$8:$A$38,"<="&$AK$18+7*(3-1)+6)+SUMIFS('2026年08月'!$Q$8:$Q$38,'2026年08月'!$A$8:$A$38,">="&$AK$18+7*(3-1),'2026年08月'!$A$8:$A$38,"<="&$AK$18+7*(3-1)+6)),"")) -> 0.33526012
A23: 46219 | B23: =MID("日月火水木金土",WEEKDAY(A23),1) -> 木 | C23: 300000 | D23: =SUM($C$8:C23) -> 6000000 | E23: 90240 | F23: 142140 | I23: =IF(COUNT(E23:H23)=0,"",SUM(E23:H23)) -> 232380 | J23: =IF(I23="","",SUM($I$8:I23)) -> 3014270 | K23: =IF(I23="","",IFERROR(I23/C23,"")) -> 0.7746 | L23: =IF(J23="","",IFERROR(J23/D23,"")) -> 0.50237833 | M23: =IF(J23="","",IF(D23=0,"",J23-D23)) -> -2985730 | N23: =IF(I23="","—",IF(D23=0,"予算未入力",IF(J23>=D23,"◎ ペース内","▲ 遅れ"))) -> ▲ 遅れ | O23: 11 | P23: 11 | Q23: 20 | R23: 11 | S23: 11 | T23: =IFERROR(O23/Q23,"") -> 0.55 | U23: =IFERROR(I23/O23,"") -> 21125.455 | V23: =IFERROR(P23/O23,"") -> 1 | W23: =IFERROR(R23/Q23,"") -> 0.55 | X23: 0 | Y23: 8822 | Z23: 0 | AC23: 4 | AD23: =IF($AK$18+7*(4-1)>$A$38,"",TEXT($AK$18+7*(4-1),"m/d")&"-"&TEXT($AK$18+7*(4-1)+6,"m/d")) -> 7/28-8/3 | AE23: =IF($AD23="","",(SUMIFS($I$8:$I$38,$A$8:$A$38,">="&$AK$18+7*(4-1),$A$8:$A$38,"<="&$AK$18+7*(4-1)+6)+SUMIFS('2026年08月'!$I$8:$I$38,'2026年08月'!$A$8:$A$38,">="&$AK$18+7*(4-1),'2026年08月'!$A$8:$A$38,"<="&$AK$18+7*(4-1)+6))) -> 723289 | AF23: =IF($AD23="","",IFERROR((SUMIFS($O$8:$O$38,$A$8:$A$38,">="&$AK$18+7*(4-1),$A$8:$A$38,"<="&$AK$18+7*(4-1)+6)+SUMIFS('2026年08月'!$O$8:$O$38,'2026年08月'!$A$8:$A$38,">="&$AK$18+7*(4-1),'2026年08月'!$A$8:$A$38,"<="&$AK$18+7*(4-1)+6))/(SUMIFS($Q$8:$Q$38,$A$8:$A$38,">="&$AK$18+7*(4-1),$A$8:$A$38,"<="&$AK$18+7*(4-1)+6)+SUMIFS('2026年08月'!$Q$8:$Q$38,'2026年08月'!$A$8:$A$38,">="&$AK$18+7*(4-1),'2026年08月'!$A$8:$A$38,"<="&$AK$18+7*(4-1)+6)),"")) -> 0.24615385 | AG23: =IF($AD23="","",IFERROR((SUMIFS($I$8:$I$38,$A$8:$A$38,">="&$AK$18+7*(4-1),$A$8:$A$38,"<="&$AK$18+7*(4-1)+6)+SUMIFS('2026年08月'!$I$8:$I$38,'2026年08月'!$A$8:$A$38,">="&$AK$18+7*(4-1),'2026年08月'!$A$8:$A$38,"<="&$AK$18+7*(4-1)+6))/(SUMIFS($O$8:$O$38,$A$8:$A$38,">="&$AK$18+7*(4-1),$A$8:$A$38,"<="&$AK$18+7*(4-1)+6)+SUMIFS('2026年08月'!$O$8:$O$38,'2026年08月'!$A$8:$A$38,">="&$AK$18+7*(4-1),'2026年08月'!$A$8:$A$38,"<="&$AK$18+7*(4-1)+6)),"")) -> 22602.781 | AH23: =IF($AD23="","",IFERROR((SUMIFS($P$8:$P$38,$A$8:$A$38,">="&$AK$18+7*(4-1),$A$8:$A$38,"<="&$AK$18+7*(4-1)+6)+SUMIFS('2026年08月'!$P$8:$P$38,'2026年08月'!$A$8:$A$38,">="&$AK$18+7*(4-1),'2026年08月'!$A$8:$A$38,"<="&$AK$18+7*(4-1)+6))/(SUMIFS($O$8:$O$38,$A$8:$A$38,">="&$AK$18+7*(4-1),$A$8:$A$38,"<="&$AK$18+7*(4-1)+6)+SUMIFS('2026年08月'!$O$8:$O$38,'2026年08月'!$A$8:$A$38,">="&$AK$18+7*(4-1),'2026年08月'!$A$8:$A$38,"<="&$AK$18+7*(4-1)+6)),"")) -> 1.03125 | AI23: =IF($AD23="","",IFERROR((SUMIFS($R$8:$R$38,$A$8:$A$38,">="&$AK$18+7*(4-1),$A$8:$A$38,"<="&$AK$18+7*(4-1)+6)+SUMIFS('2026年08月'!$R$8:$R$38,'2026年08月'!$A$8:$A$38,">="&$AK$18+7*(4-1),'2026年08月'!$A$8:$A$38,"<="&$AK$18+7*(4-1)+6))/(SUMIFS($Q$8:$Q$38,$A$8:$A$38,">="&$AK$18+7*(4-1),$A$8:$A$38,"<="&$AK$18+7*(4-1)+6)+SUMIFS('2026年08月'!$Q$8:$Q$38,'2026年08月'!$A$8:$A$38,">="&$AK$18+7*(4-1),'2026年08月'!$A$8:$A$38,"<="&$AK$18+7*(4-1)+6)),"")) -> 0.35384615
A24: 46220 | B24: =MID("日月火水木金土",WEEKDAY(A24),1) -> 金 | C24: 300000 | D24: =SUM($C$8:C24) -> 6300000 | E24: 75120 | F24: 140610 | I24: =IF(COUNT(E24:H24)=0,"",SUM(E24:H24)) -> 215730 | J24: =IF(I24="","",SUM($I$8:I24)) -> 3230000 | K24: =IF(I24="","",IFERROR(I24/C24,"")) -> 0.7191 | L24: =IF(J24="","",IFERROR(J24/D24,"")) -> 0.51269841 | M24: =IF(J24="","",IF(D24=0,"",J24-D24)) -> -3070000 | N24: =IF(I24="","—",IF(D24=0,"予算未入力",IF(J24>=D24,"◎ ペース内","▲ 遅れ"))) -> ▲ 遅れ | O24: 8 | P24: 10 | Q24: 18 | R24: 10 | S24: 14 | T24: =IFERROR(O24/Q24,"") -> 0.44444444 | U24: =IFERROR(I24/O24,"") -> 26966.25 | V24: =IFERROR(P24/O24,"") -> 1.25 | W24: =IFERROR(R24/Q24,"") -> 0.55555556 | X24: 0 | Y24: 8817 | Z24: 0 | AC24: 5 | AD24: =IF($AK$18+7*(5-1)>$A$38,"",TEXT($AK$18+7*(5-1),"m/d")&"-"&TEXT($AK$18+7*(5-1)+6,"m/d")) | AE24: =IF($AD24="","",(SUMIFS($I$8:$I$38,$A$8:$A$38,">="&$AK$18+7*(5-1),$A$8:$A$38,"<="&$AK$18+7*(5-1)+6)+SUMIFS('2026年08月'!$I$8:$I$38,'2026年08月'!$A$8:$A$38,">="&$AK$18+7*(5-1),'2026年08月'!$A$8:$A$38,"<="&$AK$18+7*(5-1)+6))) | AF24: =IF($AD24="","",IFERROR((SUMIFS($O$8:$O$38,$A$8:$A$38,">="&$AK$18+7*(5-1),$A$8:$A$38,"<="&$AK$18+7*(5-1)+6)+SUMIFS('2026年08月'!$O$8:$O$38,'2026年08月'!$A$8:$A$38,">="&$AK$18+7*(5-1),'2026年08月'!$A$8:$A$38,"<="&$AK$18+7*(5-1)+6))/(SUMIFS($Q$8:$Q$38,$A$8:$A$38,">="&$AK$18+7*(5-1),$A$8:$A$38,"<="&$AK$18+7*(5-1)+6)+SUMIFS('2026年08月'!$Q$8:$Q$38,'2026年08月'!$A$8:$A$38,">="&$AK$18+7*(5-1),'2026年08月'!$A$8:$A$38,"<="&$AK$18+7*(5-1)+6)),"")) | AG24: =IF($AD24="","",IFERROR((SUMIFS($I$8:$I$38,$A$8:$A$38,">="&$AK$18+7*(5-1),$A$8:$A$38,"<="&$AK$18+7*(5-1)+6)+SUMIFS('2026年08月'!$I$8:$I$38,'2026年08月'!$A$8:$A$38,">="&$AK$18+7*(5-1),'2026年08月'!$A$8:$A$38,"<="&$AK$18+7*(5-1)+6))/(SUMIFS($O$8:$O$38,$A$8:$A$38,">="&$AK$18+7*(5-1),$A$8:$A$38,"<="&$AK$18+7*(5-1)+6)+SUMIFS('2026年08月'!$O$8:$O$38,'2026年08月'!$A$8:$A$38,">="&$AK$18+7*(5-1),'2026年08月'!$A$8:$A$38,"<="&$AK$18+7*(5-1)+6)),"")) | AH24: =IF($AD24="","",IFERROR((SUMIFS($P$8:$P$38,$A$8:$A$38,">="&$AK$18+7*(5-1),$A$8:$A$38,"<="&$AK$18+7*(5-1)+6)+SUMIFS('2026年08月'!$P$8:$P$38,'2026年08月'!$A$8:$A$38,">="&$AK$18+7*(5-1),'2026年08月'!$A$8:$A$38,"<="&$AK$18+7*(5-1)+6))/(SUMIFS($O$8:$O$38,$A$8:$A$38,">="&$AK$18+7*(5-1),$A$8:$A$38,"<="&$AK$18+7*(5-1)+6)+SUMIFS('2026年08月'!$O$8:$O$38,'2026年08月'!$A$8:$A$38,">="&$AK$18+7*(5-1),'2026年08月'!$A$8:$A$38,"<="&$AK$18+7*(5-1)+6)),"")) | AI24: =IF($AD24="","",IFERROR((SUMIFS($R$8:$R$38,$A$8:$A$38,">="&$AK$18+7*(5-1),$A$8:$A$38,"<="&$AK$18+7*(5-1)+6)+SUMIFS('2026年08月'!$R$8:$R$38,'2026年08月'!$A$8:$A$38,">="&$AK$18+7*(5-1),'2026年08月'!$A$8:$A$38,"<="&$AK$18+7*(5-1)+6))/(SUMIFS($Q$8:$Q$38,$A$8:$A$38,">="&$AK$18+7*(5-1),$A$8:$A$38,"<="&$AK$18+7*(5-1)+6)+SUMIFS('2026年08月'!$Q$8:$Q$38,'2026年08月'!$A$8:$A$38,">="&$AK$18+7*(5-1),'2026年08月'!$A$8:$A$38,"<="&$AK$18+7*(5-1)+6)),""))
A25: 46221 | B25: =MID("日月火水木金土",WEEKDAY(A25),1) -> 土 | C25: 800000 | D25: =SUM($C$8:C25) -> 7100000 | E25: 72540 | F25: 234527 | I25: =IF(COUNT(E25:H25)=0,"",SUM(E25:H25)) -> 307067 | J25: =IF(I25="","",SUM($I$8:I25)) -> 3537067 | K25: =IF(I25="","",IFERROR(I25/C25,"")) -> 0.38383375 | L25: =IF(J25="","",IFERROR(J25/D25,"")) -> 0.49817845 | M25: =IF(J25="","",IF(D25=0,"",J25-D25)) -> -3562933 | N25: =IF(I25="","—",IF(D25=0,"予算未入力",IF(J25>=D25,"◎ ペース内","▲ 遅れ"))) -> ▲ 遅れ | O25: 14 | P25: 16 | Q25: 40 | R25: 20 | S25: 21 | T25: =IFERROR(O25/Q25,"") -> 0.35 | U25: =IFERROR(I25/O25,"") -> 21933.357 | V25: =IFERROR(P25/O25,"") -> 1.1428571 | W25: =IFERROR(R25/Q25,"") -> 0.5 | Y25: 8815 | Z25: 0 | AC25: 6 | AD25: =IF($AK$18+7*(6-1)>$A$38,"",TEXT($AK$18+7*(6-1),"m/d")&"-"&TEXT($AK$18+7*(6-1)+6,"m/d")) | AE25: =IF($AD25="","",(SUMIFS($I$8:$I$38,$A$8:$A$38,">="&$AK$18+7*(6-1),$A$8:$A$38,"<="&$AK$18+7*(6-1)+6)+SUMIFS('2026年08月'!$I$8:$I$38,'2026年08月'!$A$8:$A$38,">="&$AK$18+7*(6-1),'2026年08月'!$A$8:$A$38,"<="&$AK$18+7*(6-1)+6))) | AF25: =IF($AD25="","",IFERROR((SUMIFS($O$8:$O$38,$A$8:$A$38,">="&$AK$18+7*(6-1),$A$8:$A$38,"<="&$AK$18+7*(6-1)+6)+SUMIFS('2026年08月'!$O$8:$O$38,'2026年08月'!$A$8:$A$38,">="&$AK$18+7*(6-1),'2026年08月'!$A$8:$A$38,"<="&$AK$18+7*(6-1)+6))/(SUMIFS($Q$8:$Q$38,$A$8:$A$38,">="&$AK$18+7*(6-1),$A$8:$A$38,"<="&$AK$18+7*(6-1)+6)+SUMIFS('2026年08月'!$Q$8:$Q$38,'2026年08月'!$A$8:$A$38,">="&$AK$18+7*(6-1),'2026年08月'!$A$8:$A$38,"<="&$AK$18+7*(6-1)+6)),"")) | AG25: =IF($AD25="","",IFERROR((SUMIFS($I$8:$I$38,$A$8:$A$38,">="&$AK$18+7*(6-1),$A$8:$A$38,"<="&$AK$18+7*(6-1)+6)+SUMIFS('2026年08月'!$I$8:$I$38,'2026年08月'!$A$8:$A$38,">="&$AK$18+7*(6-1),'2026年08月'!$A$8:$A$38,"<="&$AK$18+7*(6-1)+6))/(SUMIFS($O$8:$O$38,$A$8:$A$38,">="&$AK$18+7*(6-1),$A$8:$A$38,"<="&$AK$18+7*(6-1)+6)+SUMIFS('2026年08月'!$O$8:$O$38,'2026年08月'!$A$8:$A$38,">="&$AK$18+7*(6-1),'2026年08月'!$A$8:$A$38,"<="&$AK$18+7*(6-1)+6)),"")) | AH25: =IF($AD25="","",IFERROR((SUMIFS($P$8:$P$38,$A$8:$A$38,">="&$AK$18+7*(6-1),$A$8:$A$38,"<="&$AK$18+7*(6-1)+6)+SUMIFS('2026年08月'!$P$8:$P$38,'2026年08月'!$A$8:$A$38,">="&$AK$18+7*(6-1),'2026年08月'!$A$8:$A$38,"<="&$AK$18+7*(6-1)+6))/(SUMIFS($O$8:$O$38,$A$8:$A$38,">="&$AK$18+7*(6-1),$A$8:$A$38,"<="&$AK$18+7*(6-1)+6)+SUMIFS('2026年08月'!$O$8:$O$38,'2026年08月'!$A$8:$A$38,">="&$AK$18+7*(6-1),'2026年08月'!$A$8:$A$38,"<="&$AK$18+7*(6-1)+6)),"")) | AI25: =IF($AD25="","",IFERROR((SUMIFS($R$8:$R$38,$A$8:$A$38,">="&$AK$18+7*(6-1),$A$8:$A$38,"<="&$AK$18+7*(6-1)+6)+SUMIFS('2026年08月'!$R$8:$R$38,'2026年08月'!$A$8:$A$38,">="&$AK$18+7*(6-1),'2026年08月'!$A$8:$A$38,"<="&$AK$18+7*(6-1)+6))/(SUMIFS($Q$8:$Q$38,$A$8:$A$38,">="&$AK$18+7*(6-1),$A$8:$A$38,"<="&$AK$18+7*(6-1)+6)+SUMIFS('2026年08月'!$Q$8:$Q$38,'2026年08月'!$A$8:$A$38,">="&$AK$18+7*(6-1),'2026年08月'!$A$8:$A$38,"<="&$AK$18+7*(6-1)+6)),""))
A26: 46222 | B26: =MID("日月火水木金土",WEEKDAY(A26),1) -> 日 | C26: 800000 | D26: =SUM($C$8:C26) -> 7900000 | E26: 113610 | F26: 162170 | I26: =IF(COUNT(E26:H26)=0,"",SUM(E26:H26)) -> 275780 | J26: =IF(I26="","",SUM($I$8:I26)) -> 3812847 | K26: =IF(I26="","",IFERROR(I26/C26,"")) -> 0.344725 | L26: =IF(J26="","",IFERROR(J26/D26,"")) -> 0.48263886 | M26: =IF(J26="","",IF(D26=0,"",J26-D26)) -> -4087153 | N26: =IF(I26="","—",IF(D26=0,"予算未入力",IF(J26>=D26,"◎ ペース内","▲ 遅れ"))) -> ▲ 遅れ | O26: 13 | P26: 13 | Q26: 52 | R26: 21 | S26: 30 | T26: =IFERROR(O26/Q26,"") -> 0.25 | U26: =IFERROR(I26/O26,"") -> 21213.846 | V26: =IFERROR(P26/O26,"") -> 1 | W26: =IFERROR(R26/Q26,"") -> 0.40384615 | Y26: 8812 | Z26: 0 | AC26: ※期間ラベルは第1火曜から自動生成。決定率・客単価・セット率・試着率は「週合計÷週合計」
A27: 46223 | B27: =MID("日月火水木金土",WEEKDAY(A27),1) -> 月 | C27: 400000 | D27: =SUM($C$8:C27) -> 8300000 | E27: 106240 | F27: 301477 | I27: =IF(COUNT(E27:H27)=0,"",SUM(E27:H27)) -> 407717 | J27: =IF(I27="","",SUM($I$8:I27)) -> 4220564 | K27: =IF(I27="","",IFERROR(I27/C27,"")) -> 1.0192925 | L27: =IF(J27="","",IFERROR(J27/D27,"")) -> 0.50850169 | M27: =IF(J27="","",IF(D27=0,"",J27-D27)) -> -4079436 | N27: =IF(I27="","—",IF(D27=0,"予算未入力",IF(J27>=D27,"◎ ペース内","▲ 遅れ"))) -> ▲ 遅れ | O27: 18 | P27: 19 | Q27: 48 | R27: 17 | S27: 34 | T27: =IFERROR(O27/Q27,"") -> 0.375 | U27: =IFERROR(I27/O27,"") -> 22650.944 | V27: =IFERROR(P27/O27,"") -> 1.0555556 | W27: =IFERROR(R27/Q27,"") -> 0.35416667 | Y27: 8815 | Z27: 0 | AC27: ※最終週は翌月にまたぐため、2026年08月シートの実績も自動で合算します
A28: 46224 | B28: =MID("日月火水木金土",WEEKDAY(A28),1) -> 火 | C28: 400000 | D28: =SUM($C$8:C28) -> 8700000 | E28: 25531 | F28: 162550 | I28: =IF(COUNT(E28:H28)=0,"",SUM(E28:H28)) -> 188081 | J28: =IF(I28="","",SUM($I$8:I28)) -> 4408645 | K28: =IF(I28="","",IFERROR(I28/C28,"")) -> 0.4702025 | L28: =IF(J28="","",IFERROR(J28/D28,"")) -> 0.5067408 | M28: =IF(J28="","",IF(D28=0,"",J28-D28)) -> -4291355 | N28: =IF(I28="","—",IF(D28=0,"予算未入力",IF(J28>=D28,"◎ ペース内","▲ 遅れ"))) -> ▲ 遅れ | O28: 8 | P28: 9 | Q28: 26 | R28: 11 | S28: 16 | T28: =IFERROR(O28/Q28,"") -> 0.30769231 | U28: =IFERROR(I28/O28,"") -> 23510.125 | V28: =IFERROR(P28/O28,"") -> 1.125 | W28: =IFERROR(R28/Q28,"") -> 0.42307692 | X28: 0 | Y28: 8810 | Z28: 0 | AC28: ※月初の月曜まで（例：6/1）は前月シートの最終週に含まれます
A29: 46225 | B29: =MID("日月火水木金土",WEEKDAY(A29),1) -> 水 | C29: 400000 | D29: =SUM($C$8:C29) -> 9100000 | E29: 21610 | F29: 48510 | I29: =IF(COUNT(E29:H29)=0,"",SUM(E29:H29)) -> 70120 | J29: =IF(I29="","",SUM($I$8:I29)) -> 4478765 | K29: =IF(I29="","",IFERROR(I29/C29,"")) -> 0.1753 | L29: =IF(J29="","",IFERROR(J29/D29,"")) -> 0.49217198 | M29: =IF(J29="","",IF(D29=0,"",J29-D29)) -> -4621235 | N29: =IF(I29="","—",IF(D29=0,"予算未入力",IF(J29>=D29,"◎ ペース内","▲ 遅れ"))) -> ▲ 遅れ | O29: 3 | P29: 3 | Q29: 8 | R29: 2 | S29: 2 | T29: =IFERROR(O29/Q29,"") -> 0.375 | U29: =IFERROR(I29/O29,"") -> 23373.333 | V29: =IFERROR(P29/O29,"") -> 1 | W29: =IFERROR(R29/Q29,"") -> 0.25 | X29: 0 | Y29: 8811 | Z29: 0
A30: 46226 | B30: =MID("日月火水木金土",WEEKDAY(A30),1) -> 木 | C30: 400000 | D30: =SUM($C$8:C30) -> 9500000 | E30: 90818 | F30: 120540 | I30: =IF(COUNT(E30:H30)=0,"",SUM(E30:H30)) -> 211358 | J30: =IF(I30="","",SUM($I$8:I30)) -> 4690123 | K30: =IF(I30="","",IFERROR(I30/C30,"")) -> 0.528395 | L30: =IF(J30="","",IFERROR(J30/D30,"")) -> 0.49369716 | M30: =IF(J30="","",IF(D30=0,"",J30-D30)) -> -4809877 | N30: =IF(I30="","—",IF(D30=0,"予算未入力",IF(J30>=D30,"◎ ペース内","▲ 遅れ"))) -> ▲ 遅れ | O30: 8 | P30: 9 | Q30: 24 | R30: 11 | S30: 18 | T30: =IFERROR(O30/Q30,"") -> 0.33333333 | U30: =IFERROR(I30/O30,"") -> 26419.75 | V30: =IFERROR(P30/O30,"") -> 1.125 | W30: =IFERROR(R30/Q30,"") -> 0.45833333 | X30: 0 | Y30: 8808 | Z30: 0
A31: 46227 | B31: =MID("日月火水木金土",WEEKDAY(A31),1) -> 金 | C31: 450000 | D31: =SUM($C$8:C31) -> 9950000 | E31: 24310 | F31: 19910 | I31: =IF(COUNT(E31:H31)=0,"",SUM(E31:H31)) -> 44220 | J31: =IF(I31="","",SUM($I$8:I31)) -> 4734343 | K31: =IF(I31="","",IFERROR(I31/C31,"")) -> 0.098266667 | L31: =IF(J31="","",IFERROR(J31/D31,"")) -> 0.47581337 | M31: =IF(J31="","",IF(D31=0,"",J31-D31)) -> -5215657 | N31: =IF(I31="","—",IF(D31=0,"予算未入力",IF(J31>=D31,"◎ ペース内","▲ 遅れ"))) -> ▲ 遅れ | O31: 2 | P31: 2 | Q31: 18 | R31: 2 | S31: 3 | T31: =IFERROR(O31/Q31,"") -> 0.11111111 | U31: =IFERROR(I31/O31,"") -> 22110 | V31: =IFERROR(P31/O31,"") -> 1 | W31: =IFERROR(R31/Q31,"") -> 0.11111111 | X31: 0 | Y31: 8800 | Z31: 1050
A32: 46228 | B32: =MID("日月火水木金土",WEEKDAY(A32),1) -> 土 | C32: 700000 | D32: =SUM($C$8:C32) -> 10650000 | E32: 96570 | F32: 190720 | I32: =IF(COUNT(E32:H32)=0,"",SUM(E32:H32)) -> 287290 | J32: =IF(I32="","",SUM($I$8:I32)) -> 5021633 | K32: =IF(I32="","",IFERROR(I32/C32,"")) -> 0.41041429 | L32: =IF(J32="","",IFERROR(J32/D32,"")) -> 0.47151484 | M32: =IF(J32="","",IF(D32=0,"",J32-D32)) -> -5628367 | N32: =IF(I32="","—",IF(D32=0,"予算未入力",IF(J32>=D32,"◎ ペース内","▲ 遅れ"))) -> ▲ 遅れ | O32: 12 | P32: 16 | Q32: 43 | R32: 15 | S32: 25 | T32: =IFERROR(O32/Q32,"") -> 0.27906977 | U32: =IFERROR(I32/O32,"") -> 23940.833 | V32: =IFERROR(P32/O32,"") -> 1.3333333 | W32: =IFERROR(R32/Q32,"") -> 0.34883721 | Y32: 8796 | Z32: 0
A33: 46229 | B33: =MID("日月火水木金土",WEEKDAY(A33),1) -> 日 | C33: 700000 | D33: =SUM($C$8:C33) -> 11350000 | E33: 26010 | F33: 185260 | I33: =IF(COUNT(E33:H33)=0,"",SUM(E33:H33)) -> 211270 | J33: =IF(I33="","",SUM($I$8:I33)) -> 5232903 | K33: =IF(I33="","",IFERROR(I33/C33,"")) -> 0.30181429 | L33: =IF(J33="","",IFERROR(J33/D33,"")) -> 0.46104872 | M33: =IF(J33="","",IF(D33=0,"",J33-D33)) -> -6117097 | N33: =IF(I33="","—",IF(D33=0,"予算未入力",IF(J33>=D33,"◎ ペース内","▲ 遅れ"))) -> ▲ 遅れ | O33: 8 | P33: 9 | Q33: 43 | R33: 11 | S33: 19 | T33: =IFERROR(O33/Q33,"") -> 0.18604651 | U33: =IFERROR(I33/O33,"") -> 26408.75 | V33: =IFERROR(P33/O33,"") -> 1.125 | W33: =IFERROR(R33/Q33,"") -> 0.25581395 | X33: 0 | Y33: 8792 | Z33: 0
A34: 46230 | B34: =MID("日月火水木金土",WEEKDAY(A34),1) -> 月 | C34: 450000 | D34: =SUM($C$8:C34) -> 11800000 | E34: 22110 | F34: 71621 | I34: =IF(COUNT(E34:H34)=0,"",SUM(E34:H34)) -> 93731 | J34: =IF(I34="","",SUM($I$8:I34)) -> 5326634 | K34: =IF(I34="","",IFERROR(I34/C34,"")) -> 0.20829111 | L34: =IF(J34="","",IFERROR(J34/D34,"")) -> 0.45140966 | M34: =IF(J34="","",IF(D34=0,"",J34-D34)) -> -6473366 | N34: =IF(I34="","—",IF(D34=0,"予算未入力",IF(J34>=D34,"◎ ペース内","▲ 遅れ"))) -> ▲ 遅れ | O34: 4 | P34: 4 | Q34: 11 | R34: 6 | S34: 11 | T34: =IFERROR(O34/Q34,"") -> 0.36363636 | U34: =IFERROR(I34/O34,"") -> 23432.75 | V34: =IFERROR(P34/O34,"") -> 1 | W34: =IFERROR(R34/Q34,"") -> 0.54545455 | Y34: 8784 | Z34: 0
A35: 46231 | B35: =MID("日月火水木金土",WEEKDAY(A35),1) -> 火 | C35: 450000 | D35: =SUM($C$8:C35) -> 12250000 | E35: 89030 | F35: 26010 | I35: =IF(COUNT(E35:H35)=0,"",SUM(E35:H35)) -> 115040 | J35: =IF(I35="","",SUM($I$8:I35)) -> 5441674 | K35: =IF(I35="","",IFERROR(I35/C35,"")) -> 0.25564444 | L35: =IF(J35="","",IFERROR(J35/D35,"")) -> 0.44421829 | M35: =IF(J35="","",IF(D35=0,"",J35-D35)) -> -6808326 | N35: =IF(I35="","—",IF(D35=0,"予算未入力",IF(J35>=D35,"◎ ペース内","▲ 遅れ"))) -> ▲ 遅れ | O35: 5 | P35: 5 | Q35: 18 | R35: 5 | S35: 8 | T35: =IFERROR(O35/Q35,"") -> 0.27777778 | U35: =IFERROR(I35/O35,"") -> 23008 | V35: =IFERROR(P35/O35,"") -> 1 | W35: =IFERROR(R35/Q35,"") -> 0.27777778 | Y35: 8775 | Z35: 0
A36: 46232 | B36: =MID("日月火水木金土",WEEKDAY(A36),1) -> 水 | C36: 450000 | D36: =SUM($C$8:C36) -> 12700000 | E36: 52020 | F36: 81330 | I36: =IF(COUNT(E36:H36)=0,"",SUM(E36:H36)) -> 133350 | J36: =IF(I36="","",SUM($I$8:I36)) -> 5575024 | K36: =IF(I36="","",IFERROR(I36/C36,"")) -> 0.29633333 | L36: =IF(J36="","",IFERROR(J36/D36,"")) -> 0.43897827 | M36: =IF(J36="","",IF(D36=0,"",J36-D36)) -> -7124976 | N36: =IF(I36="","—",IF(D36=0,"予算未入力",IF(J36>=D36,"◎ ペース内","▲ 遅れ"))) -> ▲ 遅れ | O36: 6 | P36: 6 | Q36: 22 | R36: 10 | S36: 13 | T36: =IFERROR(O36/Q36,"") -> 0.27272727 | U36: =IFERROR(I36/O36,"") -> 22225 | V36: =IFERROR(P36/O36,"") -> 1 | W36: =IFERROR(R36/Q36,"") -> 0.45454545 | Y36: 8772 | Z36: 0
A37: 46233 | B37: =MID("日月火水木金土",WEEKDAY(A37),1) -> 木 | C37: 450000 | D37: =SUM($C$8:C37) -> 13150000 | I37: =IF(COUNT(E37:H37)=0,"",SUM(E37:H37)) | J37: =IF(I37="","",SUM($I$8:I37)) | K37: =IF(I37="","",IFERROR(I37/C37,"")) | L37: =IF(J37="","",IFERROR(J37/D37,"")) | M37: =IF(J37="","",IF(D37=0,"",J37-D37)) | N37: =IF(I37="","—",IF(D37=0,"予算未入力",IF(J37>=D37,"◎ ペース内","▲ 遅れ"))) -> — | T37: =IFERROR(O37/Q37,"") | U37: =IFERROR(I37/O37,"") | V37: =IFERROR(P37/O37,"") | W37: =IFERROR(R37/Q37,"") | Z37: 0
A38: 46234 | B38: =MID("日月火水木金土",WEEKDAY(A38),1) -> 金 | C38: 450000 | D38: =SUM($C$8:C38) -> 13600000 | I38: =IF(COUNT(E38:H38)=0,"",SUM(E38:H38)) | J38: =IF(I38="","",SUM($I$8:I38)) | K38: =IF(I38="","",IFERROR(I38/C38,"")) | L38: =IF(J38="","",IFERROR(J38/D38,"")) | M38: =IF(J38="","",IF(D38=0,"",J38-D38)) | N38: =IF(I38="","—",IF(D38=0,"予算未入力",IF(J38>=D38,"◎ ペース内","▲ 遅れ"))) -> — | T38: =IFERROR(O38/Q38,"") | U38: =IFERROR(I38/O38,"") | V38: =IFERROR(P38/O38,"") | W38: =IFERROR(R38/Q38,"") | Z38: 0
A39: 月計 | C39: =SUM(C8:C38) -> 13600000 | D39: =C39 -> 13600000 | E39: =SUM(E8:E38) -> 1959159 | F39: =SUM(F8:F38) -> 3582865 | G39: =SUM(G8:G38) -> 33000 | H39: =SUM(H8:H38) -> 0 | I39: =SUM(I8:I38) -> 5575024 | J39: =I39 -> 5575024 | K39: =IFERROR(I39/C39,"") -> 0.40992824 | L39: =IFERROR(I39/C39,"") -> 0.40992824 | M39: =I39-C39 -> -8024976 | O39: =SUM(O8:O38) -> 241 | P39: =SUM(P8:P38) -> 262 | Q39: =SUM(Q8:Q38) -> 793 | R39: =SUM(R8:R38) -> 305 | S39: =SUM(S8:S38) -> 448 | T39: =IFERROR(O39/Q39,"") -> 0.30390921 | U39: =IFERROR(I39/O39,"") -> 23132.88 | V39: =IFERROR(P39/O39,"") -> 1.0871369 | W39: =IFERROR(R39/Q39,"") -> 0.38461538 | X39: =SUM(X8:X38) -> 0 | Y39: =IFERROR(LOOKUP(9.99E+307,Y8:Y38),"") -> 8772 | Z39: =SUM(Z8:Z38) -> 1050 | AA39: フォロワーは月末値

Sheet 2026年08月
A1: 2026年8月 名古屋店 日別売上管理
A2: 青字＋薄黄色のセルが入力欄。白セルは数式なので触らないでください。単位：円
A3: 月間予算 | C3: 当月実績 | E3: 達成率 | G3: 営業日数(/31日) | I3: 残り必要額 | K3: 残り必要日商
A4: =IF('設定'!$B$12="",SUM(C8:C38),'設定'!$B$12) -> 17400000 | C4: =SUM(I8:I38) -> 4585980 | E4: =IFERROR(C4/A4,0) -> 0.26356207 | G4: =COUNTIF(I8:I38,">0") -> 31 | I4: =A4-C4 -> 12814020 | K4: =IF((31-G4)>0,(A4-C4)/(31-G4),0) -> 0
A5: 日次予算合計 | C5: 着地見込 | E5: 決定率 | G5: 客単価 | I5: セット率 | K5: 試着率
A6: =SUM(C8:C38) -> 17400000 | C6: =IFERROR(C4/G4*31,0) -> 4585980 | E6: =IFERROR(O39/Q39,0) -> 0.26329114 | G6: =IFERROR(I39/O39,0) -> 22047.981 | I6: =IFERROR(P39/O39,0) -> 1.0625 | K6: =IFERROR(R39/Q39,0) -> 0.3721519
A7: 日付 | B7: 曜 | C7: 日次予算 | D7: 累計予算 | E7: 現金 | F7: クレジット | G7: 商品券 | H7: 内訳差額 (要確認) | I7: 実績合計 | J7: 累計実績 | K7: 日次達成 | L7: 累計達成 | M7: 累計予実差 | N7: ペース | O7: 購入人数 | P7: 販売点数 | Q7: 来客数 | R7: 試着組数 | S7: 試着個数 | T7: 決定率 | U7: 客単価 | V7: セット率 | W7: 試着率 | X7: クロス クーポン | Y7: インスタ フォロワー | Z7: 経費 | AA7: メモ | AC7: 曜日 | AD7: 平均日商 | AE7: 日数 | AF7: 決定率 | AG7: 客単価
A8: 46235 | B8: =MID("日月火水木金土",WEEKDAY(A8),1) -> 土 | C8: 660000 | D8: =SUM($C$8:C8) -> 660000 | E8: 23810 | F8: 175910 | I8: =IF(COUNT(E8:H8)=0,"",SUM(E8:H8)) -> 199720 | J8: =IF(I8="","",SUM($I$8:I8)) -> 199720 | K8: =IF(I8="","",IFERROR(I8/C8,"")) -> 0.30260606 | L8: =IF(J8="","",IFERROR(J8/D8,"")) -> 0.30260606 | M8: =IF(J8="","",IF(D8=0,"",J8-D8)) -> -460280 | N8: =IF(I8="","—",IF(D8=0,"予算未入力",IF(J8>=D8,"◎ ペース内","▲ 遅れ"))) -> ▲ 遅れ | O8: 9 | P8: 9 | Q8: 36 | R8: 17 | S8: 29 | T8: =IFERROR(O8/Q8,"") -> 0.25 | U8: =IFERROR(I8/O8,"") -> 22191.111 | V8: =IFERROR(P8/O8,"") -> 1 | W8: =IFERROR(R8/Q8,"") -> 0.47222222 | Y8: 8774 | AC8: 月 | AD8: =IFERROR(AVERAGEIFS($I$8:$I$38,$B$8:$B$38,AC8,$I$8:$I$38,">0"),0) -> 104575 | AE8: =COUNTIFS($B$8:$B$38,AC8,$I$8:$I$38,">0") -> 5 | AF8: =IFERROR(SUMIF($B$8:$B$38,AC8,$O$8:$O$38)/SUMIF($B$8:$B$38,AC8,$Q$8:$Q$38),0) -> 0.24742268 | AG8: =IFERROR(SUMIF($B$8:$B$38,AC8,$I$8:$I$38)/SUMIF($B$8:$B$38,AC8,$O$8:$O$38),0) -> 21786.458
A9: 46236 | B9: =MID("日月火水木金土",WEEKDAY(A9),1) -> 日 | C9: 660000 | D9: =SUM($C$8:C9) -> 1320000 | F9: 167450 | I9: =IF(COUNT(E9:H9)=0,"",SUM(E9:H9)) -> 167450 | J9: =IF(I9="","",SUM($I$8:I9)) -> 367170 | K9: =IF(I9="","",IFERROR(I9/C9,"")) -> 0.25371212 | L9: =IF(J9="","",IFERROR(J9/D9,"")) -> 0.27815909 | M9: =IF(J9="","",IF(D9=0,"",J9-D9)) -> -952830 | N9: =IF(I9="","—",IF(D9=0,"予算未入力",IF(J9>=D9,"◎ ペース内","▲ 遅れ"))) -> ▲ 遅れ | O9: 7 | P9: 8 | Q9: 36 | R9: 9 | S9: 16 | T9: =IFERROR(O9/Q9,"") -> 0.19444444 | U9: =IFERROR(I9/O9,"") -> 23921.429 | V9: =IFERROR(P9/O9,"") -> 1.1428571 | W9: =IFERROR(R9/Q9,"") -> 0.25 | Y9: 8773 | AC9: 火 | AD9: =IFERROR(AVERAGEIFS($I$8:$I$38,$B$8:$B$38,AC9,$I$8:$I$38,">0"),0) -> 110211.75 | AE9: =COUNTIFS($B$8:$B$38,AC9,$I$8:$I$38,">0") -> 4 | AF9: =IFERROR(SUMIF($B$8:$B$38,AC9,$O$8:$O$38)/SUMIF($B$8:$B$38,AC9,$Q$8:$Q$38),0) -> 0.19 | AG9: =IFERROR(SUMIF($B$8:$B$38,AC9,$I$8:$I$38)/SUMIF($B$8:$B$38,AC9,$O$8:$O$38),0) -> 23202.474
A10: 46237 | B10: =MID("日月火水木金土",WEEKDAY(A10),1) -> 月 | C10: 440000 | D10: =SUM($C$8:C10) -> 1760000 | E10: 43720 | F10: 64009 | I10: =IF(COUNT(E10:H10)=0,"",SUM(E10:H10)) -> 107729 | J10: =IF(I10="","",SUM($I$8:I10)) -> 474899 | K10: =IF(I10="","",IFERROR(I10/C10,"")) -> 0.24483864 | L10: =IF(J10="","",IFERROR(J10/D10,"")) -> 0.26982898 | M10: =IF(J10="","",IF(D10=0,"",J10-D10)) -> -1285101 | N10: =IF(I10="","—",IF(D10=0,"予算未入力",IF(J10>=D10,"◎ ペース内","▲ 遅れ"))) -> ▲ 遅れ | O10: 5 | P10: 5 | Q10: 18 | R10: 5 | S10: 7 | T10: =IFERROR(O10/Q10,"") -> 0.27777778 | U10: =IFERROR(I10/O10,"") -> 21545.8 | V10: =IFERROR(P10/O10,"") -> 1 | W10: =IFERROR(R10/Q10,"") -> 0.27777778 | Y10: 8770 | AC10: 水 | AD10: =IFERROR(AVERAGEIFS($I$8:$I$38,$B$8:$B$38,AC10,$I$8:$I$38,">0"),0) -> 138166.25 | AE10: =COUNTIFS($B$8:$B$38,AC10,$I$8:$I$38,">0") -> 4 | AF10: =IFERROR(SUMIF($B$8:$B$38,AC10,$O$8:$O$38)/SUMIF($B$8:$B$38,AC10,$Q$8:$Q$38),0) -> 0.29032258 | AG10: =IFERROR(SUMIF($B$8:$B$38,AC10,$I$8:$I$38)/SUMIF($B$8:$B$38,AC10,$O$8:$O$38),0) -> 20469.074
A11: 46238 | B11: =MID("日月火水木金土",WEEKDAY(A11),1) -> 火 | C11: 440000 | D11: =SUM($C$8:C11) -> 2200000 | E11: 0 | F11: 30110 | G11: 13000 | I11: =IF(COUNT(E11:H11)=0,"",SUM(E11:H11)) -> 43110 | J11: =IF(I11="","",SUM($I$8:I11)) -> 518009 | K11: =IF(I11="","",IFERROR(I11/C11,"")) -> 0.097977273 | L11: =IF(J11="","",IFERROR(J11/D11,"")) -> 0.23545864 | M11: =IF(J11="","",IF(D11=0,"",J11-D11)) -> -1681991 | N11: =IF(I11="","—",IF(D11=0,"予算未入力",IF(J11>=D11,"◎ ペース内","▲ 遅れ"))) -> ▲ 遅れ | O11: 2 | P11: 2 | Q11: 15 | R11: 4 | S11: 4 | T11: =IFERROR(O11/Q11,"") -> 0.13333333 | U11: =IFERROR(I11/O11,"") -> 21555 | V11: =IFERROR(P11/O11,"") -> 1 | W11: =IFERROR(R11/Q11,"") -> 0.26666667 | AC11: 木 | AD11: =IFERROR(AVERAGEIFS($I$8:$I$38,$B$8:$B$38,AC11,$I$8:$I$38,">0"),0) -> 134706.25 | AE11: =COUNTIFS($B$8:$B$38,AC11,$I$8:$I$38,">0") -> 4 | AF11: =IFERROR(SUMIF($B$8:$B$38,AC11,$O$8:$O$38)/SUMIF($B$8:$B$38,AC11,$Q$8:$Q$38),0) -> 0.25 | AG11: =IFERROR(SUMIF($B$8:$B$38,AC11,$I$8:$I$38)/SUMIF($B$8:$B$38,AC11,$O$8:$O$38),0) -> 22451.042
A12: 46239 | B12: =MID("日月火水木金土",WEEKDAY(A12),1) -> 水 | C12: 440000 | D12: =SUM($C$8:C12) -> 2640000 | E12: 59549 | F12: 39798 | I12: =IF(COUNT(E12:H12)=0,"",SUM(E12:H12)) -> 99347 | J12: =IF(I12="","",SUM($I$8:I12)) -> 617356 | K12: =IF(I12="","",IFERROR(I12/C12,"")) -> 0.22578864 | L12: =IF(J12="","",IFERROR(J12/D12,"")) -> 0.23384697 | M12: =IF(J12="","",IF(D12=0,"",J12-D12)) -> -2022644 | N12: =IF(I12="","—",IF(D12=0,"予算未入力",IF(J12>=D12,"◎ ペース内","▲ 遅れ"))) -> ▲ 遅れ | O12: 6 | P12: 6 | Q12: 17 | R12: 4 | S12: 6 | T12: =IFERROR(O12/Q12,"") -> 0.35294118 | U12: =IFERROR(I12/O12,"") -> 16557.833 | V12: =IFERROR(P12/O12,"") -> 1 | W12: =IFERROR(R12/Q12,"") -> 0.23529412 | Y12: 8770 | AC12: 金 | AD12: =IFERROR(AVERAGEIFS($I$8:$I$38,$B$8:$B$38,AC12,$I$8:$I$38,">0"),0) -> 132400.25 | AE12: =COUNTIFS($B$8:$B$38,AC12,$I$8:$I$38,">0") -> 4 | AF12: =IFERROR(SUMIF($B$8:$B$38,AC12,$O$8:$O$38)/SUMIF($B$8:$B$38,AC12,$Q$8:$Q$38),0) -> 0.26744186 | AG12: =IFERROR(SUMIF($B$8:$B$38,AC12,$I$8:$I$38)/SUMIF($B$8:$B$38,AC12,$O$8:$O$38),0) -> 23026.13
A13: 46240 | B13: =MID("日月火水木金土",WEEKDAY(A13),1) -> 木 | C13: 440000 | D13: =SUM($C$8:C13) -> 3080000 | E13: 0 | F13: 70230 | I13: =IF(COUNT(E13:H13)=0,"",SUM(E13:H13)) -> 70230 | J13: =IF(I13="","",SUM($I$8:I13)) -> 687586 | K13: =IF(I13="","",IFERROR(I13/C13,"")) -> 0.15961364 | L13: =IF(J13="","",IFERROR(J13/D13,"")) -> 0.22324221 | M13: =IF(J13="","",IF(D13=0,"",J13-D13)) -> -2392414 | N13: =IF(I13="","—",IF(D13=0,"予算未入力",IF(J13>=D13,"◎ ペース内","▲ 遅れ"))) -> ▲ 遅れ | O13: 3 | P13: 3 | Q13: 17 | R13: 4 | S13: 4 | T13: =IFERROR(O13/Q13,"") -> 0.17647059 | U13: =IFERROR(I13/O13,"") -> 23410 | V13: =IFERROR(P13/O13,"") -> 1 | W13: =IFERROR(R13/Q13,"") -> 0.23529412 | Y13: 8767 | AC13: 土 | AD13: =IFERROR(AVERAGEIFS($I$8:$I$38,$B$8:$B$38,AC13,$I$8:$I$38,">0"),0) -> 199168.2 | AE13: =COUNTIFS($B$8:$B$38,AC13,$I$8:$I$38,">0") -> 5 | AF13: =IFERROR(SUMIF($B$8:$B$38,AC13,$O$8:$O$38)/SUMIF($B$8:$B$38,AC13,$Q$8:$Q$38),0) -> 0.29012346 | AG13: =IFERROR(SUMIF($B$8:$B$38,AC13,$I$8:$I$38)/SUMIF($B$8:$B$38,AC13,$O$8:$O$38),0) -> 21188.106
A14: 46241 | B14: =MID("日月火水木金土",WEEKDAY(A14),1) -> 金 | C14: 440000 | D14: =SUM($C$8:C14) -> 3520000 | E14: 36828 | F14: 22110 | I14: =IF(COUNT(E14:H14)=0,"",SUM(E14:H14)) -> 58938 | J14: =IF(I14="","",SUM($I$8:I14)) -> 746524 | K14: =IF(I14="","",IFERROR(I14/C14,"")) -> 0.13395 | L14: =IF(J14="","",IFERROR(J14/D14,"")) -> 0.21208068 | M14: =IF(J14="","",IF(D14=0,"",J14-D14)) -> -2773476 | N14: =IF(I14="","—",IF(D14=0,"予算未入力",IF(J14>=D14,"◎ ペース内","▲ 遅れ"))) -> ▲ 遅れ | O14: 3 | P14: 3 | Q14: 17 | R14: 5 | S14: 6 | T14: =IFERROR(O14/Q14,"") -> 0.17647059 | U14: =IFERROR(I14/O14,"") -> 19646 | V14: =IFERROR(P14/O14,"") -> 1 | W14: =IFERROR(R14/Q14,"") -> 0.29411765 | Y14: 8767 | AC14: 日 | AD14: =IFERROR(AVERAGEIFS($I$8:$I$38,$B$8:$B$38,AC14,$I$8:$I$38,">0"),0) -> 201065.2 | AE14: =COUNTIFS($B$8:$B$38,AC14,$I$8:$I$38,">0") -> 5 | AF14: =IFERROR(SUMIF($B$8:$B$38,AC14,$O$8:$O$38)/SUMIF($B$8:$B$38,AC14,$Q$8:$Q$38),0) -> 0.28205128 | AG14: =IFERROR(SUMIF($B$8:$B$38,AC14,$I$8:$I$38)/SUMIF($B$8:$B$38,AC14,$O$8:$O$38),0) -> 22848.318
A15: 46242 | B15: =MID("日月火水木金土",WEEKDAY(A15),1) -> 土 | C15: 660000 | D15: =SUM($C$8:C15) -> 4180000 | E15: 41509 | F15: 139200 | I15: =IF(COUNT(E15:H15)=0,"",SUM(E15:H15)) -> 180709 | J15: =IF(I15="","",SUM($I$8:I15)) -> 927233 | K15: =IF(I15="","",IFERROR(I15/C15,"")) -> 0.27380152 | L15: =IF(J15="","",IFERROR(J15/D15,"")) -> 0.22182608 | M15: =IF(J15="","",IF(D15=0,"",J15-D15)) -> -3252767 | N15: =IF(I15="","—",IF(D15=0,"予算未入力",IF(J15>=D15,"◎ ペース内","▲ 遅れ"))) -> ▲ 遅れ | O15: 10 | P15: 10 | Q15: 35 | R15: 10 | S15: 15 | T15: =IFERROR(O15/Q15,"") -> 0.28571429 | U15: =IFERROR(I15/O15,"") -> 18070.9 | V15: =IFERROR(P15/O15,"") -> 1 | W15: =IFERROR(R15/Q15,"") -> 0.28571429 | Y15: 8763
A16: 46243 | B16: =MID("日月火水木金土",WEEKDAY(A16),1) -> 日 | C16: 660000 | D16: =SUM($C$8:C16) -> 4840000 | E16: 53020 | F16: 109269 | I16: =IF(COUNT(E16:H16)=0,"",SUM(E16:H16)) -> 162289 | J16: =IF(I16="","",SUM($I$8:I16)) -> 1089522 | K16: =IF(I16="","",IFERROR(I16/C16,"")) -> 0.24589242 | L16: =IF(J16="","",IFERROR(J16/D16,"")) -> 0.22510785 | M16: =IF(J16="","",IF(D16=0,"",J16-D16)) -> -3750478 | N16: =IF(I16="","—",IF(D16=0,"予算未入力",IF(J16>=D16,"◎ ペース内","▲ 遅れ"))) -> ▲ 遅れ | O16: 6 | P16: 6 | Q16: 25 | R16: 12 | S16: 20 | T16: =IFERROR(O16/Q16,"") -> 0.24 | U16: =IFERROR(I16/O16,"") -> 27048.167 | V16: =IFERROR(P16/O16,"") -> 1 | W16: =IFERROR(R16/Q16,"") -> 0.48 | Y16: 8760 | AC16: ※実績入力後に曜日別の傾向が出ます
A17: 46244 | B17: =MID("日月火水木金土",WEEKDAY(A17),1) -> 月 | C17: 440000 | D17: =SUM($C$8:C17) -> 5280000 | E17: 17210 | F17: 128669 | I17: =IF(COUNT(E17:H17)=0,"",SUM(E17:H17)) -> 145879 | J17: =IF(I17="","",SUM($I$8:I17)) -> 1235401 | K17: =IF(I17="","",IFERROR(I17/C17,"")) -> 0.33154318 | L17: =IF(J17="","",IFERROR(J17/D17,"")) -> 0.23397746 | M17: =IF(J17="","",IF(D17=0,"",J17-D17)) -> -4044599 | N17: =IF(I17="","—",IF(D17=0,"予算未入力",IF(J17>=D17,"◎ ペース内","▲ 遅れ"))) -> ▲ 遅れ | O17: 7 | P17: 8 | Q17: 25 | R17: 9 | S17: 18 | T17: =IFERROR(O17/Q17,"") -> 0.28 | U17: =IFERROR(I17/O17,"") -> 20839.857 | V17: =IFERROR(P17/O17,"") -> 1.1428571 | W17: =IFERROR(R17/Q17,"") -> 0.36 | Y17: 8757
A18: 46245 | B18: =MID("日月火水木金土",WEEKDAY(A18),1) -> 火 | C18: 660000 | D18: =SUM($C$8:C18) -> 5940000 | E18: 94040 | F18: 166569 | I18: =IF(COUNT(E18:H18)=0,"",SUM(E18:H18)) -> 260609 | J18: =IF(I18="","",SUM($I$8:I18)) -> 1496010 | K18: =IF(I18="","",IFERROR(I18/C18,"")) -> 0.39486212 | L18: =IF(J18="","",IFERROR(J18/D18,"")) -> 0.25185354 | M18: =IF(J18="","",IF(D18=0,"",J18-D18)) -> -4443990 | N18: =IF(I18="","—",IF(D18=0,"予算未入力",IF(J18>=D18,"◎ ペース内","▲ 遅れ"))) -> ▲ 遅れ | O18: 10 | P18: 11 | Q18: 45 | R18: 15 | S18: 20 | T18: =IFERROR(O18/Q18,"") -> 0.22222222 | U18: =IFERROR(I18/O18,"") -> 26060.9 | V18: =IFERROR(P18/O18,"") -> 1.1 | W18: =IFERROR(R18/Q18,"") -> 0.33333333 | Y18: 8755 | AC18: ■ 週次サマリー（火曜〜翌月曜） | AJ18: 第1火曜 | AK18: =$A$8+MOD(2-WEEKDAY($A$8,2)+7,7) -> 46238
A19: 46246 | B19: =MID("日月火水木金土",WEEKDAY(A19),1) -> 水 | C19: 440000 | D19: =SUM($C$8:C19) -> 6380000 | E19: 66920 | F19: 41778 | I19: =IF(COUNT(E19:H19)=0,"",SUM(E19:H19)) -> 108698 | J19: =IF(I19="","",SUM($I$8:I19)) -> 1604708 | K19: =IF(I19="","",IFERROR(I19/C19,"")) -> 0.24704091 | L19: =IF(J19="","",IFERROR(J19/D19,"")) -> 0.25152163 | M19: =IF(J19="","",IF(D19=0,"",J19-D19)) -> -4775292 | N19: =IF(I19="","—",IF(D19=0,"予算未入力",IF(J19>=D19,"◎ ペース内","▲ 遅れ"))) -> ▲ 遅れ | O19: 5 | P19: 5 | Q19: 34 | R19: 10 | S19: 15 | T19: =IFERROR(O19/Q19,"") -> 0.14705882 | U19: =IFERROR(I19/O19,"") -> 21739.6 | V19: =IFERROR(P19/O19,"") -> 1 | W19: =IFERROR(R19/Q19,"") -> 0.29411765 | Y19: 8754 | AC19: 週 | AD19: 期間 | AE19: 売上 | AF19: 決定率 | AG19: 客単価 | AH19: セット率 | AI19: 試着率
A20: 46247 | B20: =MID("日月火水木金土",WEEKDAY(A20),1) -> 木 | C20: 885000 | D20: =SUM($C$8:C20) -> 7265000 | E20: 42220 | F20: 118258 | I20: =IF(COUNT(E20:H20)=0,"",SUM(E20:H20)) -> 160478 | J20: =IF(I20="","",SUM($I$8:I20)) -> 1765186 | K20: =IF(I20="","",IFERROR(I20/C20,"")) -> 0.18133107 | L20: =IF(J20="","",IFERROR(J20/D20,"")) -> 0.24297123 | M20: =IF(J20="","",IF(D20=0,"",J20-D20)) -> -5499814 | N20: =IF(I20="","—",IF(D20=0,"予算未入力",IF(J20>=D20,"◎ ペース内","▲ 遅れ"))) -> ▲ 遅れ | O20: 7 | P20: 8 | Q20: 29 | R20: 7 | S20: 11 | T20: =IFERROR(O20/Q20,"") -> 0.24137931 | U20: =IFERROR(I20/O20,"") -> 22925.429 | V20: =IFERROR(P20/O20,"") -> 1.1428571 | W20: =IFERROR(R20/Q20,"") -> 0.24137931 | Y20: 8759 | AC20: 1 | AD20: =IF($AK$18+7*(1-1)>$A$38,"",TEXT($AK$18+7*(1-1),"m/d")&"-"&TEXT($AK$18+7*(1-1)+6,"m/d")) -> 8/4-8/10 | AE20: =IF($AD20="","",(SUMIFS($I$8:$I$38,$A$8:$A$38,">="&$AK$18+7*(1-1),$A$8:$A$38,"<="&$AK$18+7*(1-1)+6)+SUMIFS('2026年09月'!$I$8:$I$37,'2026年09月'!$A$8:$A$37,">="&$AK$18+7*(1-1),'2026年09月'!$A$8:$A$37,"<="&$AK$18+7*(1-1)+6))) -> 760502 | AF20: =IF($AD20="","",IFERROR((SUMIFS($O$8:$O$38,$A$8:$A$38,">="&$AK$18+7*(1-1),$A$8:$A$38,"<="&$AK$18+7*(1-1)+6)+SUMIFS('2026年09月'!$O$8:$O$37,'2026年09月'!$A$8:$A$37,">="&$AK$18+7*(1-1),'2026年09月'!$A$8:$A$37,"<="&$AK$18+7*(1-1)+6))/(SUMIFS($Q$8:$Q$38,$A$8:$A$38,">="&$AK$18+7*(1-1),$A$8:$A$38,"<="&$AK$18+7*(1-1)+6)+SUMIFS('2026年09月'!$Q$8:$Q$37,'2026年09月'!$A$8:$A$37,">="&$AK$18+7*(1-1),'2026年09月'!$A$8:$A$37,"<="&$AK$18+7*(1-1)+6)),"")) -> 0.24503311 | AG20: =IF($AD20="","",IFERROR((SUMIFS($I$8:$I$38,$A$8:$A$38,">="&$AK$18+7*(1-1),$A$8:$A$38,"<="&$AK$18+7*(1-1)+6)+SUMIFS('2026年09月'!$I$8:$I$37,'2026年09月'!$A$8:$A$37,">="&$AK$18+7*(1-1),'2026年09月'!$A$8:$A$37,"<="&$AK$18+7*(1-1)+6))/(SUMIFS($O$8:$O$38,$A$8:$A$38,">="&$AK$18+7*(1-1),$A$8:$A$38,"<="&$AK$18+7*(1-1)+6)+SUMIFS('2026年09月'!$O$8:$O$37,'2026年09月'!$A$8:$A$37,">="&$AK$18+7*(1-1),'2026年09月'!$A$8:$A$37,"<="&$AK$18+7*(1-1)+6)),"")) -> 20554.108 | AH20: =IF($AD20="","",IFERROR((SUMIFS($P$8:$P$38,$A$8:$A$38,">="&$AK$18+7*(1-1),$A$8:$A$38,"<="&$AK$18+7*(1-1)+6)+SUMIFS('2026年09月'!$P$8:$P$37,'2026年09月'!$A$8:$A$37,">="&$AK$18+7*(1-1),'2026年09月'!$A$8:$A$37,"<="&$AK$18+7*(1-1)+6))/(SUMIFS($O$8:$O$38,$A$8:$A$38,">="&$AK$18+7*(1-1),$A$8:$A$38,"<="&$AK$18+7*(1-1)+6)+SUMIFS('2026年09月'!$O$8:$O$37,'2026年09月'!$A$8:$A$37,">="&$AK$18+7*(1-1),'2026年09月'!$A$8:$A$37,"<="&$AK$18+7*(1-1)+6)),"")) -> 1.027027 | AI20: =IF($AD20="","",IFERROR((SUMIFS($R$8:$R$38,$A$8:$A$38,">="&$AK$18+7*(1-1),$A$8:$A$38,"<="&$AK$18+7*(1-1)+6)+SUMIFS('2026年09月'!$R$8:$R$37,'2026年09月'!$A$8:$A$37,">="&$AK$18+7*(1-1),'2026年09月'!$A$8:$A$37,"<="&$AK$18+7*(1-1)+6))/(SUMIFS($Q$8:$Q$38,$A$8:$A$38,">="&$AK$18+7*(1-1),$A$8:$A$38,"<="&$AK$18+7*(1-1)+6)+SUMIFS('2026年09月'!$Q$8:$Q$37,'2026年09月'!$A$8:$A$37,">="&$AK$18+7*(1-1),'2026年09月'!$A$8:$A$37,"<="&$AK$18+7*(1-1)+6)),"")) -> 0.31788079
A21: 46248 | B21: =MID("日月火水木金土",WEEKDAY(A21),1) -> 金 | C21: 885000 | D21: =SUM($C$8:C21) -> 8150000 | E21: 108288 | F21: 222427 | I21: =IF(COUNT(E21:H21)=0,"",SUM(E21:H21)) -> 330715 | J21: =IF(I21="","",SUM($I$8:I21)) -> 2095901 | K21: =IF(I21="","",IFERROR(I21/C21,"")) -> 0.37368927 | L21: =IF(J21="","",IFERROR(J21/D21,"")) -> 0.25716577 | M21: =IF(J21="","",IF(D21=0,"",J21-D21)) -> -6054099 | N21: =IF(I21="","—",IF(D21=0,"予算未入力",IF(J21>=D21,"◎ ペース内","▲ 遅れ"))) -> ▲ 遅れ | O21: 14 | P21: 15 | Q21: 24 | R21: 15 | S21: 21 | T21: =IFERROR(O21/Q21,"") -> 0.58333333 | U21: =IFERROR(I21/O21,"") -> 23622.5 | V21: =IFERROR(P21/O21,"") -> 1.0714286 | W21: =IFERROR(R21/Q21,"") -> 0.625 | Y21: 8755 | AC21: 2 | AD21: =IF($AK$18+7*(2-1)>$A$38,"",TEXT($AK$18+7*(2-1),"m/d")&"-"&TEXT($AK$18+7*(2-1)+6,"m/d")) -> 8/11-8/17 | AE21: =IF($AD21="","",(SUMIFS($I$8:$I$38,$A$8:$A$38,">="&$AK$18+7*(2-1),$A$8:$A$38,"<="&$AK$18+7*(2-1)+6)+SUMIFS('2026年09月'!$I$8:$I$37,'2026年09月'!$A$8:$A$37,">="&$AK$18+7*(2-1),'2026年09月'!$A$8:$A$37,"<="&$AK$18+7*(2-1)+6))) -> 1542973 | AF21: =IF($AD21="","",IFERROR((SUMIFS($O$8:$O$38,$A$8:$A$38,">="&$AK$18+7*(2-1),$A$8:$A$38,"<="&$AK$18+7*(2-1)+6)+SUMIFS('2026年09月'!$O$8:$O$37,'2026年09月'!$A$8:$A$37,">="&$AK$18+7*(2-1),'2026年09月'!$A$8:$A$37,"<="&$AK$18+7*(2-1)+6))/(SUMIFS($Q$8:$Q$38,$A$8:$A$38,">="&$AK$18+7*(2-1),$A$8:$A$38,"<="&$AK$18+7*(2-1)+6)+SUMIFS('2026年09月'!$Q$8:$Q$37,'2026年09月'!$A$8:$A$37,">="&$AK$18+7*(2-1),'2026年09月'!$A$8:$A$37,"<="&$AK$18+7*(2-1)+6)),"")) -> 0.29545455 | AG21: =IF($AD21="","",IFERROR((SUMIFS($I$8:$I$38,$A$8:$A$38,">="&$AK$18+7*(2-1),$A$8:$A$38,"<="&$AK$18+7*(2-1)+6)+SUMIFS('2026年09月'!$I$8:$I$37,'2026年09月'!$A$8:$A$37,">="&$AK$18+7*(2-1),'2026年09月'!$A$8:$A$37,"<="&$AK$18+7*(2-1)+6))/(SUMIFS($O$8:$O$38,$A$8:$A$38,">="&$AK$18+7*(2-1),$A$8:$A$38,"<="&$AK$18+7*(2-1)+6)+SUMIFS('2026年09月'!$O$8:$O$37,'2026年09月'!$A$8:$A$37,">="&$AK$18+7*(2-1),'2026年09月'!$A$8:$A$37,"<="&$AK$18+7*(2-1)+6)),"")) -> 23738.046 | AH21: =IF($AD21="","",IFERROR((SUMIFS($P$8:$P$38,$A$8:$A$38,">="&$AK$18+7*(2-1),$A$8:$A$38,"<="&$AK$18+7*(2-1)+6)+SUMIFS('2026年09月'!$P$8:$P$37,'2026年09月'!$A$8:$A$37,">="&$AK$18+7*(2-1),'2026年09月'!$A$8:$A$37,"<="&$AK$18+7*(2-1)+6))/(SUMIFS($O$8:$O$38,$A$8:$A$38,">="&$AK$18+7*(2-1),$A$8:$A$38,"<="&$AK$18+7*(2-1)+6)+SUMIFS('2026年09月'!$O$8:$O$37,'2026年09月'!$A$8:$A$37,">="&$AK$18+7*(2-1),'2026年09月'!$A$8:$A$37,"<="&$AK$18+7*(2-1)+6)),"")) -> 1.0923077 | AI21: =IF($AD21="","",IFERROR((SUMIFS($R$8:$R$38,$A$8:$A$38,">="&$AK$18+7*(2-1),$A$8:$A$38,"<="&$AK$18+7*(2-1)+6)+SUMIFS('2026年09月'!$R$8:$R$37,'2026年09月'!$A$8:$A$37,">="&$AK$18+7*(2-1),'2026年09月'!$A$8:$A$37,"<="&$AK$18+7*(2-1)+6))/(SUMIFS($Q$8:$Q$38,$A$8:$A$38,">="&$AK$18+7*(2-1),$A$8:$A$38,"<="&$AK$18+7*(2-1)+6)+SUMIFS('2026年09月'!$Q$8:$Q$37,'2026年09月'!$A$8:$A$37,">="&$AK$18+7*(2-1),'2026年09月'!$A$8:$A$37,"<="&$AK$18+7*(2-1)+6)),"")) -> 0.37727273
A22: 46249 | B22: =MID("日月火水木金土",WEEKDAY(A22),1) -> 土 | C22: 885000 | D22: =SUM($C$8:C22) -> 9035000 | E22: 113430 | F22: 239148 | I22: =IF(COUNT(E22:H22)=0,"",SUM(E22:H22)) -> 352578 | J22: =IF(I22="","",SUM($I$8:I22)) -> 2448479 | K22: =IF(I22="","",IFERROR(I22/C22,"")) -> 0.39839322 | L22: =IF(J22="","",IFERROR(J22/D22,"")) -> 0.27099934 | M22: =IF(J22="","",IF(D22=0,"",J22-D22)) -> -6586521 | N22: =IF(I22="","—",IF(D22=0,"予算未入力",IF(J22>=D22,"◎ ペース内","▲ 遅れ"))) -> ▲ 遅れ | O22: 14 | P22: 16 | Q22: 38 | R22: 19 | S22: 34 | T22: =IFERROR(O22/Q22,"") -> 0.36842105 | U22: =IFERROR(I22/O22,"") -> 25184.143 | V22: =IFERROR(P22/O22,"") -> 1.1428571 | W22: =IFERROR(R22/Q22,"") -> 0.5 | Y22: 8760 | AC22: 3 | AD22: =IF($AK$18+7*(3-1)>$A$38,"",TEXT($AK$18+7*(3-1),"m/d")&"-"&TEXT($AK$18+7*(3-1)+6,"m/d")) -> 8/18-8/24 | AE22: =IF($AD22="","",(SUMIFS($I$8:$I$38,$A$8:$A$38,">="&$AK$18+7*(3-1),$A$8:$A$38,"<="&$AK$18+7*(3-1)+6)+SUMIFS('2026年09月'!$I$8:$I$37,'2026年09月'!$A$8:$A$37,">="&$AK$18+7*(3-1),'2026年09月'!$A$8:$A$37,"<="&$AK$18+7*(3-1)+6))) -> 1047444 | AF22: =IF($AD22="","",IFERROR((SUMIFS($O$8:$O$38,$A$8:$A$38,">="&$AK$18+7*(3-1),$A$8:$A$38,"<="&$AK$18+7*(3-1)+6)+SUMIFS('2026年09月'!$O$8:$O$37,'2026年09月'!$A$8:$A$37,">="&$AK$18+7*(3-1),'2026年09月'!$A$8:$A$37,"<="&$AK$18+7*(3-1)+6))/(SUMIFS($Q$8:$Q$38,$A$8:$A$38,">="&$AK$18+7*(3-1),$A$8:$A$38,"<="&$AK$18+7*(3-1)+6)+SUMIFS('2026年09月'!$Q$8:$Q$37,'2026年09月'!$A$8:$A$37,">="&$AK$18+7*(3-1),'2026年09月'!$A$8:$A$37,"<="&$AK$18+7*(3-1)+6)),"")) -> 0.26203209 | AG22: =IF($AD22="","",IFERROR((SUMIFS($I$8:$I$38,$A$8:$A$38,">="&$AK$18+7*(3-1),$A$8:$A$38,"<="&$AK$18+7*(3-1)+6)+SUMIFS('2026年09月'!$I$8:$I$37,'2026年09月'!$A$8:$A$37,">="&$AK$18+7*(3-1),'2026年09月'!$A$8:$A$37,"<="&$AK$18+7*(3-1)+6))/(SUMIFS($O$8:$O$38,$A$8:$A$38,">="&$AK$18+7*(3-1),$A$8:$A$38,"<="&$AK$18+7*(3-1)+6)+SUMIFS('2026年09月'!$O$8:$O$37,'2026年09月'!$A$8:$A$37,">="&$AK$18+7*(3-1),'2026年09月'!$A$8:$A$37,"<="&$AK$18+7*(3-1)+6)),"")) -> 21376.408 | AH22: =IF($AD22="","",IFERROR((SUMIFS($P$8:$P$38,$A$8:$A$38,">="&$AK$18+7*(3-1),$A$8:$A$38,"<="&$AK$18+7*(3-1)+6)+SUMIFS('2026年09月'!$P$8:$P$37,'2026年09月'!$A$8:$A$37,">="&$AK$18+7*(3-1),'2026年09月'!$A$8:$A$37,"<="&$AK$18+7*(3-1)+6))/(SUMIFS($O$8:$O$38,$A$8:$A$38,">="&$AK$18+7*(3-1),$A$8:$A$38,"<="&$AK$18+7*(3-1)+6)+SUMIFS('2026年09月'!$O$8:$O$37,'2026年09月'!$A$8:$A$37,">="&$AK$18+7*(3-1),'2026年09月'!$A$8:$A$37,"<="&$AK$18+7*(3-1)+6)),"")) -> 1.0612245 | AI22: =IF($AD22="","",IFERROR((SUMIFS($R$8:$R$38,$A$8:$A$38,">="&$AK$18+7*(3-1),$A$8:$A$38,"<="&$AK$18+7*(3-1)+6)+SUMIFS('2026年09月'!$R$8:$R$37,'2026年09月'!$A$8:$A$37,">="&$AK$18+7*(3-1),'2026年09月'!$A$8:$A$37,"<="&$AK$18+7*(3-1)+6))/(SUMIFS($Q$8:$Q$38,$A$8:$A$38,">="&$AK$18+7*(3-1),$A$8:$A$38,"<="&$AK$18+7*(3-1)+6)+SUMIFS('2026年09月'!$Q$8:$Q$37,'2026年09月'!$A$8:$A$37,">="&$AK$18+7*(3-1),'2026年09月'!$A$8:$A$37,"<="&$AK$18+7*(3-1)+6)),"")) -> 0.36898396
A23: 46250 | B23: =MID("日月火水木金土",WEEKDAY(A23),1) -> 日 | C23: 885000 | D23: =SUM($C$8:C23) -> 9920000 | E23: 66530 | F23: 165717 | I23: =IF(COUNT(E23:H23)=0,"",SUM(E23:H23)) -> 232247 | J23: =IF(I23="","",SUM($I$8:I23)) -> 2680726 | K23: =IF(I23="","",IFERROR(I23/C23,"")) -> 0.26242599 | L23: =IF(J23="","",IFERROR(J23/D23,"")) -> 0.27023448 | M23: =IF(J23="","",IF(D23=0,"",J23-D23)) -> -7239274 | N23: =IF(I23="","—",IF(D23=0,"予算未入力",IF(J23>=D23,"◎ ペース内","▲ 遅れ"))) -> ▲ 遅れ | O23: 10 | P23: 11 | Q23: 31 | R23: 12 | S23: 17 | T23: =IFERROR(O23/Q23,"") -> 0.32258065 | U23: =IFERROR(I23/O23,"") -> 23224.7 | V23: =IFERROR(P23/O23,"") -> 1.1 | W23: =IFERROR(R23/Q23,"") -> 0.38709677 | Y23: 8766 | AC23: 4 | AD23: =IF($AK$18+7*(4-1)>$A$38,"",TEXT($AK$18+7*(4-1),"m/d")&"-"&TEXT($AK$18+7*(4-1)+6,"m/d")) -> 8/25-8/31 | AE23: =IF($AD23="","",(SUMIFS($I$8:$I$38,$A$8:$A$38,">="&$AK$18+7*(4-1),$A$8:$A$38,"<="&$AK$18+7*(4-1)+6)+SUMIFS('2026年09月'!$I$8:$I$37,'2026年09月'!$A$8:$A$37,">="&$AK$18+7*(4-1),'2026年09月'!$A$8:$A$37,"<="&$AK$18+7*(4-1)+6))) -> 760162 | AF23: =IF($AD23="","",IFERROR((SUMIFS($O$8:$O$38,$A$8:$A$38,">="&$AK$18+7*(4-1),$A$8:$A$38,"<="&$AK$18+7*(4-1)+6)+SUMIFS('2026年09月'!$O$8:$O$37,'2026年09月'!$A$8:$A$37,">="&$AK$18+7*(4-1),'2026年09月'!$A$8:$A$37,"<="&$AK$18+7*(4-1)+6))/(SUMIFS($Q$8:$Q$38,$A$8:$A$38,">="&$AK$18+7*(4-1),$A$8:$A$38,"<="&$AK$18+7*(4-1)+6)+SUMIFS('2026年09月'!$Q$8:$Q$37,'2026年09月'!$A$8:$A$37,">="&$AK$18+7*(4-1),'2026年09月'!$A$8:$A$37,"<="&$AK$18+7*(4-1)+6)),"")) -> 0.25352113 | AG23: =IF($AD23="","",IFERROR((SUMIFS($I$8:$I$38,$A$8:$A$38,">="&$AK$18+7*(4-1),$A$8:$A$38,"<="&$AK$18+7*(4-1)+6)+SUMIFS('2026年09月'!$I$8:$I$37,'2026年09月'!$A$8:$A$37,">="&$AK$18+7*(4-1),'2026年09月'!$A$8:$A$37,"<="&$AK$18+7*(4-1)+6))/(SUMIFS($O$8:$O$38,$A$8:$A$38,">="&$AK$18+7*(4-1),$A$8:$A$38,"<="&$AK$18+7*(4-1)+6)+SUMIFS('2026年09月'!$O$8:$O$37,'2026年09月'!$A$8:$A$37,">="&$AK$18+7*(4-1),'2026年09月'!$A$8:$A$37,"<="&$AK$18+7*(4-1)+6)),"")) -> 21115.611 | AH23: =IF($AD23="","",IFERROR((SUMIFS($P$8:$P$38,$A$8:$A$38,">="&$AK$18+7*(4-1),$A$8:$A$38,"<="&$AK$18+7*(4-1)+6)+SUMIFS('2026年09月'!$P$8:$P$37,'2026年09月'!$A$8:$A$37,">="&$AK$18+7*(4-1),'2026年09月'!$A$8:$A$37,"<="&$AK$18+7*(4-1)+6))/(SUMIFS($O$8:$O$38,$A$8:$A$38,">="&$AK$18+7*(4-1),$A$8:$A$38,"<="&$AK$18+7*(4-1)+6)+SUMIFS('2026年09月'!$O$8:$O$37,'2026年09月'!$A$8:$A$37,">="&$AK$18+7*(4-1),'2026年09月'!$A$8:$A$37,"<="&$AK$18+7*(4-1)+6)),"")) -> 1.0555556 | AI23: =IF($AD23="","",IFERROR((SUMIFS($R$8:$R$38,$A$8:$A$38,">="&$AK$18+7*(4-1),$A$8:$A$38,"<="&$AK$18+7*(4-1)+6)+SUMIFS('2026年09月'!$R$8:$R$37,'2026年09月'!$A$8:$A$37,">="&$AK$18+7*(4-1),'2026年09月'!$A$8:$A$37,"<="&$AK$18+7*(4-1)+6))/(SUMIFS($Q$8:$Q$38,$A$8:$A$38,">="&$AK$18+7*(4-1),$A$8:$A$38,"<="&$AK$18+7*(4-1)+6)+SUMIFS('2026年09月'!$Q$8:$Q$37,'2026年09月'!$A$8:$A$37,">="&$AK$18+7*(4-1),'2026年09月'!$A$8:$A$37,"<="&$AK$18+7*(4-1)+6)),"")) -> 0.44366197
A24: 46251 | B24: =MID("日月火水木金土",WEEKDAY(A24),1) -> 月 | C24: 440000 | D24: =SUM($C$8:C24) -> 10360000 | E24: 63289 | F24: 34359 | I24: =IF(COUNT(E24:H24)=0,"",SUM(E24:H24)) -> 97648 | J24: =IF(I24="","",SUM($I$8:I24)) -> 2778374 | K24: =IF(I24="","",IFERROR(I24/C24,"")) -> 0.22192727 | L24: =IF(J24="","",IFERROR(J24/D24,"")) -> 0.26818282 | M24: =IF(J24="","",IF(D24=0,"",J24-D24)) -> -7581626 | N24: =IF(I24="","—",IF(D24=0,"予算未入力",IF(J24>=D24,"◎ ペース内","▲ 遅れ"))) -> ▲ 遅れ | O24: 5 | P24: 5 | Q24: 19 | R24: 5 | S24: 7 | T24: =IFERROR(O24/Q24,"") -> 0.26315789 | U24: =IFERROR(I24/O24,"") -> 19529.6 | V24: =IFERROR(P24/O24,"") -> 1 | W24: =IFERROR(R24/Q24,"") -> 0.26315789 | Y24: 8760 | AC24: 5 | AD24: =IF($AK$18+7*(5-1)>$A$38,"",TEXT($AK$18+7*(5-1),"m/d")&"-"&TEXT($AK$18+7*(5-1)+6,"m/d")) | AE24: =IF($AD24="","",(SUMIFS($I$8:$I$38,$A$8:$A$38,">="&$AK$18+7*(5-1),$A$8:$A$38,"<="&$AK$18+7*(5-1)+6)+SUMIFS('2026年09月'!$I$8:$I$37,'2026年09月'!$A$8:$A$37,">="&$AK$18+7*(5-1),'2026年09月'!$A$8:$A$37,"<="&$AK$18+7*(5-1)+6))) | AF24: =IF($AD24="","",IFERROR((SUMIFS($O$8:$O$38,$A$8:$A$38,">="&$AK$18+7*(5-1),$A$8:$A$38,"<="&$AK$18+7*(5-1)+6)+SUMIFS('2026年09月'!$O$8:$O$37,'2026年09月'!$A$8:$A$37,">="&$AK$18+7*(5-1),'2026年09月'!$A$8:$A$37,"<="&$AK$18+7*(5-1)+6))/(SUMIFS($Q$8:$Q$38,$A$8:$A$38,">="&$AK$18+7*(5-1),$A$8:$A$38,"<="&$AK$18+7*(5-1)+6)+SUMIFS('2026年09月'!$Q$8:$Q$37,'2026年09月'!$A$8:$A$37,">="&$AK$18+7*(5-1),'2026年09月'!$A$8:$A$37,"<="&$AK$18+7*(5-1)+6)),"")) | AG24: =IF($AD24="","",IFERROR((SUMIFS($I$8:$I$38,$A$8:$A$38,">="&$AK$18+7*(5-1),$A$8:$A$38,"<="&$AK$18+7*(5-1)+6)+SUMIFS('2026年09月'!$I$8:$I$37,'2026年09月'!$A$8:$A$37,">="&$AK$18+7*(5-1),'2026年09月'!$A$8:$A$37,"<="&$AK$18+7*(5-1)+6))/(SUMIFS($O$8:$O$38,$A$8:$A$38,">="&$AK$18+7*(5-1),$A$8:$A$38,"<="&$AK$18+7*(5-1)+6)+SUMIFS('2026年09月'!$O$8:$O$37,'2026年09月'!$A$8:$A$37,">="&$AK$18+7*(5-1),'2026年09月'!$A$8:$A$37,"<="&$AK$18+7*(5-1)+6)),"")) | AH24: =IF($AD24="","",IFERROR((SUMIFS($P$8:$P$38,$A$8:$A$38,">="&$AK$18+7*(5-1),$A$8:$A$38,"<="&$AK$18+7*(5-1)+6)+SUMIFS('2026年09月'!$P$8:$P$37,'2026年09月'!$A$8:$A$37,">="&$AK$18+7*(5-1),'2026年09月'!$A$8:$A$37,"<="&$AK$18+7*(5-1)+6))/(SUMIFS($O$8:$O$38,$A$8:$A$38,">="&$AK$18+7*(5-1),$A$8:$A$38,"<="&$AK$18+7*(5-1)+6)+SUMIFS('2026年09月'!$O$8:$O$37,'2026年09月'!$A$8:$A$37,">="&$AK$18+7*(5-1),'2026年09月'!$A$8:$A$37,"<="&$AK$18+7*(5-1)+6)),"")) | AI24: =IF($AD24="","",IFERROR((SUMIFS($R$8:$R$38,$A$8:$A$38,">="&$AK$18+7*(5-1),$A$8:$A$38,"<="&$AK$18+7*(5-1)+6)+SUMIFS('2026年09月'!$R$8:$R$37,'2026年09月'!$A$8:$A$37,">="&$AK$18+7*(5-1),'2026年09月'!$A$8:$A$37,"<="&$AK$18+7*(5-1)+6))/(SUMIFS($Q$8:$Q$38,$A$8:$A$38,">="&$AK$18+7*(5-1),$A$8:$A$38,"<="&$AK$18+7*(5-1)+6)+SUMIFS('2026年09月'!$Q$8:$Q$37,'2026年09月'!$A$8:$A$37,">="&$AK$18+7*(5-1),'2026年09月'!$A$8:$A$37,"<="&$AK$18+7*(5-1)+6)),""))
A25: 46252 | B25: =MID("日月火水木金土",WEEKDAY(A25),1) -> 火 | C25: 440000 | D25: =SUM($C$8:C25) -> 10800000 | E25: 38320 | F25: 55099 | I25: =IF(COUNT(E25:H25)=0,"",SUM(E25:H25)) -> 93419 | J25: =IF(I25="","",SUM($I$8:I25)) -> 2871793 | K25: =IF(I25="","",IFERROR(I25/C25,"")) -> 0.21231591 | L25: =IF(J25="","",IFERROR(J25/D25,"")) -> 0.26590676 | M25: =IF(J25="","",IF(D25=0,"",J25-D25)) -> -7928207 | N25: =IF(I25="","—",IF(D25=0,"予算未入力",IF(J25>=D25,"◎ ペース内","▲ 遅れ"))) -> ▲ 遅れ | O25: 5 | P25: 5 | Q25: 22 | R25: 6 | S25: 8 | T25: =IFERROR(O25/Q25,"") -> 0.22727273 | U25: =IFERROR(I25/O25,"") -> 18683.8 | V25: =IFERROR(P25/O25,"") -> 1 | W25: =IFERROR(R25/Q25,"") -> 0.27272727 | Y25: 8761 | AC25: 6 | AD25: =IF($AK$18+7*(6-1)>$A$38,"",TEXT($AK$18+7*(6-1),"m/d")&"-"&TEXT($AK$18+7*(6-1)+6,"m/d")) | AE25: =IF($AD25="","",(SUMIFS($I$8:$I$38,$A$8:$A$38,">="&$AK$18+7*(6-1),$A$8:$A$38,"<="&$AK$18+7*(6-1)+6)+SUMIFS('2026年09月'!$I$8:$I$37,'2026年09月'!$A$8:$A$37,">="&$AK$18+7*(6-1),'2026年09月'!$A$8:$A$37,"<="&$AK$18+7*(6-1)+6))) | AF25: =IF($AD25="","",IFERROR((SUMIFS($O$8:$O$38,$A$8:$A$38,">="&$AK$18+7*(6-1),$A$8:$A$38,"<="&$AK$18+7*(6-1)+6)+SUMIFS('2026年09月'!$O$8:$O$37,'2026年09月'!$A$8:$A$37,">="&$AK$18+7*(6-1),'2026年09月'!$A$8:$A$37,"<="&$AK$18+7*(6-1)+6))/(SUMIFS($Q$8:$Q$38,$A$8:$A$38,">="&$AK$18+7*(6-1),$A$8:$A$38,"<="&$AK$18+7*(6-1)+6)+SUMIFS('2026年09月'!$Q$8:$Q$37,'2026年09月'!$A$8:$A$37,">="&$AK$18+7*(6-1),'2026年09月'!$A$8:$A$37,"<="&$AK$18+7*(6-1)+6)),"")) | AG25: =IF($AD25="","",IFERROR((SUMIFS($I$8:$I$38,$A$8:$A$38,">="&$AK$18+7*(6-1),$A$8:$A$38,"<="&$AK$18+7*(6-1)+6)+SUMIFS('2026年09月'!$I$8:$I$37,'2026年09月'!$A$8:$A$37,">="&$AK$18+7*(6-1),'2026年09月'!$A$8:$A$37,"<="&$AK$18+7*(6-1)+6))/(SUMIFS($O$8:$O$38,$A$8:$A$38,">="&$AK$18+7*(6-1),$A$8:$A$38,"<="&$AK$18+7*(6-1)+6)+SUMIFS('2026年09月'!$O$8:$O$37,'2026年09月'!$A$8:$A$37,">="&$AK$18+7*(6-1),'2026年09月'!$A$8:$A$37,"<="&$AK$18+7*(6-1)+6)),"")) | AH25: =IF($AD25="","",IFERROR((SUMIFS($P$8:$P$38,$A$8:$A$38,">="&$AK$18+7*(6-1),$A$8:$A$38,"<="&$AK$18+7*(6-1)+6)+SUMIFS('2026年09月'!$P$8:$P$37,'2026年09月'!$A$8:$A$37,">="&$AK$18+7*(6-1),'2026年09月'!$A$8:$A$37,"<="&$AK$18+7*(6-1)+6))/(SUMIFS($O$8:$O$38,$A$8:$A$38,">="&$AK$18+7*(6-1),$A$8:$A$38,"<="&$AK$18+7*(6-1)+6)+SUMIFS('2026年09月'!$O$8:$O$37,'2026年09月'!$A$8:$A$37,">="&$AK$18+7*(6-1),'2026年09月'!$A$8:$A$37,"<="&$AK$18+7*(6-1)+6)),"")) | AI25: =IF($AD25="","",IFERROR((SUMIFS($R$8:$R$38,$A$8:$A$38,">="&$AK$18+7*(6-1),$A$8:$A$38,"<="&$AK$18+7*(6-1)+6)+SUMIFS('2026年09月'!$R$8:$R$37,'2026年09月'!$A$8:$A$37,">="&$AK$18+7*(6-1),'2026年09月'!$A$8:$A$37,"<="&$AK$18+7*(6-1)+6))/(SUMIFS($Q$8:$Q$38,$A$8:$A$38,">="&$AK$18+7*(6-1),$A$8:$A$38,"<="&$AK$18+7*(6-1)+6)+SUMIFS('2026年09月'!$Q$8:$Q$37,'2026年09月'!$A$8:$A$37,">="&$AK$18+7*(6-1),'2026年09月'!$A$8:$A$37,"<="&$AK$18+7*(6-1)+6)),""))
A26: 46253 | B26: =MID("日月火水木金土",WEEKDAY(A26),1) -> 水 | C26: 440000 | D26: =SUM($C$8:C26) -> 11240000 | E26: 88010 | F26: 163970 | I26: =IF(COUNT(E26:H26)=0,"",SUM(E26:H26)) -> 251980 | J26: =IF(I26="","",SUM($I$8:I26)) -> 3123773 | K26: =IF(I26="","",IFERROR(I26/C26,"")) -> 0.57268182 | L26: =IF(J26="","",IFERROR(J26/D26,"")) -> 0.27791575 | M26: =IF(J26="","",IF(D26=0,"",J26-D26)) -> -8116227 | N26: =IF(I26="","—",IF(D26=0,"予算未入力",IF(J26>=D26,"◎ ペース内","▲ 遅れ"))) -> ▲ 遅れ | O26: 12 | P26: 15 | Q26: 26 | R26: 7 | S26: 14 | T26: =IFERROR(O26/Q26,"") -> 0.46153846 | U26: =IFERROR(I26/O26,"") -> 20998.333 | V26: =IFERROR(P26/O26,"") -> 1.25 | W26: =IFERROR(R26/Q26,"") -> 0.26923077 | Y26: 8761 | AC26: ※期間ラベルは第1火曜から自動生成。決定率・客単価・セット率・試着率は「週合計÷週合計」
A27: 46254 | B27: =MID("日月火水木金土",WEEKDAY(A27),1) -> 木 | C27: 440000 | D27: =SUM($C$8:C27) -> 11680000 | E27: 122618 | F27: 72699 | I27: =IF(COUNT(E27:H27)=0,"",SUM(E27:H27)) -> 195317 | J27: =IF(I27="","",SUM($I$8:I27)) -> 3319090 | K27: =IF(I27="","",IFERROR(I27/C27,"")) -> 0.44390227 | L27: =IF(J27="","",IFERROR(J27/D27,"")) -> 0.28416866 | M27: =IF(J27="","",IF(D27=0,"",J27-D27)) -> -8360910 | N27: =IF(I27="","—",IF(D27=0,"予算未入力",IF(J27>=D27,"◎ ペース内","▲ 遅れ"))) -> ▲ 遅れ | O27: 9 | P27: 9 | Q27: 27 | R27: 11 | S27: 16 | T27: =IFERROR(O27/Q27,"") -> 0.33333333 | U27: =IFERROR(I27/O27,"") -> 21701.889 | V27: =IFERROR(P27/O27,"") -> 1 | W27: =IFERROR(R27/Q27,"") -> 0.40740741 | Y27: 8764 | AC27: ※最終週は翌月にまたぐため、2026年09月シートの実績も自動で合算します
A28: 46255 | B28: =MID("日月火水木金土",WEEKDAY(A28),1) -> 金 | C28: 440000 | D28: =SUM($C$8:C28) -> 12120000 | E28: 26510 | F28: 23810 | I28: =IF(COUNT(E28:H28)=0,"",SUM(E28:H28)) -> 50320 | J28: =IF(I28="","",SUM($I$8:I28)) -> 3369410 | K28: =IF(I28="","",IFERROR(I28/C28,"")) -> 0.11436364 | L28: =IF(J28="","",IFERROR(J28/D28,"")) -> 0.27800413 | M28: =IF(J28="","",IF(D28=0,"",J28-D28)) -> -8750590 | N28: =IF(I28="","—",IF(D28=0,"予算未入力",IF(J28>=D28,"◎ ペース内","▲ 遅れ"))) -> ▲ 遅れ | O28: 2 | P28: 2 | Q28: 23 | R28: 8 | S28: 11 | T28: =IFERROR(O28/Q28,"") -> 0.086956522 | U28: =IFERROR(I28/O28,"") -> 25160 | V28: =IFERROR(P28/O28,"") -> 1 | W28: =IFERROR(R28/Q28,"") -> 0.34782609 | Y28: 8758 | AC28: ※月初の月曜まで（例：6/1）は前月シートの最終週に含まれます
A29: 46256 | B29: =MID("日月火水木金土",WEEKDAY(A29),1) -> 土 | C29: 660000 | D29: =SUM($C$8:C29) -> 12780000 | E29: 40420 | F29: 62899 | I29: =IF(COUNT(E29:H29)=0,"",SUM(E29:H29)) -> 103319 | J29: =IF(I29="","",SUM($I$8:I29)) -> 3472729 | K29: =IF(I29="","",IFERROR(I29/C29,"")) -> 0.15654394 | L29: =IF(J29="","",IFERROR(J29/D29,"")) -> 0.27173153 | M29: =IF(J29="","",IF(D29=0,"",J29-D29)) -> -9307271 | N29: =IF(I29="","—",IF(D29=0,"予算未入力",IF(J29>=D29,"◎ ペース内","▲ 遅れ"))) -> ▲ 遅れ | O29: 5 | P29: 5 | Q29: 31 | R29: 11 | S29: 22 | T29: =IFERROR(O29/Q29,"") -> 0.16129032 | U29: =IFERROR(I29/O29,"") -> 20663.8 | V29: =IFERROR(P29/O29,"") -> 1 | W29: =IFERROR(R29/Q29,"") -> 0.35483871 | Y29: 8759
A30: 46257 | B30: =MID("日月火水木金土",WEEKDAY(A30),1) -> 日 | C30: 660000 | D30: =SUM($C$8:C30) -> 13440000 | E30: 45920 | F30: 186530 | I30: =IF(COUNT(E30:H30)=0,"",SUM(E30:H30)) -> 232450 | J30: =IF(I30="","",SUM($I$8:I30)) -> 3705179 | K30: =IF(I30="","",IFERROR(I30/C30,"")) -> 0.35219697 | L30: =IF(J30="","",IFERROR(J30/D30,"")) -> 0.27568296 | M30: =IF(J30="","",IF(D30=0,"",J30-D30)) -> -9734821 | N30: =IF(I30="","—",IF(D30=0,"予算未入力",IF(J30>=D30,"◎ ペース内","▲ 遅れ"))) -> ▲ 遅れ | O30: 11 | P30: 11 | Q30: 37 | R30: 18 | S30: 23 | T30: =IFERROR(O30/Q30,"") -> 0.2972973 | U30: =IFERROR(I30/O30,"") -> 21131.818 | V30: =IFERROR(P30/O30,"") -> 1 | W30: =IFERROR(R30/Q30,"") -> 0.48648649 | Y30: 8771
A31: 46258 | B31: =MID("日月火水木金土",WEEKDAY(A31),1) -> 月 | C31: 440000 | D31: =SUM($C$8:C31) -> 13880000 | E31: 24310 | F31: 96329 | I31: =IF(COUNT(E31:H31)=0,"",SUM(E31:H31)) -> 120639 | J31: =IF(I31="","",SUM($I$8:I31)) -> 3825818 | K31: =IF(I31="","",IFERROR(I31/C31,"")) -> 0.27417955 | L31: =IF(J31="","",IFERROR(J31/D31,"")) -> 0.2756353 | M31: =IF(J31="","",IF(D31=0,"",J31-D31)) -> -10054182 | N31: =IF(I31="","—",IF(D31=0,"予算未入力",IF(J31>=D31,"◎ ペース内","▲ 遅れ"))) -> ▲ 遅れ | O31: 5 | P31: 5 | Q31: 21 | R31: 8 | S31: 13 | T31: =IFERROR(O31/Q31,"") -> 0.23809524 | U31: =IFERROR(I31/O31,"") -> 24127.8 | V31: =IFERROR(P31/O31,"") -> 1 | W31: =IFERROR(R31/Q31,"") -> 0.38095238
A32: 46259 | B32: =MID("日月火水木金土",WEEKDAY(A32),1) -> 火 | C32: 440000 | D32: =SUM($C$8:C32) -> 14320000 | E32: 43709 | F32: 0 | I32: =IF(COUNT(E32:H32)=0,"",SUM(E32:H32)) -> 43709 | J32: =IF(I32="","",SUM($I$8:I32)) -> 3869527 | K32: =IF(I32="","",IFERROR(I32/C32,"")) -> 0.099338636 | L32: =IF(J32="","",IFERROR(J32/D32,"")) -> 0.27021837 | M32: =IF(J32="","",IF(D32=0,"",J32-D32)) -> -10450473 | N32: =IF(I32="","—",IF(D32=0,"予算未入力",IF(J32>=D32,"◎ ペース内","▲ 遅れ"))) -> ▲ 遅れ | O32: 2 | P32: 2 | Q32: 18 | R32: 7 | S32: 11 | T32: =IFERROR(O32/Q32,"") -> 0.11111111 | U32: =IFERROR(I32/O32,"") -> 21854.5 | V32: =IFERROR(P32/O32,"") -> 1 | W32: =IFERROR(R32/Q32,"") -> 0.38888889 | Y32: 8766
A33: 46260 | B33: =MID("日月火水木金土",WEEKDAY(A33),1) -> 水 | C33: 440000 | D33: =SUM($C$8:C33) -> 14760000 | E33: 25010 | F33: 67630 | I33: =IF(COUNT(E33:H33)=0,"",SUM(E33:H33)) -> 92640 | J33: =IF(I33="","",SUM($I$8:I33)) -> 3962167 | K33: =IF(I33="","",IFERROR(I33/C33,"")) -> 0.21054545 | L33: =IF(J33="","",IFERROR(J33/D33,"")) -> 0.2684395 | M33: =IF(J33="","",IF(D33=0,"",J33-D33)) -> -10797833 | N33: =IF(I33="","—",IF(D33=0,"予算未入力",IF(J33>=D33,"◎ ペース内","▲ 遅れ"))) -> ▲ 遅れ | O33: 4 | P33: 4 | Q33: 16 | R33: 4 | S33: 6 | T33: =IFERROR(O33/Q33,"") -> 0.25 | U33: =IFERROR(I33/O33,"") -> 23160 | V33: =IFERROR(P33/O33,"") -> 1 | W33: =IFERROR(R33/Q33,"") -> 0.25 | Y33: 8766
A34: 46261 | B34: =MID("日月火水木金土",WEEKDAY(A34),1) -> 木 | C34: 440000 | D34: =SUM($C$8:C34) -> 15200000 | E34: 68690 | F34: 44110 | I34: =IF(COUNT(E34:H34)=0,"",SUM(E34:H34)) -> 112800 | J34: =IF(I34="","",SUM($I$8:I34)) -> 4074967 | K34: =IF(I34="","",IFERROR(I34/C34,"")) -> 0.25636364 | L34: =IF(J34="","",IFERROR(J34/D34,"")) -> 0.26808993 | M34: =IF(J34="","",IF(D34=0,"",J34-D34)) -> -11125033 | N34: =IF(I34="","—",IF(D34=0,"予算未入力",IF(J34>=D34,"◎ ペース内","▲ 遅れ"))) -> ▲ 遅れ | O34: 5 | P34: 5 | Q34: 23 | R34: 11 | S34: 11 | T34: =IFERROR(O34/Q34,"") -> 0.2173913 | U34: =IFERROR(I34/O34,"") -> 22560 | V34: =IFERROR(P34/O34,"") -> 1 | W34: =IFERROR(R34/Q34,"") -> 0.47826087 | Y34: 8766
A35: 46262 | B35: =MID("日月火水木金土",WEEKDAY(A35),1) -> 金 | C35: 440000 | D35: =SUM($C$8:C35) -> 15640000 | E35: 37818 | F35: 51810 | I35: =IF(COUNT(E35:H35)=0,"",SUM(E35:H35)) -> 89628 | J35: =IF(I35="","",SUM($I$8:I35)) -> 4164595 | K35: =IF(I35="","",IFERROR(I35/C35,"")) -> 0.2037 | L35: =IF(J35="","",IFERROR(J35/D35,"")) -> 0.26627845 | M35: =IF(J35="","",IF(D35=0,"",J35-D35)) -> -11475405 | N35: =IF(I35="","—",IF(D35=0,"予算未入力",IF(J35>=D35,"◎ ペース内","▲ 遅れ"))) -> ▲ 遅れ | O35: 4 | P35: 5 | Q35: 22 | R35: 11 | S35: 16 | T35: =IFERROR(O35/Q35,"") -> 0.18181818 | U35: =IFERROR(I35/O35,"") -> 22407 | V35: =IFERROR(P35/O35,"") -> 1.25 | W35: =IFERROR(R35/Q35,"") -> 0.5 | Y35: 8766
A36: 46263 | B36: =MID("日月火水木金土",WEEKDAY(A36),1) -> 土 | C36: 660000 | D36: =SUM($C$8:C36) -> 16300000 | E36: 97376 | F36: 62139 | I36: =IF(COUNT(E36:H36)=0,"",SUM(E36:H36)) -> 159515 | J36: =IF(I36="","",SUM($I$8:I36)) -> 4324110 | K36: =IF(I36="","",IFERROR(I36/C36,"")) -> 0.24168939 | L36: =IF(J36="","",IFERROR(J36/D36,"")) -> 0.26528282 | M36: =IF(J36="","",IF(D36=0,"",J36-D36)) -> -11975890 | N36: =IF(I36="","—",IF(D36=0,"予算未入力",IF(J36>=D36,"◎ ペース内","▲ 遅れ"))) -> ▲ 遅れ | O36: 9 | P36: 9 | Q36: 22 | R36: 15 | S36: 23 | T36: =IFERROR(O36/Q36,"") -> 0.40909091 | U36: =IFERROR(I36/O36,"") -> 17723.889 | V36: =IFERROR(P36/O36,"") -> 1 | W36: =IFERROR(R36/Q36,"") -> 0.68181818 | Y36: 8767
A37: 46264 | B37: =MID("日月火水木金土",WEEKDAY(A37),1) -> 日 | C37: 660000 | D37: =SUM($C$8:C37) -> 16960000 | E37: 60830 | F37: 138060 | G37: 12000 | I37: =IF(COUNT(E37:H37)=0,"",SUM(E37:H37)) -> 210890 | J37: =IF(I37="","",SUM($I$8:I37)) -> 4535000 | K37: =IF(I37="","",IFERROR(I37/C37,"")) -> 0.3195303 | L37: =IF(J37="","",IFERROR(J37/D37,"")) -> 0.26739387 | M37: =IF(J37="","",IF(D37=0,"",J37-D37)) -> -12425000 | N37: =IF(I37="","—",IF(D37=0,"予算未入力",IF(J37>=D37,"◎ ペース内","▲ 遅れ"))) -> ▲ 遅れ | O37: 10 | P37: 11 | Q37: 27 | R37: 10 | S37: 13 | T37: =IFERROR(O37/Q37,"") -> 0.37037037 | U37: =IFERROR(I37/O37,"") -> 21089 | V37: =IFERROR(P37/O37,"") -> 1.1 | W37: =IFERROR(R37/Q37,"") -> 0.37037037 | Y37: 8765
